Workbook

Sheet Cover
B2: Semiconductor FP&A Forecasting and Decision Model
B3: Fictional Embedded Control Division, modeled on Microchip Technology Inc. (NASDAQ: MCHP)
B5: Simulated data created for portfolio demonstration. It does not represent nonpublic Microchip Technology information.
B6: Reported public data comes only from Microchip Technology's SEC filings (see Sources_Log). All division-level operating data is simulated and labeled as such.
B8: Business question | C8: How would changes in demand, average selling price, product mix, manufacturing yield, capacity utilization, operating costs and capital spending affect the division's revenue, operating profit and free cash flow?
B10: Model status | C10: =Checks!$C$174 -> ALL CHECKS PASS
B11: Built by | C11: scripts/build_model.py --company MCHP (config: companies/MCHP/config.toml)
B13: Tab guide
B14: Cover | C14: This page
B15: Sources_Log | C15: Source register (SEC filings) and assumptions log
B16: Assumptions | C16: Scenario selector (one cell), 9 scenario drivers, division & product inputs, seasonality
B17: Hist_Data | C17: Reported financials FY2022-FY2026, one source per row (inputs)
B18: Hist_Analysis | C18: Growth, margins, segment mix, free cash flow, working capital (formulas)
B19: Ops_Model | C19: Product x month operating model: demand, capacity, yield, inventory, revenue, cost, gross profit
B20: Revenue | C20: Monthly revenue forecast by product line, mix, quarters, FY vs FY2026 base year
B21: PnL | C21: Monthly P&L to net income; EBITDA; FY2026 base-year comparison
B22: FCF | C22: Capex and depreciation, working capital, free cash flow
B23: Budget | C23: FY2027 budget = Base scenario, locked (does not follow the selector)
B24: Actuals | C24: SIMULATED actual results Apr-Aug 2026, same operating logic
B25: Variance | C25: YTD budget vs actual: price/volume/mix, operating-profit bridge, reconciliation flags
... B28: Checks | C28: Independent checks and hand-calculable unit tests; overall status feeds this cover
B30: Color legend
B31: 1,234.5 | C31: Blue: hardcoded input (reported value or assumption)
B32: 1,234.5 | C32: Black: formula / calculation
B33: 1,234.5 | C33: Green: direct link to another tab
B34: Input | C34: Yellow fill: key assumption / cell a user may change
B36: Value classification
C37: Reported public data - transcribed from an SEC filing (source on every row)
C38: Calculated value - Excel formula on other cells
C39: User-provided assumption - logged in Sources_Log with who decided it
C40: Simulated operational data - labeled with the disclaimer above
B42: Units & conventions | C42: USD millions unless noted. Fiscal year ends March 31. Negatives in parentheses. Capex printed negative in Hist_Data, positive in analysis.

Sheet Sources_Log
A1: Source Register and Assumptions Log
A2: Every reported value traces to a source below. Every assumption is logged with who decided it.
A3: Simulated data created for portfolio demonstration. It does not represent nonpublic Microchip Technology information.
A5: Source register
A6: ID | B6: Document | C6: Accession no. | D6: Period covered | E6: URL | F6: Used for | G6: Accessed
A7: S-001 | B7: Form 10-K fiscal 2026 | C7: 0000827054-26-000016 | D7: FY2024-FY2026 income & cash flow; FY2025-FY2026 balance sheet; product lines; segments; inventory detail; Item 1 manufacturing facts | E7: https://www.sec.gov/Archives/edgar/data/827054/000082705426000016/ | F7: Historical analysis; product-mix anchor | G7: 2026-09-22
A8: S-002 | B8: Form 10-K fiscal 2024 | C8: 0000827054-24-000098 | D8: FY2022-FY2024 income & cash flow; FY2023-FY2024 balance sheet; FY2022-FY2024 product lines | E8: https://www.sec.gov/Archives/edgar/data/827054/000082705424000098/ | F8: Historical analysis; cross-filing check | G8: 2026-09-22
A9: S-003 | B9: Form 10-K fiscal 2023 | C9: 0000827054-23-000080 | D9: FY2022-FY2023 balance sheet | E9: https://www.sec.gov/Archives/edgar/data/827054/000082705423000080/ | F9: FY2022 opening working capital; cross-filing check | G9: 2026-09-22
A10: S-004 | B10: Form 10-Q Q1 fiscal 2027 | C10: 0000827054-26-000038 | D10: Quarter ended 2026-06-30 net sales by product line | E10: https://ir.microchip.com/sec-filings/all-sec-filings/content/0000827054-26-000038/mchp-20260630.htm | F10: Context for FY2027 forecast | G10: 2026-09-22
A11: S-005 | B11: Q4 & FY2026 earnings release (Exhibit 99.1) | C11: 0000827054-26-000012 | D11: Q4 FY2026 commentary: factory utilization outlook; inventory days; Fab 2 restructuring | E11: https://www.sec.gov/Archives/edgar/data/827054/000082705426000012/exhibit991q4fy26.htm | F11: Narrative context only (no values used in model yet) | G11: 2026-09-22
A13: Assumptions log
A14: ID | B14: Area | C14: Assumption | D14: Value | E14: Rationale | F14: Classification | G14: Decided by | H14: Status
A15: A-001 | B15: Scope | C15: Public company used for historical data | D15: Microchip Technology Inc (NASDAQ: MCHP) | E15: Owns wafer fabs and internal test/assembly; many MCUs are Arm-based; files 10-K/10-Q with the SEC | F15: User-provided assumption | G15: User | H15: Final
A16: A-002 | B16: Scope | C16: Historical window | D16: FY2022-FY2026 (fiscal years ending March 31) | E16: Five years covers the FY2023 peak and the FY2024-FY2025 downturn | F16: User-provided assumption | G16: Claude (delegated by user) | H16: Final
A17: A-003 | B17: Timing | C17: Forecast period | D17: FY2027 monthly: Apr-2026 to Mar-2027 (12 months) | E17: Matches Microchip's current fiscal year; lets the budget-vs-actual comparison use a realistic year-to-date | F17: User-provided assumption | G17: Claude (delegated by user) | H17: Final
A18: A-004 | B18: Timing | C18: Actuals vs forecast split | D18: Apr-2026 to Aug-2026 = simulated actuals (5 months YTD); Sep-2026 to Mar-2027 = forecast | E18: As of 22-Sep-2026 the August close would be complete; September would not | F18: User-provided assumption | G18: Claude (delegated by user) | H18: Final
A19: A-005 | B19: Timing | C19: Month convention | D19: Calendar months (Microchip's own fiscal calendar is not replicated) | E19: Simpler and auditable; stated in methodology | F19: User-provided assumption | G19: Claude (delegated by user) | H19: Final
A20: A-006 | B20: Division | C20: Fictional division | D20: "Embedded Control Division" - fictional division modeled on Microchip's business | E20: Project requires a fictional division with three product categories | F20: User-provided assumption | G20: Claude (delegated by user) | H20: Final
A21: A-007 | B21: Division | C21: Division base-year (FY2026) revenue | D21: $1,000.0M | E21: Round number; about 21% of Microchip FY2026 net sales so it is plausibly one division | F21: User-provided assumption | G21: Claude (delegated by user) | H21: Final
A22: A-008 | B22: Division | C22: Product categories | D22: 1) Mixed-signal microcontrollers 2) Analog & power management 3) FPGAs | E22: Mirror Microchip's reported product lines. FPGAs are part of Microchip's reported 'Other' line and are NOT reported separately | F22: User-provided assumption | G22: Claude (delegated by user) | H22: Final
A23: A-009 | B23: Division | C23: Base-year product mix | D23: MCU 49.9756% / Analog & power 28.1980% / FPGA 21.8264% | E23: Microchip FY2026 reported product-line sales / FY2026 net sales (S-001). FPGA share uses the whole 'Other' line as a stand-in | F23: Calculated value | G23: Claude (delegated by user) | H23: Final
A24: A-010 | B24: Labeling | C24: Simulated-data disclaimer | D24: Simulated data created for portfolio demonstration. It does not represent nonpublic Microchip Technology information. | E24: Project data rules | F24: User-provided assumption | G24: User | H24: Final
A25: A-011 | B25: Dashboard | C25: Dashboard technology | D25: Custom static web dashboard (HTML/JS) reading JSON exported from the Excel model; Excel is the single source of truth | E25: User wants a modern look instead of Power BI | F25: User-provided assumption | G25: User | H25: Final
... A51: A-037 | B51: Dashboard | C51: Risk bins on the demand/capacity heat map | D51: OK < 0.85; TIGHT 0.85-1.00; SHORT >= 1.00 (demand / good-unit capacity at full load) | E51: Test-floor vocabulary; thresholds adjustable in dashboard/template.html (binOf) | F51: User-provided assumption | G51: Claude (delegated by user) | H51: Final

Sheet Assumptions
A1: Assumptions and Scenario Controls
A2: Change ONLY the yellow selector (C6) to switch scenario. Blue = input. Every forecast tab reads the Live column.
A3: Simulated data created for portfolio demonstration. It does not represent nonpublic Microchip Technology information.
A6: ACTIVE SCENARIO (choose Downside / Base / Upside) | C6: Base | D6: =MATCH($C$6,$C$9:$E$9,0) -> 2 | E6: <- scenario index (1 = Downside, 2 = Base, 3 = Upside)
A8: A. Scenario drivers (FY2027 vs FY2026 base year)
A9: Driver | B9: Units | C9: Downside | D9: Base | E9: Upside | F9: LIVE | P9: Classification | Q9: Rationale / reference
A10: Customer demand growth | B10: % | C10: 0.05 | D10: 0.2 | E10: 0.3 | F10: =INDEX(C10:E10,1,$D$6) -> 0.2 | P10: User-provided assumption | Q10: Microchip Q1 FY2027 sales +38% YoY and Q1 run-rate +26% vs FY2026 (section B). Base takes a more cautious +20%.
A11: Average selling price change | B11: % | C11: -0.04 | D11: -0.01 | E11: 0.01 | F11: =INDEX(C11:E11,1,$D$6) -> -0.01 | P11: User-provided assumption | Q11: Mature semiconductor prices usually drift down slowly; downside = price competition as inventory clears.
A12: Manufacturing yield change (percentage points vs base-year yield) | B12: pts | C12: -0.02 | D12: 0 | E12: 0.01 | F12: =INDEX(C12:E12,1,$D$6) -> 0 | P12: User-provided assumption | Q12: Applied to each product's base-year final-test yield (section D).
A13: Capacity utilization (internal final test) | B13: % | C13: 0.7 | D13: 0.8 | E13: 0.88 | F13: =INDEX(C13:E13,1,$D$6) -> 0.8 | P13: User-provided assumption | Q13: FY2026 implied ~65% (downturn). Microchip expects 'higher internal factory utilization' (S-005).
A14: Material-cost inflation (variable cost per unit) | B14: % | C14: 0.06 | D14: 0.03 | E14: 0.01 | F14: =INDEX(C14:E14,1,$D$6) -> 0.03 | P14: User-provided assumption | Q14: Wafer, substrate and packaging cost inflation.
A15: R&D expense growth | B15: % | C15: 0.02 | D15: 0.05 | E15: 0.08 | F15: =INDEX(C15:E15,1,$D$6) -> 0.05 | P15: User-provided assumption | Q15: Microchip R&D grew +10.4% in FY2026 (section B). Downside = hiring freeze.
A16: SG&A expense growth | B16: % | C16: 0.01 | D16: 0.04 | E16: 0.06 | F16: =INDEX(C16:E16,1,$D$6) -> 0.04 | P16: User-provided assumption | Q16: Microchip SG&A grew +9.2% in FY2026 (section B).
A17: Capital expenditures (% of revenue, excl. proposed test-equipment project) | B17: % | C17: 0.02 | D17: 0.03 | E17: 0.04 | F17: =INDEX(C17:E17,1,$D$6) -> 0.03 | P17: User-provided assumption | Q17: Microchip capex 1.9% of sales FY2026, 3.7-5.8% FY2022-FY2024 (section B).
A18: Tax rate | B18: % | C18: 0.21 | D18: 0.18 | E18: 0.16 | F18: =INDEX(C18:E18,1,$D$6) -> 0.18 | P18: User-provided assumption | Q18: Microchip effective rate 13-23% in FY2022-FY2026 excl. FY2025 (section B). Downside = US statutory 21%.
A20: B. Reference points from Microchip Technology's reported history (formulas - context for the drivers above)
A21: Q1 FY2027 net sales growth vs Q1 FY2026 | F21: =Hist_Analysis!$E$51 -> 0.3804742 | P21: Calculated value | Q21: Reported public data (Hist tabs)
A22: Q1 FY2027 sales x 4 vs FY2026 net sales | F22: =Hist_Data!$D$70*4/Hist_Data!$G$7-1 -> 0.26006238 | P22: Calculated value | Q22: Reported public data (Hist tabs)
A23: Gross margin FY2026 (reported basis) | F23: =Hist_Analysis!$G$9 -> 0.57734824 | P23: Calculated value | Q23: Reported public data (Hist tabs)
A24: Gross margin FY2023 (highest in the history) | F24: =Hist_Analysis!$D$9 -> 0.67521064 | P24: Calculated value | Q24: Reported public data (Hist tabs)
A25: R&D growth FY2026 | F25: =Hist_Data!$G$10/Hist_Data!$F$10-1 -> 0.10378126 | P25: Calculated value | Q25: Reported public data (Hist tabs)
A26: SG&A growth FY2026 | F26: =Hist_Data!$G$11/Hist_Data!$F$11-1 -> 0.091630241 | P26: Calculated value | Q26: Reported public data (Hist tabs)
A27: Capex % of sales FY2026 | F27: =Hist_Analysis!$G$37 -> 0.019329104 | P27: Calculated value | Q27: Reported public data (Hist tabs)
A28: Capex % of sales, average FY2022-FY2026 | F28: =AVERAGE(Hist_Analysis!$C$37:$G$37) -> 0.039434879 | P28: Calculated value | Q28: Reported public data (Hist tabs)
A29: Effective tax rate, average FY2022-FY2026 (years shown n.m. excluded) | F29: =AVERAGE(Hist_Analysis!$C$17:$G$17) -> 0.17922279 | P29: Calculated value | Q29: Reported public data (Hist tabs)
A30: Share of test performed internally (FY2026) | F30: =Hist_Data!$G$79 -> 0.69 | P30: Calculated value | Q30: Reported public data (Hist tabs)
A32: C. Fictional Embedded Control Division - base year FY2026 (Simulated data created for portfolio demonstration. It does not represent nonpublic Microchip Technology information.)
A33: Division net revenue, FY2026 base year | B33: $m | F33: 1000 | P33: User-provided assumption | Q33: User-provided assumption. ~21% of Microchip Technology FY2026 net sales
A34: Division R&D expense, FY2026 base year | B34: $m | F34: 200 | P34: Simulated operational data | Q34: 20% of revenue. Microchip company-wide 23.0% includes corporate R&D. Used in Phase 3.
A35: Division SG&A expense, FY2026 base year | B35: $m | F35: 100 | P35: Simulated operational data | Q35: 10% of revenue. Microchip company-wide 14.3% includes corporate overhead. Used in Phase 3.
A36: Forecast start month (first month of FY2027) | F36: 46113 | P36: User-provided assumption | Q36: FY2027 = Apr-2026 to Mar-2027, calendar months
A38: D. Product inputs - base year FY2026 (simulated) and live FY2027 drivers (calculated)
A39: Input | B39: Units | C39: Mixed-signal MCUs | D39: Analog & power | E39: FPGAs | F39: Division | P39: Classification | Q39: Notes
A40: Base-year revenue mix | B40: % | C40: =Hist_Analysis!$G$20 -> 0.499756 | D40: =Hist_Analysis!$G$21 -> 0.28198001 | E40: =Hist_Analysis!$G$22 -> 0.21826399 | F40: =SUM(C40:E40) -> 1 | P40: Calculated value | Q40: Microchip Technology FY2026 reported segment mix. FPGA uses Microchip's whole 'Other' line as a stand-in (FPGAs are not reported separately).
A41: Base-year revenue | B41: $m | C41: =$F$33*$C$40 -> 499.756 | D41: =$F$33*$D$40 -> 281.98001 | E41: =$F$33*$E$40 -> 218.26399 | F41: =SUM(C41:E41) -> 1000 | P41: Calculated value | Q41: Division revenue x mix
A42: Base-year average selling price | B42: $/unit | C42: 2 | D42: 0.8 | E42: 25 | P42: Simulated operational data | Q42: Simulated. Order of magnitude typical for each product type.
A43: Base-year final-test yield | B43: % | C43: 0.92 | D43: 0.94 | E43: 0.85 | P43: Simulated operational data | Q43: Simulated. Good units / units tested. Larger FPGA die -> lower yield.
A44: Base-year variable cost per unit produced | B44: $/unit | C44: 0.31 | D44: 0.15 | E44: 4.7 | P44: Simulated operational data | Q44: Simulated. Wafer, foundry, substrate, package, test consumables per unit started.
A45: Fixed manufacturing cost per month | B45: $m/month | C45: 9.5 | D45: 5.2 | E45: 4.4 | F45: =SUM(C45:E45) -> 19.1 | P45: Simulated operational data | Q45: Simulated. Factory overhead, depreciation, fab/test labor. Same in base year and FY2027.
A46: Internal final-test capacity | B46: m units/month | C46: 35 | D46: 46 | E46: 1.3 | P46: Simulated operational data | Q46: Simulated. Capacity = units the internal test floor can process per month (A-016).
A47: Product demand growth vs division driver | B47: pts | C47: 0 | D47: -0.05 | E47: 0.05 | P47: Simulated operational data | Q47: Simulated. Keeps mix moving: Microchip Q1 FY2027 growth was Analog +30%, MCU +39%, Other +48%.
A48: Opening finished-goods inventory (months of base-year sales) | B48: months | C48: 1 | D48: 1 | E48: 1 | P48: Simulated operational data | Q48: Simulated opening balance at 1-Apr-2026.
A50: Base-year FY2026 economics (calculated; assumes production = sales in the base year)
A51: Units sold | B51: m units | C51: =$C$41/$C$42 -> 249.878 | D51: =$D$41/$D$42 -> 352.47502 | E51: =$E$41/$E$42 -> 8.7305595 | P51: Calculated value | Q51: Revenue / ASP
A52: Units produced (tested) | B52: m units | C52: =$C$51/$C$43 -> 271.60652 | D52: =$D$51/$D$43 -> 374.97342 | E52: =$E$51/$E$43 -> 10.271246 | P52: Calculated value | Q52: Units sold / yield (no inventory change in base year)
A53: Implied capacity utilization | B53: % | C53: =$C$52/($C$46*12) -> 0.64668219 | D53: =$D$52/($D$46*12) -> 0.67929968 | E53: =$E$52/($E$46*12) -> 0.65841324 | P53: Calculated value | Q53: Units produced / (capacity x 12).
A54: Variable manufacturing cost | B54: $m | C54: =$C$52*$C$44 -> 84.198022 | D54: =$D$52*$D$44 -> 56.246013 | E54: =$E$52*$E$44 -> 48.274858 | F54: =SUM(C54:E54) -> 188.71889 | P54: Calculated value | Q54: Units produced x variable cost per unit
A55: Fixed manufacturing cost | B55: $m | C55: =$C$45*12 -> 114 | D55: =$D$45*12 -> 62.4 | E55: =$E$45*12 -> 52.8 | F55: =SUM(C55:E55) -> 229.2 | P55: Calculated value | Q55: Monthly fixed cost x 12
A56: Cost of revenue | B56: $m | C56: =$C$54+$C$55 -> 198.19802 | D56: =$D$54+$D$55 -> 118.64601 | E56: =$E$54+$E$55 -> 101.07486 | F56: =SUM(C56:E56) -> 417.91889 | P56: Calculated value | Q56: Variable + fixed manufacturing cost
A57: Gross profit | B57: $m | C57: =$C$41-$C$56 -> 301.55798 | D57: =$D$41-$D$56 -> 163.334 | E57: =$E$41-$E$56 -> 117.18913 | F57: =SUM(C57:E57) -> 582.08111 | P57: Calculated value | Q57: Revenue - cost of revenue
A58: Gross margin | B58: % | C58: =IFERROR($C$57/$C$41,0) -> 0.60341042 | D58: =IFERROR($D$57/$D$41,0) -> 0.57923963 | E58: =IFERROR($E$57/$E$41,0) -> 0.53691463 | F58: =IFERROR(F57/F41,0) -> 0.58208111 | P58: Calculated value | Q58: Calibration: compare with Microchip Technology FY2026 reported gross margin in section B
A59: Cost per good unit | B59: $/unit | C59: =$C$56/$C$51 -> 0.79317916 | D59: =$D$56/$D$51 -> 0.33660829 | E59: =$E$56/$E$51 -> 11.577134 | P59: Calculated value | Q59: Cost of revenue / good units (= units sold in base year). Values the opening inventory.
A61: Live FY2027 product drivers (calculated from the active scenario)
A62: FY2027 customer demand | B62: m units | C62: =$C$51*(1+$F$10+$C$47) -> 299.8536 | D62: =$D$51*(1+$F$10+$D$47) -> 405.34627 | E62: =$E$51*(1+$F$10+$E$47) -> 10.913199 | P62: Calculated value | Q62: Base-year units sold x (1 + demand growth + product differential)
A63: FY2027 average selling price | B63: $/unit | C63: =$C$42*(1+$F$11) -> 1.98 | D63: =$D$42*(1+$F$11) -> 0.792 | E63: =$E$42*(1+$F$11) -> 24.75 | P63: Calculated value | Q63: Base ASP x (1 + ASP change)
A64: FY2027 final-test yield | B64: % | C64: =MIN(1,MAX(0,$C$43+$F$12)) -> 0.92 | D64: =MIN(1,MAX(0,$D$43+$F$12)) -> 0.94 | E64: =MIN(1,MAX(0,$E$43+$F$12)) -> 0.85 | P64: Calculated value | Q64: Base yield + yield change, bounded 0-100%
A65: FY2027 capacity utilization | B65: % | C65: =$F$13 -> 0.8 | D65: =$F$13 -> 0.8 | E65: =$F$13 -> 0.8 | P65: Calculated value | Q65: Same scenario utilization for every product line
A66: FY2027 variable cost per unit produced | B66: $/unit | C66: =$C$44*(1+$F$14) -> 0.3193 | D66: =$D$44*(1+$F$14) -> 0.1545 | E66: =$E$44*(1+$F$14) -> 4.841 | P66: Calculated value | Q66: Base variable cost x (1 + material inflation)
A67: Opening finished-goods inventory (01-Apr-2026) | B67: m units | C67: =$C$48*$C$51/12 -> 20.823167 | D67: =$D$48*$D$51/12 -> 29.372918 | E67: =$E$48*$E$51/12 -> 0.72754663 | P67: Calculated value | Q67: Months of inventory x base-year monthly units sold
A68: Opening finished-goods inventory value | B68: $m | C68: =$C$67*$C$59 -> 16.516502 | D68: =$D$67*$D$59 -> 9.8871678 | E68: =$E$67*$E$59 -> 8.4229049 | F68: =SUM(C68:E68) -> 34.826574 | P68: Calculated value | Q68: Opening units x base-year cost per good unit
A70: E. Monthly demand seasonality (simulated; must sum to 12.00)
A71: Month | C71: =DATE(YEAR($F$36),MONTH($F$36)+0,1) -> 46113 | D71: =DATE(YEAR($F$36),MONTH($F$36)+1,1) -> 46143 | E71: =DATE(YEAR($F$36),MONTH($F$36)+2,1) -> 46174 | F71: =DATE(YEAR($F$36),MONTH($F$36)+3,1) -> 46204 | G71: =DATE(YEAR($F$36),MONTH($F$36)+4,1) -> 46235 | H71: =DATE(YEAR($F$36),MONTH($F$36)+5,1) -> 46266 | I71: =DATE(YEAR($F$36),MONTH($F$36)+6,1) -> 46296 | J71: =DATE(YEAR($F$36),MONTH($F$36)+7,1) -> 46327 | K71: =DATE(YEAR($F$36),MONTH($F$36)+8,1) -> 46357 | L71: =DATE(YEAR($F$36),MONTH($F$36)+9,1) -> 46388 | M71: =DATE(YEAR($F$36),MONTH($F$36)+10,1) -> 46419 | N71: =DATE(YEAR($F$36),MONTH($F$36)+11,1) -> 46447 | O71: Sum
A72: Seasonality factor (1.00 = average month) | C72: 0.96 | D72: 0.98 | E72: 1.02 | F72: 0.97 | G72: 0.99 | H72: 1.04 | I72: 1.03 | J72: 1.01 | K72: 0.95 | L72: 0.97 | M72: 1 | N72: 1.08 | O72: =SUM(C72:N72) -> 12 | P72: Simulated operational data | Q72: Quarter-end pulls (Jun, Sep, Mar) and a December holiday dip
A74: F. Live scenario result - FY2027 (from Ops_Model)
A75: Division revenue | F75: =Ops_Model!$O$98 -> 1184.8461 | P75: Calculated value
A76: Growth vs FY2026 base-year revenue | F76: =Ops_Model!$O$98/$F$33-1 -> 0.18484606 | P76: Calculated value
A77: Gross profit | F77: =Ops_Model!$O$105 -> 723.2538 | P77: Calculated value
A78: Gross margin | F78: =Ops_Model!$O$106 -> 0.61042006 | P78: Calculated value
A79: Revenue at risk from unmet demand | F79: =Ops_Model!$O$108 -> 0 | P79: Calculated value
A81: G. P&L and cash-flow inputs (not scenario-driven)
A82: Days sales outstanding (DSO) | B82: days | F82: 60 | P82: User-provided assumption | Q82: Microchip DSO 55-57 days FY2022-FY2025, 69 in FY2026 (reference below). AR = monthly revenue x 12 x DSO / 365
A83: Days payable outstanding on variable manufacturing cost | B83: days | F83: 40 | P83: User-provided assumption | Q83: Applied to purchases (variable manufacturing cost). AP = monthly variable cost x 12 x DPO / 365
A84: Depreciation share of fixed manufacturing cost | B84: % | F84: 0.3 | P84: Simulated operational data | Q84: Non-cash part of factory fixed cost. 30% x $229m = ~$69m/yr (~7% of revenue). Reference below
A85: Useful life of new FY2027 capex | B85: months | F85: 60 | P85: User-provided assumption | Q85: Straight-line; depreciation starts the month after spend. FY2027 capex depreciation sits in cost of revenue
A86: Reference: Microchip Technology DSO FY2026 | F86: =Hist_Analysis!$G$42 -> 69.288897 | P86: Calculated value | Q86: Reported public data (Hist tabs)
A87: Reference: Microchip Technology depreciation (D&A less intangibles amortization) % of sales FY2026 | F87: =(Hist_Data!$G$35-Hist_Data!$G$12)/Hist_Data!$G$7 -> 0.054783476 | P87: Calculated value | Q87: Reported public data (Hist tabs)
A88: Opening balances at 31-Mar-2026 (calculated from base year)
A89: Opening accounts receivable | B89: $m | F89: =$F$33*$F$82/365 -> 164.38356 | P89: Calculated value | Q89: Base-year revenue x DSO / 365
A90: Opening finished-goods inventory | B90: $m | F90: =$F$68 -> 34.826574 | P90: Calculated value | Q90: Section D opening inventory value
A91: Opening accounts payable | B91: $m | F91: =$F$54*$F$83/365 -> 20.681523 | P91: Calculated value | Q91: Base-year variable cost x DPO / 365
A92: Opening operating working capital | B92: $m | F92: =F89+F90-F91 -> 178.52861 | P92: Calculated value | Q92: AR + inventory - AP
A94: H. Live scenario result - FY2027 P&L and cash flow
A95: Operating profit | F95: =PnL!$O$17 -> 406.02262 | P95: Calculated value
A96: Operating margin | F96: =PnL!$O$18 -> 0.34267964 | P96: Calculated value
A97: Net income | F97: =PnL!$O$21 -> 332.93855 | P97: Calculated value
A98: Free cash flow | F98: =FCF!$O$25 -> 325.0553 | P98: Calculated value
A99: FCF margin | F99: =FCF!$O$26 -> 0.27434391 | P99: Calculated value

Sheet Hist_Data
A1: Historical Data - Microchip Technology (reported)
A2: USD millions unless noted. Fiscal years end March 31. Blue = hardcoded reported value from SEC filing.
A3: Simulated data created for portfolio demonstration. It does not represent nonpublic Microchip Technology information. (This tab contains reported public data and calculated values only.)
A5: Line item | B5: Units | C5: FY2022 | D5: FY2023 | E5: FY2024 | F5: FY2025 | G5: FY2026 | H5: Classification | I5: Source (filing, statement page) | J5: Notes | K5: line_id
A6: Income statement
A7: Net sales | B7: $m | C7: 6820.9 | D7: 8438.7 | E7: 7634.4 | F7: 4401.6 | G7: 4713.1 | H7: Reported public data | I7: S-002 10-K FY2024 R5.htm; S-001 10-K FY2026 R5.htm | K7: net_sales
A8: Cost of sales | B8: $m | C8: 2371.3 | D8: 2740.8 | E8: 2638.7 | F8: 1933.7 | G8: 1992 | H8: Reported public data | I8: S-002 10-K FY2024 R5.htm; S-001 10-K FY2026 R5.htm | K8: cost_of_sales
A9: Gross profit | B9: $m | C9: 4449.6 | D9: 5697.9 | E9: 4995.7 | F9: 2467.9 | G9: 2721.1 | H9: Reported public data | I9: S-002 10-K FY2024 R5.htm; S-001 10-K FY2026 R5.htm | K9: gross_profit
A10: Research and development | B10: $m | C10: 989.1 | D10: 1118.3 | E10: 1097.4 | F10: 983.8 | G10: 1085.9 | H10: Reported public data | I10: S-002 10-K FY2024 R5.htm; S-001 10-K FY2026 R5.htm | K10: rd
A11: Selling, general and administrative | B11: $m | C11: 718.9 | D11: 797.7 | E11: 734.2 | F11: 617.7 | G11: 674.3 | H11: Reported public data | I11: S-002 10-K FY2024 R5.htm; S-001 10-K FY2026 R5.htm | K11: sga
A12: Amortization of acquired intangible assets | B12: $m | C12: 862.5 | D12: 669.9 | E12: 605.4 | F12: 490.9 | G12: 431.1 | H12: Reported public data | I12: S-002 10-K FY2024 R5.htm; S-001 10-K FY2026 R5.htm | K12: other_opex:amortization
A13: Special charges (income) and other, net | B13: $m | C13: 29.5 | D13: -4 | E13: -12.3 | F13: 79.2 | G13: 39.7 | H13: Reported public data | I13: S-002 10-K FY2024 R5.htm; S-001 10-K FY2026 R5.htm | J13: Printed '(income) charges' in FY2024 10-K; negative = income. | K13: other_opex:special
A14: Operating expenses (total) | B14: $m | C14: 2600 | D14: 2581.9 | E14: 2424.7 | F14: 2171.6 | G14: 2231 | H14: Reported public data | I14: S-002 10-K FY2024 R5.htm; S-001 10-K FY2026 R5.htm | K14: total_opex
A15: Operating income | B15: $m | C15: 1849.6 | D15: 3116 | E15: 2571 | F15: 296.3 | G15: 490.1 | H15: Reported public data | I15: S-002 10-K FY2024 R5.htm; S-001 10-K FY2026 R5.htm | K15: operating_income
A16: Interest income | B16: $m | C16: 0.5 | D16: 2.1 | E16: 7.6 | F16: 9.2 | G16: 11.4 | H16: Reported public data | I16: S-002 10-K FY2024 R5.htm; S-001 10-K FY2026 R5.htm | K16: nonop:interest_income
A17: Interest expense | B17: $m | C17: -257 | D17: -203.9 | E17: -198.3 | F17: -259.2 | G17: -221.3 | H17: Reported public data | I17: S-002 10-K FY2024 R5.htm; S-001 10-K FY2026 R5.htm | K17: nonop:interest_expense
A18: Loss on settlement of debt | B18: $m | C18: -113.4 | D18: -8.3 | E18: -12.2 | F18: -1.7 | G18: 0 | H18: Reported public data | I18: S-002 10-K FY2024 R5.htm; S-001 10-K FY2026 R5.htm | K18: nonop:loss_on_debt
A19: Other income (loss), net | B19: $m | C19: 2.8 | D19: 3.8 | E19: -2.2 | F19: -5.7 | G19: -6.7 | H19: Reported public data | I19: S-002 10-K FY2024 R5.htm; S-001 10-K FY2026 R5.htm | K19: nonop:other
A20: Income before income taxes | B20: $m | C20: 1482.5 | D20: 2909.7 | E20: 2365.9 | F20: 38.9 | G20: 273.5 | H20: Reported public data | I20: S-002 10-K FY2024 R5.htm; S-001 10-K FY2026 R5.htm | K20: pretax_income
A21: Income tax provision | B21: $m | C21: 197 | D21: 672 | E21: 459 | F21: 39.4 | G21: 43.5 | H21: Reported public data | I21: S-002 10-K FY2024 R5.htm; S-001 10-K FY2026 R5.htm | K21: income_tax
A22: Net income (loss) | B22: $m | C22: 1285.5 | D22: 2237.7 | E22: 1906.9 | F22: -0.5 | G22: 230 | H22: Reported public data | I22: S-002 10-K FY2024 R5.htm; S-001 10-K FY2026 R5.htm | K22: net_income
A23: Dividends on Series A Preferred Stock | B23: $m | E23: 0 | F23: -2.2 | G23: -111.2 | H23: Reported public data | I23: S-001 10-K FY2026 R5.htm | K23: memo:preferred_dividends
A24: Net income (loss) attributable to common stockholders | B24: $m | E24: 1906.9 | F24: -2.7 | G24: 118.8 | H24: Reported public data | I24: S-001 10-K FY2026 R5.htm | K24: memo:net_income_common
A25: Net sales by reported segment / product line
A26: Mixed-signal Microcontrollers | B26: $m | C26: 3814.8 | D26: 4755.7 | E26: 4272.4 | F26: 2249.7 | G26: 2355.4 | H26: Reported public data | I26: S-002 10-K FY2024 R45.htm; S-001 10-K FY2026 R43.htm | K26: segment:mixed_signal_microcontrollers
A27: Analog | B27: $m | C27: 1939.1 | D27: 2376.9 | E27: 2016.4 | F27: 1157 | G27: 1329 | H27: Reported public data | I27: S-002 10-K FY2024 R45.htm; S-001 10-K FY2026 R43.htm | K27: segment:analog
A28: Other (incl. FPGA, licensing, memory, timing) | B28: $m | C28: 1067 | D28: 1306.1 | E28: 1345.6 | F28: 994.9 | G28: 1028.7 | H28: Reported public data | I28: S-002 10-K FY2024 R45.htm; S-001 10-K FY2026 R43.htm | J28: Per 10-K Item 1: FPGA, licensing royalties & IP sales, engineering services, memory, timing systems, manufacturing services, legacy ASICs, aerospace. FPGA not reported separately. | K28: segment:other
A29: Other segment disclosures
A30: Semiconductor products - net sales | B30: $m | E30: 7531.1 | F30: 4270.5 | G30: 4549.3 | H30: Reported public data | I30: S-001 10-K FY2026 R45.htm | J30: Segment table first disclosed in this form in S-001 (covers FY2024-FY2026 only). | K30: segment_info:semis_sales
A31: Semiconductor products - gross profit | B31: $m | E31: 4892.4 | F31: 2336.8 | G31: 2557.3 | H31: Reported public data | I31: S-001 10-K FY2026 R45.htm | K31: segment_info:semis_gross_profit
A32: Technology licensing - net sales | B32: $m | E32: 103.3 | F32: 131.1 | G32: 163.8 | H32: Reported public data | I32: S-001 10-K FY2026 R45.htm | J32: Technology licensing has no cost of sales in the segment table. | K32: segment_info:licensing_sales
A33: Cash flow statement (selected lines)
A34: Net income (loss) | B34: $m | C34: 1285.5 | D34: 2237.7 | E34: 1906.9 | F34: -0.5 | G34: 230 | H34: Reported public data | I34: S-002 10-K FY2024 R7.htm; S-001 10-K FY2026 R7.htm | K34: cf:net_income
A35: Depreciation and amortization | B35: $m | C35: 1143.5 | D35: 998.4 | E35: 879.5 | F35: 750.1 | G35: 689.3 | H35: Reported public data | I35: S-002 10-K FY2024 R7.htm; S-001 10-K FY2026 R7.htm | K35: cf:da
A36: Share-based compensation expense | B36: $m | C36: 210.2 | D36: 170.4 | E36: 177.5 | F36: 180.4 | G36: 255.4 | H36: Reported public data | I36: S-002 10-K FY2024 R7.htm; S-001 10-K FY2026 R7.htm | K36: cf:sbc
A37: (Increase) decrease in accounts receivable | B37: $m | C37: -74.9 | D37: -232.7 | E37: 161.6 | F37: 454 | G37: -204.5 | H37: Reported public data | I37: S-002 10-K FY2024 R7.htm; S-001 10-K FY2026 R7.htm | K37: wc:receivables
A38: Decrease (increase) in inventories | B38: $m | C38: -177.8 | D38: -483.2 | E38: 12.8 | F38: 31.6 | G38: 264.3 | H38: Reported public data | I38: S-002 10-K FY2024 R7.htm; S-001 10-K FY2026 R7.htm | K38: wc:inventories
A39: Increase (decrease) in accounts payable and accrued liabilities | B39: $m | C39: 192.7 | D39: 323.4 | E39: -148.4 | F39: -345.6 | G39: 26 | H39: Reported public data | I39: S-002 10-K FY2024 R7.htm; S-001 10-K FY2026 R7.htm | K39: wc:payables_accrued
A40: Change in other assets and liabilities | B40: $m | C40: 79.4 | D40: 404.5 | E40: -64.2 | F40: -38.1 | G40: -105.8 | H40: Reported public data | I40: S-002 10-K FY2024 R7.htm; S-001 10-K FY2026 R7.htm | K40: wc:other
A41: Change in income tax payable | B41: $m | C41: 14.8 | D41: -28 | E41: -38.5 | F41: -1.8 | G41: -147.7 | H41: Reported public data | I41: S-002 10-K FY2024 R7.htm; S-001 10-K FY2026 R7.htm | K41: wc:income_tax
A42: Net cash provided by operating activities | B42: $m | C42: 2842.7 | D42: 3621 | E42: 2892.7 | F42: 898.1 | G42: 962.1 | H42: Reported public data | I42: S-002 10-K FY2024 R7.htm; S-001 10-K FY2026 R7.htm | K42: cf:cfo
A43: Capital expenditures (printed negative) | B43: $m | C43: -370.1 | D43: -486.2 | E43: -285.1 | F43: -126 | G43: -91.1 | H43: Reported public data | I43: S-002 10-K FY2024 R7.htm; S-001 10-K FY2026 R7.htm | J43: Printed as a cash outflow (negative). Analysis converts to positive spend. | K43: cf:capex
A44: Net cash used in investing activities | B44: $m | C44: -477.7 | D44: -599.5 | E44: -392.1 | F44: -287.8 | G44: -195.5 | H44: Reported public data | I44: S-002 10-K FY2024 R7.htm; S-001 10-K FY2026 R7.htm | K44: cf:cfi
A45: Net cash used in financing activities | B45: $m | C45: -2327.6 | D45: -3104.9 | E45: -2414.9 | F45: -158.3 | G45: -1298 | H45: Reported public data | I45: S-002 10-K FY2024 R7.htm; S-001 10-K FY2026 R7.htm | K45: cf:cff
A46: Payment of cash dividends on common stock | B46: $m | C46: -503.8 | D46: -695.3 | E46: -911.5 | F46: -975.7 | G46: -984 | H46: Reported public data | I46: S-002 10-K FY2024 R7.htm; S-001 10-K FY2026 R7.htm | J46: FY2022-FY2023 printed as 'Payment of cash dividends' (no preferred stock outstanding then). | K46: cf:dividends
A47: Cash and cash equivalents, end of period | B47: $m | C47: 317.4 | D47: 234 | E47: 319.7 | F47: 771.7 | G47: 240.3 | H47: Reported public data | I47: S-002 10-K FY2024 R7.htm; S-001 10-K FY2026 R7.htm | K47: cf:cash_end
A48: Balance sheet (period-end, selected lines)
A49: Cash and cash equivalents | B49: $m | C49: 317.4 | D49: 234 | E49: 319.7 | F49: 771.7 | G49: 240.3 | H49: Reported public data | I49: S-003 10-K FY2023 R3.htm; S-002 10-K FY2024 R3.htm; S-001 10-K FY2026 R3.htm | K49: bs:cash
A50: Accounts receivable, net | B50: $m | C50: 1072.6 | D50: 1305.3 | E50: 1143.7 | F50: 689.7 | G50: 894.7 | H50: Reported public data | I50: S-003 10-K FY2023 R3.htm; S-002 10-K FY2024 R3.htm; S-001 10-K FY2026 R3.htm | K50: bs:receivables
A51: Inventories | B51: $m | C51: 854.4 | D51: 1324.9 | E51: 1316 | F51: 1293.5 | G51: 1035.4 | H51: Reported public data | I51: S-003 10-K FY2023 R3.htm; S-002 10-K FY2024 R3.htm; S-001 10-K FY2026 R3.htm | J51: Microchip's own reported inventory days use quarterly COGS, so they differ from the annual DIO in Hist_Analysis. | K51: bs:inventories
A52: Other current assets | B52: $m | C52: 206.2 | D52: 205.1 | E52: 233.6 | F52: 236.4 | G52: 207.2 | H52: Reported public data | I52: S-003 10-K FY2023 R3.htm; S-002 10-K FY2024 R3.htm; S-001 10-K FY2026 R3.htm | K52: bs:other_current_assets
A53: Total current assets | B53: $m | C53: 2452.6 | D53: 3069.3 | E53: 3013 | F53: 2991.3 | G53: 2377.6 | H53: Reported public data | I53: S-003 10-K FY2023 R3.htm; S-002 10-K FY2024 R3.htm; S-001 10-K FY2026 R3.htm | K53: bs:total_current_assets
A54: Property, plant and equipment, net | B54: $m | C54: 967.9 | D54: 1177.9 | E54: 1194.6 | F54: 1183.7 | G54: 1106.7 | H54: Reported public data | I54: S-003 10-K FY2023 R3.htm; S-002 10-K FY2024 R3.htm; S-001 10-K FY2026 R3.htm | K54: bs:ppe
A55: Total assets | B55: $m | C55: 16199.5 | D55: 16370.3 | E55: 15873.2 | F55: 15374.6 | G55: 14370.1 | H55: Reported public data | I55: S-003 10-K FY2023 R3.htm; S-002 10-K FY2024 R3.htm; S-001 10-K FY2026 R3.htm | K55: bs:total_assets
A56: Accounts payable | B56: $m | C56: 344.7 | D56: 396.9 | E56: 213 | F56: 160.6 | G56: 205.6 | H56: Reported public data | I56: S-003 10-K FY2023 R3.htm; S-002 10-K FY2024 R3.htm; S-001 10-K FY2026 R3.htm | K56: bs:payables
A57: Accrued liabilities | B57: $m | C57: 1054.3 | D57: 1323.5 | E57: 1307 | F57: 994.5 | G57: 930.7 | H57: Reported public data | I57: S-003 10-K FY2023 R3.htm; S-002 10-K FY2024 R3.htm; S-001 10-K FY2026 R3.htm | K57: bs:accrued
A58: Current portion of long-term debt | B58: $m | C58: 0 | D58: 1398.2 | E58: 999.4 | H58: Reported public data | I58: S-003 10-K FY2023 R3.htm; S-002 10-K FY2024 R3.htm | J58: FY2025-FY2026: no current-debt line presented on the balance sheet (blank, treated as 0 in checks). | K58: bs:current_debt
A59: Total current liabilities | B59: $m | C59: 1399 | D59: 3118.6 | E59: 2519.4 | F59: 1155.1 | G59: 1136.3 | H59: Reported public data | I59: S-003 10-K FY2023 R3.htm; S-002 10-K FY2024 R3.htm; S-001 10-K FY2026 R3.htm | K59: bs:total_current_liabilities
A60: Long-term debt | B60: $m | C60: 7687.4 | D60: 5041.7 | E60: 5000.4 | F60: 5630.4 | G60: 5496.4 | H60: Reported public data | I60: S-003 10-K FY2023 R3.htm; S-002 10-K FY2024 R3.htm; S-001 10-K FY2026 R3.htm | K60: bs:long_term_debt
A61: Total stockholders' equity | B61: $m | C61: 5894.8 | D61: 6513.6 | E61: 6657.8 | F61: 7078.3 | G61: 6432.4 | H61: Reported public data | I61: S-003 10-K FY2023 R3.htm; S-002 10-K FY2024 R3.htm; S-001 10-K FY2026 R3.htm | K61: bs:equity
A62: Short-term investments | B62: $m | C62: 2 | D62: 0 | H62: Reported public data | I62: S-003 10-K FY2023 R3.htm | J62: Printed only in the FY2023 10-K (FY2022 2.0, FY2023 0.0); blank = not presented, treated as 0. | K62: bs:st_investments
A63: Inventory detail
A64: Raw materials | B64: $m | F64: 174.8 | G64: 135.1 | H64: Reported public data | I64: S-001 10-K FY2026 R68.htm | K64: inv:raw_materials
A65: Work in process | B65: $m | F65: 857.6 | G65: 731.4 | H65: Reported public data | I65: S-001 10-K FY2026 R68.htm | K65: inv:work_in_process
A66: Finished goods | B66: $m | F66: 261.1 | G66: 168.9 | H66: Reported public data | I66: S-001 10-K FY2026 R68.htm | K66: inv:finished_goods
A68: Quarterly context - first fiscal quarter (April-June)
A69: Line item | B69: Units | C69: Q1 FY2026 | D69: Q1 FY2027 | H69: Classification | I69: Source | J69: Notes | K69: line_id
A70: Net sales | B70: $m | C70: 1075.5 | D70: 1484.7 | H70: Reported public data | I70: S-004 10-Q Q1 FY2027 mchp-20260630.htm | J70: Q1 FY2026 = prior-year comparative column | K70: net_sales
A71: Mixed-signal Microcontrollers | B71: $m | C71: 532.6 | D71: 739.1 | H71: Reported public data | I71: S-004 10-Q Q1 FY2027 mchp-20260630.htm | K71: segment:mixed_signal_microcontrollers
A72: Analog | B72: $m | C72: 316.2 | D72: 410.9 | H72: Reported public data | I72: S-004 10-Q Q1 FY2027 mchp-20260630.htm | K72: segment:analog
A73: Other (incl. FPGA, licensing, memory, timing) | B73: $m | C73: 226.7 | D73: 334.7 | H73: Reported public data | I73: S-004 10-Q Q1 FY2027 mchp-20260630.htm | K73: segment:other
A75: Operating facts stated in the FY2026 annual report (approximate, as stated)
A76: Share of sales from products made in own wafer fabs | B76: % | G76: 0.35 | H76: Reported public data | I76: S-001 10-K FY2026 (annual report, Item 1) | J76: Percent, not USD millions. Approximate figures as stated ('approximately'). | K76: fact:own_fab_share
A77: Share of sales from products made at outside foundries | B77: % | G77: 0.65 | H77: Reported public data | I77: S-001 10-K FY2026 (annual report, Item 1) | J77: Percent, not USD millions. Approximate figures as stated ('approximately'). | K77: fact:foundry_share
A78: Share of assembly performed internally | B78: % | G78: 0.67 | H78: Reported public data | I78: S-001 10-K FY2026 (annual report, Item 1) | J78: Percent, not USD millions. Approximate figures as stated ('approximately'). | K78: fact:internal_assembly_share
A79: Share of test performed internally | B79: % | G79: 0.69 | H79: Reported public data | I79: S-001 10-K FY2026 (annual report, Item 1) | J79: Percent, not USD millions. Approximate figures as stated ('approximately'). | K79: fact:internal_test_share

Sheet Hist_Analysis
A1: Historical Financial Analysis - Microchip Technology
A2: All figures are formulas on Hist_Data. Green = direct link to Hist_Data; black = calculation.
A3: Simulated data created for portfolio demonstration. It does not represent nonpublic Microchip Technology information. (This tab contains reported public data and calculated values only.)
A5: Metric | B5: Units | C5: FY2022 | D5: FY2023 | E5: FY2024 | F5: FY2025 | G5: FY2026 | H5: Classification | I5: Formula / definition
A6: Growth and profitability
A7: Net sales | B7: $m | C7: =Hist_Data!$C$7 -> 6820.9 | D7: =Hist_Data!$D$7 -> 8438.7 | E7: =Hist_Data!$E$7 -> 7634.4 | F7: =Hist_Data!$F$7 -> 4401.6 | G7: =Hist_Data!$G$7 -> 4713.1 | H7: Calculated value | I7: Link: Hist_Data net sales
A8: Net sales growth | B8: % | C8: n/a | D8: =IFERROR(Hist_Data!$D$7/Hist_Data!$C$7-1,"") -> 0.23718278 | E8: =IFERROR(Hist_Data!$E$7/Hist_Data!$D$7-1,"") -> -0.095310889 | F8: =IFERROR(Hist_Data!$F$7/Hist_Data!$E$7-1,"") -> -0.42345174 | G8: =IFERROR(Hist_Data!$G$7/Hist_Data!$F$7-1,"") -> 0.07076972 | H8: Calculated value | I8: Net sales / prior-year net sales - 1
A9: Gross margin | B9: % | C9: =IFERROR(Hist_Data!$C$9/Hist_Data!$C$7,"") -> 0.65234793 | D9: =IFERROR(Hist_Data!$D$9/Hist_Data!$D$7,"") -> 0.67521064 | E9: =IFERROR(Hist_Data!$E$9/Hist_Data!$E$7,"") -> 0.65436708 | F9: =IFERROR(Hist_Data!$F$9/Hist_Data!$F$7,"") -> 0.56068248 | G9: =IFERROR(Hist_Data!$G$9/Hist_Data!$G$7,"") -> 0.57734824 | H9: Calculated value | I9: Gross profit / net sales
A10: R&D % of sales | B10: % | C10: =IFERROR(Hist_Data!$C$10/Hist_Data!$C$7,"") -> 0.14501019 | D10: =IFERROR(Hist_Data!$D$10/Hist_Data!$D$7,"") -> 0.13252041 | E10: =IFERROR(Hist_Data!$E$10/Hist_Data!$E$7,"") -> 0.14374411 | F10: =IFERROR(Hist_Data!$F$10/Hist_Data!$F$7,"") -> 0.22350963 | G10: =IFERROR(Hist_Data!$G$10/Hist_Data!$G$7,"") -> 0.23040037 | H10: Calculated value | I10: Research and development / net sales
A11: SG&A % of sales | B11: % | C11: =IFERROR(Hist_Data!$C$11/Hist_Data!$C$7,"") -> 0.10539665 | D11: =IFERROR(Hist_Data!$D$11/Hist_Data!$D$7,"") -> 0.094528778 | E11: =IFERROR(Hist_Data!$E$11/Hist_Data!$E$7,"") -> 0.096169968 | F11: =IFERROR(Hist_Data!$F$11/Hist_Data!$F$7,"") -> 0.14033533 | G11: =IFERROR(Hist_Data!$G$11/Hist_Data!$G$7,"") -> 0.14306932 | H11: Calculated value | I11: SG&A / net sales
A12: Operating margin (GAAP) | B12: % | C12: =IFERROR(Hist_Data!$C$15/Hist_Data!$C$7,"") -> 0.27116656 | D12: =IFERROR(Hist_Data!$D$15/Hist_Data!$D$7,"") -> 0.36925119 | E12: =IFERROR(Hist_Data!$E$15/Hist_Data!$E$7,"") -> 0.33676517 | F12: =IFERROR(Hist_Data!$F$15/Hist_Data!$F$7,"") -> 0.06731643 | G12: =IFERROR(Hist_Data!$G$15/Hist_Data!$G$7,"") -> 0.10398676 | H12: Calculated value | I12: Operating income / net sales
A13: Other operating items (sum of reported components) | B13: $m | C13: =(N(Hist_Data!$C$12)+N(Hist_Data!$C$13)) -> 892 | D13: =(N(Hist_Data!$D$12)+N(Hist_Data!$D$13)) -> 665.9 | E13: =(N(Hist_Data!$E$12)+N(Hist_Data!$E$13)) -> 593.1 | F13: =(N(Hist_Data!$F$12)+N(Hist_Data!$F$13)) -> 570.1 | G13: =(N(Hist_Data!$G$12)+N(Hist_Data!$G$13)) -> 470.8 | H13: Calculated value | I13: Sum of: amortization of acquired intangible assets, special charges (income) and other, net
A14: Operating income before other operating items | B14: $m | C14: =Hist_Data!$C$15+$C$13 -> 2741.6 | D14: =Hist_Data!$D$15+$D$13 -> 3781.9 | E14: =Hist_Data!$E$15+$E$13 -> 3164.1 | F14: =Hist_Data!$F$15+$F$13 -> 866.4 | G14: =Hist_Data!$G$15+$G$13 -> 960.9 | H14: Calculated value | I14: Operating income + other operating items (amortization of acquired intangible assets, special charges (income) and other, net). Analyst calculation - NOT Microchip Technology's reported non-GAAP measure.
A15: Margin before other operating items | B15: % | C15: =IFERROR($C$14/Hist_Data!$C$7,"") -> 0.40194109 | D15: =IFERROR($D$14/Hist_Data!$D$7,"") -> 0.44816145 | E15: =IFERROR($E$14/Hist_Data!$E$7,"") -> 0.414453 | F15: =IFERROR($F$14/Hist_Data!$F$7,"") -> 0.19683751 | G15: =IFERROR($G$14/Hist_Data!$G$7,"") -> 0.20387855 | H15: Calculated value | I15: Row above / net sales. Closest proxy for a product division's operating margin.
A16: Net margin | B16: % | C16: =IFERROR(Hist_Data!$C$22/Hist_Data!$C$7,"") -> 0.18846487 | D16: =IFERROR(Hist_Data!$D$22/Hist_Data!$D$7,"") -> 0.26517118 | E16: =IFERROR(Hist_Data!$E$22/Hist_Data!$E$7,"") -> 0.24977732 | F16: =IFERROR(Hist_Data!$F$22/Hist_Data!$F$7,"") -> -0.00011359506 | G16: =IFERROR(Hist_Data!$G$22/Hist_Data!$G$7,"") -> 0.048800153 | H16: Calculated value | I16: Net income / net sales
A17: Effective tax rate | B17: % | C17: =IF(ABS(Hist_Data!$C$20)<0.02*Hist_Data!$C$7,"n.m.",IFERROR(Hist_Data!$C$21/Hist_Data!$C$20,"")) -> 0.13288364 | D17: =IF(ABS(Hist_Data!$D$20)<0.02*Hist_Data!$D$7,"n.m.",IFERROR(Hist_Data!$D$21/Hist_Data!$D$20,"")) -> 0.23095164 | E17: =IF(ABS(Hist_Data!$E$20)<0.02*Hist_Data!$E$7,"n.m.",IFERROR(Hist_Data!$E$21/Hist_Data!$E$20,"")) -> 0.19400651 | F17: =IF(ABS(Hist_Data!$F$20)<0.02*Hist_Data!$F$7,"n.m.",IFERROR(Hist_Data!$F$21/Hist_Data!$F$20,"")) -> n.m. | G17: =IF(ABS(Hist_Data!$G$20)<0.02*Hist_Data!$G$7,"n.m.",IFERROR(Hist_Data!$G$21/Hist_Data!$G$20,"")) -> 0.15904936 | H17: Calculated value | I17: Income tax / income before taxes. Shows n.m. (not meaningful) when pre-tax income is under 2% of sales.
A18: Incremental gross margin (change in GP / change in sales) | B18: % | C18: n/a | D18: =IFERROR((Hist_Data!$D$9-Hist_Data!$C$9)/(Hist_Data!$D$7-Hist_Data!$C$7),"") -> 0.77160341 | E18: =IFERROR((Hist_Data!$E$9-Hist_Data!$D$9)/(Hist_Data!$E$7-Hist_Data!$D$7),"") -> 0.87305732 | F18: =IFERROR((Hist_Data!$F$9-Hist_Data!$E$9)/(Hist_Data!$F$7-Hist_Data!$E$7),"") -> 0.78192279 | G18: =IFERROR((Hist_Data!$G$9-Hist_Data!$F$9)/(Hist_Data!$G$7-Hist_Data!$F$7),"") -> 0.81284109 | H18: Calculated value | I18: Shows operating leverage: how much gross profit moved per $1 of sales change (fixed-cost absorption)
A19: Reported segment / product-line mix and growth
A20: Mixed-signal Microcontrollers - share of net sales | B20: % | C20: =IFERROR(Hist_Data!$C$26/Hist_Data!$C$7,"") -> 0.55928103 | D20: =IFERROR(Hist_Data!$D$26/Hist_Data!$D$7,"") -> 0.56355837 | E20: =IFERROR(Hist_Data!$E$26/Hist_Data!$E$7,"") -> 0.55962486 | F20: =IFERROR(Hist_Data!$F$26/Hist_Data!$F$7,"") -> 0.5111096 | G20: =IFERROR(Hist_Data!$G$26/Hist_Data!$G$7,"") -> 0.499756 | H20: Calculated value | I20: Mixed-signal Microcontrollers sales / net sales
A21: Analog - share of net sales | B21: % | C21: =IFERROR(Hist_Data!$C$27/Hist_Data!$C$7,"") -> 0.284288 | D21: =IFERROR(Hist_Data!$D$27/Hist_Data!$D$7,"") -> 0.28166661 | E21: =IFERROR(Hist_Data!$E$27/Hist_Data!$E$7,"") -> 0.2641203 | F21: =IFERROR(Hist_Data!$F$27/Hist_Data!$F$7,"") -> 0.26285896 | G21: =IFERROR(Hist_Data!$G$27/Hist_Data!$G$7,"") -> 0.28198001 | H21: Calculated value | I21: Analog sales / net sales
A22: Other (incl. FPGA, licensing, memory, timing) - share of net sales | B22: % | C22: =IFERROR(Hist_Data!$C$28/Hist_Data!$C$7,"") -> 0.15643097 | D22: =IFERROR(Hist_Data!$D$28/Hist_Data!$D$7,"") -> 0.15477502 | E22: =IFERROR(Hist_Data!$E$28/Hist_Data!$E$7,"") -> 0.17625485 | F22: =IFERROR(Hist_Data!$F$28/Hist_Data!$F$7,"") -> 0.22603144 | G22: =IFERROR(Hist_Data!$G$28/Hist_Data!$G$7,"") -> 0.21826399 | H22: Calculated value | I22: Other (incl. FPGA, licensing, memory, timing) sales / net sales
A23: Mix total (must equal 100%) | B23: % | C23: =$C$20+$C$21+$C$22 -> 1 | D23: =$D$20+$D$21+$D$22 -> 1 | E23: =$E$20+$E$21+$E$22 -> 1 | F23: =$F$20+$F$21+$F$22 -> 1 | G23: =$G$20+$G$21+$G$22 -> 1 | H23: Calculated value | I23: Sum of the segment shares
A24: Mixed-signal Microcontrollers - growth | B24: % | C24: n/a | D24: =IFERROR(Hist_Data!$D$26/Hist_Data!$C$26-1,"") -> 0.24664465 | E24: =IFERROR(Hist_Data!$E$26/Hist_Data!$D$26-1,"") -> -0.10162542 | F24: =IFERROR(Hist_Data!$F$26/Hist_Data!$E$26-1,"") -> -0.47343414 | G24: =IFERROR(Hist_Data!$G$26/Hist_Data!$F$26-1,"") -> 0.046984042 | H24: Calculated value | I24: Mixed-signal Microcontrollers sales / prior year - 1
A25: Analog - growth | B25: % | C25: n/a | D25: =IFERROR(Hist_Data!$D$27/Hist_Data!$C$27-1,"") -> 0.22577484 | E25: =IFERROR(Hist_Data!$E$27/Hist_Data!$D$27-1,"") -> -0.15166814 | F25: =IFERROR(Hist_Data!$F$27/Hist_Data!$E$27-1,"") -> -0.42620512 | G25: =IFERROR(Hist_Data!$G$27/Hist_Data!$F$27-1,"") -> 0.14866033 | H25: Calculated value | I25: Analog sales / prior year - 1
A26: Other (incl. FPGA, licensing, memory, timing) - growth | B26: % | C26: n/a | D26: =IFERROR(Hist_Data!$D$28/Hist_Data!$C$28-1,"") -> 0.22408622 | E26: =IFERROR(Hist_Data!$E$28/Hist_Data!$D$28-1,"") -> 0.030242707 | F26: =IFERROR(Hist_Data!$F$28/Hist_Data!$E$28-1,"") -> -0.26062723 | G26: =IFERROR(Hist_Data!$G$28/Hist_Data!$F$28-1,"") -> 0.033973264 | H26: Calculated value | I26: Other (incl. FPGA, licensing, memory, timing) sales / prior year - 1
A27: Cash flow and free cash flow (project definition)
A28: Net income | B28: $m | C28: =Hist_Data!$C$22 -> 1285.5 | D28: =Hist_Data!$D$22 -> 2237.7 | E28: =Hist_Data!$E$22 -> 1906.9 | F28: =Hist_Data!$F$22 -> -0.5 | G28: =Hist_Data!$G$22 -> 230 | H28: Calculated value | I28: Link: Hist_Data net income
A29: Depreciation and amortization | B29: $m | C29: =Hist_Data!$C$35 -> 1143.5 | D29: =Hist_Data!$D$35 -> 998.4 | E29: =Hist_Data!$E$35 -> 879.5 | F29: =Hist_Data!$F$35 -> 750.1 | G29: =Hist_Data!$G$35 -> 689.3 | H29: Calculated value | I29: Link: Hist_Data D&A (cash flow statement)
A30: Capital expenditures (positive = spend) | B30: $m | C30: =-Hist_Data!$C$43 -> 370.1 | D30: =-Hist_Data!$D$43 -> 486.2 | E30: =-Hist_Data!$E$43 -> 285.1 | F30: =-Hist_Data!$F$43 -> 126 | G30: =-Hist_Data!$G$43 -> 91.1 | H30: Calculated value | I30: Negative of capex as printed. Cash-flow statement prints capex negative.
A31: Increase in working capital | B31: $m | C31: =-(N(Hist_Data!$C$37)+N(Hist_Data!$C$38)+N(Hist_Data!$C$39)+N(Hist_Data!$C$40)+N(Hist_Data!$C$41)) -> -34.2 | D31: =-(N(Hist_Data!$D$37)+N(Hist_Data!$D$38)+N(Hist_Data!$D$39)+N(Hist_Data!$D$40)+N(Hist_Data!$D$41)) -> 16 | E31: =-(N(Hist_Data!$E$37)+N(Hist_Data!$E$38)+N(Hist_Data!$E$39)+N(Hist_Data!$E$40)+N(Hist_Data!$E$41)) -> 76.7 | F31: =-(N(Hist_Data!$F$37)+N(Hist_Data!$F$38)+N(Hist_Data!$F$39)+N(Hist_Data!$F$40)+N(Hist_Data!$F$41)) -> -100.1 | G31: =-(N(Hist_Data!$G$37)+N(Hist_Data!$G$38)+N(Hist_Data!$G$39)+N(Hist_Data!$G$40)+N(Hist_Data!$G$41)) -> 167.7 | H31: Calculated value | I31: Negative of the sum of the 5 cash-flow working-capital lines. Positive = cash absorbed by working capital.
A32: Free cash flow (project definition) | B32: $m | C32: =$C$28+$C$29-$C$30-$C$31 -> 2093.1 | D32: =$D$28+$D$29-$D$30-$D$31 -> 2733.9 | E32: =$E$28+$E$29-$E$30-$E$31 -> 2424.6 | F32: =$F$28+$F$29-$F$30-$F$31 -> 723.7 | G32: =$G$28+$G$29-$G$30-$G$31 -> 660.5 | H32: Calculated value | I32: Net income + D&A - capex - increase in working capital (project formula)
A33: Other non-cash items in CFO (SBC, deferred tax, other) | B33: $m | C33: =Hist_Data!$C$42-$C$28-$C$29+$C$31 -> 379.5 | D33: =Hist_Data!$D$42-$D$28-$D$29+$D$31 -> 400.9 | E33: =Hist_Data!$E$42-$E$28-$E$29+$E$31 -> 183 | F33: =Hist_Data!$F$42-$F$28-$F$29+$F$31 -> 48.4 | G33: =Hist_Data!$G$42-$G$28-$G$29+$G$31 -> 210.5 | H33: Calculated value | I33: CFO - net income - D&A + increase in WC. Explains the gap to the CFO-based FCF below.
A34: Free cash flow (CFO - capex, common market definition) | B34: $m | C34: =Hist_Data!$C$42-$C$30 -> 2472.6 | D34: =Hist_Data!$D$42-$D$30 -> 3134.8 | E34: =Hist_Data!$E$42-$E$30 -> 2607.6 | F34: =Hist_Data!$F$42-$F$30 -> 772.1 | G34: =Hist_Data!$G$42-$G$30 -> 871 | H34: Calculated value | I34: Net cash from operations - capex. Reconciles to project FCF + other non-cash items (see Checks).
A35: FCF margin (project definition) | B35: % | C35: =IFERROR($C$32/Hist_Data!$C$7,"") -> 0.30686566 | D35: =IFERROR($D$32/Hist_Data!$D$7,"") -> 0.3239717 | E35: =IFERROR($E$32/Hist_Data!$E$7,"") -> 0.31758881 | F35: =IFERROR($F$32/Hist_Data!$F$7,"") -> 0.16441748 | G35: =IFERROR($G$32/Hist_Data!$G$7,"") -> 0.14014131 | H35: Calculated value | I35: Project FCF / net sales
A36: FCF conversion (project FCF / net income) | B36: x | C36: =IF(ABS($C$28)<0.02*Hist_Data!$C$7,"n.m.",IFERROR($C$32/$C$28,"")) -> 1.628238 | D36: =IF(ABS($D$28)<0.02*Hist_Data!$D$7,"n.m.",IFERROR($D$32/$D$28,"")) -> 1.2217455 | E36: =IF(ABS($E$28)<0.02*Hist_Data!$E$7,"n.m.",IFERROR($E$32/$E$28,"")) -> 1.2714878 | F36: =IF(ABS($F$28)<0.02*Hist_Data!$F$7,"n.m.",IFERROR($F$32/$F$28,"")) -> n.m. | G36: =IF(ABS($G$28)<0.02*Hist_Data!$G$7,"n.m.",IFERROR($G$32/$G$28,"")) -> 2.8717391 | H36: Calculated value | I36: Project FCF / net income. Shows n.m. when net income is under 2% of sales.
A37: Capex % of sales | B37: % | C37: =IFERROR($C$30/Hist_Data!$C$7,"") -> 0.054259702 | D37: =IFERROR($D$30/Hist_Data!$D$7,"") -> 0.057615509 | E37: =IFERROR($E$30/Hist_Data!$E$7,"") -> 0.037344127 | F37: =IFERROR($F$30/Hist_Data!$F$7,"") -> 0.028625954 | G37: =IFERROR($G$30/Hist_Data!$G$7,"") -> 0.019329104 | H37: Calculated value | I37: Capex / net sales - anchor for the forecast capex assumption
A38: D&A % of sales | B38: % | C38: =IFERROR(Hist_Data!$C$35/Hist_Data!$C$7,"") -> 0.1676465 | D38: =IFERROR(Hist_Data!$D$35/Hist_Data!$D$7,"") -> 0.11831206 | E38: =IFERROR(Hist_Data!$E$35/Hist_Data!$E$7,"") -> 0.11520224 | F38: =IFERROR(Hist_Data!$F$35/Hist_Data!$F$7,"") -> 0.1704153 | G38: =IFERROR(Hist_Data!$G$35/Hist_Data!$G$7,"") -> 0.14625194 | H38: Calculated value | I38: D&A / net sales
A39: Share-based compensation % of sales | B39: % | C39: =IFERROR(Hist_Data!$C$36/Hist_Data!$C$7,"") -> 0.030817048 | D39: =IFERROR(Hist_Data!$D$36/Hist_Data!$D$7,"") -> 0.020192684 | E39: =IFERROR(Hist_Data!$E$36/Hist_Data!$E$7,"") -> 0.023250026 | F39: =IFERROR(Hist_Data!$F$36/Hist_Data!$F$7,"") -> 0.040985096 | G39: =IFERROR(Hist_Data!$G$36/Hist_Data!$G$7,"") -> 0.054189387 | H39: Calculated value | I39: SBC / net sales
A40: Capex / depreciation & amortization | B40: x | C40: =IFERROR($C$30/Hist_Data!$C$35,"") -> 0.32365544 | D40: =IFERROR($D$30/Hist_Data!$D$35,"") -> 0.48697917 | E40: =IFERROR($E$30/Hist_Data!$E$35,"") -> 0.32416146 | F40: =IFERROR($F$30/Hist_Data!$F$35,"") -> 0.1679776 | G40: =IFERROR($G$30/Hist_Data!$G$35,"") -> 0.13216306 | H40: Calculated value | I40: <1.0x means spending less than D&A (asset base shrinking or amortization-heavy D&A)
A41: Working capital and asset efficiency (year-end balances)
A42: Days sales outstanding (DSO) | B42: days | C42: =IFERROR(Hist_Data!$C$50/Hist_Data!$C$7*365,"") -> 57.396971 | D42: =IFERROR(Hist_Data!$D$50/Hist_Data!$D$7*365,"") -> 56.458281 | E42: =IFERROR(Hist_Data!$E$50/Hist_Data!$E$7*365,"") -> 54.680198 | F42: =IFERROR(Hist_Data!$F$50/Hist_Data!$F$7*365,"") -> 57.192953 | G42: =IFERROR(Hist_Data!$G$50/Hist_Data!$G$7*365,"") -> 69.288897 | H42: Calculated value | I42: Accounts receivable / net sales x 365
A43: Days inventory outstanding (DIO) | B43: days | C43: =IFERROR(Hist_Data!$C$51/Hist_Data!$C$8*365,"") -> 131.51267 | D43: =IFERROR(Hist_Data!$D$51/Hist_Data!$D$8*365,"") -> 176.44064 | E43: =IFERROR(Hist_Data!$E$51/Hist_Data!$E$8*365,"") -> 182.03661 | F43: =IFERROR(Hist_Data!$F$51/Hist_Data!$F$8*365,"") -> 244.15757 | G43: =IFERROR(Hist_Data!$G$51/Hist_Data!$G$8*365,"") -> 189.71938 | H43: Calculated value | I43: Inventories / annual cost of sales x 365 (company-reported days often use quarterly COGS, so they can differ).
A44: Days payable outstanding (DPO) | B44: days | C44: =IFERROR(Hist_Data!$C$56/Hist_Data!$C$8*365,"") -> 53.057606 | D44: =IFERROR(Hist_Data!$D$56/Hist_Data!$D$8*365,"") -> 52.856283 | E44: =IFERROR(Hist_Data!$E$56/Hist_Data!$E$8*365,"") -> 29.463372 | F44: =IFERROR(Hist_Data!$F$56/Hist_Data!$F$8*365,"") -> 30.314423 | G44: =IFERROR(Hist_Data!$G$56/Hist_Data!$G$8*365,"") -> 37.672691 | H44: Calculated value | I44: Accounts payable / cost of sales x 365
A45: Cash conversion cycle | B45: days | C45: =$C$42+$C$43-$C$44 -> 135.85204 | D45: =$D$42+$D$43-$D$44 -> 180.04264 | E45: =$E$42+$E$43-$E$44 -> 207.25343 | F45: =$F$42+$F$43-$F$44 -> 271.0361 | G45: =$G$42+$G$43-$G$44 -> 221.33558 | H45: Calculated value | I45: DSO + DIO - DPO
A46: Operating working capital | B46: $m | C46: =Hist_Data!$C$50+Hist_Data!$C$51+N(Hist_Data!$C$52)-Hist_Data!$C$56-N(Hist_Data!$C$57) -> 734.2 | D46: =Hist_Data!$D$50+Hist_Data!$D$51+N(Hist_Data!$D$52)-Hist_Data!$D$56-N(Hist_Data!$D$57) -> 1114.9 | E46: =Hist_Data!$E$50+Hist_Data!$E$51+N(Hist_Data!$E$52)-Hist_Data!$E$56-N(Hist_Data!$E$57) -> 1173.3 | F46: =Hist_Data!$F$50+Hist_Data!$F$51+N(Hist_Data!$F$52)-Hist_Data!$F$56-N(Hist_Data!$F$57) -> 1064.5 | G46: =Hist_Data!$G$50+Hist_Data!$G$51+N(Hist_Data!$G$52)-Hist_Data!$G$56-N(Hist_Data!$G$57) -> 1001 | H46: Calculated value | I46: AR + inventories + other current assets - AP - accrued liabilities (excludes cash and debt)
A47: Operating working capital % of sales | B47: % | C47: =IFERROR($C$46/Hist_Data!$C$7,"") -> 0.10763975 | D47: =IFERROR($D$46/Hist_Data!$D$7,"") -> 0.13211751 | E47: =IFERROR($E$46/Hist_Data!$E$7,"") -> 0.15368595 | F47: =IFERROR($F$46/Hist_Data!$F$7,"") -> 0.24184387 | G47: =IFERROR($G$46/Hist_Data!$G$7,"") -> 0.21238675 | H47: Calculated value | I47: Anchor for the forecast working-capital assumption
A48: Net sales / net PP&E | B48: x | C48: =IFERROR(Hist_Data!$C$7/Hist_Data!$C$54,"") -> 7.0471123 | D48: =IFERROR(Hist_Data!$D$7/Hist_Data!$D$54,"") -> 7.1641905 | E48: =IFERROR(Hist_Data!$E$7/Hist_Data!$E$54,"") -> 6.3907584 | F48: =IFERROR(Hist_Data!$F$7/Hist_Data!$F$54,"") -> 3.7185098 | G48: =IFERROR(Hist_Data!$G$7/Hist_Data!$G$54,"") -> 4.258697 | H48: Calculated value | I48: Fixed-asset turnover
A49: Quarterly context (first fiscal quarter (April-June))
C50: Q1 FY2026 | D50: Q1 FY2027 | E50: YoY growth
A51: Net sales | B51: $m | C51: =Hist_Data!$C$70 -> 1075.5 | D51: =Hist_Data!$D$70 -> 1484.7 | E51: =IFERROR(D51/C51-1,"") -> 0.3804742 | H51: Calculated value | I51: Q1 FY2027 / Q1 FY2026 - 1. Context for the FY2027 demand-growth assumption.
A52: Mixed-signal Microcontrollers | B52: $m | C52: =Hist_Data!$C$71 -> 532.6 | D52: =Hist_Data!$D$71 -> 739.1 | E52: =IFERROR(D52/C52-1,"") -> 0.38772062 | H52: Calculated value | I52: Q1 FY2027 / Q1 FY2026 - 1. Context for the FY2027 demand-growth assumption.
A53: Analog | B53: $m | C53: =Hist_Data!$C$72 -> 316.2 | D53: =Hist_Data!$D$72 -> 410.9 | E53: =IFERROR(D53/C53-1,"") -> 0.29949399 | H53: Calculated value | I53: Q1 FY2027 / Q1 FY2026 - 1. Context for the FY2027 demand-growth assumption.
A54: Other (incl. FPGA, licensing, memory, timing) | B54: $m | C54: =Hist_Data!$C$73 -> 226.7 | D54: =Hist_Data!$D$73 -> 334.7 | E54: =IFERROR(D54/C54-1,"") -> 0.47640053 | H54: Calculated value | I54: Q1 FY2027 / Q1 FY2026 - 1. Context for the FY2027 demand-growth assumption.
A56: Analyst observations (each refers to a metric above; numbers quoted are formula results)
A57: Cycle | C57: ="Net sales peaked in FY2023 at $"&TEXT(Hist_Data!$D$7,"#,##0")&"m and fell "&TEXT(-(Hist_Data!$F$7/Hist_Data!$D$7-1),"0%")&" by FY2025"&", then grew "&TEXT($G$8,"0.0%")&" in FY2026." -> Net sales peaked in FY2023 at $8,439m and fell 48% by FY2025, then grew 7.1% in FY2026.
A58: Operating leverage | C58: ="Gross margin moved from "&TEXT($D$9,"0.0%")&" (FY2023) to "&TEXT($F$9,"0.0%")&" (FY2025): consistent with fixed factory cost spread over fewer units. The operating model simulates this effect." -> Gross margin moved from 67.5% (FY2023) to 56.1% (FY2025): consistent with fixed factory cost spread over fewer units. The operating model simulates this effect.
A59: Inventory | C59: ="Days of inventory were "&TEXT($C$43,"0")&" in FY2022 and "&TEXT($G$43,"0")&" in FY2026." -> Days of inventory were 132 in FY2022 and 190 in FY2026.
A60: Capex | C60: ="Capex was "&TEXT($C$37,"0.0%")&" of sales in FY2022 and "&TEXT($G$37,"0.0%")&" in FY2026; capex / D&A was "&TEXT($G$40,"0.00x")&" in FY2026." -> Capex was 5.4% of sales in FY2022 and 1.9% in FY2026; capex / D&A was 0.13x in FY2026.
A61: Latest quarter | C61: ="Q1 FY2027 net sales changed "&TEXT(E51,"+0%;-0%")&" year over year." -> Q1 FY2027 net sales changed +38% year over year.

Sheet Ops_Model
A1: Product Operating Model - FY2027 monthly (active scenario)
A2: Units in millions, money in $m, prices in $/unit. Every row traces to Assumptions. Black = formula.
A3: Simulated data created for portfolio demonstration. It does not represent nonpublic Microchip Technology information.
A4: Scenario shown: | B4: =Assumptions!$C$6 -> Base
A6: Line item | B6: Units | C6: =Assumptions!C$71 -> 46113 | D6: =Assumptions!D$71 -> 46143 | E6: =Assumptions!E$71 -> 46174 | F6: =Assumptions!F$71 -> 46204 | G6: =Assumptions!G$71 -> 46235 | H6: =Assumptions!H$71 -> 46266 | I6: =Assumptions!I$71 -> 46296 | J6: =Assumptions!J$71 -> 46327 | ... N6: =Assumptions!N$71 -> 46447 | O6: FY2027 | P6: Classification | Q6: Formula
A7: Mixed-signal microcontrollers - Simulated data created for portfolio demonstration. It does not represent nonpublic Microchip Technology information.
A8: Seasonality factor | B8: x | C8: =Assumptions!C$72 -> 0.96 | D8: =Assumptions!D$72 -> 0.98 | E8: =Assumptions!E$72 -> 1.02 | F8: =Assumptions!F$72 -> 0.97 | G8: =Assumptions!G$72 -> 0.99 | H8: =Assumptions!H$72 -> 1.04 | I8: =Assumptions!I$72 -> 1.03 | J8: =Assumptions!J$72 -> 1.01 | ... N8: =Assumptions!N$72 -> 1.08 | O8: =SUM(C8:N8) -> 12 | P8: Calculated value (simulated inputs) | Q8: Link: Assumptions section E
A9: Customer demand | B9: m units | C9: =Assumptions!$C$62*C8/12 -> 23.988288 | D9: =Assumptions!$C$62*D8/12 -> 24.488044 | E9: =Assumptions!$C$62*E8/12 -> 25.487556 | F9: =Assumptions!$C$62*F8/12 -> 24.238166 | G9: =Assumptions!$C$62*G8/12 -> 24.737922 | H9: =Assumptions!$C$62*H8/12 -> 25.987312 | I9: =Assumptions!$C$62*I8/12 -> 25.737434 | J9: =Assumptions!$C$62*J8/12 -> 25.237678 | ... N9: =Assumptions!$C$62*N8/12 -> 26.986824 | O9: =SUM(C9:N9) -> 299.8536 | P9: Calculated value (simulated inputs) | Q9: FY2027 demand x seasonality / 12
A10: Internal final-test capacity | B10: m units | C10: =Assumptions!$C$46 -> 35 | D10: =Assumptions!$C$46 -> 35 | E10: =Assumptions!$C$46 -> 35 | F10: =Assumptions!$C$46 -> 35 | G10: =Assumptions!$C$46 -> 35 | H10: =Assumptions!$C$46 -> 35 | I10: =Assumptions!$C$46 -> 35 | J10: =Assumptions!$C$46 -> 35 | ... N10: =Assumptions!$C$46 -> 35 | O10: =SUM(C10:N10) -> 420 | P10: Calculated value (simulated inputs) | Q10: Monthly capacity (Assumptions D)
A11: Capacity utilization | B11: % | C11: =Assumptions!$C$65 -> 0.8 | D11: =Assumptions!$C$65 -> 0.8 | E11: =Assumptions!$C$65 -> 0.8 | F11: =Assumptions!$C$65 -> 0.8 | G11: =Assumptions!$C$65 -> 0.8 | H11: =Assumptions!$C$65 -> 0.8 | I11: =Assumptions!$C$65 -> 0.8 | J11: =Assumptions!$C$65 -> 0.8 | ... N11: =Assumptions!$C$65 -> 0.8 | O11: =IFERROR(O12/O10,0) -> 0.8 | P11: Calculated value (simulated inputs) | Q11: Scenario utilization. FY = units produced / capacity
A12: Units produced (tested) | B12: m units | C12: =C10*C11 -> 28 | D12: =D10*D11 -> 28 | E12: =E10*E11 -> 28 | F12: =F10*F11 -> 28 | G12: =G10*G11 -> 28 | H12: =H10*H11 -> 28 | I12: =I10*I11 -> 28 | J12: =J10*J11 -> 28 | ... N12: =N10*N11 -> 28 | O12: =SUM(C12:N12) -> 336 | P12: Calculated value (simulated inputs) | Q12: Capacity x utilization
A13: Manufacturing yield (final test) | B13: % | C13: =Assumptions!$C$64 -> 0.92 | D13: =Assumptions!$C$64 -> 0.92 | E13: =Assumptions!$C$64 -> 0.92 | F13: =Assumptions!$C$64 -> 0.92 | G13: =Assumptions!$C$64 -> 0.92 | H13: =Assumptions!$C$64 -> 0.92 | I13: =Assumptions!$C$64 -> 0.92 | J13: =Assumptions!$C$64 -> 0.92 | ... N13: =Assumptions!$C$64 -> 0.92 | O13: =IFERROR(O14/O12,0) -> 0.92 | P13: Calculated value (simulated inputs) | Q13: Scenario yield. FY = good units / units produced
A14: Good units produced | B14: m units | C14: =C12*C13 -> 25.76 | D14: =D12*D13 -> 25.76 | E14: =E12*E13 -> 25.76 | F14: =F12*F13 -> 25.76 | G14: =G12*G13 -> 25.76 | H14: =H12*H13 -> 25.76 | I14: =I12*I13 -> 25.76 | J14: =J12*J13 -> 25.76 | ... N14: =N12*N13 -> 25.76 | O14: =SUM(C14:N14) -> 309.12 | P14: Calculated value (simulated inputs) | Q14: Units produced x yield
A15: Opening finished-goods inventory | B15: m units | C15: =Assumptions!$C$67 -> 20.823167 | D15: =C18 -> 22.594879 | E15: =D18 -> 23.866835 | F15: =E18 -> 24.139279 | G15: =F18 -> 25.661113 | H15: =G18 -> 26.683191 | I15: =H18 -> 26.455879 | J15: =I18 -> 26.478445 | K15: =J18 -> 27.000767 | ... N15: =M18 -> 31.316391 | O15: =C15 -> 20.823167 | P15: Calculated value (simulated inputs) | Q15: First month: Assumptions opening balance; then prior month's closing
A16: Available good units | B16: m units | C16: =C15+C14 -> 46.583167 | D16: =D15+D14 -> 48.354879 | E16: =E15+E14 -> 49.626835 | F16: =F15+F14 -> 49.899279 | G16: =G15+G14 -> 51.421113 | H16: =H15+H14 -> 52.443191 | I16: =I15+I14 -> 52.215879 | J16: =J15+J14 -> 52.238445 | ... N16: =N15+N14 -> 57.076391 | P16: Calculated value (simulated inputs) | Q16: Opening inventory + good units produced
A17: Units sold | B17: m units | C17: =MIN(C9,C16) -> 23.988288 | D17: =MIN(D9,D16) -> 24.488044 | E17: =MIN(E9,E16) -> 25.487556 | F17: =MIN(F9,F16) -> 24.238166 | G17: =MIN(G9,G16) -> 24.737922 | H17: =MIN(H9,H16) -> 25.987312 | I17: =MIN(I9,I16) -> 25.737434 | J17: =MIN(J9,J16) -> 25.237678 | ... N17: =MIN(N9,N16) -> 26.986824 | O17: =SUM(C17:N17) -> 299.8536 | P17: Calculated value (simulated inputs) | Q17: MIN(customer demand, available good units)
A18: Closing finished-goods inventory | B18: m units | C18: =C16-C17 -> 22.594879 | D18: =D16-D17 -> 23.866835 | E18: =E16-E17 -> 24.139279 | F18: =F16-F17 -> 25.661113 | G18: =G16-G17 -> 26.683191 | H18: =H16-H17 -> 26.455879 | I18: =I16-I17 -> 26.478445 | J18: =J16-J17 -> 27.000767 | ... N18: =N16-N17 -> 30.089567 | O18: =N18 -> 30.089567 | P18: Calculated value (simulated inputs) | Q18: Available - units sold
A19: Unmet demand (supply shortfall) | B19: m units | C19: =C9-C17 -> 0 | D19: =D9-D17 -> 0 | E19: =E9-E17 -> 0 | F19: =F9-F17 -> 0 | G19: =G9-G17 -> 0 | H19: =H9-H17 -> 0 | I19: =I9-I17 -> 0 | J19: =J9-J17 -> 0 | ... N19: =N9-N17 -> 0 | O19: =SUM(C19:N19) -> 0 | P19: Calculated value (simulated inputs) | Q19: Demand - units sold. >0 means lost or delayed sales
A20: Demand / good-unit capacity (risk ratio) | B20: x | C20: =IFERROR(C9/(C10*C13),0) -> 0.74497789 | D20: =IFERROR(D9/(D10*D13),0) -> 0.76049826 | E20: =IFERROR(E9/(E10*E13),0) -> 0.79153901 | F20: =IFERROR(F9/(F10*F13),0) -> 0.75273807 | G20: =IFERROR(G9/(G10*G13),0) -> 0.76825845 | H20: =IFERROR(H9/(H10*H13),0) -> 0.80705938 | I20: =IFERROR(I9/(I10*I13),0) -> 0.79929919 | J20: =IFERROR(J9/(J10*J13),0) -> 0.78377882 | ... O20: =IFERROR(O9/(O10*O13),0) -> 0.77601863 | P20: Calculated value (simulated inputs) | Q20: Demand / (capacity x yield) = share of full-load good output needed. Feeds the risk heat map
A21: Average selling price | B21: $/unit | C21: =Assumptions!$C$63 -> 1.98 | D21: =Assumptions!$C$63 -> 1.98 | E21: =Assumptions!$C$63 -> 1.98 | F21: =Assumptions!$C$63 -> 1.98 | G21: =Assumptions!$C$63 -> 1.98 | H21: =Assumptions!$C$63 -> 1.98 | I21: =Assumptions!$C$63 -> 1.98 | J21: =Assumptions!$C$63 -> 1.98 | ... N21: =Assumptions!$C$63 -> 1.98 | O21: =IFERROR(O22/O17,0) -> 1.98 | P21: Calculated value (simulated inputs) | Q21: Scenario ASP. FY = revenue / units sold
A22: Revenue | B22: $m | C22: =C17*C21 -> 47.49681 | D22: =D17*D21 -> 48.486327 | E22: =E17*E21 -> 50.465361 | F22: =F17*F21 -> 47.991569 | G22: =G17*G21 -> 48.981085 | H22: =H17*H21 -> 51.454878 | I22: =I17*I21 -> 50.960119 | J22: =J17*J21 -> 49.970602 | ... N22: =N17*N21 -> 53.433911 | O22: =SUM(C22:N22) -> 593.71013 | P22: Calculated value (simulated inputs) | Q22: Units sold x ASP
A23: Variable cost per unit produced | B23: $/unit | C23: =Assumptions!$C$66 -> 0.3193 | D23: =Assumptions!$C$66 -> 0.3193 | E23: =Assumptions!$C$66 -> 0.3193 | F23: =Assumptions!$C$66 -> 0.3193 | G23: =Assumptions!$C$66 -> 0.3193 | H23: =Assumptions!$C$66 -> 0.3193 | I23: =Assumptions!$C$66 -> 0.3193 | J23: =Assumptions!$C$66 -> 0.3193 | ... N23: =Assumptions!$C$66 -> 0.3193 | O23: =IFERROR(O24/O12,0) -> 0.3193 | P23: Calculated value (simulated inputs) | Q23: Scenario variable cost per unit
A24: Variable manufacturing cost | B24: $m | C24: =C12*C23 -> 8.9404 | D24: =D12*D23 -> 8.9404 | E24: =E12*E23 -> 8.9404 | F24: =F12*F23 -> 8.9404 | G24: =G12*G23 -> 8.9404 | H24: =H12*H23 -> 8.9404 | I24: =I12*I23 -> 8.9404 | J24: =J12*J23 -> 8.9404 | ... N24: =N12*N23 -> 8.9404 | O24: =SUM(C24:N24) -> 107.2848 | P24: Calculated value (simulated inputs) | Q24: Units produced x variable cost per unit
A25: Fixed manufacturing cost | B25: $m | C25: =Assumptions!$C$45 -> 9.5 | D25: =Assumptions!$C$45 -> 9.5 | E25: =Assumptions!$C$45 -> 9.5 | F25: =Assumptions!$C$45 -> 9.5 | G25: =Assumptions!$C$45 -> 9.5 | H25: =Assumptions!$C$45 -> 9.5 | I25: =Assumptions!$C$45 -> 9.5 | J25: =Assumptions!$C$45 -> 9.5 | ... N25: =Assumptions!$C$45 -> 9.5 | O25: =SUM(C25:N25) -> 114 | P25: Calculated value (simulated inputs) | Q25: Monthly fixed cost (Assumptions D)
A26: Total manufacturing cost | B26: $m | C26: =C24+C25 -> 18.4404 | D26: =D24+D25 -> 18.4404 | E26: =E24+E25 -> 18.4404 | F26: =F24+F25 -> 18.4404 | G26: =G24+G25 -> 18.4404 | H26: =H24+H25 -> 18.4404 | I26: =I24+I25 -> 18.4404 | J26: =J24+J25 -> 18.4404 | ... N26: =N24+N25 -> 18.4404 | O26: =SUM(C26:N26) -> 221.2848 | P26: Calculated value (simulated inputs) | Q26: Variable + fixed manufacturing cost
A27: Cost per good unit | B27: $/unit | C27: =IFERROR(C26/C14,0) -> 0.71585404 | D27: =IFERROR(D26/D14,0) -> 0.71585404 | E27: =IFERROR(E26/E14,0) -> 0.71585404 | F27: =IFERROR(F26/F14,0) -> 0.71585404 | G27: =IFERROR(G26/G14,0) -> 0.71585404 | H27: =IFERROR(H26/H14,0) -> 0.71585404 | I27: =IFERROR(I26/I14,0) -> 0.71585404 | J27: =IFERROR(J26/J14,0) -> 0.71585404 | ... O27: =IFERROR(O26/O14,0) -> 0.71585404 | P27: Calculated value (simulated inputs) | Q27: Total manufacturing cost / good units. Rises when yield or utilization falls
A28: Opening inventory value | B28: $m | C28: =Assumptions!$C$68 -> 16.516502 | D28: =C31 -> 16.95563 | E28: =D31 -> 17.470651 | F28: =E31 -> 17.467704 | G28: =F31 -> 18.466037 | H28: =G31 -> 19.151307 | I28: =H31 -> 18.96379 | J28: =I31 -> 18.967502 | K28: =J31 -> 19.335224 | ... N28: =M31 -> 22.419094 | O28: =C28 -> 16.516502 | P28: Calculated value (simulated inputs) | Q28: Prior month's closing value
A29: Average cost per available unit | B29: $/unit | C29: =IFERROR((C28+C26)/C16,0) -> 0.75041918 | D29: =IFERROR((D28+D26)/D16,0) -> 0.73200536 | E29: =IFERROR((E28+E26)/E16,0) -> 0.72362163 | F29: =IFERROR((F28+F26)/F16,0) -> 0.71961169 | G29: =IFERROR((G28+G26)/G16,0) -> 0.71772925 | H29: =IFERROR((H28+H26)/H16,0) -> 0.71680815 | I29: =IFERROR((I28+I26)/I16,0) -> 0.71633745 | J29: =IFERROR((J28+J26)/J16,0) -> 0.71609907 | ... N29: =IFERROR((N28+N26)/N16,0) -> 0.71587381 | P29: Calculated value (simulated inputs) | Q29: (Opening value + manufacturing cost) / available units - weighted-average costing
A30: Cost of revenue | B30: $m | C30: =C17*C29 -> 18.001271 | D30: =D17*D29 -> 17.925379 | E30: =E17*E29 -> 18.443347 | F30: =F17*F29 -> 17.442068 | G30: =G17*G29 -> 17.75513 | H30: =H17*H29 -> 18.627917 | I30: =I17*I29 -> 18.436688 | J30: =J17*J29 -> 18.072678 | ... N30: =N17*N29 -> 19.319161 | O30: =SUM(C30:N30) -> 216.26097 | P30: Calculated value (simulated inputs) | Q30: Units sold x average cost
A31: Closing inventory value | B31: $m | C31: =C28+C26-C30 -> 16.95563 | D31: =D28+D26-D30 -> 17.470651 | E31: =E28+E26-E30 -> 17.467704 | F31: =F28+F26-F30 -> 18.466037 | G31: =G28+G26-G30 -> 19.151307 | H31: =H28+H26-H30 -> 18.96379 | I31: =I28+I26-I30 -> 18.967502 | J31: =J28+J26-J30 -> 19.335224 | ... N31: =N28+N26-N30 -> 21.540333 | O31: =N31 -> 21.540333 | P31: Calculated value (simulated inputs) | Q31: Opening value + manufacturing cost - cost of revenue
A32: Contribution margin | B32: $m | C32: =C22-C17*IFERROR(C23/C13,0) -> 39.17131 | D32: =D22-D17*IFERROR(D23/D13,0) -> 39.987379 | E32: =E22-E17*IFERROR(E23/E13,0) -> 41.619517 | F32: =F22-F17*IFERROR(F23/F13,0) -> 39.579344 | G32: =G22-G17*IFERROR(G23/G13,0) -> 40.395413 | H32: =H22-H17*IFERROR(H23/H13,0) -> 42.435586 | I32: =I22-I17*IFERROR(I23/I13,0) -> 42.027551 | J32: =J22-J17*IFERROR(J23/J13,0) -> 41.211482 | ... N32: =N22-N17*IFERROR(N23/N13,0) -> 44.067724 | O32: =SUM(C32:N32) -> 489.64137 | P32: Calculated value (simulated inputs) | Q32: Revenue - units sold x variable cost per good unit (variable cost / yield)
A33: Contribution margin % | B33: % | C33: =IFERROR(C32/C22,0) -> 0.82471454 | D33: =IFERROR(D32/D22,0) -> 0.82471454 | E33: =IFERROR(E32/E22,0) -> 0.82471454 | F33: =IFERROR(F32/F22,0) -> 0.82471454 | G33: =IFERROR(G32/G22,0) -> 0.82471454 | H33: =IFERROR(H32/H22,0) -> 0.82471454 | I33: =IFERROR(I32/I22,0) -> 0.82471454 | J33: =IFERROR(J32/J22,0) -> 0.82471454 | ... O33: =IFERROR(O32/O22,0) -> 0.82471454 | P33: Calculated value (simulated inputs) | Q33: Contribution margin / revenue
A34: Gross profit | B34: $m | C34: =C22-C30 -> 29.495539 | D34: =D22-D30 -> 30.560948 | E34: =E22-E30 -> 32.022014 | F34: =F22-F30 -> 30.549501 | G34: =G22-G30 -> 31.225955 | H34: =H22-H30 -> 32.826961 | I34: =I22-I30 -> 32.523431 | J34: =J22-J30 -> 31.897925 | ... N34: =N22-N30 -> 34.114751 | O34: =SUM(C34:N34) -> 377.44916 | P34: Calculated value (simulated inputs) | Q34: Revenue - cost of revenue
A35: Gross margin % | B35: % | C35: =IFERROR(C34/C22,0) -> 0.62100041 | D35: =IFERROR(D34/D22,0) -> 0.63030032 | E35: =IFERROR(E34/E22,0) -> 0.63453453 | F35: =IFERROR(F34/F22,0) -> 0.63655975 | G35: =IFERROR(G34/G22,0) -> 0.63751048 | H35: =IFERROR(H34/H22,0) -> 0.63797568 | I35: =IFERROR(I34/I22,0) -> 0.63821341 | J35: =IFERROR(J34/J22,0) -> 0.6383338 | ... O35: =IFERROR(O34/O22,0) -> 0.63574654 | P35: Calculated value (simulated inputs) | Q35: Gross profit / revenue
A37: Analog & power management - Simulated data created for portfolio demonstration. It does not represent nonpublic Microchip Technology information.
A38: Seasonality factor | B38: x | C38: =Assumptions!C$72 -> 0.96 | D38: =Assumptions!D$72 -> 0.98 | E38: =Assumptions!E$72 -> 1.02 | F38: =Assumptions!F$72 -> 0.97 | G38: =Assumptions!G$72 -> 0.99 | H38: =Assumptions!H$72 -> 1.04 | I38: =Assumptions!I$72 -> 1.03 | J38: =Assumptions!J$72 -> 1.01 | ... N38: =Assumptions!N$72 -> 1.08 | O38: =SUM(C38:N38) -> 12 | P38: Calculated value (simulated inputs) | Q38: Link: Assumptions section E
A39: Customer demand | B39: m units | C39: =Assumptions!$D$62*C38/12 -> 32.427702 | D39: =Assumptions!$D$62*D38/12 -> 33.103279 | E39: =Assumptions!$D$62*E38/12 -> 34.454433 | F39: =Assumptions!$D$62*F38/12 -> 32.76549 | G39: =Assumptions!$D$62*G38/12 -> 33.441067 | H39: =Assumptions!$D$62*H38/12 -> 35.13001 | I39: =Assumptions!$D$62*I38/12 -> 34.792221 | J39: =Assumptions!$D$62*J38/12 -> 34.116644 | ... N39: =Assumptions!$D$62*N38/12 -> 36.481164 | O39: =SUM(C39:N39) -> 405.34627 | P39: Calculated value (simulated inputs) | Q39: FY2027 demand x seasonality / 12
A40: Internal final-test capacity | B40: m units | C40: =Assumptions!$D$46 -> 46 | D40: =Assumptions!$D$46 -> 46 | E40: =Assumptions!$D$46 -> 46 | F40: =Assumptions!$D$46 -> 46 | G40: =Assumptions!$D$46 -> 46 | H40: =Assumptions!$D$46 -> 46 | I40: =Assumptions!$D$46 -> 46 | J40: =Assumptions!$D$46 -> 46 | ... N40: =Assumptions!$D$46 -> 46 | O40: =SUM(C40:N40) -> 552 | P40: Calculated value (simulated inputs) | Q40: Monthly capacity (Assumptions D)
A41: Capacity utilization | B41: % | C41: =Assumptions!$D$65 -> 0.8 | D41: =Assumptions!$D$65 -> 0.8 | E41: =Assumptions!$D$65 -> 0.8 | F41: =Assumptions!$D$65 -> 0.8 | G41: =Assumptions!$D$65 -> 0.8 | H41: =Assumptions!$D$65 -> 0.8 | I41: =Assumptions!$D$65 -> 0.8 | J41: =Assumptions!$D$65 -> 0.8 | ... N41: =Assumptions!$D$65 -> 0.8 | O41: =IFERROR(O42/O40,0) -> 0.8 | P41: Calculated value (simulated inputs) | Q41: Scenario utilization. FY = units produced / capacity
A42: Units produced (tested) | B42: m units | C42: =C40*C41 -> 36.8 | D42: =D40*D41 -> 36.8 | E42: =E40*E41 -> 36.8 | F42: =F40*F41 -> 36.8 | G42: =G40*G41 -> 36.8 | H42: =H40*H41 -> 36.8 | I42: =I40*I41 -> 36.8 | J42: =J40*J41 -> 36.8 | ... N42: =N40*N41 -> 36.8 | O42: =SUM(C42:N42) -> 441.6 | P42: Calculated value (simulated inputs) | Q42: Capacity x utilization
A43: Manufacturing yield (final test) | B43: % | C43: =Assumptions!$D$64 -> 0.94 | D43: =Assumptions!$D$64 -> 0.94 | E43: =Assumptions!$D$64 -> 0.94 | F43: =Assumptions!$D$64 -> 0.94 | G43: =Assumptions!$D$64 -> 0.94 | H43: =Assumptions!$D$64 -> 0.94 | I43: =Assumptions!$D$64 -> 0.94 | J43: =Assumptions!$D$64 -> 0.94 | ... N43: =Assumptions!$D$64 -> 0.94 | O43: =IFERROR(O44/O42,0) -> 0.94 | P43: Calculated value (simulated inputs) | Q43: Scenario yield. FY = good units / units produced
A44: Good units produced | B44: m units | C44: =C42*C43 -> 34.592 | D44: =D42*D43 -> 34.592 | E44: =E42*E43 -> 34.592 | F44: =F42*F43 -> 34.592 | G44: =G42*G43 -> 34.592 | H44: =H42*H43 -> 34.592 | I44: =I42*I43 -> 34.592 | J44: =J42*J43 -> 34.592 | ... N44: =N42*N43 -> 34.592 | O44: =SUM(C44:N44) -> 415.104 | P44: Calculated value (simulated inputs) | Q44: Units produced x yield
A45: Opening finished-goods inventory | B45: m units | C45: =Assumptions!$D$67 -> 29.372918 | D45: =C48 -> 31.537217 | E45: =D48 -> 33.025938 | F45: =E48 -> 33.163505 | G45: =F48 -> 34.990015 | H45: =G48 -> 36.140948 | I45: =H48 -> 35.602938 | J45: =I48 -> 35.402716 | K45: =J48 -> 35.878072 | ... N45: =M48 -> 41.019813 | O45: =C45 -> 29.372918 | P45: Calculated value (simulated inputs) | Q45: First month: Assumptions opening balance; then prior month's closing
A46: Available good units | B46: m units | C46: =C45+C44 -> 63.964918 | D46: =D45+D44 -> 66.129217 | E46: =E45+E44 -> 67.617938 | F46: =F45+F44 -> 67.755505 | G46: =G45+G44 -> 69.582015 | H46: =H45+H44 -> 70.732948 | I46: =I45+I44 -> 70.194938 | J46: =J45+J44 -> 69.994716 | ... N46: =N45+N44 -> 75.611813 | P46: Calculated value (simulated inputs) | Q46: Opening inventory + good units produced
A47: Units sold | B47: m units | C47: =MIN(C39,C46) -> 32.427702 | D47: =MIN(D39,D46) -> 33.103279 | E47: =MIN(E39,E46) -> 34.454433 | F47: =MIN(F39,F46) -> 32.76549 | G47: =MIN(G39,G46) -> 33.441067 | H47: =MIN(H39,H46) -> 35.13001 | I47: =MIN(I39,I46) -> 34.792221 | J47: =MIN(J39,J46) -> 34.116644 | ... N47: =MIN(N39,N46) -> 36.481164 | O47: =SUM(C47:N47) -> 405.34627 | P47: Calculated value (simulated inputs) | Q47: MIN(customer demand, available good units)
A48: Closing finished-goods inventory | B48: m units | C48: =C46-C47 -> 31.537217 | D48: =D46-D47 -> 33.025938 | E48: =E46-E47 -> 33.163505 | F48: =F46-F47 -> 34.990015 | G48: =G46-G47 -> 36.140948 | H48: =H46-H47 -> 35.602938 | I48: =I46-I47 -> 35.402716 | J48: =J46-J47 -> 35.878072 | ... N48: =N46-N47 -> 39.130649 | O48: =N48 -> 39.130649 | P48: Calculated value (simulated inputs) | Q48: Available - units sold
A49: Unmet demand (supply shortfall) | B49: m units | C49: =C39-C47 -> 0 | D49: =D39-D47 -> 0 | E49: =E39-E47 -> 0 | F49: =F39-F47 -> 0 | G49: =G39-G47 -> 0 | H49: =H39-H47 -> 0 | I49: =I39-I47 -> 0 | J49: =J39-J47 -> 0 | ... N49: =N39-N47 -> 0 | O49: =SUM(C49:N49) -> 0 | P49: Calculated value (simulated inputs) | Q49: Demand - units sold. >0 means lost or delayed sales
A50: Demand / good-unit capacity (risk ratio) | B50: x | C50: =IFERROR(C39/(C40*C43),0) -> 0.74994684 | D50: =IFERROR(D39/(D40*D43),0) -> 0.76557074 | E50: =IFERROR(E39/(E40*E43),0) -> 0.79681852 | F50: =IFERROR(F39/(F40*F43),0) -> 0.75775879 | G50: =IFERROR(G39/(G40*G43),0) -> 0.77338268 | H50: =IFERROR(H39/(H40*H43),0) -> 0.81244241 | I50: =IFERROR(I39/(I40*I43),0) -> 0.80463047 | J50: =IFERROR(J39/(J40*J43),0) -> 0.78900657 | ... O50: =IFERROR(O39/(O40*O43),0) -> 0.78119463 | P50: Calculated value (simulated inputs) | Q50: Demand / (capacity x yield) = share of full-load good output needed. Feeds the risk heat map
A51: Average selling price | B51: $/unit | C51: =Assumptions!$D$63 -> 0.792 | D51: =Assumptions!$D$63 -> 0.792 | E51: =Assumptions!$D$63 -> 0.792 | F51: =Assumptions!$D$63 -> 0.792 | G51: =Assumptions!$D$63 -> 0.792 | H51: =Assumptions!$D$63 -> 0.792 | I51: =Assumptions!$D$63 -> 0.792 | J51: =Assumptions!$D$63 -> 0.792 | ... N51: =Assumptions!$D$63 -> 0.792 | O51: =IFERROR(O52/O47,0) -> 0.792 | P51: Calculated value (simulated inputs) | Q51: Scenario ASP. FY = revenue / units sold
A52: Revenue | B52: $m | C52: =C47*C51 -> 25.68274 | D52: =D47*D51 -> 26.217797 | E52: =E47*E51 -> 27.287911 | F52: =F47*F51 -> 25.950268 | G52: =G47*G51 -> 26.485325 | H52: =H47*H51 -> 27.822968 | I52: =I47*I51 -> 27.555439 | J52: =J47*J51 -> 27.020382 | ... N52: =N47*N51 -> 28.893082 | O52: =SUM(C52:N52) -> 321.03424 | P52: Calculated value (simulated inputs) | Q52: Units sold x ASP
A53: Variable cost per unit produced | B53: $/unit | C53: =Assumptions!$D$66 -> 0.1545 | D53: =Assumptions!$D$66 -> 0.1545 | E53: =Assumptions!$D$66 -> 0.1545 | F53: =Assumptions!$D$66 -> 0.1545 | G53: =Assumptions!$D$66 -> 0.1545 | H53: =Assumptions!$D$66 -> 0.1545 | I53: =Assumptions!$D$66 -> 0.1545 | J53: =Assumptions!$D$66 -> 0.1545 | ... N53: =Assumptions!$D$66 -> 0.1545 | O53: =IFERROR(O54/O42,0) -> 0.1545 | P53: Calculated value (simulated inputs) | Q53: Scenario variable cost per unit
A54: Variable manufacturing cost | B54: $m | C54: =C42*C53 -> 5.6856 | D54: =D42*D53 -> 5.6856 | E54: =E42*E53 -> 5.6856 | F54: =F42*F53 -> 5.6856 | G54: =G42*G53 -> 5.6856 | H54: =H42*H53 -> 5.6856 | I54: =I42*I53 -> 5.6856 | J54: =J42*J53 -> 5.6856 | ... N54: =N42*N53 -> 5.6856 | O54: =SUM(C54:N54) -> 68.2272 | P54: Calculated value (simulated inputs) | Q54: Units produced x variable cost per unit
A55: Fixed manufacturing cost | B55: $m | C55: =Assumptions!$D$45 -> 5.2 | D55: =Assumptions!$D$45 -> 5.2 | E55: =Assumptions!$D$45 -> 5.2 | F55: =Assumptions!$D$45 -> 5.2 | G55: =Assumptions!$D$45 -> 5.2 | H55: =Assumptions!$D$45 -> 5.2 | I55: =Assumptions!$D$45 -> 5.2 | J55: =Assumptions!$D$45 -> 5.2 | ... N55: =Assumptions!$D$45 -> 5.2 | O55: =SUM(C55:N55) -> 62.4 | P55: Calculated value (simulated inputs) | Q55: Monthly fixed cost (Assumptions D)
A56: Total manufacturing cost | B56: $m | C56: =C54+C55 -> 10.8856 | D56: =D54+D55 -> 10.8856 | E56: =E54+E55 -> 10.8856 | F56: =F54+F55 -> 10.8856 | G56: =G54+G55 -> 10.8856 | H56: =H54+H55 -> 10.8856 | I56: =I54+I55 -> 10.8856 | J56: =J54+J55 -> 10.8856 | ... N56: =N54+N55 -> 10.8856 | O56: =SUM(C56:N56) -> 130.6272 | P56: Calculated value (simulated inputs) | Q56: Variable + fixed manufacturing cost
A57: Cost per good unit | B57: $/unit | C57: =IFERROR(C56/C44,0) -> 0.31468548 | D57: =IFERROR(D56/D44,0) -> 0.31468548 | E57: =IFERROR(E56/E44,0) -> 0.31468548 | F57: =IFERROR(F56/F44,0) -> 0.31468548 | G57: =IFERROR(G56/G44,0) -> 0.31468548 | H57: =IFERROR(H56/H44,0) -> 0.31468548 | I57: =IFERROR(I56/I44,0) -> 0.31468548 | J57: =IFERROR(J56/J44,0) -> 0.31468548 | ... O57: =IFERROR(O56/O44,0) -> 0.31468548 | P57: Calculated value (simulated inputs) | Q57: Total manufacturing cost / good units. Rises when yield or utilization falls
A58: Opening inventory value | B58: $m | C58: =Assumptions!$D$68 -> 9.8871678 | D58: =C61 -> 10.24179 | E58: =D61 -> 10.55134 | F58: =E61 -> 10.513839 | G58: =F61 -> 11.051009 | H58: =G61 -> 11.39389 | I58: =H61 -> 11.214227 | J58: =I61 -> 11.146016 | K58: =J61 -> 11.293022 | ... N58: =M61 -> 12.908786 | O58: =C58 -> 9.8871678 | P58: Calculated value (simulated inputs) | Q58: Prior month's closing value
A59: Average cost per available unit | B59: $/unit | C59: =IFERROR((C58+C56)/C46,0) -> 0.32475251 | D59: =IFERROR((D58+D56)/D46,0) -> 0.31948647 | E59: =IFERROR((E58+E56)/E46,0) -> 0.31703038 | F59: =IFERROR((F58+F56)/F46,0) -> 0.31583321 | G59: =IFERROR((G58+G56)/G46,0) -> 0.31526263 | H59: =IFERROR((H58+H56)/H46,0) -> 0.31498037 | I59: =IFERROR((I58+I56)/I46,0) -> 0.31483505 | J59: =IFERROR((J58+J56)/J46,0) -> 0.31476113 | ... N59: =IFERROR((N58+N56)/N46,0) -> 0.31469138 | P59: Calculated value (simulated inputs) | Q59: (Opening value + manufacturing cost) / available units - weighted-average costing
A60: Cost of revenue | B60: $m | C60: =C47*C59 -> 10.530978 | D60: =D47*D59 -> 10.57605 | E60: =E47*E59 -> 10.923102 | F60: =F47*F59 -> 10.34843 | G60: =G47*G59 -> 10.542719 | H60: =H47*H59 -> 11.065264 | I60: =I47*I59 -> 10.953811 | J60: =J47*J59 -> 10.738593 | ... N60: =N47*N59 -> 11.480308 | O60: =SUM(C60:N60) -> 128.20029 | P60: Calculated value (simulated inputs) | Q60: Units sold x average cost
A61: Closing inventory value | B61: $m | C61: =C58+C56-C60 -> 10.24179 | D61: =D58+D56-D60 -> 10.55134 | E61: =E58+E56-E60 -> 10.513839 | F61: =F58+F56-F60 -> 11.051009 | G61: =G58+G56-G60 -> 11.39389 | H61: =H58+H56-H60 -> 11.214227 | I61: =I58+I56-I60 -> 11.146016 | J61: =J58+J56-J60 -> 11.293022 | ... N61: =N58+N56-N60 -> 12.314078 | O61: =N61 -> 12.314078 | P61: Calculated value (simulated inputs) | Q61: Opening value + manufacturing cost - cost of revenue
A62: Contribution margin | B62: $m | C62: =C52-C47*IFERROR(C53/C43,0) -> 20.352867 | D62: =D52-D47*IFERROR(D53/D43,0) -> 20.776885 | E62: =E52-E47*IFERROR(E53/E43,0) -> 21.624922 | F62: =F52-F47*IFERROR(F53/F43,0) -> 20.564876 | G62: =G52-G47*IFERROR(G53/G43,0) -> 20.988894 | H62: =H52-H47*IFERROR(H53/H43,0) -> 22.04894 | I62: =I52-I47*IFERROR(I53/I43,0) -> 21.836931 | J62: =J52-J47*IFERROR(J53/J43,0) -> 21.412913 | ... N62: =N52-N47*IFERROR(N53/N43,0) -> 22.896976 | O62: =SUM(C62:N62) -> 254.41084 | P62: Calculated value (simulated inputs) | Q62: Revenue - units sold x variable cost per good unit (variable cost / yield)
A63: Contribution margin % | B63: % | C63: =IFERROR(C62/C52,0) -> 0.7924726 | D63: =IFERROR(D62/D52,0) -> 0.7924726 | E63: =IFERROR(E62/E52,0) -> 0.7924726 | F63: =IFERROR(F62/F52,0) -> 0.7924726 | G63: =IFERROR(G62/G52,0) -> 0.7924726 | H63: =IFERROR(H62/H52,0) -> 0.7924726 | I63: =IFERROR(I62/I52,0) -> 0.7924726 | J63: =IFERROR(J62/J52,0) -> 0.7924726 | ... O63: =IFERROR(O62/O52,0) -> 0.7924726 | P63: Calculated value (simulated inputs) | Q63: Contribution margin / revenue
A64: Gross profit | B64: $m | C64: =C52-C60 -> 15.151762 | D64: =D52-D60 -> 15.641747 | E64: =E52-E60 -> 16.364809 | F64: =F52-F60 -> 15.601838 | G64: =G52-G60 -> 15.942607 | H64: =H52-H60 -> 16.757704 | I64: =I52-I60 -> 16.601629 | J64: =J52-J60 -> 16.281789 | ... N64: =N52-N60 -> 17.412774 | O64: =SUM(C64:N64) -> 192.83396 | P64: Calculated value (simulated inputs) | Q64: Revenue - cost of revenue
A65: Gross margin % | B65: % | C65: =IFERROR(C64/C52,0) -> 0.58995895 | D65: =IFERROR(D64/D52,0) -> 0.59660799 | E65: =IFERROR(E64/E52,0) -> 0.59970912 | F65: =IFERROR(F64/F52,0) -> 0.6012207 | G65: =IFERROR(G64/G52,0) -> 0.60194113 | H65: =IFERROR(H64/H52,0) -> 0.60229751 | I65: =IFERROR(I64/I52,0) -> 0.602481 | J65: =IFERROR(J64/J52,0) -> 0.60257433 | ... O65: =IFERROR(O64/O52,0) -> 0.60066475 | P65: Calculated value (simulated inputs) | Q65: Gross profit / revenue
A67: FPGAs - Simulated data created for portfolio demonstration. It does not represent nonpublic Microchip Technology information.
A68: Seasonality factor | B68: x | C68: =Assumptions!C$72 -> 0.96 | D68: =Assumptions!D$72 -> 0.98 | E68: =Assumptions!E$72 -> 1.02 | F68: =Assumptions!F$72 -> 0.97 | G68: =Assumptions!G$72 -> 0.99 | H68: =Assumptions!H$72 -> 1.04 | I68: =Assumptions!I$72 -> 1.03 | J68: =Assumptions!J$72 -> 1.01 | ... N68: =Assumptions!N$72 -> 1.08 | O68: =SUM(C68:N68) -> 12 | P68: Calculated value (simulated inputs) | Q68: Link: Assumptions section E
A69: Customer demand | B69: m units | C69: =Assumptions!$E$62*C68/12 -> 0.87305595 | D69: =Assumptions!$E$62*D68/12 -> 0.89124462 | E69: =Assumptions!$E$62*E68/12 -> 0.92762195 | F69: =Assumptions!$E$62*F68/12 -> 0.88215028 | G69: =Assumptions!$E$62*G68/12 -> 0.90033895 | H69: =Assumptions!$E$62*H68/12 -> 0.94581061 | I69: =Assumptions!$E$62*I68/12 -> 0.93671628 | J69: =Assumptions!$E$62*J68/12 -> 0.91852761 | ... N69: =Assumptions!$E$62*N68/12 -> 0.98218794 | O69: =SUM(C69:N69) -> 10.913199 | P69: Calculated value (simulated inputs) | Q69: FY2027 demand x seasonality / 12
A70: Internal final-test capacity | B70: m units | C70: =Assumptions!$E$46 -> 1.3 | D70: =Assumptions!$E$46 -> 1.3 | E70: =Assumptions!$E$46 -> 1.3 | F70: =Assumptions!$E$46 -> 1.3 | G70: =Assumptions!$E$46 -> 1.3 | H70: =Assumptions!$E$46 -> 1.3 | I70: =Assumptions!$E$46 -> 1.3 | J70: =Assumptions!$E$46 -> 1.3 | ... N70: =Assumptions!$E$46 -> 1.3 | O70: =SUM(C70:N70) -> 15.6 | P70: Calculated value (simulated inputs) | Q70: Monthly capacity (Assumptions D)
A71: Capacity utilization | B71: % | C71: =Assumptions!$E$65 -> 0.8 | D71: =Assumptions!$E$65 -> 0.8 | E71: =Assumptions!$E$65 -> 0.8 | F71: =Assumptions!$E$65 -> 0.8 | G71: =Assumptions!$E$65 -> 0.8 | H71: =Assumptions!$E$65 -> 0.8 | I71: =Assumptions!$E$65 -> 0.8 | J71: =Assumptions!$E$65 -> 0.8 | ... N71: =Assumptions!$E$65 -> 0.8 | O71: =IFERROR(O72/O70,0) -> 0.8 | P71: Calculated value (simulated inputs) | Q71: Scenario utilization. FY = units produced / capacity
A72: Units produced (tested) | B72: m units | C72: =C70*C71 -> 1.04 | D72: =D70*D71 -> 1.04 | E72: =E70*E71 -> 1.04 | F72: =F70*F71 -> 1.04 | G72: =G70*G71 -> 1.04 | H72: =H70*H71 -> 1.04 | I72: =I70*I71 -> 1.04 | J72: =J70*J71 -> 1.04 | ... N72: =N70*N71 -> 1.04 | O72: =SUM(C72:N72) -> 12.48 | P72: Calculated value (simulated inputs) | Q72: Capacity x utilization
A73: Manufacturing yield (final test) | B73: % | C73: =Assumptions!$E$64 -> 0.85 | D73: =Assumptions!$E$64 -> 0.85 | E73: =Assumptions!$E$64 -> 0.85 | F73: =Assumptions!$E$64 -> 0.85 | G73: =Assumptions!$E$64 -> 0.85 | H73: =Assumptions!$E$64 -> 0.85 | I73: =Assumptions!$E$64 -> 0.85 | J73: =Assumptions!$E$64 -> 0.85 | ... N73: =Assumptions!$E$64 -> 0.85 | O73: =IFERROR(O74/O72,0) -> 0.85 | P73: Calculated value (simulated inputs) | Q73: Scenario yield. FY = good units / units produced
A74: Good units produced | B74: m units | C74: =C72*C73 -> 0.884 | D74: =D72*D73 -> 0.884 | E74: =E72*E73 -> 0.884 | F74: =F72*F73 -> 0.884 | G74: =G72*G73 -> 0.884 | H74: =H72*H73 -> 0.884 | I74: =I72*I73 -> 0.884 | J74: =J72*J73 -> 0.884 | ... N74: =N72*N73 -> 0.884 | O74: =SUM(C74:N74) -> 10.608 | P74: Calculated value (simulated inputs) | Q74: Units produced x yield
A75: Opening finished-goods inventory | B75: m units | C75: =Assumptions!$E$67 -> 0.72754663 | D75: =C78 -> 0.73849067 | E75: =D78 -> 0.73124606 | F75: =E78 -> 0.68762411 | G75: =F78 -> 0.68947383 | H75: =G78 -> 0.67313488 | I75: =H78 -> 0.61132427 | J75: =I78 -> 0.55860799 | K75: =J78 -> 0.52408037 | ... N75: =M78 -> 0.52053519 | O75: =C75 -> 0.72754663 | P75: Calculated value (simulated inputs) | Q75: First month: Assumptions opening balance; then prior month's closing
A76: Available good units | B76: m units | C76: =C75+C74 -> 1.6115466 | D76: =D75+D74 -> 1.6224907 | E76: =E75+E74 -> 1.6152461 | F76: =F75+F74 -> 1.5716241 | G76: =G75+G74 -> 1.5734738 | H76: =H75+H74 -> 1.5571349 | I76: =I75+I74 -> 1.4953243 | J76: =J75+J74 -> 1.442608 | ... N76: =N75+N74 -> 1.4045352 | P76: Calculated value (simulated inputs) | Q76: Opening inventory + good units produced
A77: Units sold | B77: m units | C77: =MIN(C69,C76) -> 0.87305595 | D77: =MIN(D69,D76) -> 0.89124462 | E77: =MIN(E69,E76) -> 0.92762195 | F77: =MIN(F69,F76) -> 0.88215028 | G77: =MIN(G69,G76) -> 0.90033895 | H77: =MIN(H69,H76) -> 0.94581061 | I77: =MIN(I69,I76) -> 0.93671628 | J77: =MIN(J69,J76) -> 0.91852761 | ... N77: =MIN(N69,N76) -> 0.98218794 | O77: =SUM(C77:N77) -> 10.913199 | P77: Calculated value (simulated inputs) | Q77: MIN(customer demand, available good units)
A78: Closing finished-goods inventory | B78: m units | C78: =C76-C77 -> 0.73849067 | D78: =D76-D77 -> 0.73124606 | E78: =E76-E77 -> 0.68762411 | F78: =F76-F77 -> 0.68947383 | G78: =G76-G77 -> 0.67313488 | H78: =H76-H77 -> 0.61132427 | I78: =I76-I77 -> 0.55860799 | J78: =J76-J77 -> 0.52408037 | ... N78: =N76-N77 -> 0.42234724 | O78: =N78 -> 0.42234724 | P78: Calculated value (simulated inputs) | Q78: Available - units sold
A79: Unmet demand (supply shortfall) | B79: m units | C79: =C69-C77 -> 0 | D79: =D69-D77 -> 0 | E79: =E69-E77 -> 0 | F79: =F69-F77 -> 0 | G79: =G69-G77 -> 0 | H79: =H69-H77 -> 0 | I79: =I69-I77 -> 0 | J79: =J69-J77 -> 0 | ... N79: =N69-N77 -> 0 | O79: =SUM(C79:N79) -> 0 | P79: Calculated value (simulated inputs) | Q79: Demand - units sold. >0 means lost or delayed sales
A80: Demand / good-unit capacity (risk ratio) | B80: x | C80: =IFERROR(C69/(C70*C73),0) -> 0.79009588 | D80: =IFERROR(D69/(D70*D73),0) -> 0.80655621 | E80: =IFERROR(E69/(E70*E73),0) -> 0.83947688 | F80: =IFERROR(F69/(F70*F73),0) -> 0.79832605 | G80: =IFERROR(G69/(G70*G73),0) -> 0.81478638 | H80: =IFERROR(H69/(H70*H73),0) -> 0.85593721 | I80: =IFERROR(I69/(I70*I73),0) -> 0.84770704 | J80: =IFERROR(J69/(J70*J73),0) -> 0.83124671 | ... O80: =IFERROR(O69/(O70*O73),0) -> 0.82301654 | P80: Calculated value (simulated inputs) | Q80: Demand / (capacity x yield) = share of full-load good output needed. Feeds the risk heat map
A81: Average selling price | B81: $/unit | C81: =Assumptions!$E$63 -> 24.75 | D81: =Assumptions!$E$63 -> 24.75 | E81: =Assumptions!$E$63 -> 24.75 | F81: =Assumptions!$E$63 -> 24.75 | G81: =Assumptions!$E$63 -> 24.75 | H81: =Assumptions!$E$63 -> 24.75 | I81: =Assumptions!$E$63 -> 24.75 | J81: =Assumptions!$E$63 -> 24.75 | ... N81: =Assumptions!$E$63 -> 24.75 | O81: =IFERROR(O82/O77,0) -> 24.75 | P81: Calculated value (simulated inputs) | Q81: Scenario ASP. FY = revenue / units sold
A82: Revenue | B82: $m | C82: =C77*C81 -> 21.608135 | D82: =D77*D81 -> 22.058304 | E82: =E77*E81 -> 22.958643 | F82: =F77*F81 -> 21.83322 | G82: =G77*G81 -> 22.283389 | H82: =H77*H81 -> 23.408813 | I82: =I77*I81 -> 23.183728 | J82: =J77*J81 -> 22.733558 | ... N82: =N77*N81 -> 24.309152 | O82: =SUM(C82:N82) -> 270.10168 | P82: Calculated value (simulated inputs) | Q82: Units sold x ASP
A83: Variable cost per unit produced | B83: $/unit | C83: =Assumptions!$E$66 -> 4.841 | D83: =Assumptions!$E$66 -> 4.841 | E83: =Assumptions!$E$66 -> 4.841 | F83: =Assumptions!$E$66 -> 4.841 | G83: =Assumptions!$E$66 -> 4.841 | H83: =Assumptions!$E$66 -> 4.841 | I83: =Assumptions!$E$66 -> 4.841 | J83: =Assumptions!$E$66 -> 4.841 | ... N83: =Assumptions!$E$66 -> 4.841 | O83: =IFERROR(O84/O72,0) -> 4.841 | P83: Calculated value (simulated inputs) | Q83: Scenario variable cost per unit
A84: Variable manufacturing cost | B84: $m | C84: =C72*C83 -> 5.03464 | D84: =D72*D83 -> 5.03464 | E84: =E72*E83 -> 5.03464 | F84: =F72*F83 -> 5.03464 | G84: =G72*G83 -> 5.03464 | H84: =H72*H83 -> 5.03464 | I84: =I72*I83 -> 5.03464 | J84: =J72*J83 -> 5.03464 | ... N84: =N72*N83 -> 5.03464 | O84: =SUM(C84:N84) -> 60.41568 | P84: Calculated value (simulated inputs) | Q84: Units produced x variable cost per unit
A85: Fixed manufacturing cost | B85: $m | C85: =Assumptions!$E$45 -> 4.4 | D85: =Assumptions!$E$45 -> 4.4 | E85: =Assumptions!$E$45 -> 4.4 | F85: =Assumptions!$E$45 -> 4.4 | G85: =Assumptions!$E$45 -> 4.4 | H85: =Assumptions!$E$45 -> 4.4 | I85: =Assumptions!$E$45 -> 4.4 | J85: =Assumptions!$E$45 -> 4.4 | ... N85: =Assumptions!$E$45 -> 4.4 | O85: =SUM(C85:N85) -> 52.8 | P85: Calculated value (simulated inputs) | Q85: Monthly fixed cost (Assumptions D)
A86: Total manufacturing cost | B86: $m | C86: =C84+C85 -> 9.43464 | D86: =D84+D85 -> 9.43464 | E86: =E84+E85 -> 9.43464 | F86: =F84+F85 -> 9.43464 | G86: =G84+G85 -> 9.43464 | H86: =H84+H85 -> 9.43464 | I86: =I84+I85 -> 9.43464 | J86: =J84+J85 -> 9.43464 | ... N86: =N84+N85 -> 9.43464 | O86: =SUM(C86:N86) -> 113.21568 | P86: Calculated value (simulated inputs) | Q86: Variable + fixed manufacturing cost
A87: Cost per good unit | B87: $/unit | C87: =IFERROR(C86/C74,0) -> 10.67267 | D87: =IFERROR(D86/D74,0) -> 10.67267 | E87: =IFERROR(E86/E74,0) -> 10.67267 | F87: =IFERROR(F86/F74,0) -> 10.67267 | G87: =IFERROR(G86/G74,0) -> 10.67267 | H87: =IFERROR(H86/H74,0) -> 10.67267 | I87: =IFERROR(I86/I74,0) -> 10.67267 | J87: =IFERROR(J86/J74,0) -> 10.67267 | ... O87: =IFERROR(O86/O74,0) -> 10.67267 | P87: Calculated value (simulated inputs) | Q87: Total manufacturing cost / good units. Rises when yield or utilization falls
A88: Opening inventory value | B88: $m | C88: =Assumptions!$E$68 -> 8.4229049 | D88: =C91 -> 8.1832137 | E88: =D91 -> 7.9402528 | F88: =E91 -> 7.396641 | G88: =F91 -> 7.3839079 | H88: =G91 -> 7.1950045 | I88: =H91 -> 6.5287249 | J88: =I91 -> 5.963431 | K88: =J91 -> 5.5939152 | ... N88: =M91 -> 5.5555312 | O88: =C88 -> 8.4229049 | P88: Calculated value (simulated inputs) | Q88: Prior month's closing value
A89: Average cost per available unit | B89: $/unit | C89: =IFERROR((C88+C86)/C76,0) -> 11.080998 | D89: =IFERROR((D88+D86)/D76,0) -> 10.858524 | E89: =IFERROR((E88+E86)/E76,0) -> 10.756809 | F89: =IFERROR((F88+F86)/F76,0) -> 10.709483 | G89: =IFERROR((G88+G86)/G76,0) -> 10.688801 | H89: =IFERROR((H88+H86)/H76,0) -> 10.679643 | I89: =IFERROR((I88+I86)/I76,0) -> 10.675521 | J89: =IFERROR((J88+J86)/J76,0) -> 10.673774 | ... N89: =IFERROR((N88+N86)/N76,0) -> 10.672692 | P89: Calculated value (simulated inputs) | Q89: (Opening value + manufacturing cost) / available units - weighted-average costing
A90: Cost of revenue | B90: $m | C90: =C77*C89 -> 9.6743312 | D90: =D77*D89 -> 9.6776009 | E90: =E77*E89 -> 9.9782518 | F90: =F77*F89 -> 9.4473731 | G90: =G77*G89 -> 9.6235435 | H90: =H77*H89 -> 10.10092 | I90: =I77*I89 -> 9.9999339 | J90: =J77*J89 -> 9.8041558 | ... N90: =N77*N89 -> 10.482589 | O90: =SUM(C90:N90) -> 117.131 | P90: Calculated value (simulated inputs) | Q90: Units sold x average cost
A91: Closing inventory value | B91: $m | C91: =C88+C86-C90 -> 8.1832137 | D91: =D88+D86-D90 -> 7.9402528 | E91: =E88+E86-E90 -> 7.396641 | F91: =F88+F86-F90 -> 7.3839079 | G91: =G88+G86-G90 -> 7.1950045 | H91: =H88+H86-H90 -> 6.5287249 | I91: =I88+I86-I90 -> 5.963431 | J91: =J88+J86-J90 -> 5.5939152 | ... N91: =N88+N86-N90 -> 4.507582 | O91: =N91 -> 4.507582 | P91: Calculated value (simulated inputs) | Q91: Opening value + manufacturing cost - cost of revenue
A92: Contribution margin | B92: $m | C92: =C82-C77*IFERROR(C83/C73,0) -> 16.635824 | D92: =D82-D77*IFERROR(D83/D73,0) -> 16.982404 | E92: =E82-E77*IFERROR(E83/E73,0) -> 17.675563 | F92: =F82-F77*IFERROR(F83/F73,0) -> 16.809114 | G92: =G82-G77*IFERROR(G83/G73,0) -> 17.155694 | H92: =H82-H77*IFERROR(H83/H73,0) -> 18.022143 | I92: =I82-I77*IFERROR(I83/I73,0) -> 17.848853 | J92: =J82-J77*IFERROR(J83/J73,0) -> 17.502274 | ... N92: =N82-N77*IFERROR(N83/N73,0) -> 18.715302 | O92: =SUM(C92:N92) -> 207.9478 | P92: Calculated value (simulated inputs) | Q92: Revenue - units sold x variable cost per good unit (variable cost / yield)
A93: Contribution margin % | B93: % | C93: =IFERROR(C92/C82,0) -> 0.76988711 | D93: =IFERROR(D92/D82,0) -> 0.76988711 | E93: =IFERROR(E92/E82,0) -> 0.76988711 | F93: =IFERROR(F92/F82,0) -> 0.76988711 | G93: =IFERROR(G92/G82,0) -> 0.76988711 | H93: =IFERROR(H92/H82,0) -> 0.76988711 | I93: =IFERROR(I92/I82,0) -> 0.76988711 | J93: =IFERROR(J92/J82,0) -> 0.76988711 | ... O93: =IFERROR(O92/O82,0) -> 0.76988711 | P93: Calculated value (simulated inputs) | Q93: Contribution margin / revenue
A94: Gross profit | B94: $m | C94: =C82-C90 -> 11.933804 | D94: =D82-D90 -> 12.380703 | E94: =E82-E90 -> 12.980391 | F94: =F82-F90 -> 12.385846 | G94: =G82-G90 -> 12.659846 | H94: =H82-H90 -> 13.307893 | I94: =I82-I90 -> 13.183794 | J94: =J82-J90 -> 12.929403 | ... N94: =N82-N90 -> 13.826562 | O94: =SUM(C94:N94) -> 152.97068 | P94: Calculated value (simulated inputs) | Q94: Revenue - cost of revenue
A95: Gross margin % | B95: % | C95: =IFERROR(C94/C82,0) -> 0.55228291 | D95: =IFERROR(D94/D82,0) -> 0.56127176 | E95: =IFERROR(E94/E82,0) -> 0.56538147 | F95: =IFERROR(F94/F82,0) -> 0.56729363 | G95: =IFERROR(G94/G82,0) -> 0.56812927 | H95: =IFERROR(H94/H82,0) -> 0.56849928 | I95: =IFERROR(I94/I82,0) -> 0.56866584 | J95: =IFERROR(J94/J82,0) -> 0.56873642 | ... O95: =IFERROR(O94/O82,0) -> 0.56634479 | P95: Calculated value (simulated inputs) | Q95: Gross profit / revenue
A97: Division total - Simulated data created for portfolio demonstration. It does not represent nonpublic Microchip Technology information.
A98: Revenue | B98: $m | C98: =C22+C52+C82 -> 94.787685 | D98: =D22+D52+D82 -> 96.762428 | E98: =E22+E52+E82 -> 100.71191 | F98: =F22+F52+F82 -> 95.775056 | G98: =G22+G52+G82 -> 97.7498 | H98: =H22+H52+H82 -> 102.68666 | I98: =I22+I52+I82 -> 101.69929 | J98: =J22+J52+J82 -> 99.724543 | ... N98: =N22+N52+N82 -> 106.63615 | O98: =SUM(C98:N98) -> 1184.8461 | P98: Calculated value (simulated inputs) | Q98: Sum of the three product lines
A99: Variable manufacturing cost | B99: $m | C99: =C24+C54+C84 -> 19.66064 | D99: =D24+D54+D84 -> 19.66064 | E99: =E24+E54+E84 -> 19.66064 | F99: =F24+F54+F84 -> 19.66064 | G99: =G24+G54+G84 -> 19.66064 | H99: =H24+H54+H84 -> 19.66064 | I99: =I24+I54+I84 -> 19.66064 | J99: =J24+J54+J84 -> 19.66064 | ... N99: =N24+N54+N84 -> 19.66064 | O99: =SUM(C99:N99) -> 235.92768 | P99: Calculated value (simulated inputs) | Q99: Sum of the three product lines
A100: Fixed manufacturing cost | B100: $m | C100: =C25+C55+C85 -> 19.1 | D100: =D25+D55+D85 -> 19.1 | E100: =E25+E55+E85 -> 19.1 | F100: =F25+F55+F85 -> 19.1 | G100: =G25+G55+G85 -> 19.1 | H100: =H25+H55+H85 -> 19.1 | I100: =I25+I55+I85 -> 19.1 | J100: =J25+J55+J85 -> 19.1 | ... N100: =N25+N55+N85 -> 19.1 | O100: =SUM(C100:N100) -> 229.2 | P100: Calculated value (simulated inputs) | Q100: Sum of the three product lines
A101: Total manufacturing cost | B101: $m | C101: =C26+C56+C86 -> 38.76064 | D101: =D26+D56+D86 -> 38.76064 | E101: =E26+E56+E86 -> 38.76064 | F101: =F26+F56+F86 -> 38.76064 | G101: =G26+G56+G86 -> 38.76064 | H101: =H26+H56+H86 -> 38.76064 | I101: =I26+I56+I86 -> 38.76064 | J101: =J26+J56+J86 -> 38.76064 | ... N101: =N26+N56+N86 -> 38.76064 | O101: =SUM(C101:N101) -> 465.12768 | P101: Calculated value (simulated inputs) | Q101: Sum of the three product lines
A102: Cost of revenue | B102: $m | C102: =C30+C60+C90 -> 38.20658 | D102: =D30+D60+D90 -> 38.17903 | E102: =E30+E60+E90 -> 39.3447 | F102: =F30+F60+F90 -> 37.23787 | G102: =G30+G60+G90 -> 37.921392 | H102: =H30+H60+H90 -> 39.7941 | I102: =I30+I60+I90 -> 39.390432 | J102: =J30+J60+J90 -> 38.615427 | ... N102: =N30+N60+N90 -> 41.282058 | O102: =SUM(C102:N102) -> 461.59226 | P102: Calculated value (simulated inputs) | Q102: Sum of the three product lines
A103: Contribution margin | B103: $m | C103: =C32+C62+C92 -> 76.160002 | D103: =D32+D62+D92 -> 77.746668 | E103: =E32+E62+E92 -> 80.920002 | F103: =F32+F62+F92 -> 76.953335 | G103: =G32+G62+G92 -> 78.540002 | H103: =H32+H62+H92 -> 82.506668 | I103: =I32+I62+I92 -> 81.713335 | J103: =J32+J62+J92 -> 80.126668 | ... N103: =N32+N62+N92 -> 85.680002 | O103: =SUM(C103:N103) -> 952.00002 | P103: Calculated value (simulated inputs) | Q103: Sum of the three product lines
A104: Contribution margin % | B104: % | C104: =IFERROR(C103/C98,0) -> 0.80347992 | D104: =IFERROR(D103/D98,0) -> 0.80347992 | E104: =IFERROR(E103/E98,0) -> 0.80347992 | F104: =IFERROR(F103/F98,0) -> 0.80347992 | G104: =IFERROR(G103/G98,0) -> 0.80347992 | H104: =IFERROR(H103/H98,0) -> 0.80347992 | I104: =IFERROR(I103/I98,0) -> 0.80347992 | J104: =IFERROR(J103/J98,0) -> 0.80347992 | ... O104: =IFERROR(O103/O98,0) -> 0.80347992 | P104: Calculated value (simulated inputs) | Q104: Contribution margin / revenue
...

Sheet Revenue
A1: Monthly Revenue Forecast - FY2027 (active scenario)
A2: Revenue by product line, units in millions, $m. Simulated data created for portfolio demonstration. It does not represent nonpublic Microchip Technology information.
A3: Simulated data created for portfolio demonstration. It does not represent nonpublic Microchip Technology information.
A4: Scenario shown: | B4: =Assumptions!$C$6 -> Base
A6: Line item | B6: Units | C6: =Ops_Model!C$6 -> 46113 | D6: =Ops_Model!D$6 -> 46143 | E6: =Ops_Model!E$6 -> 46174 | F6: =Ops_Model!F$6 -> 46204 | G6: =Ops_Model!G$6 -> 46235 | H6: =Ops_Model!H$6 -> 46266 | I6: =Ops_Model!I$6 -> 46296 | J6: =Ops_Model!J$6 -> 46327 | ... N6: =Ops_Model!N$6 -> 46447 | O6: FY2027 | P6: Q1 FY27 | Q6: Q2 FY27 | R6: Q3 FY27 | S6: Q4 FY27 | T6: FY2026 base | U6: FY27 vs FY26 | V6: Classification | W6: Formula
A7: Mixed-signal microcontrollers
A8: Units sold | B8: m units | C8: =Ops_Model!C$17 -> 23.988288 | D8: =Ops_Model!D$17 -> 24.488044 | E8: =Ops_Model!E$17 -> 25.487556 | F8: =Ops_Model!F$17 -> 24.238166 | G8: =Ops_Model!G$17 -> 24.737922 | H8: =Ops_Model!H$17 -> 25.987312 | I8: =Ops_Model!I$17 -> 25.737434 | J8: =Ops_Model!J$17 -> 25.237678 | ... N8: =Ops_Model!N$17 -> 26.986824 | O8: =SUM(C8:N8) -> 299.8536 | P8: =SUM(C8:E8) -> 73.963888 | Q8: =SUM(F8:H8) -> 74.9634 | R8: =SUM(I8:K8) -> 74.713522 | S8: =SUM(L8:N8) -> 76.21279 | T8: =Assumptions!C$51 -> 249.878 | U8: =IFERROR(O8/T8-1,"") -> 0.2 | V8: Calculated value (simulated inputs) | W8: Link: Ops_Model units sold
A9: Revenue | B9: $m | C9: =Ops_Model!C$22 -> 47.49681 | D9: =Ops_Model!D$22 -> 48.486327 | E9: =Ops_Model!E$22 -> 50.465361 | F9: =Ops_Model!F$22 -> 47.991569 | G9: =Ops_Model!G$22 -> 48.981085 | H9: =Ops_Model!H$22 -> 51.454878 | I9: =Ops_Model!I$22 -> 50.960119 | J9: =Ops_Model!J$22 -> 49.970602 | ... N9: =Ops_Model!N$22 -> 53.433911 | O9: =SUM(C9:N9) -> 593.71013 | P9: =SUM(C9:E9) -> 146.4485 | Q9: =SUM(F9:H9) -> 148.42753 | R9: =SUM(I9:K9) -> 147.93277 | S9: =SUM(L9:N9) -> 150.90132 | T9: =Assumptions!C$41 -> 499.756 | U9: =IFERROR(O9/T9-1,"") -> 0.188 | V9: Calculated value (simulated inputs) | W9: Link: Ops_Model revenue
A10: Average selling price | B10: $/unit | C10: =IFERROR(C9/C8,0) -> 1.98 | D10: =IFERROR(D9/D8,0) -> 1.98 | E10: =IFERROR(E9/E8,0) -> 1.98 | F10: =IFERROR(F9/F8,0) -> 1.98 | G10: =IFERROR(G9/G8,0) -> 1.98 | H10: =IFERROR(H9/H8,0) -> 1.98 | I10: =IFERROR(I9/I8,0) -> 1.98 | J10: =IFERROR(J9/J8,0) -> 1.98 | ... T10: =IFERROR(T9/T8,0) -> 2 | V10: Calculated value (simulated inputs) | W10: Revenue / units sold
A12: Analog & power management
A13: Units sold | B13: m units | C13: =Ops_Model!C$47 -> 32.427702 | D13: =Ops_Model!D$47 -> 33.103279 | E13: =Ops_Model!E$47 -> 34.454433 | F13: =Ops_Model!F$47 -> 32.76549 | G13: =Ops_Model!G$47 -> 33.441067 | H13: =Ops_Model!H$47 -> 35.13001 | I13: =Ops_Model!I$47 -> 34.792221 | J13: =Ops_Model!J$47 -> 34.116644 | ... N13: =Ops_Model!N$47 -> 36.481164 | O13: =SUM(C13:N13) -> 405.34627 | P13: =SUM(C13:E13) -> 99.985413 | Q13: =SUM(F13:H13) -> 101.33657 | R13: =SUM(I13:K13) -> 100.99878 | S13: =SUM(L13:N13) -> 103.02551 | T13: =Assumptions!D$51 -> 352.47502 | U13: =IFERROR(O13/T13-1,"") -> 0.15 | V13: Calculated value (simulated inputs) | W13: Link: Ops_Model units sold
A14: Revenue | B14: $m | C14: =Ops_Model!C$52 -> 25.68274 | D14: =Ops_Model!D$52 -> 26.217797 | E14: =Ops_Model!E$52 -> 27.287911 | F14: =Ops_Model!F$52 -> 25.950268 | G14: =Ops_Model!G$52 -> 26.485325 | H14: =Ops_Model!H$52 -> 27.822968 | I14: =Ops_Model!I$52 -> 27.555439 | J14: =Ops_Model!J$52 -> 27.020382 | ... N14: =Ops_Model!N$52 -> 28.893082 | O14: =SUM(C14:N14) -> 321.03424 | P14: =SUM(C14:E14) -> 79.188447 | Q14: =SUM(F14:H14) -> 80.258561 | R14: =SUM(I14:K14) -> 79.991033 | S14: =SUM(L14:N14) -> 81.596204 | T14: =Assumptions!D$41 -> 281.98001 | U14: =IFERROR(O14/T14-1,"") -> 0.1385 | V14: Calculated value (simulated inputs) | W14: Link: Ops_Model revenue
A15: Average selling price | B15: $/unit | C15: =IFERROR(C14/C13,0) -> 0.792 | D15: =IFERROR(D14/D13,0) -> 0.792 | E15: =IFERROR(E14/E13,0) -> 0.792 | F15: =IFERROR(F14/F13,0) -> 0.792 | G15: =IFERROR(G14/G13,0) -> 0.792 | H15: =IFERROR(H14/H13,0) -> 0.792 | I15: =IFERROR(I14/I13,0) -> 0.792 | J15: =IFERROR(J14/J13,0) -> 0.792 | ... T15: =IFERROR(T14/T13,0) -> 0.8 | V15: Calculated value (simulated inputs) | W15: Revenue / units sold
A17: FPGAs
A18: Units sold | B18: m units | C18: =Ops_Model!C$77 -> 0.87305595 | D18: =Ops_Model!D$77 -> 0.89124462 | E18: =Ops_Model!E$77 -> 0.92762195 | F18: =Ops_Model!F$77 -> 0.88215028 | G18: =Ops_Model!G$77 -> 0.90033895 | H18: =Ops_Model!H$77 -> 0.94581061 | I18: =Ops_Model!I$77 -> 0.93671628 | J18: =Ops_Model!J$77 -> 0.91852761 | ... N18: =Ops_Model!N$77 -> 0.98218794 | O18: =SUM(C18:N18) -> 10.913199 | P18: =SUM(C18:E18) -> 2.6919225 | Q18: =SUM(F18:H18) -> 2.7282998 | R18: =SUM(I18:K18) -> 2.7192055 | S18: =SUM(L18:N18) -> 2.7737715 | T18: =Assumptions!E$51 -> 8.7305595 | U18: =IFERROR(O18/T18-1,"") -> 0.25 | V18: Calculated value (simulated inputs) | W18: Link: Ops_Model units sold
A19: Revenue | B19: $m | C19: =Ops_Model!C$82 -> 21.608135 | D19: =Ops_Model!D$82 -> 22.058304 | E19: =Ops_Model!E$82 -> 22.958643 | F19: =Ops_Model!F$82 -> 21.83322 | G19: =Ops_Model!G$82 -> 22.283389 | H19: =Ops_Model!H$82 -> 23.408813 | I19: =Ops_Model!I$82 -> 23.183728 | J19: =Ops_Model!J$82 -> 22.733558 | ... N19: =Ops_Model!N$82 -> 24.309152 | O19: =SUM(C19:N19) -> 270.10168 | P19: =SUM(C19:E19) -> 66.625082 | Q19: =SUM(F19:H19) -> 67.525421 | R19: =SUM(I19:K19) -> 67.300336 | S19: =SUM(L19:N19) -> 68.650845 | T19: =Assumptions!E$41 -> 218.26399 | U19: =IFERROR(O19/T19-1,"") -> 0.2375 | V19: Calculated value (simulated inputs) | W19: Link: Ops_Model revenue
A20: Average selling price | B20: $/unit | C20: =IFERROR(C19/C18,0) -> 24.75 | D20: =IFERROR(D19/D18,0) -> 24.75 | E20: =IFERROR(E19/E18,0) -> 24.75 | F20: =IFERROR(F19/F18,0) -> 24.75 | G20: =IFERROR(G19/G18,0) -> 24.75 | H20: =IFERROR(H19/H18,0) -> 24.75 | I20: =IFERROR(I19/I18,0) -> 24.75 | J20: =IFERROR(J19/J18,0) -> 24.75 | ... T20: =IFERROR(T19/T18,0) -> 25 | V20: Calculated value (simulated inputs) | W20: Revenue / units sold
A22: Division
A23: Division revenue | B23: $m | C23: =C9+C14+C19 -> 94.787685 | D23: =D9+D14+D19 -> 96.762428 | E23: =E9+E14+E19 -> 100.71191 | F23: =F9+F14+F19 -> 95.775056 | G23: =G9+G14+G19 -> 97.7498 | H23: =H9+H14+H19 -> 102.68666 | I23: =I9+I14+I19 -> 101.69929 | J23: =J9+J14+J19 -> 99.724543 | ... N23: =N9+N14+N19 -> 106.63615 | O23: =SUM(C23:N23) -> 1184.8461 | P23: =SUM(C23:E23) -> 292.26203 | Q23: =SUM(F23:H23) -> 296.21151 | R23: =SUM(I23:K23) -> 295.22414 | S23: =SUM(L23:N23) -> 301.14837 | T23: =T9+T14+T19 -> 1000 | U23: =IFERROR(O23/T23-1,"") -> 0.18484606 | V23: Calculated value (simulated inputs) | W23: Sum of product lines
A24: Mix - Mixed-signal microcontrollers | B24: % | C24: =IFERROR(C9/C23,0) -> 0.5010863 | D24: =IFERROR(D9/D23,0) -> 0.5010863 | E24: =IFERROR(E9/E23,0) -> 0.5010863 | F24: =IFERROR(F9/F23,0) -> 0.5010863 | G24: =IFERROR(G9/G23,0) -> 0.5010863 | H24: =IFERROR(H9/H23,0) -> 0.5010863 | I24: =IFERROR(I9/I23,0) -> 0.5010863 | J24: =IFERROR(J9/J23,0) -> 0.5010863 | ... T24: =IFERROR(T9/T23,0) -> 0.499756 | V24: Calculated value (simulated inputs) | W24: Product revenue / division revenue
A25: Mix - Analog & power management | B25: % | C25: =IFERROR(C14/C23,0) -> 0.27095017 | D25: =IFERROR(D14/D23,0) -> 0.27095017 | E25: =IFERROR(E14/E23,0) -> 0.27095017 | F25: =IFERROR(F14/F23,0) -> 0.27095017 | G25: =IFERROR(G14/G23,0) -> 0.27095017 | H25: =IFERROR(H14/H23,0) -> 0.27095017 | I25: =IFERROR(I14/I23,0) -> 0.27095017 | J25: =IFERROR(J14/J23,0) -> 0.27095017 | ... T25: =IFERROR(T14/T23,0) -> 0.28198001 | V25: Calculated value (simulated inputs) | W25: Product revenue / division revenue
A26: Mix - FPGAs | B26: % | C26: =IFERROR(C19/C23,0) -> 0.22796353 | D26: =IFERROR(D19/D23,0) -> 0.22796353 | E26: =IFERROR(E19/E23,0) -> 0.22796353 | F26: =IFERROR(F19/F23,0) -> 0.22796353 | G26: =IFERROR(G19/G23,0) -> 0.22796353 | H26: =IFERROR(H19/H23,0) -> 0.22796353 | I26: =IFERROR(I19/I23,0) -> 0.22796353 | J26: =IFERROR(J19/J23,0) -> 0.22796353 | ... T26: =IFERROR(T19/T23,0) -> 0.21826399 | V26: Calculated value (simulated inputs) | W26: Product revenue / division revenue
A27: Mix total | B27: % | C27: =C24+C25+C26 -> 1 | D27: =D24+D25+D26 -> 1 | E27: =E24+E25+E26 -> 1 | F27: =F24+F25+F26 -> 1 | G27: =G24+G25+G26 -> 1 | H27: =H24+H25+H26 -> 1 | I27: =I24+I25+I26 -> 1 | J27: =J24+J25+J26 -> 1 | ... T27: =T24+T25+T26 -> 1 | V27: Calculated value (simulated inputs) | W27: Must be 100%

Sheet PnL
A1: Monthly P&L Forecast - FY2027 (active scenario)
A2: Division P&L to net income, $m. No division-level interest (financing sits at corporate). Simulated data created for portfolio demonstration. It does not represent nonpublic Microchip Technology information.
A3: Simulated data created for portfolio demonstration. It does not represent nonpublic Microchip Technology information.
A4: Scenario shown: | B4: =Assumptions!$C$6 -> Base
A6: Line item | B6: Units | C6: =Ops_Model!C$6 -> 46113 | D6: =Ops_Model!D$6 -> 46143 | E6: =Ops_Model!E$6 -> 46174 | F6: =Ops_Model!F$6 -> 46204 | G6: =Ops_Model!G$6 -> 46235 | H6: =Ops_Model!H$6 -> 46266 | I6: =Ops_Model!I$6 -> 46296 | J6: =Ops_Model!J$6 -> 46327 | ... N6: =Ops_Model!N$6 -> 46447 | O6: FY2027 | P6: Q1 FY27 | Q6: Q2 FY27 | R6: Q3 FY27 | S6: Q4 FY27 | T6: FY2026 base | U6: FY27 vs FY26 | V6: Classification | W6: Formula
A7: Income statement
A8: Revenue | B8: $m | C8: =Revenue!C$23 -> 94.787685 | D8: =Revenue!D$23 -> 96.762428 | E8: =Revenue!E$23 -> 100.71191 | F8: =Revenue!F$23 -> 95.775056 | G8: =Revenue!G$23 -> 97.7498 | H8: =Revenue!H$23 -> 102.68666 | I8: =Revenue!I$23 -> 101.69929 | J8: =Revenue!J$23 -> 99.724543 | ... N8: =Revenue!N$23 -> 106.63615 | O8: =SUM(C8:N8) -> 1184.8461 | P8: =SUM(C8:E8) -> 292.26203 | Q8: =SUM(F8:H8) -> 296.21151 | R8: =SUM(I8:K8) -> 295.22414 | S8: =SUM(L8:N8) -> 301.14837 | T8: =Assumptions!$F$33 -> 1000 | U8: =IFERROR(O8/T8-1,"") -> 0.18484606 | V8: Calculated value (simulated inputs) | W8: Link: Revenue tab
A9: Cost of revenue - manufacturing | B9: $m | C9: =Ops_Model!C$102 -> 38.20658 | D9: =Ops_Model!D$102 -> 38.17903 | E9: =Ops_Model!E$102 -> 39.3447 | F9: =Ops_Model!F$102 -> 37.23787 | G9: =Ops_Model!G$102 -> 37.921392 | H9: =Ops_Model!H$102 -> 39.7941 | I9: =Ops_Model!I$102 -> 39.390432 | J9: =Ops_Model!J$102 -> 38.615427 | ... N9: =Ops_Model!N$102 -> 41.282058 | O9: =SUM(C9:N9) -> 461.59226 | P9: =SUM(C9:E9) -> 115.73031 | Q9: =SUM(F9:H9) -> 114.95336 | R9: =SUM(I9:K9) -> 114.32267 | S9: =SUM(L9:N9) -> 116.58592 | T9: =Assumptions!$F$56 -> 417.91889 | U9: =IFERROR(O9/T9-1,"") -> 0.10450202 | V9: Calculated value (simulated inputs) | W9: Link: Ops_Model (weighted-average inventory cost)
A10: Cost of revenue - depreciation on FY2027 capex | B10: $m | C10: =FCF!C$9 -> 0 | D10: =FCF!D$9 -> 0.047393842 | E10: =FCF!E$9 -> 0.095775056 | F10: =FCF!F$9 -> 0.14613101 | G10: =FCF!G$9 -> 0.19401854 | H10: =FCF!H$9 -> 0.24289344 | I10: =FCF!I$9 -> 0.29423677 | J10: =FCF!J$9 -> 0.34508641 | ... N10: =FCF!N$9 -> 0.53910496 | O10: =SUM(C10:N10) -> 3.2311739 | P10: =SUM(C10:E10) -> 0.1431689 | Q10: =SUM(F10:H10) -> 0.583043 | R10: =SUM(I10:K10) -> 1.0342719 | S10: =SUM(L10:N10) -> 1.4706902 | T10: =0 -> 0 | V10: Calculated value (simulated inputs) | W10: Link: FCF tab section A
A11: Total cost of revenue | B11: $m | C11: =C9+C10 -> 38.20658 | D11: =D9+D10 -> 38.226424 | E11: =E9+E10 -> 39.440475 | F11: =F9+F10 -> 37.384001 | G11: =G9+G10 -> 38.115411 | H11: =H9+H10 -> 40.036994 | I11: =I9+I10 -> 39.684669 | J11: =J9+J10 -> 38.960513 | ... N11: =N9+N10 -> 41.821163 | O11: =SUM(C11:N11) -> 464.82344 | P11: =SUM(C11:E11) -> 115.87348 | Q11: =SUM(F11:H11) -> 115.53641 | R11: =SUM(I11:K11) -> 115.35694 | S11: =SUM(L11:N11) -> 118.05661 | T11: =T9+T10 -> 417.91889 | U11: =IFERROR(O11/T11-1,"") -> 0.1122336 | V11: Calculated value (simulated inputs) | W11: Manufacturing + new-capex depreciation
A12: Gross profit | B12: $m | C12: =C8-C11 -> 56.581104 | D12: =D8-D11 -> 58.536004 | E12: =E8-E11 -> 61.271439 | F12: =F8-F11 -> 58.391055 | G12: =G8-G11 -> 59.634389 | H12: =H8-H11 -> 62.649665 | I12: =I8-I11 -> 62.014617 | J12: =J8-J11 -> 60.76403 | ... N12: =N8-N11 -> 64.814982 | O12: =SUM(C12:N12) -> 720.02262 | P12: =SUM(C12:E12) -> 176.38855 | Q12: =SUM(F12:H12) -> 180.67511 | R12: =SUM(I12:K12) -> 179.8672 | S12: =SUM(L12:N12) -> 183.09176 | T12: =T8-T11 -> 582.08111 | U12: =IFERROR(O12/T12-1,"") -> 0.23697989 | V12: Calculated value (simulated inputs) | W12: Revenue - cost of revenue
A13: Gross margin | B13: % | C13: =IFERROR(C12/C8,0) -> 0.59692464 | D13: =IFERROR(D12/D8,0) -> 0.60494559 | E13: =IFERROR(E12/E8,0) -> 0.60838322 | F13: =IFERROR(F12/F8,0) -> 0.60966871 | G13: =IFERROR(G12/G8,0) -> 0.61007172 | H13: =IFERROR(H12/H8,0) -> 0.61010521 | I13: =IFERROR(I12/I8,0) -> 0.60978419 | J13: =IFERROR(J12/J8,0) -> 0.60931871 | ... T13: =IFERROR(T12/T8,0) -> 0.58208111 | V13: Calculated value (simulated inputs) | W13: Gross profit / revenue
A14: Research and development | B14: $m | C14: =Assumptions!$F$34*(1+Assumptions!$F$15)/12 -> 17.5 | D14: =Assumptions!$F$34*(1+Assumptions!$F$15)/12 -> 17.5 | E14: =Assumptions!$F$34*(1+Assumptions!$F$15)/12 -> 17.5 | F14: =Assumptions!$F$34*(1+Assumptions!$F$15)/12 -> 17.5 | G14: =Assumptions!$F$34*(1+Assumptions!$F$15)/12 -> 17.5 | H14: =Assumptions!$F$34*(1+Assumptions!$F$15)/12 -> 17.5 | I14: =Assumptions!$F$34*(1+Assumptions!$F$15)/12 -> 17.5 | J14: =Assumptions!$F$34*(1+Assumptions!$F$15)/12 -> 17.5 | ... N14: =Assumptions!$F$34*(1+Assumptions!$F$15)/12 -> 17.5 | O14: =SUM(C14:N14) -> 210 | P14: =SUM(C14:E14) -> 52.5 | Q14: =SUM(F14:H14) -> 52.5 | R14: =SUM(I14:K14) -> 52.5 | S14: =SUM(L14:N14) -> 52.5 | T14: =Assumptions!$F$34 -> 200 | U14: =IFERROR(O14/T14-1,"") -> 0.05 | V14: Calculated value (simulated inputs) | W14: Base-year R&D x (1 + R&D growth) / 12
A15: Selling, general and administrative | B15: $m | C15: =Assumptions!$F$35*(1+Assumptions!$F$16)/12 -> 8.6666667 | D15: =Assumptions!$F$35*(1+Assumptions!$F$16)/12 -> 8.6666667 | E15: =Assumptions!$F$35*(1+Assumptions!$F$16)/12 -> 8.6666667 | F15: =Assumptions!$F$35*(1+Assumptions!$F$16)/12 -> 8.6666667 | G15: =Assumptions!$F$35*(1+Assumptions!$F$16)/12 -> 8.6666667 | H15: =Assumptions!$F$35*(1+Assumptions!$F$16)/12 -> 8.6666667 | I15: =Assumptions!$F$35*(1+Assumptions!$F$16)/12 -> 8.6666667 | J15: =Assumptions!$F$35*(1+Assumptions!$F$16)/12 -> 8.6666667 | ... N15: =Assumptions!$F$35*(1+Assumptions!$F$16)/12 -> 8.6666667 | O15: =SUM(C15:N15) -> 104 | P15: =SUM(C15:E15) -> 26 | Q15: =SUM(F15:H15) -> 26 | R15: =SUM(I15:K15) -> 26 | S15: =SUM(L15:N15) -> 26 | T15: =Assumptions!$F$35 -> 100 | U15: =IFERROR(O15/T15-1,"") -> 0.04 | V15: Calculated value (simulated inputs) | W15: Base-year SG&A x (1 + SG&A growth) / 12
A16: Total operating expenses | B16: $m | C16: =C14+C15 -> 26.166667 | D16: =D14+D15 -> 26.166667 | E16: =E14+E15 -> 26.166667 | F16: =F14+F15 -> 26.166667 | G16: =G14+G15 -> 26.166667 | H16: =H14+H15 -> 26.166667 | I16: =I14+I15 -> 26.166667 | J16: =J14+J15 -> 26.166667 | ... N16: =N14+N15 -> 26.166667 | O16: =SUM(C16:N16) -> 314 | P16: =SUM(C16:E16) -> 78.5 | Q16: =SUM(F16:H16) -> 78.5 | R16: =SUM(I16:K16) -> 78.5 | S16: =SUM(L16:N16) -> 78.5 | T16: =T14+T15 -> 300 | U16: =IFERROR(O16/T16-1,"") -> 0.046666667 | V16: Calculated value (simulated inputs) | W16: R&D + SG&A
A17: Operating profit | B17: $m | C17: =C12-C16 -> 30.414438 | D17: =D12-D16 -> 32.369337 | E17: =E12-E16 -> 35.104773 | F17: =F12-F16 -> 32.224388 | G17: =G12-G16 -> 33.467722 | H17: =H12-H16 -> 36.482998 | I17: =I12-I16 -> 35.847951 | J17: =J12-J16 -> 34.597363 | ... N17: =N12-N16 -> 38.648316 | O17: =SUM(C17:N17) -> 406.02262 | P17: =SUM(C17:E17) -> 97.888548 | Q17: =SUM(F17:H17) -> 102.17511 | R17: =SUM(I17:K17) -> 101.3672 | S17: =SUM(L17:N17) -> 104.59176 | T17: =T12-T16 -> 282.08111 | U17: =IFERROR(O17/T17-1,"") -> 0.43938255 | V17: Calculated value (simulated inputs) | W17: Gross profit - operating expenses
A18: Operating margin | B18: % | C18: =IFERROR(C17/C8,0) -> 0.32086909 | D18: =IFERROR(D17/D8,0) -> 0.33452382 | E18: =IFERROR(E17/E8,0) -> 0.34856623 | F18: =IFERROR(F17/F8,0) -> 0.33645909 | G18: =IFERROR(G17/G8,0) -> 0.34238149 | H18: =IFERROR(H17/H8,0) -> 0.35528469 | I18: =IFERROR(I17/I8,0) -> 0.3524897 | J18: =IFERROR(J17/J8,0) -> 0.34692927 | ... T18: =IFERROR(T17/T8,0) -> 0.28208111 | V18: Calculated value (simulated inputs) | W18: Operating profit / revenue
A19: Pre-tax income | B19: $m | C19: =C17 -> 30.414438 | D19: =D17 -> 32.369337 | E19: =E17 -> 35.104773 | F19: =F17 -> 32.224388 | G19: =G17 -> 33.467722 | H19: =H17 -> 36.482998 | I19: =I17 -> 35.847951 | J19: =J17 -> 34.597363 | ... N19: =N17 -> 38.648316 | O19: =SUM(C19:N19) -> 406.02262 | P19: =SUM(C19:E19) -> 97.888548 | Q19: =SUM(F19:H19) -> 102.17511 | R19: =SUM(I19:K19) -> 101.3672 | S19: =SUM(L19:N19) -> 104.59176 | V19: Calculated value (simulated inputs) | W19: Equals operating profit (no division-level interest or other income)
A20: Income tax | B20: $m | C20: =C19*Assumptions!$F$18 -> 5.4745988 | D20: =D19*Assumptions!$F$18 -> 5.8264807 | E20: =E19*Assumptions!$F$18 -> 6.3188591 | F20: =F19*Assumptions!$F$18 -> 5.8003899 | G20: =G19*Assumptions!$F$18 -> 6.02419 | H20: =H19*Assumptions!$F$18 -> 6.5669396 | I20: =I19*Assumptions!$F$18 -> 6.4526311 | J20: =J19*Assumptions!$F$18 -> 6.2275254 | ... N20: =N19*Assumptions!$F$18 -> 6.9566968 | O20: =SUM(C20:N20) -> 73.084072 | P20: =SUM(C20:E20) -> 17.619939 | Q20: =SUM(F20:H20) -> 18.39152 | R20: =SUM(I20:K20) -> 18.246096 | S20: =SUM(L20:N20) -> 18.826518 | V20: Calculated value (simulated inputs) | W20: Pre-tax income x scenario tax rate (a loss month gives a tax credit)
A21: Net income | B21: $m | C21: =C19-C20 -> 24.939839 | D21: =D19-D20 -> 26.542857 | E21: =E19-E20 -> 28.785914 | F21: =F19-F20 -> 26.423998 | G21: =G19-G20 -> 27.443532 | H21: =H19-H20 -> 29.916058 | I21: =I19-I20 -> 29.39532 | J21: =J19-J20 -> 28.369838 | ... N21: =N19-N20 -> 31.691619 | O21: =SUM(C21:N21) -> 332.93855 | P21: =SUM(C21:E21) -> 80.268609 | Q21: =SUM(F21:H21) -> 83.783589 | R21: =SUM(I21:K21) -> 83.121104 | S21: =SUM(L21:N21) -> 85.765247 | V21: Calculated value (simulated inputs) | W21: Pre-tax income - tax
A22: Net margin | B22: % | C22: =IFERROR(C21/C8,0) -> 0.26311265 | D22: =IFERROR(D21/D8,0) -> 0.27430953 | E22: =IFERROR(E21/E8,0) -> 0.28582431 | F22: =IFERROR(F21/F8,0) -> 0.27589645 | G22: =IFERROR(G21/G8,0) -> 0.28075282 | H22: =IFERROR(H21/H8,0) -> 0.29133345 | I22: =IFERROR(I21/I8,0) -> 0.28904155 | J22: =IFERROR(J21/J8,0) -> 0.284482 | ... S22: =IFERROR(S21/S8,0) -> 0.28479399 | V22: Calculated value (simulated inputs) | W22: Net income / revenue
A24: Memo
A25: Depreciation (from FCF tab) | B25: $m | C25: =FCF!C$11 -> 5.73 | D25: =FCF!D$11 -> 5.7773938 | E25: =FCF!E$11 -> 5.8257751 | F25: =FCF!F$11 -> 5.876131 | G25: =FCF!G$11 -> 5.9240185 | H25: =FCF!H$11 -> 5.9728934 | I25: =FCF!I$11 -> 6.0242368 | J25: =FCF!J$11 -> 6.0750864 | ... N25: =FCF!N$11 -> 6.269105 | O25: =SUM(C25:N25) -> 71.991174 | P25: =SUM(C25:E25) -> 17.333169 | Q25: =SUM(F25:H25) -> 17.773043 | R25: =SUM(I25:K25) -> 18.224272 | S25: =SUM(L25:N25) -> 18.66069 | V25: Calculated value (simulated inputs) | W25: Link: FCF tab total depreciation
A26: EBITDA | B26: $m | C26: =C17+C25 -> 36.144438 | D26: =D17+D25 -> 38.146731 | E26: =E17+E25 -> 40.930548 | F26: =F17+F25 -> 38.100519 | G26: =G17+G25 -> 39.391741 | H26: =H17+H25 -> 42.455891 | I26: =I17+I25 -> 41.872188 | J26: =J17+J25 -> 40.67245 | ... N26: =N17+N25 -> 44.917421 | O26: =SUM(C26:N26) -> 478.0138 | P26: =SUM(C26:E26) -> 115.22172 | Q26: =SUM(F26:H26) -> 119.94815 | R26: =SUM(I26:K26) -> 119.59147 | S26: =SUM(L26:N26) -> 123.25246 | V26: Calculated value (simulated inputs) | W26: Operating profit + depreciation
A27: EBITDA margin | B27: % | C27: =IFERROR(C26/C8,0) -> 0.38131998 | D27: =IFERROR(D26/D8,0) -> 0.39423082 | E27: =IFERROR(E26/E8,0) -> 0.40641217 | F27: =IFERROR(F26/F8,0) -> 0.39781255 | G27: =IFERROR(G26/G8,0) -> 0.40298539 | H27: =IFERROR(H26/H8,0) -> 0.4134509 | I27: =IFERROR(I26/I8,0) -> 0.41172548 | J27: =IFERROR(J26/J8,0) -> 0.40784794 | ... S27: =IFERROR(S26/S8,0) -> 0.40927485 | V27: Calculated value (simulated inputs) | W27: EBITDA / revenue
A28: Contribution margin (from Ops_Model) | B28: $m | C28: =Ops_Model!C$103 -> 76.160002 | D28: =Ops_Model!D$103 -> 77.746668 | E28: =Ops_Model!E$103 -> 80.920002 | F28: =Ops_Model!F$103 -> 76.953335 | G28: =Ops_Model!G$103 -> 78.540002 | H28: =Ops_Model!H$103 -> 82.506668 | I28: =Ops_Model!I$103 -> 81.713335 | J28: =Ops_Model!J$103 -> 80.126668 | ... N28: =Ops_Model!N$103 -> 85.680002 | O28: =SUM(C28:N28) -> 952.00002 | P28: =SUM(C28:E28) -> 234.82667 | Q28: =SUM(F28:H28) -> 238 | R28: =SUM(I28:K28) -> 237.20667 | S28: =SUM(L28:N28) -> 241.96667 | V28: Calculated value (simulated inputs) | W28: Revenue - variable cost of units sold

Sheet FCF
A1: Free Cash Flow Forecast - FY2027 (active scenario)
A2: FCF = net income + depreciation - capital expenditures - increase in working capital. Simulated data created for portfolio demonstration. It does not represent nonpublic Microchip Technology information.
A3: Simulated data created for portfolio demonstration. It does not represent nonpublic Microchip Technology information.
A4: Scenario shown: | B4: =Assumptions!$C$6 -> Base
A6: Line item | B6: Units | C6: =Ops_Model!C$6 -> 46113 | D6: =Ops_Model!D$6 -> 46143 | E6: =Ops_Model!E$6 -> 46174 | F6: =Ops_Model!F$6 -> 46204 | G6: =Ops_Model!G$6 -> 46235 | H6: =Ops_Model!H$6 -> 46266 | I6: =Ops_Model!I$6 -> 46296 | J6: =Ops_Model!J$6 -> 46327 | ... N6: =Ops_Model!N$6 -> 46447 | O6: FY2027 | P6: Q1 FY27 | Q6: Q2 FY27 | R6: Q3 FY27 | S6: Q4 FY27 | T6: FY2026 base | U6: FY27 vs FY26 | V6: Classification | W6: Formula
A7: A. Capital expenditures and depreciation
A8: Capital expenditures | B8: $m | C8: =Revenue!C$23*Assumptions!$F$17 -> 2.8436305 | D8: =Revenue!D$23*Assumptions!$F$17 -> 2.9028728 | E8: =Revenue!E$23*Assumptions!$F$17 -> 3.0213574 | F8: =Revenue!F$23*Assumptions!$F$17 -> 2.8732517 | G8: =Revenue!G$23*Assumptions!$F$17 -> 2.932494 | H8: =Revenue!H$23*Assumptions!$F$17 -> 3.0805997 | I8: =Revenue!I$23*Assumptions!$F$17 -> 3.0509786 | J8: =Revenue!J$23*Assumptions!$F$17 -> 2.9917363 | ... N8: =Revenue!N$23*Assumptions!$F$17 -> 3.1990844 | O8: =SUM(C8:N8) -> 35.545382 | P8: =SUM(C8:E8) -> 8.7678608 | Q8: =SUM(F8:H8) -> 8.8863454 | R8: =SUM(I8:K8) -> 8.8567243 | S8: =SUM(L8:N8) -> 9.0344512 | V8: Calculated value (simulated inputs) | W8: Revenue x capex % (scenario). Excludes the Phase 5 test-equipment proposal
A9: Depreciation on FY2027 capex | B9: $m | C9: =0 -> 0 | D9: =SUM($C$8:C8)/Assumptions!$F$85 -> 0.047393842 | E9: =SUM($C$8:D8)/Assumptions!$F$85 -> 0.095775056 | F9: =SUM($C$8:E8)/Assumptions!$F$85 -> 0.14613101 | G9: =SUM($C$8:F8)/Assumptions!$F$85 -> 0.19401854 | H9: =SUM($C$8:G8)/Assumptions!$F$85 -> 0.24289344 | I9: =SUM($C$8:H8)/Assumptions!$F$85 -> 0.29423677 | J9: =SUM($C$8:I8)/Assumptions!$F$85 -> 0.34508641 | K9: =SUM($C$8:J8)/Assumptions!$F$85 -> 0.39494869 | ... N9: =SUM($C$8:M8)/Assumptions!$F$85 -> 0.53910496 | O9: =SUM(C9:N9) -> 3.2311739 | P9: =SUM(C9:E9) -> 0.1431689 | Q9: =SUM(F9:H9) -> 0.583043 | R9: =SUM(I9:K9) -> 1.0342719 | S9: =SUM(L9:N9) -> 1.4706902 | V9: Calculated value (simulated inputs) | W9: Straight-line over useful life; starts the month after spend
A10: Depreciation inside fixed manufacturing cost | B10: $m | C10: =Ops_Model!C$100*Assumptions!$F$84 -> 5.73 | D10: =Ops_Model!D$100*Assumptions!$F$84 -> 5.73 | E10: =Ops_Model!E$100*Assumptions!$F$84 -> 5.73 | F10: =Ops_Model!F$100*Assumptions!$F$84 -> 5.73 | G10: =Ops_Model!G$100*Assumptions!$F$84 -> 5.73 | H10: =Ops_Model!H$100*Assumptions!$F$84 -> 5.73 | I10: =Ops_Model!I$100*Assumptions!$F$84 -> 5.73 | J10: =Ops_Model!J$100*Assumptions!$F$84 -> 5.73 | ... N10: =Ops_Model!N$100*Assumptions!$F$84 -> 5.73 | O10: =SUM(C10:N10) -> 68.76 | P10: =SUM(C10:E10) -> 17.19 | Q10: =SUM(F10:H10) -> 17.19 | R10: =SUM(I10:K10) -> 17.19 | S10: =SUM(L10:N10) -> 17.19 | V10: Calculated value (simulated inputs) | W10: Fixed manufacturing cost x depreciation share
A11: Total depreciation | B11: $m | C11: =C9+C10 -> 5.73 | D11: =D9+D10 -> 5.7773938 | E11: =E9+E10 -> 5.8257751 | F11: =F9+F10 -> 5.876131 | G11: =G9+G10 -> 5.9240185 | H11: =H9+H10 -> 5.9728934 | I11: =I9+I10 -> 6.0242368 | J11: =J9+J10 -> 6.0750864 | ... N11: =N9+N10 -> 6.269105 | O11: =SUM(C11:N11) -> 71.991174 | P11: =SUM(C11:E11) -> 17.333169 | Q11: =SUM(F11:H11) -> 17.773043 | R11: =SUM(I11:K11) -> 18.224272 | S11: =SUM(L11:N11) -> 18.66069 | V11: Calculated value (simulated inputs) | W11: Sum of the two lines above
A13: B. Operating working capital (period-end balances)
A14: Accounts receivable | B14: $m | C14: =Revenue!C$23*12*Assumptions!$F$82/365 -> 186.97845 | D14: =Revenue!D$23*12*Assumptions!$F$82/365 -> 190.87383 | E14: =Revenue!E$23*12*Assumptions!$F$82/365 -> 198.6646 | F14: =Revenue!F$23*12*Assumptions!$F$82/365 -> 188.92614 | G14: =Revenue!G$23*12*Assumptions!$F$82/365 -> 192.82152 | H14: =Revenue!H$23*12*Assumptions!$F$82/365 -> 202.55998 | I14: =Revenue!I$23*12*Assumptions!$F$82/365 -> 200.61229 | J14: =Revenue!J$23*12*Assumptions!$F$82/365 -> 196.71691 | ... N14: =Revenue!N$23*12*Assumptions!$F$82/365 -> 210.35075 | O14: =N14 -> 210.35075 | P14: =E14 -> 198.6646 | Q14: =H14 -> 202.55998 | R14: =K14 -> 185.03075 | S14: =N14 -> 210.35075 | V14: Calculated value (simulated inputs) | W14: Monthly revenue x 12 x DSO / 365
A15: Inventory (finished goods) | B15: $m | C15: =Ops_Model!C$107 -> 35.380634 | D15: =Ops_Model!D$107 -> 35.962244 | E15: =Ops_Model!E$107 -> 35.378184 | F15: =Ops_Model!F$107 -> 36.900953 | G15: =Ops_Model!G$107 -> 37.740201 | H15: =Ops_Model!H$107 -> 36.706741 | I15: =Ops_Model!I$107 -> 36.076949 | J15: =Ops_Model!J$107 -> 36.222162 | ... N15: =Ops_Model!N$107 -> 38.361993 | O15: =N15 -> 38.361993 | P15: =E15 -> 35.378184 | Q15: =H15 -> 36.706741 | R15: =K15 -> 38.665991 | S15: =N15 -> 38.361993 | V15: Calculated value (simulated inputs) | W15: Link: Ops_Model closing inventory value
A16: Accounts payable | B16: $m | C16: =Ops_Model!C$99*12*Assumptions!$F$83/365 -> 25.855088 | D16: =Ops_Model!D$99*12*Assumptions!$F$83/365 -> 25.855088 | E16: =Ops_Model!E$99*12*Assumptions!$F$83/365 -> 25.855088 | F16: =Ops_Model!F$99*12*Assumptions!$F$83/365 -> 25.855088 | G16: =Ops_Model!G$99*12*Assumptions!$F$83/365 -> 25.855088 | H16: =Ops_Model!H$99*12*Assumptions!$F$83/365 -> 25.855088 | I16: =Ops_Model!I$99*12*Assumptions!$F$83/365 -> 25.855088 | J16: =Ops_Model!J$99*12*Assumptions!$F$83/365 -> 25.855088 | ... N16: =Ops_Model!N$99*12*Assumptions!$F$83/365 -> 25.855088 | O16: =N16 -> 25.855088 | P16: =E16 -> 25.855088 | Q16: =H16 -> 25.855088 | R16: =K16 -> 25.855088 | S16: =N16 -> 25.855088 | V16: Calculated value (simulated inputs) | W16: Monthly variable manufacturing cost x 12 x DPO / 365
A17: Operating working capital | B17: $m | C17: =C14+C15-C16 -> 196.50399 | D17: =D14+D15-D16 -> 200.98099 | E17: =E14+E15-E16 -> 208.18769 | F17: =F14+F15-F16 -> 199.972 | G17: =G14+G15-G16 -> 204.70664 | H17: =H14+H15-H16 -> 213.41164 | I17: =I14+I15-I16 -> 210.83415 | J17: =J14+J15-J16 -> 207.08398 | ... N17: =N14+N15-N16 -> 222.85766 | O17: =N17 -> 222.85766 | P17: =E17 -> 208.18769 | Q17: =H17 -> 213.41164 | R17: =K17 -> 197.84166 | S17: =N17 -> 222.85766 | V17: Calculated value (simulated inputs) | W17: AR + inventory - AP
A18: Increase in working capital | B18: $m | C18: =C17-Assumptions!$F$92 -> 17.975379 | D18: =D17-C17 -> 4.4769942 | E18: =E17-D17 -> 7.2067082 | F18: =F17-E17 -> -8.2156912 | G18: =G17-F17 -> 4.7346321 | H18: =H17-G17 -> 8.7050006 | I18: =I17-H17 -> -2.5774845 | J18: =J17-I17 -> -3.7501712 | K18: =K17-J17 -> -9.2423237 | ... N18: =N17-M17 -> 13.060119 | O18: =SUM(C18:N18) -> 44.329043 | P18: =SUM(C18:E18) -> 29.659081 | Q18: =SUM(F18:H18) -> 5.2239415 | R18: =SUM(I18:K18) -> -15.569979 | S18: =SUM(L18:N18) -> 25.016 | V18: Calculated value (simulated inputs) | W18: This month's working capital - prior month's (first month vs 31-Mar-2026 opening balance)
A20: C. Free cash flow
A21: Net income | B21: $m | C21: =PnL!C$21 -> 24.939839 | D21: =PnL!D$21 -> 26.542857 | E21: =PnL!E$21 -> 28.785914 | F21: =PnL!F$21 -> 26.423998 | G21: =PnL!G$21 -> 27.443532 | H21: =PnL!H$21 -> 29.916058 | I21: =PnL!I$21 -> 29.39532 | J21: =PnL!J$21 -> 28.369838 | ... N21: =PnL!N$21 -> 31.691619 | O21: =SUM(C21:N21) -> 332.93855 | P21: =SUM(C21:E21) -> 80.268609 | Q21: =SUM(F21:H21) -> 83.783589 | R21: =SUM(I21:K21) -> 83.121104 | S21: =SUM(L21:N21) -> 85.765247 | V21: Calculated value (simulated inputs) | W21: Link: PnL
A22: + Depreciation | B22: $m | C22: =C11 -> 5.73 | D22: =D11 -> 5.7773938 | E22: =E11 -> 5.8257751 | F22: =F11 -> 5.876131 | G22: =G11 -> 5.9240185 | H22: =H11 -> 5.9728934 | I22: =I11 -> 6.0242368 | J22: =J11 -> 6.0750864 | ... N22: =N11 -> 6.269105 | O22: =SUM(C22:N22) -> 71.991174 | P22: =SUM(C22:E22) -> 17.333169 | Q22: =SUM(F22:H22) -> 17.773043 | R22: =SUM(I22:K22) -> 18.224272 | S22: =SUM(L22:N22) -> 18.66069 | V22: Calculated value (simulated inputs) | W22: Section A
A23: - Capital expenditures | B23: $m | C23: =-C8 -> -2.8436305 | D23: =-D8 -> -2.9028728 | E23: =-E8 -> -3.0213574 | F23: =-F8 -> -2.8732517 | G23: =-G8 -> -2.932494 | H23: =-H8 -> -3.0805997 | I23: =-I8 -> -3.0509786 | J23: =-J8 -> -2.9917363 | ... N23: =-N8 -> -3.1990844 | O23: =SUM(C23:N23) -> -35.545382 | P23: =SUM(C23:E23) -> -8.7678608 | Q23: =SUM(F23:H23) -> -8.8863454 | R23: =SUM(I23:K23) -> -8.8567243 | S23: =SUM(L23:N23) -> -9.0344512 | V23: Calculated value (simulated inputs) | W23: Section A
A24: - Increase in working capital | B24: $m | C24: =-C18 -> -17.975379 | D24: =-D18 -> -4.4769942 | E24: =-E18 -> -7.2067082 | F24: =-F18 -> 8.2156912 | G24: =-G18 -> -4.7346321 | H24: =-H18 -> -8.7050006 | I24: =-I18 -> 2.5774845 | J24: =-J18 -> 3.7501712 | ... N24: =-N18 -> -13.060119 | O24: =SUM(C24:N24) -> -44.329043 | P24: =SUM(C24:E24) -> -29.659081 | Q24: =SUM(F24:H24) -> -5.2239415 | R24: =SUM(I24:K24) -> 15.569979 | S24: =SUM(L24:N24) -> -25.016 | V24: Calculated value (simulated inputs) | W24: Section B
A25: Free cash flow | B25: $m | C25: =C21+C22+C23+C24 -> 9.8508296 | D25: =D21+D22+D23+D24 -> 24.940383 | E25: =E21+E22+E23+E24 -> 24.383623 | F25: =F21+F22+F23+F24 -> 37.642569 | G25: =G21+G22+G23+G24 -> 25.700425 | H25: =H21+H22+H23+H24 -> 24.103351 | I25: =I21+I22+I23+I24 -> 34.946062 | J25: =J21+J22+J23+J24 -> 35.203359 | ... N25: =N21+N22+N23+N24 -> 21.70152 | O25: =SUM(C25:N25) -> 325.0553 | P25: =SUM(C25:E25) -> 59.174836 | Q25: =SUM(F25:H25) -> 87.446345 | R25: =SUM(I25:K25) -> 108.05863 | S25: =SUM(L25:N25) -> 70.375486 | V25: Calculated value (simulated inputs) | W25: Net income + depreciation - capex - increase in working capital
A26: FCF margin | B26: % | C26: =IFERROR(C25/Revenue!C$23,0) -> 0.10392521 | D26: =IFERROR(D25/Revenue!D$23,0) -> 0.25774863 | E26: =IFERROR(E25/Revenue!E$23,0) -> 0.24211259 | F26: =IFERROR(F25/Revenue!F$23,0) -> 0.39303103 | G26: =IFERROR(G25/Revenue!G$23,0) -> 0.26292048 | H26: =IFERROR(H25/Revenue!H$23,0) -> 0.2347272 | I26: =IFERROR(I25/Revenue!I$23,0) -> 0.34362151 | J26: =IFERROR(J25/Revenue!J$23,0) -> 0.35300597 | ... S26: =IFERROR(S25/Revenue!S$23,0) -> 0.23369041 | V26: Calculated value (simulated inputs) | W26: FCF / revenue
A27: FCF conversion (FCF / net income) | B27: x | C27: =IFERROR(C25/C21,0) -> 0.39498369 | D27: =IFERROR(D25/D21,0) -> 0.93962695 | E27: =IFERROR(E25/E21,0) -> 0.84706789 | F27: =IFERROR(F25/F21,0) -> 1.4245599 | G27: =IFERROR(G25/G21,0) -> 0.93648385 | H27: =IFERROR(H25/H21,0) -> 0.80569944 | I27: =IFERROR(I25/I21,0) -> 1.1888308 | J27: =IFERROR(J25/J21,0) -> 1.2408728 | ... S27: =IFERROR(S25/S21,0) -> 0.82055947 | V27: Calculated value (simulated inputs) | W27: FCF / net income
A28: Cumulative free cash flow | B28: $m | C28: =C25 -> 9.8508296 | D28: =C28+D25 -> 34.791213 | E28: =D28+E25 -> 59.174836 | F28: =E28+F25 -> 96.817405 | G28: =F28+G25 -> 122.51783 | H28: =G28+H25 -> 146.62118 | I28: =H28+I25 -> 181.56724 | J28: =I28+J25 -> 216.7706 | K28: =J28+K25 -> 254.67981 | ... N28: =M28+N25 -> 325.0553 | O28: =N28 -> 325.0553 | P28: =E28 -> 59.174836 | Q28: =H28 -> 146.62118 | R28: =K28 -> 254.67981 | S28: =N28 -> 325.0553 | V28: Calculated value (simulated inputs) | W28: Running total from April 2026

Sheet Budget
A1: FY2027 Budget - Base scenario, LOCKED
A2: Reads the Base column (Assumptions column D) directly, so it does NOT change with the scenario selector.
A3: Simulated data created for portfolio demonstration. It does not represent nonpublic Microchip Technology information.
A6: Line item | B6: Units | C6: =Ops_Model!C$6 -> 46113 | D6: =Ops_Model!D$6 -> 46143 | E6: =Ops_Model!E$6 -> 46174 | F6: =Ops_Model!F$6 -> 46204 | G6: =Ops_Model!G$6 -> 46235 | H6: =Ops_Model!H$6 -> 46266 | I6: =Ops_Model!I$6 -> 46296 | J6: =Ops_Model!J$6 -> 46327 | ... N6: =Ops_Model!N$6 -> 46447 | O6: FY2027 | P6: YTD Apr-Aug | Q6: Classification | R6: Formula
A8: Budget drivers (links to the Base column of Assumptions section A)
A9: Customer demand growth | C9: =Assumptions!$D$10 -> 0.2 | Q9: User-provided assumption (Base)
A10: Average selling price change | C10: =Assumptions!$D$11 -> -0.01 | Q10: User-provided assumption (Base)
A11: Manufacturing yield change (percentage points vs base-year yield) | C11: =Assumptions!$D$12 -> 0 | Q11: User-provided assumption (Base)
A12: Capacity utilization (internal final test) | C12: =Assumptions!$D$13 -> 0.8 | Q12: User-provided assumption (Base)
A13: Material-cost inflation (variable cost per unit) | C13: =Assumptions!$D$14 -> 0.03 | Q13: User-provided assumption (Base)
A14: R&D expense growth | C14: =Assumptions!$D$15 -> 0.05 | Q14: User-provided assumption (Base)
A15: SG&A expense growth | C15: =Assumptions!$D$16 -> 0.04 | Q15: User-provided assumption (Base)
A16: Capital expenditures (% of revenue, excl. proposed test-equipment project) | C16: =Assumptions!$D$17 -> 0.03 | Q16: User-provided assumption (Base)
A18: Mixed-signal microcontrollers - budget (Simulated data created for portfolio demonstration. It does not represent nonpublic Microchip Technology information.)
A19: Customer demand | B19: m units | C19: =Assumptions!$C$51*(1+$C$9+Assumptions!$C$47)*Assumptions!C$72/12 -> 23.988288 | D19: =Assumptions!$C$51*(1+$C$9+Assumptions!$C$47)*Assumptions!D$72/12 -> 24.488044 | E19: =Assumptions!$C$51*(1+$C$9+Assumptions!$C$47)*Assumptions!E$72/12 -> 25.487556 | F19: =Assumptions!$C$51*(1+$C$9+Assumptions!$C$47)*Assumptions!F$72/12 -> 24.238166 | G19: =Assumptions!$C$51*(1+$C$9+Assumptions!$C$47)*Assumptions!G$72/12 -> 24.737922 | H19: =Assumptions!$C$51*(1+$C$9+Assumptions!$C$47)*Assumptions!H$72/12 -> 25.987312 | I19: =Assumptions!$C$51*(1+$C$9+Assumptions!$C$47)*Assumptions!I$72/12 -> 25.737434 | J19: =Assumptions!$C$51*(1+$C$9+Assumptions!$C$47)*Assumptions!J$72/12 -> 25.237678 | ... N19: =Assumptions!$C$51*(1+$C$9+Assumptions!$C$47)*Assumptions!N$72/12 -> 26.986824 | O19: =SUM(C19:N19) -> 299.8536 | P19: =SUM(C19:G19) -> 122.93998 | Q19: Calculated value (budget)
A20: Internal final-test capacity | B20: m units | C20: =Assumptions!$C$46 -> 35 | D20: =Assumptions!$C$46 -> 35 | E20: =Assumptions!$C$46 -> 35 | F20: =Assumptions!$C$46 -> 35 | G20: =Assumptions!$C$46 -> 35 | H20: =Assumptions!$C$46 -> 35 | I20: =Assumptions!$C$46 -> 35 | J20: =Assumptions!$C$46 -> 35 | ... N20: =Assumptions!$C$46 -> 35 | O20: =SUM(C20:N20) -> 420 | P20: =SUM(C20:G20) -> 175 | Q20: Calculated value (budget)
A21: Capacity utilization | B21: % | C21: =$C$12 -> 0.8 | D21: =$C$12 -> 0.8 | E21: =$C$12 -> 0.8 | F21: =$C$12 -> 0.8 | G21: =$C$12 -> 0.8 | H21: =$C$12 -> 0.8 | I21: =$C$12 -> 0.8 | J21: =$C$12 -> 0.8 | ... N21: =$C$12 -> 0.8 | O21: =IFERROR(O22/O20,0) -> 0.8 | P21: =IFERROR(P22/P20,0) -> 0.8 | Q21: Calculated value (budget)
A22: Units produced (tested) | B22: m units | C22: =C20*C21 -> 28 | D22: =D20*D21 -> 28 | E22: =E20*E21 -> 28 | F22: =F20*F21 -> 28 | G22: =G20*G21 -> 28 | H22: =H20*H21 -> 28 | I22: =I20*I21 -> 28 | J22: =J20*J21 -> 28 | ... N22: =N20*N21 -> 28 | O22: =SUM(C22:N22) -> 336 | P22: =SUM(C22:G22) -> 140 | Q22: Calculated value (budget) | R22: Capacity x utilization
A23: Manufacturing yield (final test) | B23: % | C23: =MIN(1,MAX(0,Assumptions!$C$43+$C$11)) -> 0.92 | D23: =MIN(1,MAX(0,Assumptions!$C$43+$C$11)) -> 0.92 | E23: =MIN(1,MAX(0,Assumptions!$C$43+$C$11)) -> 0.92 | F23: =MIN(1,MAX(0,Assumptions!$C$43+$C$11)) -> 0.92 | G23: =MIN(1,MAX(0,Assumptions!$C$43+$C$11)) -> 0.92 | H23: =MIN(1,MAX(0,Assumptions!$C$43+$C$11)) -> 0.92 | I23: =MIN(1,MAX(0,Assumptions!$C$43+$C$11)) -> 0.92 | J23: =MIN(1,MAX(0,Assumptions!$C$43+$C$11)) -> 0.92 | ... N23: =MIN(1,MAX(0,Assumptions!$C$43+$C$11)) -> 0.92 | O23: =IFERROR(O24/O22,0) -> 0.92 | P23: =IFERROR(P24/P22,0) -> 0.92 | Q23: Calculated value (budget)
A24: Good units produced | B24: m units | C24: =C22*C23 -> 25.76 | D24: =D22*D23 -> 25.76 | E24: =E22*E23 -> 25.76 | F24: =F22*F23 -> 25.76 | G24: =G22*G23 -> 25.76 | H24: =H22*H23 -> 25.76 | I24: =I22*I23 -> 25.76 | J24: =J22*J23 -> 25.76 | ... N24: =N22*N23 -> 25.76 | O24: =SUM(C24:N24) -> 309.12 | P24: =SUM(C24:G24) -> 128.8 | Q24: Calculated value (budget) | R24: Units produced x yield
A25: Opening finished-goods inventory | B25: m units | C25: =Assumptions!$C$67 -> 20.823167 | D25: =C28 -> 22.594879 | E25: =D28 -> 23.866835 | F25: =E28 -> 24.139279 | G25: =F28 -> 25.661113 | H25: =G28 -> 26.683191 | I25: =H28 -> 26.455879 | J25: =I28 -> 26.478445 | K25: =J28 -> 27.000767 | ... N25: =M28 -> 31.316391 | O25: =C25 -> 20.823167 | P25: =C25 -> 20.823167 | Q25: Calculated value (budget)
A26: Available good units | B26: m units | C26: =C25+C24 -> 46.583167 | D26: =D25+D24 -> 48.354879 | E26: =E25+E24 -> 49.626835 | F26: =F25+F24 -> 49.899279 | G26: =G25+G24 -> 51.421113 | H26: =H25+H24 -> 52.443191 | I26: =I25+I24 -> 52.215879 | J26: =J25+J24 -> 52.238445 | ... N26: =N25+N24 -> 57.076391 | Q26: Calculated value (budget)
A27: Units sold | B27: m units | C27: =MIN(C19,C26) -> 23.988288 | D27: =MIN(D19,D26) -> 24.488044 | E27: =MIN(E19,E26) -> 25.487556 | F27: =MIN(F19,F26) -> 24.238166 | G27: =MIN(G19,G26) -> 24.737922 | H27: =MIN(H19,H26) -> 25.987312 | I27: =MIN(I19,I26) -> 25.737434 | J27: =MIN(J19,J26) -> 25.237678 | ... N27: =MIN(N19,N26) -> 26.986824 | O27: =SUM(C27:N27) -> 299.8536 | P27: =SUM(C27:G27) -> 122.93998 | Q27: Calculated value (budget) | R27: MIN(demand, available)
A28: Closing finished-goods inventory | B28: m units | C28: =C26-C27 -> 22.594879 | D28: =D26-D27 -> 23.866835 | E28: =E26-E27 -> 24.139279 | F28: =F26-F27 -> 25.661113 | G28: =G26-G27 -> 26.683191 | H28: =H26-H27 -> 26.455879 | I28: =I26-I27 -> 26.478445 | J28: =J26-J27 -> 27.000767 | ... N28: =N26-N27 -> 30.089567 | O28: =N28 -> 30.089567 | P28: =G28 -> 26.683191 | Q28: Calculated value (budget) | R28: Available - sold
A29: Unmet demand | B29: m units | C29: =C19-C27 -> 0 | D29: =D19-D27 -> 0 | E29: =E19-E27 -> 0 | F29: =F19-F27 -> 0 | G29: =G19-G27 -> 0 | H29: =H19-H27 -> 0 | I29: =I19-I27 -> 0 | J29: =J19-J27 -> 0 | ... N29: =N19-N27 -> 0 | O29: =SUM(C29:N29) -> 0 | P29: =SUM(C29:G29) -> 0 | Q29: Calculated value (budget)
A30: Average selling price | B30: $/unit | C30: =Assumptions!$C$42*(1+$C$10) -> 1.98 | D30: =Assumptions!$C$42*(1+$C$10) -> 1.98 | E30: =Assumptions!$C$42*(1+$C$10) -> 1.98 | F30: =Assumptions!$C$42*(1+$C$10) -> 1.98 | G30: =Assumptions!$C$42*(1+$C$10) -> 1.98 | H30: =Assumptions!$C$42*(1+$C$10) -> 1.98 | I30: =Assumptions!$C$42*(1+$C$10) -> 1.98 | J30: =Assumptions!$C$42*(1+$C$10) -> 1.98 | ... N30: =Assumptions!$C$42*(1+$C$10) -> 1.98 | O30: =IFERROR(O31/O27,0) -> 1.98 | P30: =IFERROR(P31/P27,0) -> 1.98 | Q30: Calculated value (budget)
A31: Revenue | B31: $m | C31: =C27*C30 -> 47.49681 | D31: =D27*D30 -> 48.486327 | E31: =E27*E30 -> 50.465361 | F31: =F27*F30 -> 47.991569 | G31: =G27*G30 -> 48.981085 | H31: =H27*H30 -> 51.454878 | I31: =I27*I30 -> 50.960119 | J31: =J27*J30 -> 49.970602 | ... N31: =N27*N30 -> 53.433911 | O31: =SUM(C31:N31) -> 593.71013 | P31: =SUM(C31:G31) -> 243.42115 | Q31: Calculated value (budget) | R31: Units sold x ASP
A32: Variable cost per unit produced | B32: $/unit | C32: =Assumptions!$C$44*(1+$C$13) -> 0.3193 | D32: =Assumptions!$C$44*(1+$C$13) -> 0.3193 | E32: =Assumptions!$C$44*(1+$C$13) -> 0.3193 | F32: =Assumptions!$C$44*(1+$C$13) -> 0.3193 | G32: =Assumptions!$C$44*(1+$C$13) -> 0.3193 | H32: =Assumptions!$C$44*(1+$C$13) -> 0.3193 | I32: =Assumptions!$C$44*(1+$C$13) -> 0.3193 | J32: =Assumptions!$C$44*(1+$C$13) -> 0.3193 | ... N32: =Assumptions!$C$44*(1+$C$13) -> 0.3193 | O32: =IFERROR(O33/O22,0) -> 0.3193 | P32: =IFERROR(P33/P22,0) -> 0.3193 | Q32: Calculated value (budget)
A33: Variable manufacturing cost | B33: $m | C33: =C22*C32 -> 8.9404 | D33: =D22*D32 -> 8.9404 | E33: =E22*E32 -> 8.9404 | F33: =F22*F32 -> 8.9404 | G33: =G22*G32 -> 8.9404 | H33: =H22*H32 -> 8.9404 | I33: =I22*I32 -> 8.9404 | J33: =J22*J32 -> 8.9404 | ... N33: =N22*N32 -> 8.9404 | O33: =SUM(C33:N33) -> 107.2848 | P33: =SUM(C33:G33) -> 44.702 | Q33: Calculated value (budget) | R33: Units produced x variable cost
A34: Fixed manufacturing cost | B34: $m | C34: =Assumptions!$C$45 -> 9.5 | D34: =Assumptions!$C$45 -> 9.5 | E34: =Assumptions!$C$45 -> 9.5 | F34: =Assumptions!$C$45 -> 9.5 | G34: =Assumptions!$C$45 -> 9.5 | H34: =Assumptions!$C$45 -> 9.5 | I34: =Assumptions!$C$45 -> 9.5 | J34: =Assumptions!$C$45 -> 9.5 | ... N34: =Assumptions!$C$45 -> 9.5 | O34: =SUM(C34:N34) -> 114 | P34: =SUM(C34:G34) -> 47.5 | Q34: Calculated value (budget)
A35: Total manufacturing cost | B35: $m | C35: =C33+C34 -> 18.4404 | D35: =D33+D34 -> 18.4404 | E35: =E33+E34 -> 18.4404 | F35: =F33+F34 -> 18.4404 | G35: =G33+G34 -> 18.4404 | H35: =H33+H34 -> 18.4404 | I35: =I33+I34 -> 18.4404 | J35: =J33+J34 -> 18.4404 | ... N35: =N33+N34 -> 18.4404 | O35: =SUM(C35:N35) -> 221.2848 | P35: =SUM(C35:G35) -> 92.202 | Q35: Calculated value (budget) | R35: Variable + fixed
A36: Cost per good unit | B36: $/unit | C36: =IFERROR(C35/C24,0) -> 0.71585404 | D36: =IFERROR(D35/D24,0) -> 0.71585404 | E36: =IFERROR(E35/E24,0) -> 0.71585404 | F36: =IFERROR(F35/F24,0) -> 0.71585404 | G36: =IFERROR(G35/G24,0) -> 0.71585404 | H36: =IFERROR(H35/H24,0) -> 0.71585404 | I36: =IFERROR(I35/I24,0) -> 0.71585404 | J36: =IFERROR(J35/J24,0) -> 0.71585404 | ... P36: =IFERROR(P35/P24,0) -> 0.71585404 | Q36: Calculated value (budget)
A37: Opening inventory value | B37: $m | C37: =Assumptions!$C$68 -> 16.516502 | D37: =C40 -> 16.95563 | E37: =D40 -> 17.470651 | F37: =E40 -> 17.467704 | G37: =F40 -> 18.466037 | H37: =G40 -> 19.151307 | I37: =H40 -> 18.96379 | J37: =I40 -> 18.967502 | K37: =J40 -> 19.335224 | ... N37: =M40 -> 22.419094 | O37: =C37 -> 16.516502 | P37: =C37 -> 16.516502 | Q37: Calculated value (budget)
A38: Average cost per available unit | B38: $/unit | C38: =IFERROR((C37+C35)/C26,0) -> 0.75041918 | D38: =IFERROR((D37+D35)/D26,0) -> 0.73200536 | E38: =IFERROR((E37+E35)/E26,0) -> 0.72362163 | F38: =IFERROR((F37+F35)/F26,0) -> 0.71961169 | G38: =IFERROR((G37+G35)/G26,0) -> 0.71772925 | H38: =IFERROR((H37+H35)/H26,0) -> 0.71680815 | I38: =IFERROR((I37+I35)/I26,0) -> 0.71633745 | J38: =IFERROR((J37+J35)/J26,0) -> 0.71609907 | ... N38: =IFERROR((N37+N35)/N26,0) -> 0.71587381 | Q38: Calculated value (budget) | R38: Weighted-average cost
A39: Cost of revenue (manufacturing) | B39: $m | C39: =C27*C38 -> 18.001271 | D39: =D27*D38 -> 17.925379 | E39: =E27*E38 -> 18.443347 | F39: =F27*F38 -> 17.442068 | G39: =G27*G38 -> 17.75513 | H39: =H27*H38 -> 18.627917 | I39: =I27*I38 -> 18.436688 | J39: =J27*J38 -> 18.072678 | ... N39: =N27*N38 -> 19.319161 | O39: =SUM(C39:N39) -> 216.26097 | P39: =SUM(C39:G39) -> 89.567195 | Q39: Calculated value (budget) | R39: Units sold x average cost
A40: Closing inventory value | B40: $m | C40: =C37+C35-C39 -> 16.95563 | D40: =D37+D35-D39 -> 17.470651 | E40: =E37+E35-E39 -> 17.467704 | F40: =F37+F35-F39 -> 18.466037 | G40: =G37+G35-G39 -> 19.151307 | H40: =H37+H35-H39 -> 18.96379 | I40: =I37+I35-I39 -> 18.967502 | J40: =J37+J35-J39 -> 19.335224 | ... N40: =N37+N35-N39 -> 21.540333 | O40: =N40 -> 21.540333 | P40: =G40 -> 19.151307 | Q40: Calculated value (budget) | R40: Opening + manufacturing cost - cost of revenue
A41: Gross profit (before new-capex depreciation) | B41: $m | C41: =C31-C39 -> 29.495539 | D41: =D31-D39 -> 30.560948 | E41: =E31-E39 -> 32.022014 | F41: =F31-F39 -> 30.549501 | G41: =G31-G39 -> 31.225955 | H41: =H31-H39 -> 32.826961 | I41: =I31-I39 -> 32.523431 | J41: =J31-J39 -> 31.897925 | ... N41: =N31-N39 -> 34.114751 | O41: =SUM(C41:N41) -> 377.44916 | P41: =SUM(C41:G41) -> 153.85396 | Q41: Calculated value (budget) | R41: Revenue - cost of revenue
A42: Gross margin | B42: % | C42: =IFERROR(C41/C31,0) -> 0.62100041 | D42: =IFERROR(D41/D31,0) -> 0.63030032 | E42: =IFERROR(E41/E31,0) -> 0.63453453 | F42: =IFERROR(F41/F31,0) -> 0.63655975 | G42: =IFERROR(G41/G31,0) -> 0.63751048 | H42: =IFERROR(H41/H31,0) -> 0.63797568 | I42: =IFERROR(I41/I31,0) -> 0.63821341 | J42: =IFERROR(J41/J31,0) -> 0.6383338 | ... P42: =IFERROR(P41/P31,0) -> 0.63204843 | Q42: Calculated value (budget)
A44: Analog & power management - budget (Simulated data created for portfolio demonstration. It does not represent nonpublic Microchip Technology information.)
A45: Customer demand | B45: m units | C45: =Assumptions!$D$51*(1+$C$9+Assumptions!$D$47)*Assumptions!C$72/12 -> 32.427702 | D45: =Assumptions!$D$51*(1+$C$9+Assumptions!$D$47)*Assumptions!D$72/12 -> 33.103279 | E45: =Assumptions!$D$51*(1+$C$9+Assumptions!$D$47)*Assumptions!E$72/12 -> 34.454433 | F45: =Assumptions!$D$51*(1+$C$9+Assumptions!$D$47)*Assumptions!F$72/12 -> 32.76549 | G45: =Assumptions!$D$51*(1+$C$9+Assumptions!$D$47)*Assumptions!G$72/12 -> 33.441067 | H45: =Assumptions!$D$51*(1+$C$9+Assumptions!$D$47)*Assumptions!H$72/12 -> 35.13001 | I45: =Assumptions!$D$51*(1+$C$9+Assumptions!$D$47)*Assumptions!I$72/12 -> 34.792221 | J45: =Assumptions!$D$51*(1+$C$9+Assumptions!$D$47)*Assumptions!J$72/12 -> 34.116644 | ... N45: =Assumptions!$D$51*(1+$C$9+Assumptions!$D$47)*Assumptions!N$72/12 -> 36.481164 | O45: =SUM(C45:N45) -> 405.34627 | P45: =SUM(C45:G45) -> 166.19197 | Q45: Calculated value (budget)
A46: Internal final-test capacity | B46: m units | C46: =Assumptions!$D$46 -> 46 | D46: =Assumptions!$D$46 -> 46 | E46: =Assumptions!$D$46 -> 46 | F46: =Assumptions!$D$46 -> 46 | G46: =Assumptions!$D$46 -> 46 | H46: =Assumptions!$D$46 -> 46 | I46: =Assumptions!$D$46 -> 46 | J46: =Assumptions!$D$46 -> 46 | ... N46: =Assumptions!$D$46 -> 46 | O46: =SUM(C46:N46) -> 552 | P46: =SUM(C46:G46) -> 230 | Q46: Calculated value (budget)
A47: Capacity utilization | B47: % | C47: =$C$12 -> 0.8 | D47: =$C$12 -> 0.8 | E47: =$C$12 -> 0.8 | F47: =$C$12 -> 0.8 | G47: =$C$12 -> 0.8 | H47: =$C$12 -> 0.8 | I47: =$C$12 -> 0.8 | J47: =$C$12 -> 0.8 | ... N47: =$C$12 -> 0.8 | O47: =IFERROR(O48/O46,0) -> 0.8 | P47: =IFERROR(P48/P46,0) -> 0.8 | Q47: Calculated value (budget)
A48: Units produced (tested) | B48: m units | C48: =C46*C47 -> 36.8 | D48: =D46*D47 -> 36.8 | E48: =E46*E47 -> 36.8 | F48: =F46*F47 -> 36.8 | G48: =G46*G47 -> 36.8 | H48: =H46*H47 -> 36.8 | I48: =I46*I47 -> 36.8 | J48: =J46*J47 -> 36.8 | ... N48: =N46*N47 -> 36.8 | O48: =SUM(C48:N48) -> 441.6 | P48: =SUM(C48:G48) -> 184 | Q48: Calculated value (budget) | R48: Capacity x utilization
A49: Manufacturing yield (final test) | B49: % | C49: =MIN(1,MAX(0,Assumptions!$D$43+$C$11)) -> 0.94 | D49: =MIN(1,MAX(0,Assumptions!$D$43+$C$11)) -> 0.94 | E49: =MIN(1,MAX(0,Assumptions!$D$43+$C$11)) -> 0.94 | F49: =MIN(1,MAX(0,Assumptions!$D$43+$C$11)) -> 0.94 | G49: =MIN(1,MAX(0,Assumptions!$D$43+$C$11)) -> 0.94 | H49: =MIN(1,MAX(0,Assumptions!$D$43+$C$11)) -> 0.94 | I49: =MIN(1,MAX(0,Assumptions!$D$43+$C$11)) -> 0.94 | J49: =MIN(1,MAX(0,Assumptions!$D$43+$C$11)) -> 0.94 | ... N49: =MIN(1,MAX(0,Assumptions!$D$43+$C$11)) -> 0.94 | O49: =IFERROR(O50/O48,0) -> 0.94 | P49: =IFERROR(P50/P48,0) -> 0.94 | Q49: Calculated value (budget)
A50: Good units produced | B50: m units | C50: =C48*C49 -> 34.592 | D50: =D48*D49 -> 34.592 | E50: =E48*E49 -> 34.592 | F50: =F48*F49 -> 34.592 | G50: =G48*G49 -> 34.592 | H50: =H48*H49 -> 34.592 | I50: =I48*I49 -> 34.592 | J50: =J48*J49 -> 34.592 | ... N50: =N48*N49 -> 34.592 | O50: =SUM(C50:N50) -> 415.104 | P50: =SUM(C50:G50) -> 172.96 | Q50: Calculated value (budget) | R50: Units produced x yield
A51: Opening finished-goods inventory | B51: m units | C51: =Assumptions!$D$67 -> 29.372918 | D51: =C54 -> 31.537217 | E51: =D54 -> 33.025938 | F51: =E54 -> 33.163505 | G51: =F54 -> 34.990015 | H51: =G54 -> 36.140948 | I51: =H54 -> 35.602938 | J51: =I54 -> 35.402716 | K51: =J54 -> 35.878072 | ... N51: =M54 -> 41.019813 | O51: =C51 -> 29.372918 | P51: =C51 -> 29.372918 | Q51: Calculated value (budget)
A52: Available good units | B52: m units | C52: =C51+C50 -> 63.964918 | D52: =D51+D50 -> 66.129217 | E52: =E51+E50 -> 67.617938 | F52: =F51+F50 -> 67.755505 | G52: =G51+G50 -> 69.582015 | H52: =H51+H50 -> 70.732948 | I52: =I51+I50 -> 70.194938 | J52: =J51+J50 -> 69.994716 | ... N52: =N51+N50 -> 75.611813 | Q52: Calculated value (budget)
A53: Units sold | B53: m units | C53: =MIN(C45,C52) -> 32.427702 | D53: =MIN(D45,D52) -> 33.103279 | E53: =MIN(E45,E52) -> 34.454433 | F53: =MIN(F45,F52) -> 32.76549 | G53: =MIN(G45,G52) -> 33.441067 | H53: =MIN(H45,H52) -> 35.13001 | I53: =MIN(I45,I52) -> 34.792221 | J53: =MIN(J45,J52) -> 34.116644 | ... N53: =MIN(N45,N52) -> 36.481164 | O53: =SUM(C53:N53) -> 405.34627 | P53: =SUM(C53:G53) -> 166.19197 | Q53: Calculated value (budget) | R53: MIN(demand, available)
A54: Closing finished-goods inventory | B54: m units | C54: =C52-C53 -> 31.537217 | D54: =D52-D53 -> 33.025938 | E54: =E52-E53 -> 33.163505 | F54: =F52-F53 -> 34.990015 | G54: =G52-G53 -> 36.140948 | H54: =H52-H53 -> 35.602938 | I54: =I52-I53 -> 35.402716 | J54: =J52-J53 -> 35.878072 | ... N54: =N52-N53 -> 39.130649 | O54: =N54 -> 39.130649 | P54: =G54 -> 36.140948 | Q54: Calculated value (budget) | R54: Available - sold
A55: Unmet demand | B55: m units | C55: =C45-C53 -> 0 | D55: =D45-D53 -> 0 | E55: =E45-E53 -> 0 | F55: =F45-F53 -> 0 | G55: =G45-G53 -> 0 | H55: =H45-H53 -> 0 | I55: =I45-I53 -> 0 | J55: =J45-J53 -> 0 | ... N55: =N45-N53 -> 0 | O55: =SUM(C55:N55) -> 0 | P55: =SUM(C55:G55) -> 0 | Q55: Calculated value (budget)
A56: Average selling price | B56: $/unit | C56: =Assumptions!$D$42*(1+$C$10) -> 0.792 | D56: =Assumptions!$D$42*(1+$C$10) -> 0.792 | E56: =Assumptions!$D$42*(1+$C$10) -> 0.792 | F56: =Assumptions!$D$42*(1+$C$10) -> 0.792 | G56: =Assumptions!$D$42*(1+$C$10) -> 0.792 | H56: =Assumptions!$D$42*(1+$C$10) -> 0.792 | I56: =Assumptions!$D$42*(1+$C$10) -> 0.792 | J56: =Assumptions!$D$42*(1+$C$10) -> 0.792 | ... N56: =Assumptions!$D$42*(1+$C$10) -> 0.792 | O56: =IFERROR(O57/O53,0) -> 0.792 | P56: =IFERROR(P57/P53,0) -> 0.792 | Q56: Calculated value (budget)
A57: Revenue | B57: $m | C57: =C53*C56 -> 25.68274 | D57: =D53*D56 -> 26.217797 | E57: =E53*E56 -> 27.287911 | F57: =F53*F56 -> 25.950268 | G57: =G53*G56 -> 26.485325 | H57: =H53*H56 -> 27.822968 | I57: =I53*I56 -> 27.555439 | J57: =J53*J56 -> 27.020382 | ... N57: =N53*N56 -> 28.893082 | O57: =SUM(C57:N57) -> 321.03424 | P57: =SUM(C57:G57) -> 131.62404 | Q57: Calculated value (budget) | R57: Units sold x ASP
A58: Variable cost per unit produced | B58: $/unit | C58: =Assumptions!$D$44*(1+$C$13) -> 0.1545 | D58: =Assumptions!$D$44*(1+$C$13) -> 0.1545 | E58: =Assumptions!$D$44*(1+$C$13) -> 0.1545 | F58: =Assumptions!$D$44*(1+$C$13) -> 0.1545 | G58: =Assumptions!$D$44*(1+$C$13) -> 0.1545 | H58: =Assumptions!$D$44*(1+$C$13) -> 0.1545 | I58: =Assumptions!$D$44*(1+$C$13) -> 0.1545 | J58: =Assumptions!$D$44*(1+$C$13) -> 0.1545 | ... N58: =Assumptions!$D$44*(1+$C$13) -> 0.1545 | O58: =IFERROR(O59/O48,0) -> 0.1545 | P58: =IFERROR(P59/P48,0) -> 0.1545 | Q58: Calculated value (budget)
A59: Variable manufacturing cost | B59: $m | C59: =C48*C58 -> 5.6856 | D59: =D48*D58 -> 5.6856 | E59: =E48*E58 -> 5.6856 | F59: =F48*F58 -> 5.6856 | G59: =G48*G58 -> 5.6856 | H59: =H48*H58 -> 5.6856 | I59: =I48*I58 -> 5.6856 | J59: =J48*J58 -> 5.6856 | ... N59: =N48*N58 -> 5.6856 | O59: =SUM(C59:N59) -> 68.2272 | P59: =SUM(C59:G59) -> 28.428 | Q59: Calculated value (budget) | R59: Units produced x variable cost
A60: Fixed manufacturing cost | B60: $m | C60: =Assumptions!$D$45 -> 5.2 | D60: =Assumptions!$D$45 -> 5.2 | E60: =Assumptions!$D$45 -> 5.2 | F60: =Assumptions!$D$45 -> 5.2 | G60: =Assumptions!$D$45 -> 5.2 | H60: =Assumptions!$D$45 -> 5.2 | I60: =Assumptions!$D$45 -> 5.2 | J60: =Assumptions!$D$45 -> 5.2 | ... N60: =Assumptions!$D$45 -> 5.2 | O60: =SUM(C60:N60) -> 62.4 | P60: =SUM(C60:G60) -> 26 | Q60: Calculated value (budget)
A61: Total manufacturing cost | B61: $m | C61: =C59+C60 -> 10.8856 | D61: =D59+D60 -> 10.8856 | E61: =E59+E60 -> 10.8856 | F61: =F59+F60 -> 10.8856 | G61: =G59+G60 -> 10.8856 | H61: =H59+H60 -> 10.8856 | I61: =I59+I60 -> 10.8856 | J61: =J59+J60 -> 10.8856 | ... N61: =N59+N60 -> 10.8856 | O61: =SUM(C61:N61) -> 130.6272 | P61: =SUM(C61:G61) -> 54.428 | Q61: Calculated value (budget) | R61: Variable + fixed
A62: Cost per good unit | B62: $/unit | C62: =IFERROR(C61/C50,0) -> 0.31468548 | D62: =IFERROR(D61/D50,0) -> 0.31468548 | E62: =IFERROR(E61/E50,0) -> 0.31468548 | F62: =IFERROR(F61/F50,0) -> 0.31468548 | G62: =IFERROR(G61/G50,0) -> 0.31468548 | H62: =IFERROR(H61/H50,0) -> 0.31468548 | I62: =IFERROR(I61/I50,0) -> 0.31468548 | J62: =IFERROR(J61/J50,0) -> 0.31468548 | ... P62: =IFERROR(P61/P50,0) -> 0.31468548 | Q62: Calculated value (budget)
A63: Opening inventory value | B63: $m | C63: =Assumptions!$D$68 -> 9.8871678 | D63: =C66 -> 10.24179 | E63: =D66 -> 10.55134 | F63: =E66 -> 10.513839 | G63: =F66 -> 11.051009 | H63: =G66 -> 11.39389 | I63: =H66 -> 11.214227 | J63: =I66 -> 11.146016 | K63: =J66 -> 11.293022 | ... N63: =M66 -> 12.908786 | O63: =C63 -> 9.8871678 | P63: =C63 -> 9.8871678 | Q63: Calculated value (budget)
A64: Average cost per available unit | B64: $/unit | C64: =IFERROR((C63+C61)/C52,0) -> 0.32475251 | D64: =IFERROR((D63+D61)/D52,0) -> 0.31948647 | E64: =IFERROR((E63+E61)/E52,0) -> 0.31703038 | F64: =IFERROR((F63+F61)/F52,0) -> 0.31583321 | G64: =IFERROR((G63+G61)/G52,0) -> 0.31526263 | H64: =IFERROR((H63+H61)/H52,0) -> 0.31498037 | I64: =IFERROR((I63+I61)/I52,0) -> 0.31483505 | J64: =IFERROR((J63+J61)/J52,0) -> 0.31476113 | ... N64: =IFERROR((N63+N61)/N52,0) -> 0.31469138 | Q64: Calculated value (budget) | R64: Weighted-average cost
A65: Cost of revenue (manufacturing) | B65: $m | C65: =C53*C64 -> 10.530978 | D65: =D53*D64 -> 10.57605 | E65: =E53*E64 -> 10.923102 | F65: =F53*F64 -> 10.34843 | G65: =G53*G64 -> 10.542719 | H65: =H53*H64 -> 11.065264 | I65: =I53*I64 -> 10.953811 | J65: =J53*J64 -> 10.738593 | ... N65: =N53*N64 -> 11.480308 | O65: =SUM(C65:N65) -> 128.20029 | P65: =SUM(C65:G65) -> 52.921278 | Q65: Calculated value (budget) | R65: Units sold x average cost
A66: Closing inventory value | B66: $m | C66: =C63+C61-C65 -> 10.24179 | D66: =D63+D61-D65 -> 10.55134 | E66: =E63+E61-E65 -> 10.513839 | F66: =F63+F61-F65 -> 11.051009 | G66: =G63+G61-G65 -> 11.39389 | H66: =H63+H61-H65 -> 11.214227 | I66: =I63+I61-I65 -> 11.146016 | J66: =J63+J61-J65 -> 11.293022 | ... N66: =N63+N61-N65 -> 12.314078 | O66: =N66 -> 12.314078 | P66: =G66 -> 11.39389 | Q66: Calculated value (budget) | R66: Opening + manufacturing cost - cost of revenue
A67: Gross profit (before new-capex depreciation) | B67: $m | C67: =C57-C65 -> 15.151762 | D67: =D57-D65 -> 15.641747 | E67: =E57-E65 -> 16.364809 | F67: =F57-F65 -> 15.601838 | G67: =G57-G65 -> 15.942607 | H67: =H57-H65 -> 16.757704 | I67: =I57-I65 -> 16.601629 | J67: =J57-J65 -> 16.281789 | ... N67: =N57-N65 -> 17.412774 | O67: =SUM(C67:N67) -> 192.83396 | P67: =SUM(C67:G67) -> 78.702763 | Q67: Calculated value (budget) | R67: Revenue - cost of revenue
A68: Gross margin | B68: % | C68: =IFERROR(C67/C57,0) -> 0.58995895 | D68: =IFERROR(D67/D57,0) -> 0.59660799 | E68: =IFERROR(E67/E57,0) -> 0.59970912 | F68: =IFERROR(F67/F57,0) -> 0.6012207 | G68: =IFERROR(G67/G57,0) -> 0.60194113 | H68: =IFERROR(H67/H57,0) -> 0.60229751 | I68: =IFERROR(I67/I57,0) -> 0.602481 | J68: =IFERROR(J67/J57,0) -> 0.60257433 | ... P68: =IFERROR(P67/P57,0) -> 0.59793608 | Q68: Calculated value (budget)
A70: FPGAs - budget (Simulated data created for portfolio demonstration. It does not represent nonpublic Microchip Technology information.)
A71: Customer demand | B71: m units | C71: =Assumptions!$E$51*(1+$C$9+Assumptions!$E$47)*Assumptions!C$72/12 -> 0.87305595 | D71: =Assumptions!$E$51*(1+$C$9+Assumptions!$E$47)*Assumptions!D$72/12 -> 0.89124462 | E71: =Assumptions!$E$51*(1+$C$9+Assumptions!$E$47)*Assumptions!E$72/12 -> 0.92762195 | F71: =Assumptions!$E$51*(1+$C$9+Assumptions!$E$47)*Assumptions!F$72/12 -> 0.88215028 | G71: =Assumptions!$E$51*(1+$C$9+Assumptions!$E$47)*Assumptions!G$72/12 -> 0.90033895 | H71: =Assumptions!$E$51*(1+$C$9+Assumptions!$E$47)*Assumptions!H$72/12 -> 0.94581061 | I71: =Assumptions!$E$51*(1+$C$9+Assumptions!$E$47)*Assumptions!I$72/12 -> 0.93671628 | J71: =Assumptions!$E$51*(1+$C$9+Assumptions!$E$47)*Assumptions!J$72/12 -> 0.91852761 | ... N71: =Assumptions!$E$51*(1+$C$9+Assumptions!$E$47)*Assumptions!N$72/12 -> 0.98218794 | O71: =SUM(C71:N71) -> 10.913199 | P71: =SUM(C71:G71) -> 4.4744117 | Q71: Calculated value (budget)
A72: Internal final-test capacity | B72: m units | C72: =Assumptions!$E$46 -> 1.3 | D72: =Assumptions!$E$46 -> 1.3 | E72: =Assumptions!$E$46 -> 1.3 | F72: =Assumptions!$E$46 -> 1.3 | G72: =Assumptions!$E$46 -> 1.3 | H72: =Assumptions!$E$46 -> 1.3 | I72: =Assumptions!$E$46 -> 1.3 | J72: =Assumptions!$E$46 -> 1.3 | ... N72: =Assumptions!$E$46 -> 1.3 | O72: =SUM(C72:N72) -> 15.6 | P72: =SUM(C72:G72) -> 6.5 | Q72: Calculated value (budget)
A73: Capacity utilization | B73: % | C73: =$C$12 -> 0.8 | D73: =$C$12 -> 0.8 | E73: =$C$12 -> 0.8 | F73: =$C$12 -> 0.8 | G73: =$C$12 -> 0.8 | H73: =$C$12 -> 0.8 | I73: =$C$12 -> 0.8 | J73: =$C$12 -> 0.8 | ... N73: =$C$12 -> 0.8 | O73: =IFERROR(O74/O72,0) -> 0.8 | P73: =IFERROR(P74/P72,0) -> 0.8 | Q73: Calculated value (budget)
A74: Units produced (tested) | B74: m units | C74: =C72*C73 -> 1.04 | D74: =D72*D73 -> 1.04 | E74: =E72*E73 -> 1.04 | F74: =F72*F73 -> 1.04 | G74: =G72*G73 -> 1.04 | H74: =H72*H73 -> 1.04 | I74: =I72*I73 -> 1.04 | J74: =J72*J73 -> 1.04 | ... N74: =N72*N73 -> 1.04 | O74: =SUM(C74:N74) -> 12.48 | P74: =SUM(C74:G74) -> 5.2 | Q74: Calculated value (budget) | R74: Capacity x utilization
A75: Manufacturing yield (final test) | B75: % | C75: =MIN(1,MAX(0,Assumptions!$E$43+$C$11)) -> 0.85 | D75: =MIN(1,MAX(0,Assumptions!$E$43+$C$11)) -> 0.85 | E75: =MIN(1,MAX(0,Assumptions!$E$43+$C$11)) -> 0.85 | F75: =MIN(1,MAX(0,Assumptions!$E$43+$C$11)) -> 0.85 | G75: =MIN(1,MAX(0,Assumptions!$E$43+$C$11)) -> 0.85 | H75: =MIN(1,MAX(0,Assumptions!$E$43+$C$11)) -> 0.85 | I75: =MIN(1,MAX(0,Assumptions!$E$43+$C$11)) -> 0.85 | J75: =MIN(1,MAX(0,Assumptions!$E$43+$C$11)) -> 0.85 | ... N75: =MIN(1,MAX(0,Assumptions!$E$43+$C$11)) -> 0.85 | O75: =IFERROR(O76/O74,0) -> 0.85 | P75: =IFERROR(P76/P74,0) -> 0.85 | Q75: Calculated value (budget)
A76: Good units produced | B76: m units | C76: =C74*C75 -> 0.884 | D76: =D74*D75 -> 0.884 | E76: =E74*E75 -> 0.884 | F76: =F74*F75 -> 0.884 | G76: =G74*G75 -> 0.884 | H76: =H74*H75 -> 0.884 | I76: =I74*I75 -> 0.884 | J76: =J74*J75 -> 0.884 | ... N76: =N74*N75 -> 0.884 | O76: =SUM(C76:N76) -> 10.608 | P76: =SUM(C76:G76) -> 4.42 | Q76: Calculated value (budget) | R76: Units produced x yield
A77: Opening finished-goods inventory | B77: m units | C77: =Assumptions!$E$67 -> 0.72754663 | D77: =C80 -> 0.73849067 | E77: =D80 -> 0.73124606 | F77: =E80 -> 0.68762411 | G77: =F80 -> 0.68947383 | H77: =G80 -> 0.67313488 | I77: =H80 -> 0.61132427 | J77: =I80 -> 0.55860799 | K77: =J80 -> 0.52408037 | ... N77: =M80 -> 0.52053519 | O77: =C77 -> 0.72754663 | P77: =C77 -> 0.72754663 | Q77: Calculated value (budget)
A78: Available good units | B78: m units | C78: =C77+C76 -> 1.6115466 | D78: =D77+D76 -> 1.6224907 | E78: =E77+E76 -> 1.6152461 | F78: =F77+F76 -> 1.5716241 | G78: =G77+G76 -> 1.5734738 | H78: =H77+H76 -> 1.5571349 | I78: =I77+I76 -> 1.4953243 | J78: =J77+J76 -> 1.442608 | ... N78: =N77+N76 -> 1.4045352 | Q78: Calculated value (budget)
A79: Units sold | B79: m units | C79: =MIN(C71,C78) -> 0.87305595 | D79: =MIN(D71,D78) -> 0.89124462 | E79: =MIN(E71,E78) -> 0.92762195 | F79: =MIN(F71,F78) -> 0.88215028 | G79: =MIN(G71,G78) -> 0.90033895 | H79: =MIN(H71,H78) -> 0.94581061 | I79: =MIN(I71,I78) -> 0.93671628 | J79: =MIN(J71,J78) -> 0.91852761 | ... N79: =MIN(N71,N78) -> 0.98218794 | O79: =SUM(C79:N79) -> 10.913199 | P79: =SUM(C79:G79) -> 4.4744117 | Q79: Calculated value (budget) | R79: MIN(demand, available)
A80: Closing finished-goods inventory | B80: m units | C80: =C78-C79 -> 0.73849067 | D80: =D78-D79 -> 0.73124606 | E80: =E78-E79 -> 0.68762411 | F80: =F78-F79 -> 0.68947383 | G80: =G78-G79 -> 0.67313488 | H80: =H78-H79 -> 0.61132427 | I80: =I78-I79 -> 0.55860799 | J80: =J78-J79 -> 0.52408037 | ... N80: =N78-N79 -> 0.42234724 | O80: =N80 -> 0.42234724 | P80: =G80 -> 0.67313488 | Q80: Calculated value (budget) | R80: Available - sold
A81: Unmet demand | B81: m units | C81: =C71-C79 -> 0 | D81: =D71-D79 -> 0 | E81: =E71-E79 -> 0 | F81: =F71-F79 -> 0 | G81: =G71-G79 -> 0 | H81: =H71-H79 -> 0 | I81: =I71-I79 -> 0 | J81: =J71-J79 -> 0 | ... N81: =N71-N79 -> 0 | O81: =SUM(C81:N81) -> 0 | P81: =SUM(C81:G81) -> 0 | Q81: Calculated value (budget)
A82: Average selling price | B82: $/unit | C82: =Assumptions!$E$42*(1+$C$10) -> 24.75 | D82: =Assumptions!$E$42*(1+$C$10) -> 24.75 | E82: =Assumptions!$E$42*(1+$C$10) -> 24.75 | F82: =Assumptions!$E$42*(1+$C$10) -> 24.75 | G82: =Assumptions!$E$42*(1+$C$10) -> 24.75 | H82: =Assumptions!$E$42*(1+$C$10) -> 24.75 | I82: =Assumptions!$E$42*(1+$C$10) -> 24.75 | J82: =Assumptions!$E$42*(1+$C$10) -> 24.75 | ... N82: =Assumptions!$E$42*(1+$C$10) -> 24.75 | O82: =IFERROR(O83/O79,0) -> 24.75 | P82: =IFERROR(P83/P79,0) -> 24.75 | Q82: Calculated value (budget)
A83: Revenue | B83: $m | C83: =C79*C82 -> 21.608135 | D83: =D79*D82 -> 22.058304 | E83: =E79*E82 -> 22.958643 | F83: =F79*F82 -> 21.83322 | G83: =G79*G82 -> 22.283389 | H83: =H79*H82 -> 23.408813 | I83: =I79*I82 -> 23.183728 | J83: =J79*J82 -> 22.733558 | ... N83: =N79*N82 -> 24.309152 | O83: =SUM(C83:N83) -> 270.10168 | P83: =SUM(C83:G83) -> 110.74169 | Q83: Calculated value (budget) | R83: Units sold x ASP
A84: Variable cost per unit produced | B84: $/unit | C84: =Assumptions!$E$44*(1+$C$13) -> 4.841 | D84: =Assumptions!$E$44*(1+$C$13) -> 4.841 | E84: =Assumptions!$E$44*(1+$C$13) -> 4.841 | F84: =Assumptions!$E$44*(1+$C$13) -> 4.841 | G84: =Assumptions!$E$44*(1+$C$13) -> 4.841 | H84: =Assumptions!$E$44*(1+$C$13) -> 4.841 | I84: =Assumptions!$E$44*(1+$C$13) -> 4.841 | J84: =Assumptions!$E$44*(1+$C$13) -> 4.841 | ... N84: =Assumptions!$E$44*(1+$C$13) -> 4.841 | O84: =IFERROR(O85/O74,0) -> 4.841 | P84: =IFERROR(P85/P74,0) -> 4.841 | Q84: Calculated value (budget)
A85: Variable manufacturing cost | B85: $m | C85: =C74*C84 -> 5.03464 | D85: =D74*D84 -> 5.03464 | E85: =E74*E84 -> 5.03464 | F85: =F74*F84 -> 5.03464 | G85: =G74*G84 -> 5.03464 | H85: =H74*H84 -> 5.03464 | I85: =I74*I84 -> 5.03464 | J85: =J74*J84 -> 5.03464 | ... N85: =N74*N84 -> 5.03464 | O85: =SUM(C85:N85) -> 60.41568 | P85: =SUM(C85:G85) -> 25.1732 | Q85: Calculated value (budget) | R85: Units produced x variable cost
A86: Fixed manufacturing cost | B86: $m | C86: =Assumptions!$E$45 -> 4.4 | D86: =Assumptions!$E$45 -> 4.4 | E86: =Assumptions!$E$45 -> 4.4 | F86: =Assumptions!$E$45 -> 4.4 | G86: =Assumptions!$E$45 -> 4.4 | H86: =Assumptions!$E$45 -> 4.4 | I86: =Assumptions!$E$45 -> 4.4 | J86: =Assumptions!$E$45 -> 4.4 | ... N86: =Assumptions!$E$45 -> 4.4 | O86: =SUM(C86:N86) -> 52.8 | P86: =SUM(C86:G86) -> 22 | Q86: Calculated value (budget)
A87: Total manufacturing cost | B87: $m | C87: =C85+C86 -> 9.43464 | D87: =D85+D86 -> 9.43464 | E87: =E85+E86 -> 9.43464 | F87: =F85+F86 -> 9.43464 | G87: =G85+G86 -> 9.43464 | H87: =H85+H86 -> 9.43464 | I87: =I85+I86 -> 9.43464 | J87: =J85+J86 -> 9.43464 | ... N87: =N85+N86 -> 9.43464 | O87: =SUM(C87:N87) -> 113.21568 | P87: =SUM(C87:G87) -> 47.1732 | Q87: Calculated value (budget) | R87: Variable + fixed
A88: Cost per good unit | B88: $/unit | C88: =IFERROR(C87/C76,0) -> 10.67267 | D88: =IFERROR(D87/D76,0) -> 10.67267 | E88: =IFERROR(E87/E76,0) -> 10.67267 | F88: =IFERROR(F87/F76,0) -> 10.67267 | G88: =IFERROR(G87/G76,0) -> 10.67267 | H88: =IFERROR(H87/H76,0) -> 10.67267 | I88: =IFERROR(I87/I76,0) -> 10.67267 | J88: =IFERROR(J87/J76,0) -> 10.67267 | ... P88: =IFERROR(P87/P76,0) -> 10.67267 | Q88: Calculated value (budget)
A89: Opening inventory value | B89: $m | C89: =Assumptions!$E$68 -> 8.4229049 | D89: =C92 -> 8.1832137 | E89: =D92 -> 7.9402528 | F89: =E92 -> 7.396641 | G89: =F92 -> 7.3839079 | H89: =G92 -> 7.1950045 | I89: =H92 -> 6.5287249 | J89: =I92 -> 5.963431 | K89: =J92 -> 5.5939152 | ... N89: =M92 -> 5.5555312 | O89: =C89 -> 8.4229049 | P89: =C89 -> 8.4229049 | Q89: Calculated value (budget)
A90: Average cost per available unit | B90: $/unit | C90: =IFERROR((C89+C87)/C78,0) -> 11.080998 | D90: =IFERROR((D89+D87)/D78,0) -> 10.858524 | E90: =IFERROR((E89+E87)/E78,0) -> 10.756809 | F90: =IFERROR((F89+F87)/F78,0) -> 10.709483 | G90: =IFERROR((G89+G87)/G78,0) -> 10.688801 | H90: =IFERROR((H89+H87)/H78,0) -> 10.679643 | I90: =IFERROR((I89+I87)/I78,0) -> 10.675521 | J90: =IFERROR((J89+J87)/J78,0) -> 10.673774 | ... N90: =IFERROR((N89+N87)/N78,0) -> 10.672692 | Q90: Calculated value (budget) | R90: Weighted-average cost
A91: Cost of revenue (manufacturing) | B91: $m | C91: =C79*C90 -> 9.6743312 | D91: =D79*D90 -> 9.6776009 | E91: =E79*E90 -> 9.9782518 | F91: =F79*F90 -> 9.4473731 | G91: =G79*G90 -> 9.6235435 | H91: =H79*H90 -> 10.10092 | I91: =I79*I90 -> 9.9999339 | J91: =J79*J90 -> 9.8041558 | ... N91: =N79*N90 -> 10.482589 | O91: =SUM(C91:N91) -> 117.131 | P91: =SUM(C91:G91) -> 48.4011 | Q91: Calculated value (budget) | R91: Units sold x average cost
A92: Closing inventory value | B92: $m | C92: =C89+C87-C91 -> 8.1832137 | D92: =D89+D87-D91 -> 7.9402528 | E92: =E89+E87-E91 -> 7.396641 | F92: =F89+F87-F91 -> 7.3839079 | G92: =G89+G87-G91 -> 7.1950045 | H92: =H89+H87-H91 -> 6.5287249 | I92: =I89+I87-I91 -> 5.963431 | J92: =J89+J87-J91 -> 5.5939152 | ... N92: =N89+N87-N91 -> 4.507582 | O92: =N92 -> 4.507582 | P92: =G92 -> 7.1950045 | Q92: Calculated value (budget) | R92: Opening + manufacturing cost - cost of revenue
A93: Gross profit (before new-capex depreciation) | B93: $m | C93: =C83-C91 -> 11.933804 | D93: =D83-D91 -> 12.380703 | E93: =E83-E91 -> 12.980391 | F93: =F83-F91 -> 12.385846 | G93: =G83-G91 -> 12.659846 | H93: =H83-H91 -> 13.307893 | I93: =I83-I91 -> 13.183794 | J93: =J83-J91 -> 12.929403 | ... N93: =N83-N91 -> 13.826562 | O93: =SUM(C93:N93) -> 152.97068 | P93: =SUM(C93:G93) -> 62.34059 | Q93: Calculated value (budget) | R93: Revenue - cost of revenue
A94: Gross margin | B94: % | C94: =IFERROR(C93/C83,0) -> 0.55228291 | D94: =IFERROR(D93/D83,0) -> 0.56127176 | E94: =IFERROR(E93/E83,0) -> 0.56538147 | F94: =IFERROR(F93/F83,0) -> 0.56729363 | G94: =IFERROR(G93/G83,0) -> 0.56812927 | H94: =IFERROR(H93/H83,0) -> 0.56849928 | I94: =IFERROR(I93/I83,0) -> 0.56866584 | J94: =IFERROR(J93/J83,0) -> 0.56873642 | ... P94: =IFERROR(P93/P83,0) -> 0.56293696 | Q94: Calculated value (budget)
A96: Division budget P&L to operating profit (Simulated data created for portfolio demonstration. It does not represent nonpublic Microchip Technology information.)
A97: Revenue | B97: $m | C97: =C31+C57+C83 -> 94.787685 | D97: =D31+D57+D83 -> 96.762428 | E97: =E31+E57+E83 -> 100.71191 | F97: =F31+F57+F83 -> 95.775056 | G97: =G31+G57+G83 -> 97.7498 | H97: =H31+H57+H83 -> 102.68666 | I97: =I31+I57+I83 -> 101.69929 | J97: =J31+J57+J83 -> 99.724543 | ... N97: =N31+N57+N83 -> 106.63615 | O97: =SUM(C97:N97) -> 1184.8461 | P97: =SUM(C97:G97) -> 485.78688 | Q97: Calculated value (budget)
A98: Variable manufacturing cost | B98: $m | C98: =C33+C59+C85 -> 19.66064 | D98: =D33+D59+D85 -> 19.66064 | E98: =E33+E59+E85 -> 19.66064 | F98: =F33+F59+F85 -> 19.66064 | G98: =G33+G59+G85 -> 19.66064 | H98: =H33+H59+H85 -> 19.66064 | I98: =I33+I59+I85 -> 19.66064 | J98: =J33+J59+J85 -> 19.66064 | ... N98: =N33+N59+N85 -> 19.66064 | O98: =SUM(C98:N98) -> 235.92768 | P98: =SUM(C98:G98) -> 98.3032 | Q98: Calculated value (budget)
A99: Fixed manufacturing cost | B99: $m | C99: =C34+C60+C86 -> 19.1 | D99: =D34+D60+D86 -> 19.1 | E99: =E34+E60+E86 -> 19.1 | F99: =F34+F60+F86 -> 19.1 | G99: =G34+G60+G86 -> 19.1 | H99: =H34+H60+H86 -> 19.1 | I99: =I34+I60+I86 -> 19.1 | J99: =J34+J60+J86 -> 19.1 | ... N99: =N34+N60+N86 -> 19.1 | O99: =SUM(C99:N99) -> 229.2 | P99: =SUM(C99:G99) -> 95.5 | Q99: Calculated value (budget)
A100: Cost of revenue - manufacturing | B100: $m | C100: =C39+C65+C91 -> 38.20658 | D100: =D39+D65+D91 -> 38.17903 | E100: =E39+E65+E91 -> 39.3447 | F100: =F39+F65+F91 -> 37.23787 | G100: =G39+G65+G91 -> 37.921392 | H100: =H39+H65+H91 -> 39.7941 | I100: =I39+I65+I91 -> 39.390432 | J100: =J39+J65+J91 -> 38.615427 | ... N100: =N39+N65+N91 -> 41.282058 | O100: =SUM(C100:N100) -> 461.59226 | P100: =SUM(C100:G100) -> 190.88957 | Q100: Calculated value (budget)
A101: Capital expenditures | B101: $m | C101: =C97*$C$16 -> 2.8436305 | D101: =D97*$C$16 -> 2.9028728 | E101: =E97*$C$16 -> 3.0213574 | F101: =F97*$C$16 -> 2.8732517 | G101: =G97*$C$16 -> 2.932494 | H101: =H97*$C$16 -> 3.0805997 | I101: =I97*$C$16 -> 3.0509786 | J101: =J97*$C$16 -> 2.9917363 | ... N101: =N97*$C$16 -> 3.1990844 | O101: =SUM(C101:N101) -> 35.545382 | P101: =SUM(C101:G101) -> 14.573606 | Q101: Calculated value (budget)
A102: Depreciation on FY2027 capex | B102: $m | C102: =0 -> 0 | D102: =SUM($C$101:C101)/Assumptions!$F$85 -> 0.047393842 | E102: =SUM($C$101:D101)/Assumptions!$F$85 -> 0.095775056 | F102: =SUM($C$101:E101)/Assumptions!$F$85 -> 0.14613101 | G102: =SUM($C$101:F101)/Assumptions!$F$85 -> 0.19401854 | H102: =SUM($C$101:G101)/Assumptions!$F$85 -> 0.24289344 | I102: =SUM($C$101:H101)/Assumptions!$F$85 -> 0.29423677 | J102: =SUM($C$101:I101)/Assumptions!$F$85 -> 0.34508641 | K102: =SUM($C$101:J101)/Assumptions!$F$85 -> 0.39494869 | ... N102: =SUM($C$101:M101)/Assumptions!$F$85 -> 0.53910496 | O102: =SUM(C102:N102) -> 3.2311739 | P102: =SUM(C102:G102) -> 0.48331845 | Q102: Calculated value (budget)
A103: Total cost of revenue | B103: $m | C103: =C100+C102 -> 38.20658 | D103: =D100+D102 -> 38.226424 | E103: =E100+E102 -> 39.440475 | F103: =F100+F102 -> 37.384001 | G103: =G100+G102 -> 38.115411 | H103: =H100+H102 -> 40.036994 | I103: =I100+I102 -> 39.684669 | J103: =J100+J102 -> 38.960513 | ... N103: =N100+N102 -> 41.821163 | O103: =SUM(C103:N103) -> 464.82344 | P103: =SUM(C103:G103) -> 191.37289 | Q103: Calculated value (budget)
A104: Gross profit | B104: $m | C104: =C97-C103 -> 56.581104 | D104: =D97-D103 -> 58.536004 | E104: =E97-E103 -> 61.271439 | F104: =F97-F103 -> 58.391055 | G104: =G97-G103 -> 59.634389 | H104: =H97-H103 -> 62.649665 | I104: =I97-I103 -> 62.014617 | J104: =J97-J103 -> 60.76403 | ... N104: =N97-N103 -> 64.814982 | O104: =SUM(C104:N104) -> 720.02262 | P104: =SUM(C104:G104) -> 294.41399 | Q104: Calculated value (budget)
A105: Gross margin | B105: % | C105: =IFERROR(C104/C97,0) -> 0.59692464 | D105: =IFERROR(D104/D97,0) -> 0.60494559 | E105: =IFERROR(E104/E97,0) -> 0.60838322 | F105: =IFERROR(F104/F97,0) -> 0.60966871 | G105: =IFERROR(G104/G97,0) -> 0.61007172 | H105: =IFERROR(H104/H97,0) -> 0.61010521 | I105: =IFERROR(I104/I97,0) -> 0.60978419 | J105: =IFERROR(J104/J97,0) -> 0.60931871 | ... P105: =IFERROR(P104/P97,0) -> 0.60605587 | Q105: Calculated value (budget)
A106: Research and development | B106: $m | C106: =Assumptions!$F$34*(1+$C$14)/12 -> 17.5 | D106: =Assumptions!$F$34*(1+$C$14)/12 -> 17.5 | E106: =Assumptions!$F$34*(1+$C$14)/12 -> 17.5 | F106: =Assumptions!$F$34*(1+$C$14)/12 -> 17.5 | G106: =Assumptions!$F$34*(1+$C$14)/12 -> 17.5 | H106: =Assumptions!$F$34*(1+$C$14)/12 -> 17.5 | I106: =Assumptions!$F$34*(1+$C$14)/12 -> 17.5 | J106: =Assumptions!$F$34*(1+$C$14)/12 -> 17.5 | ... N106: =Assumptions!$F$34*(1+$C$14)/12 -> 17.5 | O106: =SUM(C106:N106) -> 210 | P106: =SUM(C106:G106) -> 87.5 | Q106: Calculated value (budget)
A107: Selling, general and administrative | B107: $m | C107: =Assumptions!$F$35*(1+$C$15)/12 -> 8.6666667 | D107: =Assumptions!$F$35*(1+$C$15)/12 -> 8.6666667 | E107: =Assumptions!$F$35*(1+$C$15)/12 -> 8.6666667 | F107: =Assumptions!$F$35*(1+$C$15)/12 -> 8.6666667 | G107: =Assumptions!$F$35*(1+$C$15)/12 -> 8.6666667 | H107: =Assumptions!$F$35*(1+$C$15)/12 -> 8.6666667 | I107: =Assumptions!$F$35*(1+$C$15)/12 -> 8.6666667 | J107: =Assumptions!$F$35*(1+$C$15)/12 -> 8.6666667 | ... N107: =Assumptions!$F$35*(1+$C$15)/12 -> 8.6666667 | O107: =SUM(C107:N107) -> 104 | P107: =SUM(C107:G107) -> 43.333333 | Q107: Calculated value (budget)
...

Sheet Actuals
A1: Actual Results - Apr-Aug 2026 (SIMULATED)
A2: Simulated actuals for the budget-vs-actual exercise. Same operating logic as the budget, different inputs.
A3: Simulated data created for portfolio demonstration. It does not represent nonpublic Microchip Technology information. ALL VALUES ON THIS TAB ARE SIMULATED.
A6: Line item | B6: Units | C6: =Ops_Model!C$6 -> 46113 | D6: =Ops_Model!D$6 -> 46143 | E6: =Ops_Model!E$6 -> 46174 | F6: =Ops_Model!F$6 -> 46204 | G6: =Ops_Model!G$6 -> 46235 | H6: YTD Apr-Aug | I6: Classification | J6: Formula
A8: Simulated actual inputs
A9: Input | B9: Units | C9: MCU | D9: Analog & power | E9: FPGA | I9: Classification | J9: Note
A10: Demand vs budget | B10: % | C10: 0.04 | D10: -0.06 | E10: 0.12 | I10: Simulated operational data | J10: Design wins in MCUs and FPGAs; analog channel still digesting inventory
A11: ASP change vs FY2026 base-year ASP | B11: % | C11: -0.02 | D11: -0.005 | E11: 0.02 | I11: Simulated operational data | J11: Budget assumed -1.0% for every product
A12: Actual final-test yield | B12: % | C12: 0.925 | D12: 0.935 | E12: 0.82 | I12: Simulated operational data | J12: FPGA yield problem on the older test platform (budget 85%)
A13: Actual capacity utilization | B13: % | C13: 0.82 | D13: 0.76 | E13: 0.88 | I13: Simulated operational data | J13: Analog loading cut to limit inventory; FPGA run hard to meet demand (budget 80%)
A14: Variable cost change vs FY2026 base-year cost | B14: % | C14: 0.045 | D14: 0.04 | E14: 0.06 | I14: Simulated operational data | J14: Substrate and foundry wafer price increases (budget +3.0%)
A15: Actual fixed manufacturing cost per month | B15: $m | C15: 9.6 | D15: 5.1 | E15: 4.6 | I15: Simulated operational data | J15: FPGA overtime and maintenance on the older testers
A16: Actual R&D expense per month | B16: $m | C16: 18 | I16: Simulated operational data | J16: Budget $17.5m: accelerated hiring for next-gen MCU
A17: Actual SG&A expense per month | B17: $m | C17: 8.4 | I17: Simulated operational data | J17: Budget $8.67m: travel and marketing held back
A18: Actual capex % of revenue | B18: % | C18: 0.026 | I18: Simulated operational data | J18: Budget 3.0%: some projects deferred
A19: Monthly demand noise (applies to all products) | B19: x | C19: 0.99 | D19: 1.02 | E19: 1 | F19: 0.98 | G19: 1.01 | I19: Simulated operational data | J19: Row is by month (Apr-Aug), not by product
A21: Mixed-signal microcontrollers - actual (Simulated data created for portfolio demonstration. It does not represent nonpublic Microchip Technology information.)
A22: Customer demand | B22: m units | C22: =Budget!C19*(1+$C$10)*C$19 -> 24.698341 | D22: =Budget!D19*(1+$C$10)*D$19 -> 25.976917 | E22: =Budget!E19*(1+$C$10)*E$19 -> 26.507058 | F22: =Budget!F19*(1+$C$10)*F$19 -> 24.703539 | G22: =Budget!G19*(1+$C$10)*G$19 -> 25.984713 | H22: =SUM(C22:G22) -> 127.87057 | I22: Simulated operational data
A23: Internal final-test capacity | B23: m units | C23: =Assumptions!$C$46 -> 35 | D23: =Assumptions!$C$46 -> 35 | E23: =Assumptions!$C$46 -> 35 | F23: =Assumptions!$C$46 -> 35 | G23: =Assumptions!$C$46 -> 35 | H23: =SUM(C23:G23) -> 175 | I23: Simulated operational data
A24: Capacity utilization | B24: % | C24: =$C$13 -> 0.82 | D24: =$C$13 -> 0.82 | E24: =$C$13 -> 0.82 | F24: =$C$13 -> 0.82 | G24: =$C$13 -> 0.82 | H24: =IFERROR(H25/H23,0) -> 0.82 | I24: Simulated operational data
A25: Units produced (tested) | B25: m units | C25: =C23*C24 -> 28.7 | D25: =D23*D24 -> 28.7 | E25: =E23*E24 -> 28.7 | F25: =F23*F24 -> 28.7 | G25: =G23*G24 -> 28.7 | H25: =SUM(C25:G25) -> 143.5 | I25: Simulated operational data | J25: Capacity x utilization
A26: Manufacturing yield (final test) | B26: % | C26: =$C$12 -> 0.925 | D26: =$C$12 -> 0.925 | E26: =$C$12 -> 0.925 | F26: =$C$12 -> 0.925 | G26: =$C$12 -> 0.925 | H26: =IFERROR(H27/H25,0) -> 0.925 | I26: Simulated operational data
A27: Good units produced | B27: m units | C27: =C25*C26 -> 26.5475 | D27: =D25*D26 -> 26.5475 | E27: =E25*E26 -> 26.5475 | F27: =F25*F26 -> 26.5475 | G27: =G25*G26 -> 26.5475 | H27: =SUM(C27:G27) -> 132.7375 | I27: Simulated operational data | J27: Units produced x yield
A28: Opening finished-goods inventory | B28: m units | C28: =Assumptions!$C$67 -> 20.823167 | D28: =C31 -> 22.672325 | E28: =D31 -> 23.242908 | F28: =E31 -> 23.28335 | G28: =F31 -> 25.127311 | H28: =C28 -> 20.823167 | I28: Simulated operational data
A29: Available good units | B29: m units | C29: =C28+C27 -> 47.370667 | D29: =D28+D27 -> 49.219825 | E29: =E28+E27 -> 49.790408 | F29: =F28+F27 -> 49.83085 | G29: =G28+G27 -> 51.674811 | I29: Simulated operational data
A30: Units sold | B30: m units | C30: =MIN(C22,C29) -> 24.698341 | D30: =MIN(D22,D29) -> 25.976917 | E30: =MIN(E22,E29) -> 26.507058 | F30: =MIN(F22,F29) -> 24.703539 | G30: =MIN(G22,G29) -> 25.984713 | H30: =SUM(C30:G30) -> 127.87057 | I30: Simulated operational data | J30: MIN(demand, available)
A31: Closing finished-goods inventory | B31: m units | C31: =C29-C30 -> 22.672325 | D31: =D29-D30 -> 23.242908 | E31: =E29-E30 -> 23.28335 | F31: =F29-F30 -> 25.127311 | G31: =G29-G30 -> 25.690098 | H31: =G31 -> 25.690098 | I31: Simulated operational data | J31: Available - sold
A32: Unmet demand | B32: m units | C32: =C22-C30 -> 0 | D32: =D22-D30 -> 0 | E32: =E22-E30 -> 0 | F32: =F22-F30 -> 0 | G32: =G22-G30 -> 0 | H32: =SUM(C32:G32) -> 0 | I32: Simulated operational data
A33: Average selling price | B33: $/unit | C33: =Assumptions!$C$42*(1+$C$11) -> 1.96 | D33: =Assumptions!$C$42*(1+$C$11) -> 1.96 | E33: =Assumptions!$C$42*(1+$C$11) -> 1.96 | F33: =Assumptions!$C$42*(1+$C$11) -> 1.96 | G33: =Assumptions!$C$42*(1+$C$11) -> 1.96 | H33: =IFERROR(H34/H30,0) -> 1.96 | I33: Simulated operational data
A34: Revenue | B34: $m | C34: =C30*C33 -> 48.408749 | D34: =D30*D33 -> 50.914757 | E34: =E30*E33 -> 51.953834 | F34: =F30*F33 -> 48.418936 | G34: =G30*G33 -> 50.930038 | H34: =SUM(C34:G34) -> 250.62631 | I34: Simulated operational data | J34: Units sold x ASP
A35: Variable cost per unit produced | B35: $/unit | C35: =Assumptions!$C$44*(1+$C$14) -> 0.32395 | D35: =Assumptions!$C$44*(1+$C$14) -> 0.32395 | E35: =Assumptions!$C$44*(1+$C$14) -> 0.32395 | F35: =Assumptions!$C$44*(1+$C$14) -> 0.32395 | G35: =Assumptions!$C$44*(1+$C$14) -> 0.32395 | H35: =IFERROR(H36/H25,0) -> 0.32395 | I35: Simulated operational data
A36: Variable manufacturing cost | B36: $m | C36: =C25*C35 -> 9.297365 | D36: =D25*D35 -> 9.297365 | E36: =E25*E35 -> 9.297365 | F36: =F25*F35 -> 9.297365 | G36: =G25*G35 -> 9.297365 | H36: =SUM(C36:G36) -> 46.486825 | I36: Simulated operational data | J36: Units produced x variable cost
A37: Fixed manufacturing cost | B37: $m | C37: =$C$15 -> 9.6 | D37: =$C$15 -> 9.6 | E37: =$C$15 -> 9.6 | F37: =$C$15 -> 9.6 | G37: =$C$15 -> 9.6 | H37: =SUM(C37:G37) -> 48 | I37: Simulated operational data
A38: Total manufacturing cost | B38: $m | C38: =C36+C37 -> 18.897365 | D38: =D36+D37 -> 18.897365 | E38: =E36+E37 -> 18.897365 | F38: =F36+F37 -> 18.897365 | G38: =G36+G37 -> 18.897365 | H38: =SUM(C38:G38) -> 94.486825 | I38: Simulated operational data | J38: Variable + fixed
A39: Cost per good unit | B39: $/unit | C39: =IFERROR(C38/C27,0) -> 0.71183219 | D39: =IFERROR(D38/D27,0) -> 0.71183219 | E39: =IFERROR(E38/E27,0) -> 0.71183219 | F39: =IFERROR(F38/F27,0) -> 0.71183219 | G39: =IFERROR(G38/G27,0) -> 0.71183219 | H39: =IFERROR(H38/H27,0) -> 0.71183219 | I39: Simulated operational data
A40: Opening inventory value | B40: $m | C40: =Assumptions!$C$68 -> 16.516502 | D40: =C43 -> 16.949618 | E40: =D43 -> 16.927897 | F40: =E43 -> 16.752868 | G40: =F43 -> 17.976705 | H40: =C40 -> 16.516502 | I40: Simulated operational data
A41: Average cost per available unit | B41: $/unit | C41: =IFERROR((C40+C38)/C29,0) -> 0.74759064 | D41: =IFERROR((D40+D38)/D29,0) -> 0.72830374 | E41: =IFERROR((E40+E38)/E29,0) -> 0.71952136 | F41: =IFERROR((F40+F38)/F29,0) -> 0.71542493 | G41: =IFERROR((G40+G38)/G29,0) -> 0.71357919 | I41: Simulated operational data | J41: Weighted-average cost
A42: Cost of revenue (manufacturing) | B42: $m | C42: =C30*C41 -> 18.464249 | D42: =D30*D41 -> 18.919086 | E42: =E30*E41 -> 19.072394 | F42: =F30*F41 -> 17.673528 | G42: =G30*G41 -> 18.542151 | H42: =SUM(C42:G42) -> 92.671407 | I42: Simulated operational data | J42: Units sold x average cost
A43: Closing inventory value | B43: $m | C43: =C40+C38-C42 -> 16.949618 | D43: =D40+D38-D42 -> 16.927897 | E43: =E40+E38-E42 -> 16.752868 | F43: =F40+F38-F42 -> 17.976705 | G43: =G40+G38-G42 -> 18.331919 | H43: =G43 -> 18.331919 | I43: Simulated operational data | J43: Opening + manufacturing cost - cost of revenue
A44: Gross profit (before new-capex depreciation) | B44: $m | C44: =C34-C42 -> 29.9445 | D44: =D34-D42 -> 31.995671 | E44: =E34-E42 -> 32.88144 | F44: =F34-F42 -> 30.745408 | G44: =G34-G42 -> 32.387887 | H44: =SUM(C44:G44) -> 157.95491 | I44: Simulated operational data | J44: Revenue - cost of revenue
A45: Gross margin | B45: % | C45: =IFERROR(C44/C34,0) -> 0.61857621 | D45: =IFERROR(D44/D34,0) -> 0.62841646 | E45: =IFERROR(E44/E34,0) -> 0.63289727 | F45: =IFERROR(F44/F34,0) -> 0.63498728 | G45: =IFERROR(G44/G34,0) -> 0.63592898 | H45: =IFERROR(H44/H34,0) -> 0.63024071 | I45: Simulated operational data
A47: Analog & power management - actual (Simulated data created for portfolio demonstration. It does not represent nonpublic Microchip Technology information.)
A48: Customer demand | B48: m units | C48: =Budget!C45*(1+$D$10)*C$19 -> 30.177219 | D48: =Budget!D45*(1+$D$10)*D$19 -> 31.739424 | E48: =Budget!E45*(1+$D$10)*E$19 -> 32.387167 | F48: =Budget!F45*(1+$D$10)*F$19 -> 30.183569 | G48: =Budget!G45*(1+$D$10)*G$19 -> 31.748949 | H48: =SUM(C48:G48) -> 156.23633 | I48: Simulated operational data
A49: Internal final-test capacity | B49: m units | C49: =Assumptions!$D$46 -> 46 | D49: =Assumptions!$D$46 -> 46 | E49: =Assumptions!$D$46 -> 46 | F49: =Assumptions!$D$46 -> 46 | G49: =Assumptions!$D$46 -> 46 | H49: =SUM(C49:G49) -> 230 | I49: Simulated operational data
A50: Capacity utilization | B50: % | C50: =$D$13 -> 0.76 | D50: =$D$13 -> 0.76 | E50: =$D$13 -> 0.76 | F50: =$D$13 -> 0.76 | G50: =$D$13 -> 0.76 | H50: =IFERROR(H51/H49,0) -> 0.76 | I50: Simulated operational data
A51: Units produced (tested) | B51: m units | C51: =C49*C50 -> 34.96 | D51: =D49*D50 -> 34.96 | E51: =E49*E50 -> 34.96 | F51: =F49*F50 -> 34.96 | G51: =G49*G50 -> 34.96 | H51: =SUM(C51:G51) -> 174.8 | I51: Simulated operational data | J51: Capacity x utilization
A52: Manufacturing yield (final test) | B52: % | C52: =$D$12 -> 0.935 | D52: =$D$12 -> 0.935 | E52: =$D$12 -> 0.935 | F52: =$D$12 -> 0.935 | G52: =$D$12 -> 0.935 | H52: =IFERROR(H53/H51,0) -> 0.935 | I52: Simulated operational data
A53: Good units produced | B53: m units | C53: =C51*C52 -> 32.6876 | D53: =D51*D52 -> 32.6876 | E53: =E51*E52 -> 32.6876 | F53: =F51*F52 -> 32.6876 | G53: =G51*G52 -> 32.6876 | H53: =SUM(C53:G53) -> 163.438 | I53: Simulated operational data | J53: Units produced x yield
A54: Opening finished-goods inventory | B54: m units | C54: =Assumptions!$D$67 -> 29.372918 | D54: =C57 -> 31.883299 | E54: =D57 -> 32.831475 | F54: =E57 -> 33.131909 | G54: =F57 -> 35.635939 | H54: =C54 -> 29.372918 | I54: Simulated operational data
A55: Available good units | B55: m units | C55: =C54+C53 -> 62.060518 | D55: =D54+D53 -> 64.570899 | E55: =E54+E53 -> 65.519075 | F55: =F54+F53 -> 65.819509 | G55: =G54+G53 -> 68.323539 | I55: Simulated operational data
A56: Units sold | B56: m units | C56: =MIN(C48,C55) -> 30.177219 | D56: =MIN(D48,D55) -> 31.739424 | E56: =MIN(E48,E55) -> 32.387167 | F56: =MIN(F48,F55) -> 30.183569 | G56: =MIN(G48,G55) -> 31.748949 | H56: =SUM(C56:G56) -> 156.23633 | I56: Simulated operational data | J56: MIN(demand, available)
A57: Closing finished-goods inventory | B57: m units | C57: =C55-C56 -> 31.883299 | D57: =D55-D56 -> 32.831475 | E57: =E55-E56 -> 33.131909 | F57: =F55-F56 -> 35.635939 | G57: =G55-G56 -> 36.57459 | H57: =G57 -> 36.57459 | I57: Simulated operational data | J57: Available - sold
A58: Unmet demand | B58: m units | C58: =C48-C56 -> 0 | D58: =D48-D56 -> 0 | E58: =E48-E56 -> 0 | F58: =F48-F56 -> 0 | G58: =G48-G56 -> 0 | H58: =SUM(C58:G58) -> 0 | I58: Simulated operational data
A59: Average selling price | B59: $/unit | C59: =Assumptions!$D$42*(1+$D$11) -> 0.796 | D59: =Assumptions!$D$42*(1+$D$11) -> 0.796 | E59: =Assumptions!$D$42*(1+$D$11) -> 0.796 | F59: =Assumptions!$D$42*(1+$D$11) -> 0.796 | G59: =Assumptions!$D$42*(1+$D$11) -> 0.796 | H59: =IFERROR(H60/H56,0) -> 0.796 | I59: Simulated operational data
A60: Revenue | B60: $m | C60: =C56*C59 -> 24.021066 | D60: =D56*D59 -> 25.264581 | E60: =E56*E59 -> 25.780185 | F60: =F56*F59 -> 24.026121 | G60: =G56*G59 -> 25.272164 | H60: =SUM(C60:G60) -> 124.36412 | I60: Simulated operational data | J60: Units sold x ASP
A61: Variable cost per unit produced | B61: $/unit | C61: =Assumptions!$D$44*(1+$D$14) -> 0.156 | D61: =Assumptions!$D$44*(1+$D$14) -> 0.156 | E61: =Assumptions!$D$44*(1+$D$14) -> 0.156 | F61: =Assumptions!$D$44*(1+$D$14) -> 0.156 | G61: =Assumptions!$D$44*(1+$D$14) -> 0.156 | H61: =IFERROR(H62/H51,0) -> 0.156 | I61: Simulated operational data
A62: Variable manufacturing cost | B62: $m | C62: =C51*C61 -> 5.45376 | D62: =D51*D61 -> 5.45376 | E62: =E51*E61 -> 5.45376 | F62: =F51*F61 -> 5.45376 | G62: =G51*G61 -> 5.45376 | H62: =SUM(C62:G62) -> 27.2688 | I62: Simulated operational data | J62: Units produced x variable cost
A63: Fixed manufacturing cost | B63: $m | C63: =$D$15 -> 5.1 | D63: =$D$15 -> 5.1 | E63: =$D$15 -> 5.1 | F63: =$D$15 -> 5.1 | G63: =$D$15 -> 5.1 | H63: =SUM(C63:G63) -> 25.5 | I63: Simulated operational data
A64: Total manufacturing cost | B64: $m | C64: =C62+C63 -> 10.55376 | D64: =D62+D63 -> 10.55376 | E64: =E62+E63 -> 10.55376 | F64: =F62+F63 -> 10.55376 | G64: =G62+G63 -> 10.55376 | H64: =SUM(C64:G64) -> 52.7688 | I64: Simulated operational data | J64: Variable + fixed
A65: Cost per good unit | B65: $/unit | C65: =IFERROR(C64/C53,0) -> 0.32286739 | D65: =IFERROR(D64/D53,0) -> 0.32286739 | E65: =IFERROR(E64/E53,0) -> 0.32286739 | F65: =IFERROR(F64/F53,0) -> 0.32286739 | G65: =IFERROR(G64/G53,0) -> 0.32286739 | H65: =IFERROR(H64/H53,0) -> 0.32286739 | I65: Simulated operational data
A66: Opening inventory value | B66: $m | C66: =Assumptions!$D$68 -> 9.8871678 | D66: =C69 -> 10.50143 | E66: =D69 -> 10.705643 | F66: =E69 -> 10.750527 | G66: =F69 -> 11.534548 | H66: =C66 -> 9.8871678 | I66: Simulated operational data
A67: Average cost per available unit | B67: $/unit | C67: =IFERROR((C66+C64)/C55,0) -> 0.32937089 | D67: =IFERROR((D66+D64)/D55,0) -> 0.32607863 | E67: =IFERROR((E66+E64)/E55,0) -> 0.32447654 | F67: =IFERROR((F66+F64)/F55,0) -> 0.32367739 | G67: =IFERROR((G66+G64)/G55,0) -> 0.32328987 | I67: Simulated operational data | J67: Weighted-average cost
A68: Cost of revenue (manufacturing) | B68: $m | C68: =C56*C67 -> 9.9394973 | D68: =D56*D67 -> 10.349548 | E68: =E56*E67 -> 10.508876 | F68: =F56*F67 -> 9.7697391 | G68: =G56*G67 -> 10.264114 | H68: =SUM(C68:G68) -> 50.831773 | I68: Simulated operational data | J68: Units sold x average cost
A69: Closing inventory value | B69: $m | C69: =C66+C64-C68 -> 10.50143 | D69: =D66+D64-D68 -> 10.705643 | E69: =E66+E64-E68 -> 10.750527 | F69: =F66+F64-F68 -> 11.534548 | G69: =G66+G64-G68 -> 11.824194 | H69: =G69 -> 11.824194 | I69: Simulated operational data | J69: Opening + manufacturing cost - cost of revenue
A70: Gross profit (before new-capex depreciation) | B70: $m | C70: =C60-C68 -> 14.081569 | D70: =D60-D68 -> 14.915033 | E70: =E60-E68 -> 15.271309 | F70: =F60-F68 -> 14.256382 | G70: =G60-G68 -> 15.00805 | H70: =SUM(C70:G70) -> 73.532344 | I70: Simulated operational data | J70: Revenue - cost of revenue
A71: Gross margin | B71: % | C71: =IFERROR(C70/C60,0) -> 0.58621748 | D71: =IFERROR(D70/D60,0) -> 0.59035348 | E71: =IFERROR(E70/E60,0) -> 0.59236616 | F71: =IFERROR(F70/F60,0) -> 0.59337011 | G71: =IFERROR(G70/G60,0) -> 0.59385695 | H71: =IFERROR(H70/H60,0) -> 0.59126656 | I71: Simulated operational data
A73: FPGAs - actual (Simulated data created for portfolio demonstration. It does not represent nonpublic Microchip Technology information.)
A74: Customer demand | B74: m units | C74: =Budget!C71*(1+$E$10)*C$19 -> 0.96804444 | D74: =Budget!D71*(1+$E$10)*D$19 -> 1.0181578 | E74: =Budget!E71*(1+$E$10)*E$19 -> 1.0389366 | F74: =Budget!F71*(1+$E$10)*F$19 -> 0.96824815 | G74: =Budget!G71*(1+$E$10)*G$19 -> 1.0184634 | H74: =SUM(C74:G74) -> 5.0118504 | I74: Simulated operational data
A75: Internal final-test capacity | B75: m units | C75: =Assumptions!$E$46 -> 1.3 | D75: =Assumptions!$E$46 -> 1.3 | E75: =Assumptions!$E$46 -> 1.3 | F75: =Assumptions!$E$46 -> 1.3 | G75: =Assumptions!$E$46 -> 1.3 | H75: =SUM(C75:G75) -> 6.5 | I75: Simulated operational data
A76: Capacity utilization | B76: % | C76: =$E$13 -> 0.88 | D76: =$E$13 -> 0.88 | E76: =$E$13 -> 0.88 | F76: =$E$13 -> 0.88 | G76: =$E$13 -> 0.88 | H76: =IFERROR(H77/H75,0) -> 0.88 | I76: Simulated operational data
A77: Units produced (tested) | B77: m units | C77: =C75*C76 -> 1.144 | D77: =D75*D76 -> 1.144 | E77: =E75*E76 -> 1.144 | F77: =F75*F76 -> 1.144 | G77: =G75*G76 -> 1.144 | H77: =SUM(C77:G77) -> 5.72 | I77: Simulated operational data | J77: Capacity x utilization
A78: Manufacturing yield (final test) | B78: % | C78: =$E$12 -> 0.82 | D78: =$E$12 -> 0.82 | E78: =$E$12 -> 0.82 | F78: =$E$12 -> 0.82 | G78: =$E$12 -> 0.82 | H78: =IFERROR(H79/H77,0) -> 0.82 | I78: Simulated operational data
A79: Good units produced | B79: m units | C79: =C77*C78 -> 0.93808 | D79: =D77*D78 -> 0.93808 | E79: =E77*E78 -> 0.93808 | F79: =F77*F78 -> 0.93808 | G79: =G77*G78 -> 0.93808 | H79: =SUM(C79:G79) -> 4.6904 | I79: Simulated operational data | J79: Units produced x yield
A80: Opening finished-goods inventory | B80: m units | C80: =Assumptions!$E$67 -> 0.72754663 | D80: =C83 -> 0.69758219 | E80: =D83 -> 0.61750434 | F80: =E83 -> 0.51664776 | G80: =F83 -> 0.48647961 | H80: =C80 -> 0.72754663 | I80: Simulated operational data
A81: Available good units | B81: m units | C81: =C80+C79 -> 1.6656266 | D81: =D80+D79 -> 1.6356622 | E81: =E80+E79 -> 1.5555843 | F81: =F80+F79 -> 1.4547278 | G81: =G80+G79 -> 1.4245596 | I81: Simulated operational data
A82: Units sold | B82: m units | C82: =MIN(C74,C81) -> 0.96804444 | D82: =MIN(D74,D81) -> 1.0181578 | E82: =MIN(E74,E81) -> 1.0389366 | F82: =MIN(F74,F81) -> 0.96824815 | G82: =MIN(G74,G81) -> 1.0184634 | H82: =SUM(C82:G82) -> 5.0118504 | I82: Simulated operational data | J82: MIN(demand, available)
A83: Closing finished-goods inventory | B83: m units | C83: =C81-C82 -> 0.69758219 | D83: =D81-D82 -> 0.61750434 | E83: =E81-E82 -> 0.51664776 | F83: =F81-F82 -> 0.48647961 | G83: =G81-G82 -> 0.40609619 | H83: =G83 -> 0.40609619 | I83: Simulated operational data | J83: Available - sold
A84: Unmet demand | B84: m units | C84: =C74-C82 -> 0 | D84: =D74-D82 -> 0 | E84: =E74-E82 -> 0 | F84: =F74-F82 -> 0 | G84: =G74-G82 -> 0 | H84: =SUM(C84:G84) -> 0 | I84: Simulated operational data
A85: Average selling price | B85: $/unit | C85: =Assumptions!$E$42*(1+$E$11) -> 25.5 | D85: =Assumptions!$E$42*(1+$E$11) -> 25.5 | E85: =Assumptions!$E$42*(1+$E$11) -> 25.5 | F85: =Assumptions!$E$42*(1+$E$11) -> 25.5 | G85: =Assumptions!$E$42*(1+$E$11) -> 25.5 | H85: =IFERROR(H86/H82,0) -> 25.5 | I85: Simulated operational data
A86: Revenue | B86: $m | C86: =C82*C85 -> 24.685133 | D86: =D82*D85 -> 25.963025 | E86: =E82*E85 -> 26.492883 | F86: =F82*F85 -> 24.690328 | G86: =G82*G85 -> 25.970817 | H86: =SUM(C86:G86) -> 127.80219 | I86: Simulated operational data | J86: Units sold x ASP
A87: Variable cost per unit produced | B87: $/unit | C87: =Assumptions!$E$44*(1+$E$14) -> 4.982 | D87: =Assumptions!$E$44*(1+$E$14) -> 4.982 | E87: =Assumptions!$E$44*(1+$E$14) -> 4.982 | F87: =Assumptions!$E$44*(1+$E$14) -> 4.982 | G87: =Assumptions!$E$44*(1+$E$14) -> 4.982 | H87: =IFERROR(H88/H77,0) -> 4.982 | I87: Simulated operational data
A88: Variable manufacturing cost | B88: $m | C88: =C77*C87 -> 5.699408 | D88: =D77*D87 -> 5.699408 | E88: =E77*E87 -> 5.699408 | F88: =F77*F87 -> 5.699408 | G88: =G77*G87 -> 5.699408 | H88: =SUM(C88:G88) -> 28.49704 | I88: Simulated operational data | J88: Units produced x variable cost
A89: Fixed manufacturing cost | B89: $m | C89: =$E$15 -> 4.6 | D89: =$E$15 -> 4.6 | E89: =$E$15 -> 4.6 | F89: =$E$15 -> 4.6 | G89: =$E$15 -> 4.6 | H89: =SUM(C89:G89) -> 23 | I89: Simulated operational data
A90: Total manufacturing cost | B90: $m | C90: =C88+C89 -> 10.299408 | D90: =D88+D89 -> 10.299408 | E90: =E88+E89 -> 10.299408 | F90: =F88+F89 -> 10.299408 | G90: =G88+G89 -> 10.299408 | H90: =SUM(C90:G90) -> 51.49704 | I90: Simulated operational data | J90: Variable + fixed
A91: Cost per good unit | B91: $/unit | C91: =IFERROR(C90/C79,0) -> 10.979243 | D91: =IFERROR(D90/D79,0) -> 10.979243 | E91: =IFERROR(E90/E79,0) -> 10.979243 | F91: =IFERROR(F90/F79,0) -> 10.979243 | G91: =IFERROR(G90/G79,0) -> 10.979243 | H91: =IFERROR(H90/H79,0) -> 10.979243 | I91: Simulated operational data
A92: Opening inventory value | B92: $m | C92: =Assumptions!$E$68 -> 8.4229049 | D92: =C95 -> 7.8411042 | E92: =D95 -> 6.8485076 | F92: =E95 -> 5.6952439 | G92: =F95 -> 5.3488166 | H92: =C92 -> 8.4229049 | I92: Simulated operational data
A93: Average cost per available unit | B93: $/unit | C93: =IFERROR((C92+C90)/C81,0) -> 11.240402 | D93: =IFERROR((D92+D90)/D81,0) -> 11.090623 | E93: =IFERROR((E92+E90)/E81,0) -> 11.023456 | F93: =IFERROR((F92+F90)/F81,0) -> 10.994945 | G93: =IFERROR((G92+G90)/G81,0) -> 10.984605 | I93: Simulated operational data | J93: Weighted-average cost
A94: Cost of revenue (manufacturing) | B94: $m | C94: =C82*C93 -> 10.881209 | D94: =D82*D93 -> 11.292005 | E94: =E82*E93 -> 11.452672 | F94: =F82*F93 -> 10.645835 | G94: =G82*G93 -> 11.187418 | H94: =SUM(C94:G94) -> 55.459139 | I94: Simulated operational data | J94: Units sold x average cost
A95: Closing inventory value | B95: $m | C95: =C92+C90-C94 -> 7.8411042 | D95: =D92+D90-D94 -> 6.8485076 | E95: =E92+E90-E94 -> 5.6952439 | F95: =F92+F90-F94 -> 5.3488166 | G95: =G92+G90-G94 -> 4.4608062 | H95: =G95 -> 4.4608062 | I95: Simulated operational data | J95: Opening + manufacturing cost - cost of revenue
A96: Gross profit (before new-capex depreciation) | B96: $m | C96: =C86-C94 -> 13.803925 | D96: =D86-D94 -> 14.671021 | E96: =E86-E94 -> 15.040211 | F96: =F86-F94 -> 14.044493 | G96: =G86-G94 -> 14.783399 | H96: =SUM(C96:G96) -> 72.343048 | I96: Simulated operational data | J96: Revenue - cost of revenue
A97: Gross margin | B97: % | C97: =IFERROR(C96/C86,0) -> 0.55919992 | D97: =IFERROR(D96/D86,0) -> 0.56507362 | E97: =IFERROR(E96/E86,0) -> 0.5677076 | F97: =IFERROR(F96/F86,0) -> 0.56882568 | G97: =IFERROR(G96/G86,0) -> 0.56923118 | H97: =IFERROR(H96/H86,0) -> 0.56605485 | I97: Simulated operational data
A99: Division actual P&L to operating profit (Simulated data created for portfolio demonstration. It does not represent nonpublic Microchip Technology information.)
A100: Revenue | B100: $m | C100: =C34+C60+C86 -> 97.114948 | D100: =D34+D60+D86 -> 102.14236 | E100: =E34+E60+E86 -> 104.2269 | F100: =F34+F60+F86 -> 97.135385 | G100: =G34+G60+G86 -> 102.17302 | H100: =SUM(C100:G100) -> 502.79262 | I100: Simulated operational data
A101: Variable manufacturing cost | B101: $m | C101: =C36+C62+C88 -> 20.450533 | D101: =D36+D62+D88 -> 20.450533 | E101: =E36+E62+E88 -> 20.450533 | F101: =F36+F62+F88 -> 20.450533 | G101: =G36+G62+G88 -> 20.450533 | H101: =SUM(C101:G101) -> 102.25266 | I101: Simulated operational data
A102: Fixed manufacturing cost | B102: $m | C102: =C37+C63+C89 -> 19.3 | D102: =D37+D63+D89 -> 19.3 | E102: =E37+E63+E89 -> 19.3 | F102: =F37+F63+F89 -> 19.3 | G102: =G37+G63+G89 -> 19.3 | H102: =SUM(C102:G102) -> 96.5 | I102: Simulated operational data
