Workbook

Sheet Cover
B2: Semiconductor FP&A Forecasting and Decision Model
B3: Fictional Power, Signal & Embedded Division, modeled on Texas Instruments Incorporated (NASDAQ: TXN)
B5: Simulated data created for portfolio demonstration. It does not represent nonpublic Texas Instruments information.
B6: Reported public data comes only from Texas Instruments's SEC filings (see Sources_Log). All division-level operating data is simulated and labeled as such.
B8: Business question | C8: How would changes in demand, average selling price, product mix, manufacturing yield, capacity utilization, operating costs and capital spending affect the division's revenue, operating profit and free cash flow?
B10: Model status | C10: =Checks!$C$172 -> ALL CHECKS PASS
B11: Built by | C11: scripts/build_model.py --company TXN (config: companies/TXN/config.toml)
B13: Tab guide
B14: Cover | C14: This page
B15: Sources_Log | C15: Source register (SEC filings) and assumptions log
B16: Assumptions | C16: Scenario selector (one cell), 9 scenario drivers, division & product inputs, seasonality
B17: Hist_Data | C17: Reported financials FY2021-FY2025, one source per row (inputs)
B18: Hist_Analysis | C18: Growth, margins, segment mix, free cash flow, working capital (formulas)
B19: Ops_Model | C19: Product x month operating model: demand, capacity, yield, inventory, revenue, cost, gross profit
B20: Revenue | C20: Monthly revenue forecast by product line, mix, quarters, FY vs FY2025 base year
B21: PnL | C21: Monthly P&L to net income; EBITDA; FY2025 base-year comparison
B22: FCF | C22: Capex and depreciation, working capital, free cash flow
B23: Budget | C23: FY2026 budget = Base scenario, locked (does not follow the selector)
B24: Actuals | C24: SIMULATED actual results Jan-May 2026, same operating logic
B25: Variance | C25: YTD budget vs actual: price/volume/mix, operating-profit bridge, reconciliation flags
... B28: Checks | C28: Independent checks and hand-calculable unit tests; overall status feeds this cover
B30: Color legend
B31: 1,234.5 | C31: Blue: hardcoded input (reported value or assumption)
B32: 1,234.5 | C32: Black: formula / calculation
B33: 1,234.5 | C33: Green: direct link to another tab
B34: Input | C34: Yellow fill: key assumption / cell a user may change
B36: Value classification
C37: Reported public data - transcribed from an SEC filing (source on every row)
C38: Calculated value - Excel formula on other cells
C39: User-provided assumption - logged in Sources_Log with who decided it
C40: Simulated operational data - labeled with the disclaimer above
B42: Units & conventions | C42: USD millions unless noted. Fiscal year ends December 31. Negatives in parentheses. Capex printed negative in Hist_Data, positive in analysis.

Sheet Sources_Log
A1: Source Register and Assumptions Log
A2: Every reported value traces to a source below. Every assumption is logged with who decided it.
A3: Simulated data created for portfolio demonstration. It does not represent nonpublic Texas Instruments information.
A5: Source register
A6: ID | B6: Document | C6: Accession no. | D6: Period covered | E6: URL | F6: Used for | G6: Accessed
A7: S-001 | B7: Form 10-K fiscal 2025 | C7: 0000097476-26-000059 | D7: FY2023-FY2025 income statement & cash flow; FY2024-FY2025 balance sheet; segment revenue and gross profit FY2023-FY2025 | E7: https://www.sec.gov/Archives/edgar/data/97476/000009747626000059/ | F7: Historical analysis; product-mix anchor | G7: 2026-09-22
A8: S-002 | B8: Form 10-K fiscal 2023 | C8: 0000097476-24-000007 | D8: FY2021-FY2022 income statement & cash flow; FY2022-FY2023 balance sheet; FY2021-FY2022 segment revenue | E8: https://www.sec.gov/Archives/edgar/data/97476/000009747624000007/ | F8: Historical analysis; cross-filing check | G8: 2026-09-22
A9: S-003 | B9: Form 10-K fiscal 2022 | C9: 0000097476-23-000007 | D9: FY2021 balance sheet | E9: https://www.sec.gov/Archives/edgar/data/97476/000009747623000007/ | F9: Historical analysis; cross-filing check | G9: 2026-09-22
A10: S-004 | B10: Form 10-K fiscal 2024 | C10: 0000097476-25-000007 | D10: FY2023-FY2024 balance sheet (second transcription) | E10: https://www.sec.gov/Archives/edgar/data/97476/000009747625000007/ | F10: Cross-filing check only | G10: 2026-09-22
A11: S-005 | B11: Form 10-Q second quarter 2026 | C11: 0000097476-26-000152 | D11: Three months ended June 30 2026 and 2025: income statement and segment revenue | E11: https://www.sec.gov/Archives/edgar/data/97476/000009747626000152/ | F11: Quarterly context for the demand-growth assumption | G11: 2026-09-22
A13: Assumptions log
A14: ID | B14: Area | C14: Assumption | D14: Value | E14: Rationale | F14: Classification | G14: Decided by | H14: Status
A15: A-001 | B15: Scope | C15: Public company used for historical data | D15: Texas Instruments Incorporated (NASDAQ: TXN) | E15: Second test company for the multi-company engine (Phase 10c) | F15: User-provided assumption | G15: User | H15: Final
A16: A-002 | B16: Scope | C16: Historical window | D16: FY2021-FY2025 (fiscal year = calendar year) | E16: Five reported years (engine layout); covers the 2022 peak and the 2024 trough | F16: User-provided assumption | G16: Claude (delegated by user) | H16: Final
A17: A-003 | B17: Timing | C17: Forecast period | D17: FY2026 monthly: Jan-2026 to Dec-2026 | E17: TI's current fiscal year | F17: User-provided assumption | G17: Claude (delegated by user) | H17: Final
A18: A-004 | B18: Timing | C18: Actuals vs forecast split | D18: Jan-May 2026 = simulated actuals; Jun-Dec = forecast | E18: The engine layout uses exactly five actual months; as of September this is conservative (June-August not loaded) | F18: User-provided assumption | G18: Claude (delegated by user) | H18: Final
A19: A-005 | B19: Division | C19: Fictional division | D19: "Power, Signal & Embedded Division" - fictional, modeled on TI | E19: Matches the three product categories in the project brief | F19: User-provided assumption | G19: Claude (delegated by user) | H19: Final
A20: A-006 | B20: Division | C20: Division base-year (FY2025) revenue | D20: $1000.0M | E20: Same scale as the Microchip build for comparability | F20: User-provided assumption | G20: Claude (delegated by user) | H20: Final
A21: A-007 | B21: Division | C21: Product categories and mapping | D21: 1) Power-management chips 2) Signal-chain chips 3) Embedded processors; power and signal = assumed split of TI's Analog segment; embedded = TI's Embedded Processing segment | E21: User chose option B (follow the brief) over option A (TI's own segments) | F21: User-provided assumption | G21: User | H21: Final
A22: A-008 | B22: Division | C22: Split of TI's Analog segment | D22: Power 50% / Signal chain 50% | E22: TI does not report power and signal chain separately; 50/50 is a neutral placeholder - replace if a sourced split is available | F22: User-provided assumption | G22: Claude (delegated by user) | H22: Open - user may change
A23: A-009 | B23: Division | C23: Segments not modeled | D23: TI Other segment (5.5% of FY2025 revenue) excluded; three-product mix renormalized to 100% | E23: The brief names three product categories only | F23: User-provided assumption | G23: Claude (delegated by user) | H23: Final
A24: A-010 | B24: Labeling | C24: Simulated-data disclaimer | D24: Simulated data created for portfolio demonstration. It does not represent nonpublic Texas Instruments information. | E24: Project rule | F24: User-provided assumption | G24: User | H24: Final
A25: A-011 | B25: Operations | C25: Base-year product inputs | D25: ASP $0.60 / $0.95 / $3.40; yield 95% / 93% / 88%; variable cost $0.14 / $0.21 / $0.95; fixed $5.8m / $6.2m / $2.5m per month; capacity 88 / 60 / 7 m units per month | E25: Calibrated so base-year division gross margin (57.2%) is close to TI's reported FY2025 gross margin (57.0%) | F25: Simulated operational data | G25: Claude (delegated by user) | H25: Final
... A38: A-024 | B38: Data | C38: Sign convention for interest and restructuring | D38: Interest and debt expense stored negative; restructuring credit (2024) stored negative | E38: So pre-tax income = operating profit + non-operating items holds; noted on each row | F38: User-provided assumption | G38: Claude (delegated by user) | H38: Final

Sheet Assumptions
A1: Assumptions and Scenario Controls
A2: Change ONLY the yellow selector (C6) to switch scenario. Blue = input. Every forecast tab reads the Live column.
A3: Simulated data created for portfolio demonstration. It does not represent nonpublic Texas Instruments information.
A6: ACTIVE SCENARIO (choose Downside / Base / Upside) | C6: Base | D6: =MATCH($C$6,$C$9:$E$9,0) -> 2 | E6: <- scenario index (1 = Downside, 2 = Base, 3 = Upside)
A8: A. Scenario drivers (FY2026 vs FY2025 base year)
A9: Driver | B9: Units | C9: Downside | D9: Base | E9: Upside | F9: LIVE | P9: Classification | Q9: Rationale / reference
A10: Customer demand growth | B10: % | C10: 0.03 | D10: 0.15 | E10: 0.24 | F10: =INDEX(C10:E10,1,$D$6) -> 0.15 | P10: User-provided assumption | Q10: TI Q2 FY2026 revenue +22.8% YoY (section B). Base takes a more cautious +15% for the full year.
A11: Average selling price change | B11: % | C11: -0.03 | D11: -0.01 | E11: 0.01 | F11: =INDEX(C11:E11,1,$D$6) -> -0.01 | P11: User-provided assumption | Q11: Mature analog prices drift down slowly; downside = price competition.
A12: Manufacturing yield change (percentage points vs base-year yield) | B12: pts | C12: -0.02 | D12: 0 | E12: 0.01 | F12: =INDEX(C12:E12,1,$D$6) -> 0 | P12: User-provided assumption | Q12: Applied to each product's base-year final-test yield (section D).
A13: Capacity utilization (internal final test) | B13: % | C13: 0.68 | D13: 0.78 | E13: 0.86 | F13: =INDEX(C13:E13,1,$D$6) -> 0.78 | P13: User-provided assumption | Q13: Assumed. TI does not disclose utilization; implied base-year loading is shown in section D.
A14: Material-cost inflation (variable cost per unit) | B14: % | C14: 0.05 | D14: 0.03 | E14: 0.01 | F14: =INDEX(C14:E14,1,$D$6) -> 0.03 | P14: User-provided assumption | Q14: Wafer, substrate and packaging cost inflation.
A15: R&D expense growth | B15: % | C15: 0.02 | D15: 0.05 | E15: 0.08 | F15: =INDEX(C15:E15,1,$D$6) -> 0.05 | P15: User-provided assumption | Q15: TI R&D grew +6.3% in FY2025 (section B).
A16: SG&A expense growth | B16: % | C16: 0.01 | D16: 0.03 | E16: 0.05 | F16: =INDEX(C16:E16,1,$D$6) -> 0.03 | P16: User-provided assumption | Q16: TI SG&A grew +3.7% in FY2025 (section B).
A17: Capital expenditures (% of revenue, excl. proposed test-equipment project) | B17: % | C17: 0.04 | D17: 0.05 | E17: 0.06 | F17: =INDEX(C17:E17,1,$D$6) -> 0.05 | P17: User-provided assumption | Q17: TI capex was 25.7% of revenue in FY2025 (section B), driven by its corporate 300-mm fab build-out; division equipment capex assumed far lower.
A18: Tax rate | B18: % | C18: 0.16 | D18: 0.13 | E18: 0.12 | F18: =INDEX(C18:E18,1,$D$6) -> 0.13 | P18: User-provided assumption | Q18: TI effective rate about 12-13% in FY2021-FY2025 (section B). Downside = higher rate.
A20: B. Reference points from Texas Instruments's reported history (formulas - context for the drivers above)
A21: Q2 FY2026 net sales growth vs Q2 FY2025 | F21: =Hist_Analysis!$E$51 -> 0.22819245 | P21: Calculated value | Q21: Reported public data (Hist tabs)
A22: Q2 FY2026 sales x 4 vs FY2025 net sales | F22: =Hist_Data!$D$68*4/Hist_Data!$G$7-1 -> 0.23583305 | P22: Calculated value | Q22: Reported public data (Hist tabs)
A23: Gross margin FY2025 (reported basis) | F23: =Hist_Analysis!$G$9 -> 0.57024092 | P23: Calculated value | Q23: Reported public data (Hist tabs)
A24: Gross margin FY2022 (highest in the history) | F24: =Hist_Analysis!$D$9 -> 0.68758738 | P24: Calculated value | Q24: Reported public data (Hist tabs)
A25: R&D growth FY2025 | F25: =Hist_Data!$G$10/Hist_Data!$F$10-1 -> 0.063297601 | P25: Calculated value | Q25: Reported public data (Hist tabs)
A26: SG&A growth FY2025 | F26: =Hist_Data!$G$11/Hist_Data!$F$11-1 -> 0.036789298 | P26: Calculated value | Q26: Reported public data (Hist tabs)
A27: Capex % of sales FY2025 | F27: =Hist_Analysis!$G$37 -> 0.25732383 | P27: Calculated value | Q27: Reported public data (Hist tabs)
A28: Capex % of sales, average FY2021-FY2025 | F28: =AVERAGE(Hist_Analysis!$C$37:$G$37) -> 0.22576255 | P28: Calculated value | Q28: Reported public data (Hist tabs)
A29: Effective tax rate, average FY2021-FY2025 (years shown n.m. excluded) | F29: =AVERAGE(Hist_Analysis!$C$17:$G$17) -> 0.12466721 | P29: Calculated value | Q29: Reported public data (Hist tabs)
A31: C. Fictional Power, Signal & Embedded Division - base year FY2025 (Simulated data created for portfolio demonstration. It does not represent nonpublic Texas Instruments information.)
A32: Division net revenue, FY2025 base year | B32: $m | F32: 1000 | P32: User-provided assumption | Q32: User-provided assumption. ~6% of Texas Instruments FY2025 net sales
A33: Division R&D expense, FY2025 base year | B33: $m | F33: 120 | P33: Simulated operational data | Q33: 12% of revenue. TI company-wide R&D was 11.8% of revenue in FY2025. Used in Phase 3.
A34: Division SG&A expense, FY2025 base year | B34: $m | F34: 100 | P34: Simulated operational data | Q34: 10% of revenue. TI company-wide SG&A was 10.5% of revenue in FY2025. Used in Phase 3.
A35: Forecast start month (first month of FY2026) | F35: 46023 | P35: User-provided assumption | Q35: FY2026 = Jan-2026 to Dec-2026, calendar months
A37: D. Product inputs - base year FY2025 (simulated) and live FY2026 drivers (calculated)
A38: Input | B38: Units | C38: Power management | D38: Signal chain | E38: Embedded processors | F38: Division | P38: Classification | Q38: Notes
A39: Share of the reported segment assigned to this product | B39: % | C39: 0.5 | D39: 0.5 | E39: 1 | P39: User-provided assumption | Q39: User-provided assumption (option B). TI does not report power and signal chain separately; 50/50 is a neutral split. Change it in companies/TXN/config.toml.
A40: Reported segment share of net sales x assigned share | B40: % | C40: =Hist_Analysis!$G$20*$C$39 -> 0.39605248 | D40: =Hist_Analysis!$G$20*$D$39 -> 0.39605248 | E40: =Hist_Analysis!$G$21*$E$39 -> 0.15252799 | F40: =SUM(C40:E40) -> 0.94463296 | P40: Calculated value | Q40: Texas Instruments FY2025 reported segment mix x the split above. Power = 50% of TI's reported Analog segment (user-provided split; TI does not report power separately). Signal chain = the other 50% of Analog.
A41: Base-year revenue mix | B41: % | C41: =$C$40/$F$40 -> 0.419266 | D41: =$D$40/$F$40 -> 0.419266 | E41: =$E$40/$F$40 -> 0.161468 | F41: =SUM(C41:E41) -> 1 | P41: Calculated value | Q41: Renormalized to 100% over the three products (reported segments not modeled are excluded).
A42: Base-year revenue | B42: $m | C42: =$F$32*$C$41 -> 419.266 | D42: =$F$32*$D$41 -> 419.266 | E42: =$F$32*$E$41 -> 161.468 | F42: =SUM(C42:E42) -> 1000 | P42: Calculated value | Q42: Division revenue x mix
A43: Base-year average selling price | B43: $/unit | C43: 0.6 | D43: 0.95 | E43: 3.4 | P43: Simulated operational data | Q43: Simulated. Order of magnitude typical for each product type.
A44: Base-year final-test yield | B44: % | C44: 0.95 | D44: 0.93 | E44: 0.88 | P44: Simulated operational data | Q44: Simulated. Good units / units tested. Larger embedded die -> lower yield.
A45: Base-year variable cost per unit produced | B45: $/unit | C45: 0.14 | D45: 0.21 | E45: 0.95 | P45: Simulated operational data | Q45: Simulated. Wafer, package, test consumables per unit started. Calibrated so the base-year division gross margin (57.2%) is close to TI's reported FY2025 57.0%.
A46: Fixed manufacturing cost per month | B46: $m/month | C46: 5.8 | D46: 6.2 | E46: 2.5 | F46: =SUM(C46:E46) -> 14.5 | P46: Simulated operational data | Q46: Simulated. Factory overhead, depreciation, test labor.
A47: Internal final-test capacity | B47: m units/month | C47: 88 | D47: 60 | E47: 7 | P47: Simulated operational data | Q47: Simulated. Capacity = units the internal test floor can process per month (A-016).
A48: Product demand growth vs division driver | B48: pts | C48: 0.02 | D48: 0.02 | E48: -0.06 | P48: Simulated operational data | Q48: Simulated. TI Q2 FY2026 revenue growth was Analog +26.4%, Embedded Processing +16.1% (section B).
A49: Opening finished-goods inventory (months of base-year sales) | B49: months | C49: 1 | D49: 1 | E49: 1 | P49: Simulated operational data | Q49: Simulated opening balance at 1-Jan-2026.
A51: Base-year FY2025 economics (calculated; assumes production = sales in the base year)
A52: Units sold | B52: m units | C52: =$C$42/$C$43 -> 698.77667 | D52: =$D$42/$D$43 -> 441.33263 | E52: =$E$42/$E$43 -> 47.490588 | P52: Calculated value | Q52: Revenue / ASP
A53: Units produced (tested) | B53: m units | C53: =$C$52/$C$44 -> 735.55439 | D53: =$D$52/$D$44 -> 474.55122 | E53: =$E$52/$E$44 -> 53.966577 | P53: Calculated value | Q53: Units sold / yield (no inventory change in base year)
A54: Implied capacity utilization | B54: % | C54: =$C$53/($C$47*12) -> 0.69654771 | D54: =$D$53/($D$47*12) -> 0.65909891 | E54: =$E$53/($E$47*12) -> 0.64245926 | P54: Calculated value | Q54: Units produced / (capacity x 12).
A55: Variable manufacturing cost | B55: $m | C55: =$C$53*$C$45 -> 102.97761 | D55: =$D$53*$D$45 -> 99.655756 | E55: =$E$53*$E$45 -> 51.268249 | F55: =SUM(C55:E55) -> 253.90162 | P55: Calculated value | Q55: Units produced x variable cost per unit
A56: Fixed manufacturing cost | B56: $m | C56: =$C$46*12 -> 69.6 | D56: =$D$46*12 -> 74.4 | E56: =$E$46*12 -> 30 | F56: =SUM(C56:E56) -> 174 | P56: Calculated value | Q56: Monthly fixed cost x 12
A57: Cost of revenue | B57: $m | C57: =$C$55+$C$56 -> 172.57761 | D57: =$D$55+$D$56 -> 174.05576 | E57: =$E$55+$E$56 -> 81.268249 | F57: =SUM(C57:E57) -> 427.90162 | P57: Calculated value | Q57: Variable + fixed manufacturing cost
A58: Gross profit | B58: $m | C58: =$C$42-$C$57 -> 246.68839 | D58: =$D$42-$D$57 -> 245.21024 | E58: =$E$42-$E$57 -> 80.199751 | F58: =SUM(C58:E58) -> 572.09838 | P58: Calculated value | Q58: Revenue - cost of revenue
A59: Gross margin | B59: % | C59: =IFERROR($C$58/$C$42,0) -> 0.58838157 | D59: =IFERROR($D$58/$D$42,0) -> 0.58485602 | E59: =IFERROR($E$58/$E$42,0) -> 0.4966913 | F59: =IFERROR(F58/F42,0) -> 0.57209838 | P59: Calculated value | Q59: Calibration: compare with Texas Instruments FY2025 reported gross margin in section B
A60: Cost per good unit | B60: $/unit | C60: =$C$57/$C$52 -> 0.24697106 | D60: =$D$57/$D$52 -> 0.39438678 | E60: =$E$57/$E$52 -> 1.7112496 | P60: Calculated value | Q60: Cost of revenue / good units (= units sold in base year). Values the opening inventory.
A62: Live FY2026 product drivers (calculated from the active scenario)
A63: FY2026 customer demand | B63: m units | C63: =$C$52*(1+$F$10+$C$48) -> 817.5687 | D63: =$D$52*(1+$F$10+$D$48) -> 516.35918 | E63: =$E$52*(1+$F$10+$E$48) -> 51.764741 | P63: Calculated value | Q63: Base-year units sold x (1 + demand growth + product differential)
A64: FY2026 average selling price | B64: $/unit | C64: =$C$43*(1+$F$11) -> 0.594 | D64: =$D$43*(1+$F$11) -> 0.9405 | E64: =$E$43*(1+$F$11) -> 3.366 | P64: Calculated value | Q64: Base ASP x (1 + ASP change)
A65: FY2026 final-test yield | B65: % | C65: =MIN(1,MAX(0,$C$44+$F$12)) -> 0.95 | D65: =MIN(1,MAX(0,$D$44+$F$12)) -> 0.93 | E65: =MIN(1,MAX(0,$E$44+$F$12)) -> 0.88 | P65: Calculated value | Q65: Base yield + yield change, bounded 0-100%
A66: FY2026 capacity utilization | B66: % | C66: =$F$13 -> 0.78 | D66: =$F$13 -> 0.78 | E66: =$F$13 -> 0.78 | P66: Calculated value | Q66: Same scenario utilization for every product line
A67: FY2026 variable cost per unit produced | B67: $/unit | C67: =$C$45*(1+$F$14) -> 0.1442 | D67: =$D$45*(1+$F$14) -> 0.2163 | E67: =$E$45*(1+$F$14) -> 0.9785 | P67: Calculated value | Q67: Base variable cost x (1 + material inflation)
A68: Opening finished-goods inventory (01-Jan-2026) | B68: m units | C68: =$C$49*$C$52/12 -> 58.231389 | D68: =$D$49*$D$52/12 -> 36.777719 | E68: =$E$49*$E$52/12 -> 3.957549 | P68: Calculated value | Q68: Months of inventory x base-year monthly units sold
A69: Opening finished-goods inventory value | B69: $m | C69: =$C$68*$C$60 -> 14.381468 | D69: =$D$68*$D$60 -> 14.504646 | E69: =$E$68*$E$60 -> 6.772354 | F69: =SUM(C69:E69) -> 35.658468 | P69: Calculated value | Q69: Opening units x base-year cost per good unit
A71: E. Monthly demand seasonality (simulated; must sum to 12.00)
A72: Month | C72: =DATE(YEAR($F$35),MONTH($F$35)+0,1) -> 46023 | D72: =DATE(YEAR($F$35),MONTH($F$35)+1,1) -> 46054 | E72: =DATE(YEAR($F$35),MONTH($F$35)+2,1) -> 46082 | F72: =DATE(YEAR($F$35),MONTH($F$35)+3,1) -> 46113 | G72: =DATE(YEAR($F$35),MONTH($F$35)+4,1) -> 46143 | H72: =DATE(YEAR($F$35),MONTH($F$35)+5,1) -> 46174 | I72: =DATE(YEAR($F$35),MONTH($F$35)+6,1) -> 46204 | J72: =DATE(YEAR($F$35),MONTH($F$35)+7,1) -> 46235 | K72: =DATE(YEAR($F$35),MONTH($F$35)+8,1) -> 46266 | L72: =DATE(YEAR($F$35),MONTH($F$35)+9,1) -> 46296 | M72: =DATE(YEAR($F$35),MONTH($F$35)+10,1) -> 46327 | N72: =DATE(YEAR($F$35),MONTH($F$35)+11,1) -> 46357 | O72: Sum
A73: Seasonality factor (1.00 = average month) | C73: 0.94 | D73: 0.96 | E73: 1.02 | F73: 0.99 | G73: 1 | H73: 1.03 | I73: 1.02 | J73: 1.03 | K73: 1.05 | L73: 1.02 | M73: 0.98 | N73: 0.96 | O73: =SUM(C73:N73) -> 12 | P73: Simulated operational data | Q73: Softer January-February, quarter-end pulls, Q3 seasonal peak, December dip
A75: F. Live scenario result - FY2026 (from Ops_Model)
A76: Division revenue | F76: =Ops_Model!$O$98 -> 1145.5117 | P76: Calculated value
A77: Growth vs FY2025 base-year revenue | F77: =Ops_Model!$O$98/$F$32-1 -> 0.14551173 | P77: Calculated value
A78: Gross profit | F78: =Ops_Model!$O$105 -> 669.16402 | P78: Calculated value
A79: Gross margin | F79: =Ops_Model!$O$106 -> 0.58416165 | P79: Calculated value
A80: Revenue at risk from unmet demand | F80: =Ops_Model!$O$108 -> 0 | P80: Calculated value
A82: G. P&L and cash-flow inputs (not scenario-driven)
A83: Days sales outstanding (DSO) | B83: days | F83: 40 | P83: User-provided assumption | Q83: TI DSO about 40 days in FY2025 (reference below). AR = monthly revenue x 12 x DSO / 365
A84: Days payable outstanding on variable manufacturing cost | B84: days | F84: 36 | P84: User-provided assumption | Q84: Applied to purchases (variable manufacturing cost). AP = monthly variable cost x 12 x DPO / 365
A85: Depreciation share of fixed manufacturing cost | B85: % | F85: 0.35 | P85: Simulated operational data | Q85: Non-cash part of factory fixed cost. 30% x $229m = ~$69m/yr (~7% of revenue). Reference below
A86: Useful life of new FY2026 capex | B86: months | F86: 60 | P86: User-provided assumption | Q86: Straight-line; depreciation starts the month after spend. FY2026 capex depreciation sits in cost of revenue
A87: Reference: Texas Instruments DSO FY2025 | F87: =Hist_Analysis!$G$42 -> 40.521151 | P87: Calculated value | Q87: Reported public data (Hist tabs)
A88: Reference: Texas Instruments D&A % of sales FY2025 | F88: =Hist_Data!$G$30/Hist_Data!$G$7 -> 0.10847189 | P88: Calculated value | Q88: Reported public data (Hist tabs)
A89: Opening balances at 31-Dec-2025 (calculated from base year)
A90: Opening accounts receivable | B90: $m | F90: =$F$32*$F$83/365 -> 109.58904 | P90: Calculated value | Q90: Base-year revenue x DSO / 365
A91: Opening finished-goods inventory | B91: $m | F91: =$F$69 -> 35.658468 | P91: Calculated value | Q91: Section D opening inventory value
A92: Opening accounts payable | B92: $m | F92: =$F$55*$F$84/365 -> 25.042351 | P92: Calculated value | Q92: Base-year variable cost x DPO / 365
A93: Opening operating working capital | B93: $m | F93: =F90+F91-F92 -> 120.20516 | P93: Calculated value | Q93: AR + inventory - AP
A95: H. Live scenario result - FY2026 P&L and cash flow
A96: Operating profit | F96: =PnL!$O$17 -> 434.94479 | P96: Calculated value
A97: Operating margin | F97: =PnL!$O$18 -> 0.37969475 | P97: Calculated value
A98: Net income | F98: =PnL!$O$21 -> 378.40196 | P98: Calculated value
A99: Free cash flow | F99: =FCF!$O$25 -> 379.28492 | P99: Calculated value
A100: FCF margin | F100: =FCF!$O$26 -> 0.33110523 | P100: Calculated value

Sheet Hist_Data
A1: Historical Data - Texas Instruments (reported)
A2: USD millions unless noted. Fiscal years end December 31. Blue = hardcoded reported value from SEC filing.
A3: Simulated data created for portfolio demonstration. It does not represent nonpublic Texas Instruments information. (This tab contains reported public data and calculated values only.)
A5: Line item | B5: Units | C5: FY2021 | D5: FY2022 | E5: FY2023 | F5: FY2024 | G5: FY2025 | H5: Classification | I5: Source (filing, statement page) | J5: Notes | K5: line_id
A6: Income statement
A7: Revenue | B7: $m | C7: 18344 | D7: 20028 | E7: 17519 | F7: 15641 | G7: 17682 | H7: Reported public data | I7: S-002 10-K FY2023 R3.htm; S-001 10-K FY2025 R3.htm | K7: net_sales
A8: Cost of revenue (COR) | B8: $m | C8: 5968 | D8: 6257 | E8: 6500 | F8: 6547 | G8: 7599 | H8: Reported public data | I8: S-002 10-K FY2023 R3.htm; S-001 10-K FY2025 R3.htm | K8: cost_of_sales
A9: Gross profit | B9: $m | C9: 12376 | D9: 13771 | E9: 11019 | F9: 9094 | G9: 10083 | H9: Reported public data | I9: S-002 10-K FY2023 R3.htm; S-001 10-K FY2025 R3.htm | K9: gross_profit
A10: Research and development (R&D) | B10: $m | C10: 1554 | D10: 1670 | E10: 1863 | F10: 1959 | G10: 2083 | H10: Reported public data | I10: S-002 10-K FY2023 R3.htm; S-001 10-K FY2025 R3.htm | K10: rd
A11: Selling, general and administrative (SG&A) | B11: $m | C11: 1666 | D11: 1704 | E11: 1825 | F11: 1794 | G11: 1860 | H11: Reported public data | I11: S-002 10-K FY2023 R3.htm; S-001 10-K FY2025 R3.htm | K11: sga
A12: Restructuring charges/other | B12: $m | C12: 54 | D12: 257 | E12: 0 | F12: -124 | G12: 117 | H12: Reported public data | I12: S-002 10-K FY2023 R3.htm; S-001 10-K FY2025 R3.htm | K12: other_opex:restructuring
A13: Acquisition charges | B13: $m | C13: 142 | D13: 0 | H13: Reported public data | I13: S-002 10-K FY2023 R3.htm | J13: Printed in the FY2023 10-K for FY2021-FY2022 only; blank = not presented, treated as 0. | K13: other_opex:acquisition
A14: Operating profit | B14: $m | C14: 8960 | D14: 10140 | E14: 7331 | F14: 5465 | G14: 6023 | H14: Reported public data | I14: S-002 10-K FY2023 R3.htm; S-001 10-K FY2025 R3.htm | K14: operating_income
A15: Other income (expense), net (OI&E) | B15: $m | C15: 143 | D15: 106 | E15: 440 | F15: 496 | G15: 230 | H15: Reported public data | I15: S-002 10-K FY2023 R3.htm; S-001 10-K FY2025 R3.htm | K15: nonop:other_income
A16: Interest and debt expense | B16: $m | C16: -184 | D16: -214 | E16: -353 | F16: -508 | G16: -543 | H16: Reported public data | I16: S-002 10-K FY2023 R3.htm; S-001 10-K FY2025 R3.htm | J16: Printed as a positive expense; stored negative (effect on pre-tax income). | K16: nonop:interest
A17: Income before income taxes | B17: $m | C17: 8919 | D17: 10032 | E17: 7418 | F17: 5453 | G17: 5710 | H17: Reported public data | I17: S-002 10-K FY2023 R3.htm; S-001 10-K FY2025 R3.htm | K17: pretax_income
A18: Provision for income taxes | B18: $m | C18: 1150 | D18: 1283 | E18: 908 | F18: 654 | G18: 709 | H18: Reported public data | I18: S-002 10-K FY2023 R3.htm; S-001 10-K FY2025 R3.htm | K18: income_tax
A19: Net income | B19: $m | C19: 7769 | D19: 8749 | E19: 6510 | F19: 4799 | G19: 5001 | H19: Reported public data | I19: S-002 10-K FY2023 R3.htm; S-001 10-K FY2025 R3.htm | K19: net_income
A20: Net sales by reported segment / product line
A21: Analog | B21: $m | C21: 14050 | D21: 15359 | E21: 13040 | F21: 12161 | G21: 14006 | H21: Reported public data | I21: S-002 10-K FY2023 R34.htm; S-001 10-K FY2025 R37.htm | J21: Reported segment. Split 50/50 into power management and signal chain in this model (user-provided assumption). | K21: segment:analog
A22: Embedded Processing | B22: $m | C22: 3049 | D22: 3261 | E22: 3368 | F22: 2533 | G22: 2697 | H22: Reported public data | I22: S-002 10-K FY2023 R34.htm; S-001 10-K FY2025 R37.htm | K22: segment:embedded_processing
A23: Other | B23: $m | C23: 1245 | D23: 1408 | E23: 1111 | F23: 947 | G23: 979 | H23: Reported public data | I23: S-002 10-K FY2023 R34.htm; S-001 10-K FY2025 R37.htm | J23: TI's reported Other segment. Not modeled in the division (mix renormalized over the three products). | K23: segment:other
A24: Other segment disclosures
A25: Analog - gross profit | B25: $m | E25: 8425 | F25: 7292 | G25: 8242 | H25: Reported public data | I25: S-001 10-K FY2025 R37.htm | K25: segment_info:analog_gross_profit
A26: Embedded Processing - gross profit | B26: $m | E26: 1875 | F26: 1218 | G26: 1226 | H26: Reported public data | I26: S-001 10-K FY2025 R37.htm | K26: segment_info:embedded_gross_profit
A27: Other - gross profit | B27: $m | E27: 719 | F27: 584 | G27: 615 | H27: Reported public data | I27: S-001 10-K FY2025 R37.htm | K27: segment_info:other_gross_profit
A28: Cash flow statement (selected lines)
A29: Net income | B29: $m | C29: 7769 | D29: 8749 | E29: 6510 | F29: 4799 | G29: 5001 | H29: Reported public data | I29: S-002 10-K FY2023 R8.htm; S-001 10-K FY2025 R7.htm | K29: cf:net_income
A30: Depreciation | B30: $m | C30: 755 | D30: 925 | E30: 1175 | F30: 1508 | G30: 1918 | H30: Reported public data | I30: S-002 10-K FY2023 R8.htm; S-001 10-K FY2025 R7.htm | J30: Depreciation only; TI prints amortization of capitalized software separately. | K30: cf:da
A31: Stock compensation | B31: $m | C31: 230 | D31: 289 | E31: 362 | F31: 387 | G31: 419 | H31: Reported public data | I31: S-002 10-K FY2023 R8.htm; S-001 10-K FY2025 R7.htm | K31: cf:sbc
A32: Accounts receivable | B32: $m | C32: -287 | D32: -194 | E32: 108 | F32: 68 | G32: -244 | H32: Reported public data | I32: S-002 10-K FY2023 R8.htm; S-001 10-K FY2025 R7.htm | K32: wc:receivables
A33: Inventories | B33: $m | C33: 45 | D33: -847 | E33: -1242 | F33: -528 | G33: -277 | H33: Reported public data | I33: S-002 10-K FY2023 R8.htm; S-001 10-K FY2025 R7.htm | K33: wc:inventories
A34: Prepaid expenses and other current assets | B34: $m | C34: 57 | D34: 6 | E34: 46 | F34: 7 | G34: 10 | H34: Reported public data | I34: S-002 10-K FY2023 R8.htm; S-001 10-K FY2025 R7.htm | K34: wc:prepaid
A35: Accounts payable and accrued expenses | B35: $m | C35: 33 | D35: 106 | E35: -33 | F35: 125 | G35: 77 | H35: Reported public data | I35: S-002 10-K FY2023 R8.htm; S-001 10-K FY2025 R7.htm | K35: wc:payables_accrued
A36: Accrued compensation | B36: $m | C36: 7 | D36: 22 | E36: 29 | F36: -12 | G36: -28 | H36: Reported public data | I36: S-002 10-K FY2023 R8.htm; S-001 10-K FY2025 R7.htm | K36: wc:accrued_compensation
A37: Income taxes payable | B37: $m | C37: -20 | D37: 94 | E37: -7 | F37: 597 | G37: 191 | H37: Reported public data | I37: S-002 10-K FY2023 R8.htm; S-001 10-K FY2025 R7.htm | K37: wc:income_tax
A38: Cash flows from operating activities | B38: $m | C38: 8756 | D38: 8720 | E38: 6420 | F38: 6318 | G38: 7153 | H38: Reported public data | I38: S-002 10-K FY2023 R8.htm; S-001 10-K FY2025 R7.htm | K38: cf:cfo
A39: Capital expenditures | B39: $m | C39: -2462 | D39: -2797 | E39: -5071 | F39: -4820 | G39: -4550 | H39: Reported public data | I39: S-002 10-K FY2023 R8.htm; S-001 10-K FY2025 R7.htm | J39: Printed as a cash outflow (negative). Analysis converts to positive spend. | K39: cf:capex
A40: Cash flows from investing activities | B40: $m | C40: -4095 | D40: -3583 | E40: -4362 | F40: -3202 | G40: -1439 | H40: Reported public data | I40: S-002 10-K FY2023 R8.htm; S-001 10-K FY2025 R7.htm | K40: cf:cfi
A41: Cash flows from financing activities | B41: $m | C41: -3137 | D41: -6718 | E41: -2144 | F41: -2880 | G41: -5689 | H41: Reported public data | I41: S-002 10-K FY2023 R8.htm; S-001 10-K FY2025 R7.htm | K41: cf:cff
A42: Dividends paid | B42: $m | C42: -3886 | D42: -4297 | E42: -4557 | F42: -4795 | G42: -4999 | H42: Reported public data | I42: S-002 10-K FY2023 R8.htm; S-001 10-K FY2025 R7.htm | K42: cf:dividends
A43: Cash and cash equivalents at end of period | B43: $m | C43: 4631 | D43: 3050 | E43: 2964 | F43: 3200 | G43: 3225 | H43: Reported public data | I43: S-002 10-K FY2023 R8.htm; S-001 10-K FY2025 R7.htm | K43: cf:cash_end
A44: Balance sheet (period-end, selected lines)
A45: Cash and cash equivalents | B45: $m | C45: 4631 | D45: 3050 | E45: 2964 | F45: 3200 | G45: 3225 | H45: Reported public data | I45: S-003 10-K FY2022 R6.htm; S-002 10-K FY2023 R6.htm; S-001 10-K FY2025 R5.htm | K45: bs:cash
A46: Short-term investments | B46: $m | C46: 5108 | D46: 6017 | E46: 5611 | F46: 4380 | G46: 1656 | H46: Reported public data | I46: S-003 10-K FY2022 R6.htm; S-002 10-K FY2023 R6.htm; S-001 10-K FY2025 R5.htm | K46: bs:st_investments
A47: Accounts receivable, net | B47: $m | C47: 1701 | D47: 1895 | E47: 1787 | F47: 1719 | G47: 1963 | H47: Reported public data | I47: S-003 10-K FY2022 R6.htm; S-002 10-K FY2023 R6.htm; S-001 10-K FY2025 R5.htm | K47: bs:receivables
A48: Inventories | B48: $m | C48: 1910 | D48: 2757 | E48: 3999 | F48: 4527 | G48: 4804 | H48: Reported public data | I48: S-003 10-K FY2022 R6.htm; S-002 10-K FY2023 R6.htm; S-001 10-K FY2025 R5.htm | K48: bs:inventories
A49: Prepaid expenses and other current assets | B49: $m | C49: 335 | D49: 302 | E49: 761 | F49: 1200 | G49: 2102 | H49: Reported public data | I49: S-003 10-K FY2022 R6.htm; S-002 10-K FY2023 R6.htm; S-001 10-K FY2025 R5.htm | K49: bs:other_current_assets
A50: Total current assets | B50: $m | C50: 13685 | D50: 14021 | E50: 15122 | F50: 15026 | G50: 13750 | H50: Reported public data | I50: S-003 10-K FY2022 R6.htm; S-002 10-K FY2023 R6.htm; S-001 10-K FY2025 R5.htm | K50: bs:total_current_assets
A51: Property, plant and equipment (net) | B51: $m | C51: 5141 | D51: 6876 | E51: 9999 | F51: 11347 | G51: 12320 | H51: Reported public data | I51: S-003 10-K FY2022 R6.htm; S-002 10-K FY2023 R6.htm; S-001 10-K FY2025 R5.htm | K51: bs:ppe
A52: Total assets | B52: $m | C52: 24676 | D52: 27207 | E52: 32348 | F52: 35509 | G52: 34585 | H52: Reported public data | I52: S-003 10-K FY2022 R6.htm; S-002 10-K FY2023 R6.htm; S-001 10-K FY2025 R5.htm | K52: bs:total_assets
A53: Current portion of long-term debt | B53: $m | C53: 500 | D53: 500 | E53: 599 | F53: 750 | G53: 500 | H53: Reported public data | I53: S-003 10-K FY2022 R6.htm; S-002 10-K FY2023 R6.htm; S-001 10-K FY2025 R5.htm | K53: bs:current_debt
A54: Accounts payable | B54: $m | C54: 571 | D54: 851 | E54: 802 | F54: 820 | G54: 756 | H54: Reported public data | I54: S-003 10-K FY2022 R6.htm; S-002 10-K FY2023 R6.htm; S-001 10-K FY2025 R5.htm | K54: bs:payables
A55: Accrued compensation | B55: $m | C55: 775 | D55: 799 | E55: 836 | F55: 839 | G55: 829 | H55: Reported public data | I55: S-003 10-K FY2022 R6.htm; S-002 10-K FY2023 R6.htm; S-001 10-K FY2025 R5.htm | K55: bs:cl_other:accrued_compensation
A56: Income taxes payable | B56: $m | C56: 121 | D56: 189 | E56: 172 | F56: 159 | G56: 67 | H56: Reported public data | I56: S-003 10-K FY2022 R6.htm; S-002 10-K FY2023 R6.htm; S-001 10-K FY2025 R5.htm | K56: bs:cl_other:income_taxes_payable
... A60: Total stockholders' equity | B60: $m | C60: 13333 | D60: 14577 | E60: 16897 | F60: 16903 | G60: 16273 | H60: Reported public data | I60: S-003 10-K FY2022 R6.htm; S-002 10-K FY2023 R6.htm; S-001 10-K FY2025 R5.htm | K60: bs:equity
A61: Inventory detail
A62: Raw materials | B62: $m | C62: 245 | D62: 353 | E62: 420 | F62: 395 | G62: 465 | H62: Reported public data | I62: S-003 10-K FY2022 R6.htm; S-002 10-K FY2023 R6.htm; S-001 10-K FY2025 R5.htm | K62: inv:raw_materials
A63: Work in process | B63: $m | C63: 1067 | D63: 1546 | E63: 2109 | F63: 2214 | G63: 2372 | H63: Reported public data | I63: S-003 10-K FY2022 R6.htm; S-002 10-K FY2023 R6.htm; S-001 10-K FY2025 R5.htm | K63: inv:work_in_process
A64: Finished goods | B64: $m | C64: 598 | D64: 858 | E64: 1470 | F64: 1918 | G64: 1967 | H64: Reported public data | I64: S-003 10-K FY2022 R6.htm; S-002 10-K FY2023 R6.htm; S-001 10-K FY2025 R5.htm | K64: inv:finished_goods
A66: Quarterly context - second fiscal quarter (April-June)
A67: Line item | B67: Units | C67: Q2 FY2025 | D67: Q2 FY2026 | H67: Classification | I67: Source | J67: Notes | K67: line_id
A68: Revenue | B68: $m | C68: 4448 | D68: 5463 | H68: Reported public data | I68: S-005 10-Q Q2 FY2026 R2.htm | J68: Q2 FY2025 = prior-year comparative column | K68: net_sales
A69: Analog | B69: $m | C69: 3452 | D69: 4365 | H69: Reported public data | I69: S-005 10-Q Q2 FY2026 R27.htm | K69: segment:analog
A70: Embedded Processing | B70: $m | C70: 679 | D70: 788 | H70: Reported public data | I70: S-005 10-Q Q2 FY2026 R27.htm | K70: segment:embedded_processing
A71: Other | B71: $m | C71: 317 | D71: 310 | H71: Reported public data | I71: S-005 10-Q Q2 FY2026 R27.htm | K71: segment:other

Sheet Hist_Analysis
A1: Historical Financial Analysis - Texas Instruments
A2: All figures are formulas on Hist_Data. Green = direct link to Hist_Data; black = calculation.
A3: Simulated data created for portfolio demonstration. It does not represent nonpublic Texas Instruments information. (This tab contains reported public data and calculated values only.)
A5: Metric | B5: Units | C5: FY2021 | D5: FY2022 | E5: FY2023 | F5: FY2024 | G5: FY2025 | H5: Classification | I5: Formula / definition
A6: Growth and profitability
A7: Net sales | B7: $m | C7: =Hist_Data!$C$7 -> 18344 | D7: =Hist_Data!$D$7 -> 20028 | E7: =Hist_Data!$E$7 -> 17519 | F7: =Hist_Data!$F$7 -> 15641 | G7: =Hist_Data!$G$7 -> 17682 | H7: Calculated value | I7: Link: Hist_Data net sales
A8: Net sales growth | B8: % | C8: n/a | D8: =IFERROR(Hist_Data!$D$7/Hist_Data!$C$7-1,"") -> 0.091801134 | E8: =IFERROR(Hist_Data!$E$7/Hist_Data!$D$7-1,"") -> -0.12527462 | F8: =IFERROR(Hist_Data!$F$7/Hist_Data!$E$7-1,"") -> -0.1071979 | G8: =IFERROR(Hist_Data!$G$7/Hist_Data!$F$7-1,"") -> 0.13049038 | H8: Calculated value | I8: Net sales / prior-year net sales - 1
A9: Gross margin | B9: % | C9: =IFERROR(Hist_Data!$C$9/Hist_Data!$C$7,"") -> 0.67466201 | D9: =IFERROR(Hist_Data!$D$9/Hist_Data!$D$7,"") -> 0.68758738 | E9: =IFERROR(Hist_Data!$E$9/Hist_Data!$E$7,"") -> 0.62897426 | F9: =IFERROR(Hist_Data!$F$9/Hist_Data!$F$7,"") -> 0.58142063 | G9: =IFERROR(Hist_Data!$G$9/Hist_Data!$G$7,"") -> 0.57024092 | H9: Calculated value | I9: Gross profit / net sales
A10: R&D % of sales | B10: % | C10: =IFERROR(Hist_Data!$C$10/Hist_Data!$C$7,"") -> 0.084714348 | D10: =IFERROR(Hist_Data!$D$10/Hist_Data!$D$7,"") -> 0.083383263 | E10: =IFERROR(Hist_Data!$E$10/Hist_Data!$E$7,"") -> 0.10634169 | F10: =IFERROR(Hist_Data!$F$10/Hist_Data!$F$7,"") -> 0.12524775 | G10: =IFERROR(Hist_Data!$G$10/Hist_Data!$G$7,"") -> 0.11780342 | H10: Calculated value | I10: Research and development / net sales
A11: SG&A % of sales | B11: % | C11: =IFERROR(Hist_Data!$C$11/Hist_Data!$C$7,"") -> 0.090819887 | D11: =IFERROR(Hist_Data!$D$11/Hist_Data!$D$7,"") -> 0.085080887 | E11: =IFERROR(Hist_Data!$E$11/Hist_Data!$E$7,"") -> 0.10417261 | F11: =IFERROR(Hist_Data!$F$11/Hist_Data!$F$7,"") -> 0.11469855 | G11: =IFERROR(Hist_Data!$G$11/Hist_Data!$G$7,"") -> 0.10519172 | H11: Calculated value | I11: SG&A / net sales
A12: Operating margin (GAAP) | B12: % | C12: =IFERROR(Hist_Data!$C$14/Hist_Data!$C$7,"") -> 0.48844309 | D12: =IFERROR(Hist_Data!$D$14/Hist_Data!$D$7,"") -> 0.50629119 | E12: =IFERROR(Hist_Data!$E$14/Hist_Data!$E$7,"") -> 0.41845996 | F12: =IFERROR(Hist_Data!$F$14/Hist_Data!$F$7,"") -> 0.34940221 | G12: =IFERROR(Hist_Data!$G$14/Hist_Data!$G$7,"") -> 0.34062889 | H12: Calculated value | I12: Operating income / net sales
A13: Other operating items (sum of reported components) | B13: $m | C13: =(N(Hist_Data!$C$12)+N(Hist_Data!$C$13)) -> 196 | D13: =(N(Hist_Data!$D$12)+N(Hist_Data!$D$13)) -> 257 | E13: =(N(Hist_Data!$E$12)+N(Hist_Data!$E$13)) -> 0 | F13: =(N(Hist_Data!$F$12)+N(Hist_Data!$F$13)) -> -124 | G13: =(N(Hist_Data!$G$12)+N(Hist_Data!$G$13)) -> 117 | H13: Calculated value | I13: Sum of: restructuring charges/other, acquisition charges
A14: Operating income before other operating items | B14: $m | C14: =Hist_Data!$C$14+$C$13 -> 9156 | D14: =Hist_Data!$D$14+$D$13 -> 10397 | E14: =Hist_Data!$E$14+$E$13 -> 7331 | F14: =Hist_Data!$F$14+$F$13 -> 5341 | G14: =Hist_Data!$G$14+$G$13 -> 6140 | H14: Calculated value | I14: Operating income + other operating items (restructuring charges/other, acquisition charges). Analyst calculation - NOT Texas Instruments's reported non-GAAP measure.
A15: Margin before other operating items | B15: % | C15: =IFERROR($C$14/Hist_Data!$C$7,"") -> 0.49912778 | D15: =IFERROR($D$14/Hist_Data!$D$7,"") -> 0.51912323 | E15: =IFERROR($E$14/Hist_Data!$E$7,"") -> 0.41845996 | F15: =IFERROR($F$14/Hist_Data!$F$7,"") -> 0.34147433 | G15: =IFERROR($G$14/Hist_Data!$G$7,"") -> 0.34724579 | H15: Calculated value | I15: Row above / net sales. Closest proxy for a product division's operating margin.
A16: Net margin | B16: % | C16: =IFERROR(Hist_Data!$C$19/Hist_Data!$C$7,"") -> 0.42351723 | D16: =IFERROR(Hist_Data!$D$19/Hist_Data!$D$7,"") -> 0.43683843 | E16: =IFERROR(Hist_Data!$E$19/Hist_Data!$E$7,"") -> 0.37159655 | F16: =IFERROR(Hist_Data!$F$19/Hist_Data!$F$7,"") -> 0.30682181 | G16: =IFERROR(Hist_Data!$G$19/Hist_Data!$G$7,"") -> 0.28283 | H16: Calculated value | I16: Net income / net sales
A17: Effective tax rate | B17: % | C17: =IF(ABS(Hist_Data!$C$17)<0.02*Hist_Data!$C$7,"n.m.",IFERROR(Hist_Data!$C$18/Hist_Data!$C$17,"")) -> 0.12893822 | D17: =IF(ABS(Hist_Data!$D$17)<0.02*Hist_Data!$D$7,"n.m.",IFERROR(Hist_Data!$D$18/Hist_Data!$D$17,"")) -> 0.12789075 | E17: =IF(ABS(Hist_Data!$E$17)<0.02*Hist_Data!$E$7,"n.m.",IFERROR(Hist_Data!$E$18/Hist_Data!$E$17,"")) -> 0.12240496 | F17: =IF(ABS(Hist_Data!$F$17)<0.02*Hist_Data!$F$7,"n.m.",IFERROR(Hist_Data!$F$18/Hist_Data!$F$17,"")) -> 0.11993398 | G17: =IF(ABS(Hist_Data!$G$17)<0.02*Hist_Data!$G$7,"n.m.",IFERROR(Hist_Data!$G$18/Hist_Data!$G$17,"")) -> 0.12416813 | H17: Calculated value | I17: Income tax / income before taxes. Shows n.m. (not meaningful) when pre-tax income is under 2% of sales.
A18: Incremental gross margin (change in GP / change in sales) | B18: % | C18: n/a | D18: =IFERROR((Hist_Data!$D$9-Hist_Data!$C$9)/(Hist_Data!$D$7-Hist_Data!$C$7),"") -> 0.8283848 | E18: =IFERROR((Hist_Data!$E$9-Hist_Data!$D$9)/(Hist_Data!$E$7-Hist_Data!$D$7),"") -> 1.0968513 | F18: =IFERROR((Hist_Data!$F$9-Hist_Data!$E$9)/(Hist_Data!$F$7-Hist_Data!$E$7),"") -> 1.0250266 | G18: =IFERROR((Hist_Data!$G$9-Hist_Data!$F$9)/(Hist_Data!$G$7-Hist_Data!$F$7),"") -> 0.48456639 | H18: Calculated value | I18: Shows operating leverage: how much gross profit moved per $1 of sales change (fixed-cost absorption)
A19: Reported segment / product-line mix and growth
A20: Analog - share of net sales | B20: % | C20: =IFERROR(Hist_Data!$C$21/Hist_Data!$C$7,"") -> 0.76591801 | D20: =IFERROR(Hist_Data!$D$21/Hist_Data!$D$7,"") -> 0.76687637 | E20: =IFERROR(Hist_Data!$E$21/Hist_Data!$E$7,"") -> 0.74433472 | F20: =IFERROR(Hist_Data!$F$21/Hist_Data!$F$7,"") -> 0.77750783 | G20: =IFERROR(Hist_Data!$G$21/Hist_Data!$G$7,"") -> 0.79210497 | H20: Calculated value | I20: Analog sales / net sales
A21: Embedded Processing - share of net sales | B21: % | C21: =IFERROR(Hist_Data!$C$22/Hist_Data!$C$7,"") -> 0.16621239 | D21: =IFERROR(Hist_Data!$D$22/Hist_Data!$D$7,"") -> 0.16282205 | E21: =IFERROR(Hist_Data!$E$22/Hist_Data!$E$7,"") -> 0.19224842 | F21: =IFERROR(Hist_Data!$F$22/Hist_Data!$F$7,"") -> 0.16194617 | G21: =IFERROR(Hist_Data!$G$22/Hist_Data!$G$7,"") -> 0.15252799 | H21: Calculated value | I21: Embedded Processing sales / net sales
A22: Other - share of net sales | B22: % | C22: =IFERROR(Hist_Data!$C$23/Hist_Data!$C$7,"") -> 0.067869603 | D22: =IFERROR(Hist_Data!$D$23/Hist_Data!$D$7,"") -> 0.070301578 | E22: =IFERROR(Hist_Data!$E$23/Hist_Data!$E$7,"") -> 0.063416862 | F22: =IFERROR(Hist_Data!$F$23/Hist_Data!$F$7,"") -> 0.060546001 | G22: =IFERROR(Hist_Data!$G$23/Hist_Data!$G$7,"") -> 0.05536704 | H22: Calculated value | I22: Other sales / net sales
A23: Mix total (must equal 100%) | B23: % | C23: =$C$20+$C$21+$C$22 -> 1 | D23: =$D$20+$D$21+$D$22 -> 1 | E23: =$E$20+$E$21+$E$22 -> 1 | F23: =$F$20+$F$21+$F$22 -> 1 | G23: =$G$20+$G$21+$G$22 -> 1 | H23: Calculated value | I23: Sum of the segment shares
A24: Analog - growth | B24: % | C24: n/a | D24: =IFERROR(Hist_Data!$D$21/Hist_Data!$C$21-1,"") -> 0.09316726 | E24: =IFERROR(Hist_Data!$E$21/Hist_Data!$D$21-1,"") -> -0.15098639 | F24: =IFERROR(Hist_Data!$F$21/Hist_Data!$E$21-1,"") -> -0.067407975 | G24: =IFERROR(Hist_Data!$G$21/Hist_Data!$F$21-1,"") -> 0.1517145 | H24: Calculated value | I24: Analog sales / prior year - 1
A25: Embedded Processing - growth | B25: % | C25: n/a | D25: =IFERROR(Hist_Data!$D$22/Hist_Data!$C$22-1,"") -> 0.069530994 | E25: =IFERROR(Hist_Data!$E$22/Hist_Data!$D$22-1,"") -> 0.032812021 | F25: =IFERROR(Hist_Data!$F$22/Hist_Data!$E$22-1,"") -> -0.24792162 | G25: =IFERROR(Hist_Data!$G$22/Hist_Data!$F$22-1,"") -> 0.064745361 | H25: Calculated value | I25: Embedded Processing sales / prior year - 1
A26: Other - growth | B26: % | C26: n/a | D26: =IFERROR(Hist_Data!$D$23/Hist_Data!$C$23-1,"") -> 0.13092369 | E26: =IFERROR(Hist_Data!$E$23/Hist_Data!$D$23-1,"") -> -0.2109375 | F26: =IFERROR(Hist_Data!$F$23/Hist_Data!$E$23-1,"") -> -0.14761476 | G26: =IFERROR(Hist_Data!$G$23/Hist_Data!$F$23-1,"") -> 0.033790919 | H26: Calculated value | I26: Other sales / prior year - 1
A27: Cash flow and free cash flow (project definition)
A28: Net income | B28: $m | C28: =Hist_Data!$C$19 -> 7769 | D28: =Hist_Data!$D$19 -> 8749 | E28: =Hist_Data!$E$19 -> 6510 | F28: =Hist_Data!$F$19 -> 4799 | G28: =Hist_Data!$G$19 -> 5001 | H28: Calculated value | I28: Link: Hist_Data net income
A29: Depreciation and amortization | B29: $m | C29: =Hist_Data!$C$30 -> 755 | D29: =Hist_Data!$D$30 -> 925 | E29: =Hist_Data!$E$30 -> 1175 | F29: =Hist_Data!$F$30 -> 1508 | G29: =Hist_Data!$G$30 -> 1918 | H29: Calculated value | I29: Link: Hist_Data D&A (cash flow statement)
A30: Capital expenditures (positive = spend) | B30: $m | C30: =-Hist_Data!$C$39 -> 2462 | D30: =-Hist_Data!$D$39 -> 2797 | E30: =-Hist_Data!$E$39 -> 5071 | F30: =-Hist_Data!$F$39 -> 4820 | G30: =-Hist_Data!$G$39 -> 4550 | H30: Calculated value | I30: Negative of capex as printed. Cash-flow statement prints capex negative.
A31: Increase in working capital | B31: $m | C31: =-(N(Hist_Data!$C$32)+N(Hist_Data!$C$33)+N(Hist_Data!$C$34)+N(Hist_Data!$C$35)+N(Hist_Data!$C$36)+N(Hist_Data!$C$37)) -> 165 | D31: =-(N(Hist_Data!$D$32)+N(Hist_Data!$D$33)+N(Hist_Data!$D$34)+N(Hist_Data!$D$35)+N(Hist_Data!$D$36)+N(Hist_Data!$D$37)) -> 813 | E31: =-(N(Hist_Data!$E$32)+N(Hist_Data!$E$33)+N(Hist_Data!$E$34)+N(Hist_Data!$E$35)+N(Hist_Data!$E$36)+N(Hist_Data!$E$37)) -> 1099 | F31: =-(N(Hist_Data!$F$32)+N(Hist_Data!$F$33)+N(Hist_Data!$F$34)+N(Hist_Data!$F$35)+N(Hist_Data!$F$36)+N(Hist_Data!$F$37)) -> -257 | G31: =-(N(Hist_Data!$G$32)+N(Hist_Data!$G$33)+N(Hist_Data!$G$34)+N(Hist_Data!$G$35)+N(Hist_Data!$G$36)+N(Hist_Data!$G$37)) -> 271 | H31: Calculated value | I31: Negative of the sum of the 6 cash-flow working-capital lines. Positive = cash absorbed by working capital.
A32: Free cash flow (project definition) | B32: $m | C32: =$C$28+$C$29-$C$30-$C$31 -> 5897 | D32: =$D$28+$D$29-$D$30-$D$31 -> 6064 | E32: =$E$28+$E$29-$E$30-$E$31 -> 1515 | F32: =$F$28+$F$29-$F$30-$F$31 -> 1744 | G32: =$G$28+$G$29-$G$30-$G$31 -> 2098 | H32: Calculated value | I32: Net income + D&A - capex - increase in working capital (project formula)
A33: Other non-cash items in CFO (SBC, deferred tax, other) | B33: $m | C33: =Hist_Data!$C$38-$C$28-$C$29+$C$31 -> 397 | D33: =Hist_Data!$D$38-$D$28-$D$29+$D$31 -> -141 | E33: =Hist_Data!$E$38-$E$28-$E$29+$E$31 -> -166 | F33: =Hist_Data!$F$38-$F$28-$F$29+$F$31 -> -246 | G33: =Hist_Data!$G$38-$G$28-$G$29+$G$31 -> 505 | H33: Calculated value | I33: CFO - net income - D&A + increase in WC. Explains the gap to the CFO-based FCF below.
A34: Free cash flow (CFO - capex, common market definition) | B34: $m | C34: =Hist_Data!$C$38-$C$30 -> 6294 | D34: =Hist_Data!$D$38-$D$30 -> 5923 | E34: =Hist_Data!$E$38-$E$30 -> 1349 | F34: =Hist_Data!$F$38-$F$30 -> 1498 | G34: =Hist_Data!$G$38-$G$30 -> 2603 | H34: Calculated value | I34: Net cash from operations - capex. Reconciles to project FCF + other non-cash items (see Checks).
A35: FCF margin (project definition) | B35: % | C35: =IFERROR($C$32/Hist_Data!$C$7,"") -> 0.32146751 | D35: =IFERROR($D$32/Hist_Data!$D$7,"") -> 0.30277611 | E35: =IFERROR($E$32/Hist_Data!$E$7,"") -> 0.086477539 | F35: =IFERROR($F$32/Hist_Data!$F$7,"") -> 0.11150182 | G35: =IFERROR($G$32/Hist_Data!$G$7,"") -> 0.11865174 | H35: Calculated value | I35: Project FCF / net sales
A36: FCF conversion (project FCF / net income) | B36: x | C36: =IF(ABS($C$28)<0.02*Hist_Data!$C$7,"n.m.",IFERROR($C$32/$C$28,"")) -> 0.75904235 | D36: =IF(ABS($D$28)<0.02*Hist_Data!$D$7,"n.m.",IFERROR($D$32/$D$28,"")) -> 0.69310778 | E36: =IF(ABS($E$28)<0.02*Hist_Data!$E$7,"n.m.",IFERROR($E$32/$E$28,"")) -> 0.23271889 | F36: =IF(ABS($F$28)<0.02*Hist_Data!$F$7,"n.m.",IFERROR($F$32/$F$28,"")) -> 0.36340904 | G36: =IF(ABS($G$28)<0.02*Hist_Data!$G$7,"n.m.",IFERROR($G$32/$G$28,"")) -> 0.4195161 | H36: Calculated value | I36: Project FCF / net income. Shows n.m. when net income is under 2% of sales.
A37: Capex % of sales | B37: % | C37: =IFERROR($C$30/Hist_Data!$C$7,"") -> 0.13421282 | D37: =IFERROR($D$30/Hist_Data!$D$7,"") -> 0.13965448 | E37: =IFERROR($E$30/Hist_Data!$E$7,"") -> 0.28945716 | F37: =IFERROR($F$30/Hist_Data!$F$7,"") -> 0.30816444 | G37: =IFERROR($G$30/Hist_Data!$G$7,"") -> 0.25732383 | H37: Calculated value | I37: Capex / net sales - anchor for the forecast capex assumption
A38: D&A % of sales | B38: % | C38: =IFERROR(Hist_Data!$C$30/Hist_Data!$C$7,"") -> 0.041157872 | D38: =IFERROR(Hist_Data!$D$30/Hist_Data!$D$7,"") -> 0.046185341 | E38: =IFERROR(Hist_Data!$E$30/Hist_Data!$E$7,"") -> 0.067070038 | F38: =IFERROR(Hist_Data!$F$30/Hist_Data!$F$7,"") -> 0.096413273 | G38: =IFERROR(Hist_Data!$G$30/Hist_Data!$G$7,"") -> 0.10847189 | H38: Calculated value | I38: D&A / net sales
A39: Share-based compensation % of sales | B39: % | C39: =IFERROR(Hist_Data!$C$31/Hist_Data!$C$7,"") -> 0.01253816 | D39: =IFERROR(Hist_Data!$D$31/Hist_Data!$D$7,"") -> 0.014429798 | E39: =IFERROR(Hist_Data!$E$31/Hist_Data!$E$7,"") -> 0.02066328 | F39: =IFERROR(Hist_Data!$F$31/Hist_Data!$F$7,"") -> 0.024742664 | G39: =IFERROR(Hist_Data!$G$31/Hist_Data!$G$7,"") -> 0.023696414 | H39: Calculated value | I39: SBC / net sales
A40: Capex / depreciation & amortization | B40: x | C40: =IFERROR($C$30/Hist_Data!$C$30,"") -> 3.2609272 | D40: =IFERROR($D$30/Hist_Data!$D$30,"") -> 3.0237838 | E40: =IFERROR($E$30/Hist_Data!$E$30,"") -> 4.3157447 | F40: =IFERROR($F$30/Hist_Data!$F$30,"") -> 3.1962865 | G40: =IFERROR($G$30/Hist_Data!$G$30,"") -> 2.3722628 | H40: Calculated value | I40: <1.0x means spending less than D&A (asset base shrinking or amortization-heavy D&A)
A41: Working capital and asset efficiency (year-end balances)
A42: Days sales outstanding (DSO) | B42: days | C42: =IFERROR(Hist_Data!$C$47/Hist_Data!$C$7*365,"") -> 33.845672 | D42: =IFERROR(Hist_Data!$D$47/Hist_Data!$D$7*365,"") -> 34.5354 | E42: =IFERROR(Hist_Data!$E$47/Hist_Data!$E$7*365,"") -> 37.231292 | F42: =IFERROR(Hist_Data!$F$47/Hist_Data!$F$7*365,"") -> 40.114762 | G42: =IFERROR(Hist_Data!$G$47/Hist_Data!$G$7*365,"") -> 40.521151 | H42: Calculated value | I42: Accounts receivable / net sales x 365
A43: Days inventory outstanding (DIO) | B43: days | C43: =IFERROR(Hist_Data!$C$48/Hist_Data!$C$8*365,"") -> 116.81468 | D43: =IFERROR(Hist_Data!$D$48/Hist_Data!$D$8*365,"") -> 160.82867 | E43: =IFERROR(Hist_Data!$E$48/Hist_Data!$E$8*365,"") -> 224.55923 | F43: =IFERROR(Hist_Data!$F$48/Hist_Data!$F$8*365,"") -> 252.38353 | G43: =IFERROR(Hist_Data!$G$48/Hist_Data!$G$8*365,"") -> 230.74878 | H43: Calculated value | I43: Inventories / annual cost of sales x 365 (company-reported days often use quarterly COGS, so they can differ).
A44: Days payable outstanding (DPO) | B44: days | C44: =IFERROR(Hist_Data!$C$54/Hist_Data!$C$8*365,"") -> 34.922084 | D44: =IFERROR(Hist_Data!$D$54/Hist_Data!$D$8*365,"") -> 49.6428 | E44: =IFERROR(Hist_Data!$E$54/Hist_Data!$E$8*365,"") -> 45.035385 | F44: =IFERROR(Hist_Data!$F$54/Hist_Data!$F$8*365,"") -> 45.715595 | G44: =IFERROR(Hist_Data!$G$54/Hist_Data!$G$8*365,"") -> 36.312673 | H44: Calculated value | I44: Accounts payable / cost of sales x 365
A45: Cash conversion cycle | B45: days | C45: =$C$42+$C$43-$C$44 -> 115.73827 | D45: =$D$42+$D$43-$D$44 -> 145.72127 | E45: =$E$42+$E$43-$E$44 -> 216.75514 | F45: =$F$42+$F$43-$F$44 -> 246.7827 | G45: =$G$42+$G$43-$G$44 -> 234.95726 | H45: Calculated value | I45: DSO + DIO - DPO
A46: Operating working capital | B46: $m | C46: =Hist_Data!$C$47+Hist_Data!$C$48+N(Hist_Data!$C$49)-Hist_Data!$C$54-N(Hist_Data!$C$57) -> 2773 | D46: =Hist_Data!$D$47+Hist_Data!$D$48+N(Hist_Data!$D$49)-Hist_Data!$D$54-N(Hist_Data!$D$57) -> 3457 | E46: =Hist_Data!$E$47+Hist_Data!$E$48+N(Hist_Data!$E$49)-Hist_Data!$E$54-N(Hist_Data!$E$57) -> 4834 | F46: =Hist_Data!$F$47+Hist_Data!$F$48+N(Hist_Data!$F$49)-Hist_Data!$F$54-N(Hist_Data!$F$57) -> 5551 | G46: =Hist_Data!$G$47+Hist_Data!$G$48+N(Hist_Data!$G$49)-Hist_Data!$G$54-N(Hist_Data!$G$57) -> 7106 | H46: Calculated value | I46: AR + inventories + other current assets - AP - accrued liabilities (excludes cash and debt)
A47: Operating working capital % of sales | B47: % | C47: =IFERROR($C$46/Hist_Data!$C$7,"") -> 0.15116659 | D47: =IFERROR($D$46/Hist_Data!$D$7,"") -> 0.17260835 | E47: =IFERROR($E$46/Hist_Data!$E$7,"") -> 0.27592899 | F47: =IFERROR($F$46/Hist_Data!$F$7,"") -> 0.35490058 | G47: =IFERROR($G$46/Hist_Data!$G$7,"") -> 0.40187762 | H47: Calculated value | I47: Anchor for the forecast working-capital assumption
A48: Net sales / net PP&E | B48: x | C48: =IFERROR(Hist_Data!$C$7/Hist_Data!$C$51,"") -> 3.5681774 | D48: =IFERROR(Hist_Data!$D$7/Hist_Data!$D$51,"") -> 2.91274 | E48: =IFERROR(Hist_Data!$E$7/Hist_Data!$E$51,"") -> 1.7520752 | F48: =IFERROR(Hist_Data!$F$7/Hist_Data!$F$51,"") -> 1.378426 | G48: =IFERROR(Hist_Data!$G$7/Hist_Data!$G$51,"") -> 1.4352273 | H48: Calculated value | I48: Fixed-asset turnover
A49: Quarterly context (second fiscal quarter (April-June))
C50: Q2 FY2025 | D50: Q2 FY2026 | E50: YoY growth
A51: Revenue | B51: $m | C51: =Hist_Data!$C$68 -> 4448 | D51: =Hist_Data!$D$68 -> 5463 | E51: =IFERROR(D51/C51-1,"") -> 0.22819245 | H51: Calculated value | I51: Q2 FY2026 / Q2 FY2025 - 1. Context for the FY2026 demand-growth assumption.
A52: Analog | B52: $m | C52: =Hist_Data!$C$69 -> 3452 | D52: =Hist_Data!$D$69 -> 4365 | E52: =IFERROR(D52/C52-1,"") -> 0.26448436 | H52: Calculated value | I52: Q2 FY2026 / Q2 FY2025 - 1. Context for the FY2026 demand-growth assumption.
A53: Embedded Processing | B53: $m | C53: =Hist_Data!$C$70 -> 679 | D53: =Hist_Data!$D$70 -> 788 | E53: =IFERROR(D53/C53-1,"") -> 0.16053019 | H53: Calculated value | I53: Q2 FY2026 / Q2 FY2025 - 1. Context for the FY2026 demand-growth assumption.
A54: Other | B54: $m | C54: =Hist_Data!$C$71 -> 317 | D54: =Hist_Data!$D$71 -> 310 | E54: =IFERROR(D54/C54-1,"") -> -0.022082019 | H54: Calculated value | I54: Q2 FY2026 / Q2 FY2025 - 1. Context for the FY2026 demand-growth assumption.
A56: Analyst observations (each refers to a metric above; numbers quoted are formula results)
A57: Cycle | C57: ="Net sales peaked in FY2022 at $"&TEXT(Hist_Data!$D$7,"#,##0")&"m and fell "&TEXT(-(Hist_Data!$F$7/Hist_Data!$D$7-1),"0%")&" by FY2024"&", then grew "&TEXT($G$8,"0.0%")&" in FY2025." -> Net sales peaked in FY2022 at $20,028m and fell 22% by FY2024, then grew 13.0% in FY2025.
A58: Operating leverage | C58: ="Gross margin moved from "&TEXT($D$9,"0.0%")&" (FY2022) to "&TEXT($F$9,"0.0%")&" (FY2024): consistent with fixed factory cost spread over fewer units. The operating model simulates this effect." -> Gross margin moved from 68.8% (FY2022) to 58.1% (FY2024): consistent with fixed factory cost spread over fewer units. The operating model simulates this effect.
A59: Inventory | C59: ="Days of inventory were "&TEXT($C$43,"0")&" in FY2021 and "&TEXT($G$43,"0")&" in FY2025." -> Days of inventory were 117 in FY2021 and 231 in FY2025.
A60: Capex | C60: ="Capex was "&TEXT($C$37,"0.0%")&" of sales in FY2021 and "&TEXT($G$37,"0.0%")&" in FY2025; capex / D&A was "&TEXT($G$40,"0.00x")&" in FY2025." -> Capex was 13.4% of sales in FY2021 and 25.7% in FY2025; capex / D&A was 2.37x in FY2025.
A61: Latest quarter | C61: ="Q2 FY2026 net sales changed "&TEXT(E51,"+0%;-0%")&" year over year." -> Q2 FY2026 net sales changed +23% year over year.

Sheet Ops_Model
A1: Product Operating Model - FY2026 monthly (active scenario)
A2: Units in millions, money in $m, prices in $/unit. Every row traces to Assumptions. Black = formula.
A3: Simulated data created for portfolio demonstration. It does not represent nonpublic Texas Instruments information.
A4: Scenario shown: | B4: =Assumptions!$C$6 -> Base
A6: Line item | B6: Units | C6: =Assumptions!C$72 -> 46023 | D6: =Assumptions!D$72 -> 46054 | E6: =Assumptions!E$72 -> 46082 | F6: =Assumptions!F$72 -> 46113 | G6: =Assumptions!G$72 -> 46143 | H6: =Assumptions!H$72 -> 46174 | I6: =Assumptions!I$72 -> 46204 | J6: =Assumptions!J$72 -> 46235 | ... N6: =Assumptions!N$72 -> 46357 | O6: FY2026 | P6: Classification | Q6: Formula
A7: Power-management chips - Simulated data created for portfolio demonstration. It does not represent nonpublic Texas Instruments information.
A8: Seasonality factor | B8: x | C8: =Assumptions!C$73 -> 0.94 | D8: =Assumptions!D$73 -> 0.96 | E8: =Assumptions!E$73 -> 1.02 | F8: =Assumptions!F$73 -> 0.99 | G8: =Assumptions!G$73 -> 1 | H8: =Assumptions!H$73 -> 1.03 | I8: =Assumptions!I$73 -> 1.02 | J8: =Assumptions!J$73 -> 1.03 | ... N8: =Assumptions!N$73 -> 0.96 | O8: =SUM(C8:N8) -> 12 | P8: Calculated value (simulated inputs) | Q8: Link: Assumptions section E
A9: Customer demand | B9: m units | C9: =Assumptions!$C$63*C8/12 -> 64.042882 | D9: =Assumptions!$C$63*D8/12 -> 65.405496 | E9: =Assumptions!$C$63*E8/12 -> 69.49334 | F9: =Assumptions!$C$63*F8/12 -> 67.449418 | G9: =Assumptions!$C$63*G8/12 -> 68.130725 | H9: =Assumptions!$C$63*H8/12 -> 70.174647 | I9: =Assumptions!$C$63*I8/12 -> 69.49334 | J9: =Assumptions!$C$63*J8/12 -> 70.174647 | ... N9: =Assumptions!$C$63*N8/12 -> 65.405496 | O9: =SUM(C9:N9) -> 817.5687 | P9: Calculated value (simulated inputs) | Q9: FY2026 demand x seasonality / 12
A10: Internal final-test capacity | B10: m units | C10: =Assumptions!$C$47 -> 88 | D10: =Assumptions!$C$47 -> 88 | E10: =Assumptions!$C$47 -> 88 | F10: =Assumptions!$C$47 -> 88 | G10: =Assumptions!$C$47 -> 88 | H10: =Assumptions!$C$47 -> 88 | I10: =Assumptions!$C$47 -> 88 | J10: =Assumptions!$C$47 -> 88 | ... N10: =Assumptions!$C$47 -> 88 | O10: =SUM(C10:N10) -> 1056 | P10: Calculated value (simulated inputs) | Q10: Monthly capacity (Assumptions D)
A11: Capacity utilization | B11: % | C11: =Assumptions!$C$66 -> 0.78 | D11: =Assumptions!$C$66 -> 0.78 | E11: =Assumptions!$C$66 -> 0.78 | F11: =Assumptions!$C$66 -> 0.78 | G11: =Assumptions!$C$66 -> 0.78 | H11: =Assumptions!$C$66 -> 0.78 | I11: =Assumptions!$C$66 -> 0.78 | J11: =Assumptions!$C$66 -> 0.78 | ... N11: =Assumptions!$C$66 -> 0.78 | O11: =IFERROR(O12/O10,0) -> 0.78 | P11: Calculated value (simulated inputs) | Q11: Scenario utilization. FY = units produced / capacity
A12: Units produced (tested) | B12: m units | C12: =C10*C11 -> 68.64 | D12: =D10*D11 -> 68.64 | E12: =E10*E11 -> 68.64 | F12: =F10*F11 -> 68.64 | G12: =G10*G11 -> 68.64 | H12: =H10*H11 -> 68.64 | I12: =I10*I11 -> 68.64 | J12: =J10*J11 -> 68.64 | ... N12: =N10*N11 -> 68.64 | O12: =SUM(C12:N12) -> 823.68 | P12: Calculated value (simulated inputs) | Q12: Capacity x utilization
A13: Manufacturing yield (final test) | B13: % | C13: =Assumptions!$C$65 -> 0.95 | D13: =Assumptions!$C$65 -> 0.95 | E13: =Assumptions!$C$65 -> 0.95 | F13: =Assumptions!$C$65 -> 0.95 | G13: =Assumptions!$C$65 -> 0.95 | H13: =Assumptions!$C$65 -> 0.95 | I13: =Assumptions!$C$65 -> 0.95 | J13: =Assumptions!$C$65 -> 0.95 | ... N13: =Assumptions!$C$65 -> 0.95 | O13: =IFERROR(O14/O12,0) -> 0.95 | P13: Calculated value (simulated inputs) | Q13: Scenario yield. FY = good units / units produced
A14: Good units produced | B14: m units | C14: =C12*C13 -> 65.208 | D14: =D12*D13 -> 65.208 | E14: =E12*E13 -> 65.208 | F14: =F12*F13 -> 65.208 | G14: =G12*G13 -> 65.208 | H14: =H12*H13 -> 65.208 | I14: =I12*I13 -> 65.208 | J14: =J12*J13 -> 65.208 | ... N14: =N12*N13 -> 65.208 | O14: =SUM(C14:N14) -> 782.496 | P14: Calculated value (simulated inputs) | Q14: Units produced x yield
A15: Opening finished-goods inventory | B15: m units | C15: =Assumptions!$C$68 -> 58.231389 | D15: =C18 -> 59.396507 | E15: =D18 -> 59.199011 | F15: =E18 -> 54.913672 | G15: =F18 -> 52.672254 | H15: =G18 -> 49.749529 | I15: =H18 -> 44.782882 | J15: =I18 -> 40.497543 | K15: =J18 -> 35.530896 | ... N15: =M18 -> 23.356185 | O15: =C15 -> 58.231389 | P15: Calculated value (simulated inputs) | Q15: First month: Assumptions opening balance; then prior month's closing
A16: Available good units | B16: m units | C16: =C15+C14 -> 123.43939 | D16: =D15+D14 -> 124.60451 | E16: =E15+E14 -> 124.40701 | F16: =F15+F14 -> 120.12167 | G16: =G15+G14 -> 117.88025 | H16: =H15+H14 -> 114.95753 | I16: =I15+I14 -> 109.99088 | J16: =J15+J14 -> 105.70554 | ... N16: =N15+N14 -> 88.564185 | P16: Calculated value (simulated inputs) | Q16: Opening inventory + good units produced
A17: Units sold | B17: m units | C17: =MIN(C9,C16) -> 64.042882 | D17: =MIN(D9,D16) -> 65.405496 | E17: =MIN(E9,E16) -> 69.49334 | F17: =MIN(F9,F16) -> 67.449418 | G17: =MIN(G9,G16) -> 68.130725 | H17: =MIN(H9,H16) -> 70.174647 | I17: =MIN(I9,I16) -> 69.49334 | J17: =MIN(J9,J16) -> 70.174647 | ... N17: =MIN(N9,N16) -> 65.405496 | O17: =SUM(C17:N17) -> 817.5687 | P17: Calculated value (simulated inputs) | Q17: MIN(customer demand, available good units)
A18: Closing finished-goods inventory | B18: m units | C18: =C16-C17 -> 59.396507 | D18: =D16-D17 -> 59.199011 | E18: =E16-E17 -> 54.913672 | F18: =F16-F17 -> 52.672254 | G18: =G16-G17 -> 49.749529 | H18: =H16-H17 -> 44.782882 | I18: =I16-I17 -> 40.497543 | J18: =J16-J17 -> 35.530896 | ... N18: =N16-N17 -> 23.158689 | O18: =N18 -> 23.158689 | P18: Calculated value (simulated inputs) | Q18: Available - units sold
A19: Unmet demand (supply shortfall) | B19: m units | C19: =C9-C17 -> 0 | D19: =D9-D17 -> 0 | E19: =E9-E17 -> 0 | F19: =F9-F17 -> 0 | G19: =G9-G17 -> 0 | H19: =H9-H17 -> 0 | I19: =I9-I17 -> 0 | J19: =J9-J17 -> 0 | ... N19: =N9-N17 -> 0 | O19: =SUM(C19:N19) -> 0 | P19: Calculated value (simulated inputs) | Q19: Demand - units sold. >0 means lost or delayed sales
A20: Demand / good-unit capacity (risk ratio) | B20: x | C20: =IFERROR(C9/(C10*C13),0) -> 0.76606318 | D20: =IFERROR(D9/(D10*D13),0) -> 0.78236239 | E20: =IFERROR(E9/(E10*E13),0) -> 0.83126004 | F20: =IFERROR(F9/(F10*F13),0) -> 0.80681122 | G20: =IFERROR(G9/(G10*G13),0) -> 0.81496083 | H20: =IFERROR(H9/(H10*H13),0) -> 0.83940965 | I20: =IFERROR(I9/(I10*I13),0) -> 0.83126004 | J20: =IFERROR(J9/(J10*J13),0) -> 0.83940965 | ... O20: =IFERROR(O9/(O10*O13),0) -> 0.81496083 | P20: Calculated value (simulated inputs) | Q20: Demand / (capacity x yield) = share of full-load good output needed. Feeds the risk heat map
A21: Average selling price | B21: $/unit | C21: =Assumptions!$C$64 -> 0.594 | D21: =Assumptions!$C$64 -> 0.594 | E21: =Assumptions!$C$64 -> 0.594 | F21: =Assumptions!$C$64 -> 0.594 | G21: =Assumptions!$C$64 -> 0.594 | H21: =Assumptions!$C$64 -> 0.594 | I21: =Assumptions!$C$64 -> 0.594 | J21: =Assumptions!$C$64 -> 0.594 | ... N21: =Assumptions!$C$64 -> 0.594 | O21: =IFERROR(O22/O17,0) -> 0.594 | P21: Calculated value (simulated inputs) | Q21: Scenario ASP. FY = revenue / units sold
A22: Revenue | B22: $m | C22: =C17*C21 -> 38.041472 | D22: =D17*D21 -> 38.850865 | E22: =E17*E21 -> 41.279044 | F22: =F17*F21 -> 40.064954 | G22: =G17*G21 -> 40.469651 | H22: =H17*H21 -> 41.68374 | I22: =I17*I21 -> 41.279044 | J22: =J17*J21 -> 41.68374 | ... N22: =N17*N21 -> 38.850865 | O22: =SUM(C22:N22) -> 485.63581 | P22: Calculated value (simulated inputs) | Q22: Units sold x ASP
A23: Variable cost per unit produced | B23: $/unit | C23: =Assumptions!$C$67 -> 0.1442 | D23: =Assumptions!$C$67 -> 0.1442 | E23: =Assumptions!$C$67 -> 0.1442 | F23: =Assumptions!$C$67 -> 0.1442 | G23: =Assumptions!$C$67 -> 0.1442 | H23: =Assumptions!$C$67 -> 0.1442 | I23: =Assumptions!$C$67 -> 0.1442 | J23: =Assumptions!$C$67 -> 0.1442 | ... N23: =Assumptions!$C$67 -> 0.1442 | O23: =IFERROR(O24/O12,0) -> 0.1442 | P23: Calculated value (simulated inputs) | Q23: Scenario variable cost per unit
A24: Variable manufacturing cost | B24: $m | C24: =C12*C23 -> 9.897888 | D24: =D12*D23 -> 9.897888 | E24: =E12*E23 -> 9.897888 | F24: =F12*F23 -> 9.897888 | G24: =G12*G23 -> 9.897888 | H24: =H12*H23 -> 9.897888 | I24: =I12*I23 -> 9.897888 | J24: =J12*J23 -> 9.897888 | ... N24: =N12*N23 -> 9.897888 | O24: =SUM(C24:N24) -> 118.77466 | P24: Calculated value (simulated inputs) | Q24: Units produced x variable cost per unit
A25: Fixed manufacturing cost | B25: $m | C25: =Assumptions!$C$46 -> 5.8 | D25: =Assumptions!$C$46 -> 5.8 | E25: =Assumptions!$C$46 -> 5.8 | F25: =Assumptions!$C$46 -> 5.8 | G25: =Assumptions!$C$46 -> 5.8 | H25: =Assumptions!$C$46 -> 5.8 | I25: =Assumptions!$C$46 -> 5.8 | J25: =Assumptions!$C$46 -> 5.8 | ... N25: =Assumptions!$C$46 -> 5.8 | O25: =SUM(C25:N25) -> 69.6 | P25: Calculated value (simulated inputs) | Q25: Monthly fixed cost (Assumptions D)
A26: Total manufacturing cost | B26: $m | C26: =C24+C25 -> 15.697888 | D26: =D24+D25 -> 15.697888 | E26: =E24+E25 -> 15.697888 | F26: =F24+F25 -> 15.697888 | G26: =G24+G25 -> 15.697888 | H26: =H24+H25 -> 15.697888 | I26: =I24+I25 -> 15.697888 | J26: =J24+J25 -> 15.697888 | ... N26: =N24+N25 -> 15.697888 | O26: =SUM(C26:N26) -> 188.37466 | P26: Calculated value (simulated inputs) | Q26: Variable + fixed manufacturing cost
A27: Cost per good unit | B27: $/unit | C27: =IFERROR(C26/C14,0) -> 0.24073562 | D27: =IFERROR(D26/D14,0) -> 0.24073562 | E27: =IFERROR(E26/E14,0) -> 0.24073562 | F27: =IFERROR(F26/F14,0) -> 0.24073562 | G27: =IFERROR(G26/G14,0) -> 0.24073562 | H27: =IFERROR(H26/H14,0) -> 0.24073562 | I27: =IFERROR(I26/I14,0) -> 0.24073562 | J27: =IFERROR(J26/J14,0) -> 0.24073562 | ... O27: =IFERROR(O26/O14,0) -> 0.24073562 | P27: Calculated value (simulated inputs) | Q27: Total manufacturing cost / good units. Rises when yield or utilization falls
A28: Opening inventory value | B28: $m | C28: =Assumptions!$C$69 -> 14.381468 | D28: =C31 -> 14.47357 | E28: =D31 -> 14.334317 | F28: =E31 -> 13.256316 | G28: =F31 -> 12.696154 | H28: =G31 -> 11.983264 | I28: =H31 -> 10.783476 | J28: =I31 -> 9.7501734 | K28: =J31 -> 8.553879 | ... N28: =M31 -> 5.622672 | O28: =C28 -> 14.381468 | P28: Calculated value (simulated inputs) | Q28: Prior month's closing value
A29: Average cost per available unit | B29: $/unit | C29: =IFERROR((C28+C26)/C16,0) -> 0.24367713 | D29: =IFERROR((D28+D26)/D16,0) -> 0.24213778 | E29: =IFERROR((E28+E26)/E16,0) -> 0.24140283 | F29: =IFERROR((F28+F26)/F16,0) -> 0.24104063 | G29: =IFERROR((G28+G26)/G16,0) -> 0.24087191 | H29: =IFERROR((H28+H26)/H16,0) -> 0.2407946 | I29: =IFERROR((I28+I26)/I16,0) -> 0.24075963 | J29: =IFERROR((J28+J26)/J16,0) -> 0.24074482 | ... N29: =IFERROR((N28+N26)/N16,0) -> 0.24073569 | P29: Calculated value (simulated inputs) | Q29: (Opening value + manufacturing cost) / available units - weighted-average costing
A30: Cost of revenue | B30: $m | C30: =C17*C29 -> 15.605785 | D30: =D17*D29 -> 15.837141 | E30: =E17*E29 -> 16.775889 | F30: =F17*F29 -> 16.25805 | G30: =G17*G29 -> 16.410778 | H30: =H17*H29 -> 16.897676 | I30: =I17*I29 -> 16.731191 | J30: =J17*J29 -> 16.894182 | ... N30: =N17*N29 -> 15.745437 | O30: =SUM(C30:N30) -> 197.181 | P30: Calculated value (simulated inputs) | Q30: Units sold x average cost
A31: Closing inventory value | B31: $m | C31: =C28+C26-C30 -> 14.47357 | D31: =D28+D26-D30 -> 14.334317 | E31: =E28+E26-E30 -> 13.256316 | F31: =F28+F26-F30 -> 12.696154 | G31: =G28+G26-G30 -> 11.983264 | H31: =H28+H26-H30 -> 10.783476 | I31: =I28+I26-I30 -> 9.7501734 | J31: =J28+J26-J30 -> 8.553879 | ... N31: =N28+N26-N30 -> 5.5751229 | O31: =N31 -> 5.5751229 | P31: Calculated value (simulated inputs) | Q31: Opening value + manufacturing cost - cost of revenue
A32: Contribution margin | B32: $m | C32: =C22-C17*IFERROR(C23/C13,0) -> 28.320436 | D32: =D22-D17*IFERROR(D23/D13,0) -> 28.922999 | E32: =E22-E17*IFERROR(E23/E13,0) -> 30.730686 | F32: =F22-F17*IFERROR(F23/F13,0) -> 29.826843 | G32: =G22-G17*IFERROR(G23/G13,0) -> 30.128124 | H32: =H22-H17*IFERROR(H23/H13,0) -> 31.031967 | I32: =I22-I17*IFERROR(I23/I13,0) -> 30.730686 | J32: =J22-J17*IFERROR(J23/J13,0) -> 31.031967 | ... N32: =N22-N17*IFERROR(N23/N13,0) -> 28.922999 | O32: =SUM(C32:N32) -> 361.53749 | P32: Calculated value (simulated inputs) | Q32: Revenue - units sold x variable cost per good unit (variable cost / yield)
A33: Contribution margin % | B33: % | C33: =IFERROR(C32/C22,0) -> 0.74446217 | D33: =IFERROR(D32/D22,0) -> 0.74446217 | E33: =IFERROR(E32/E22,0) -> 0.74446217 | F33: =IFERROR(F32/F22,0) -> 0.74446217 | G33: =IFERROR(G32/G22,0) -> 0.74446217 | H33: =IFERROR(H32/H22,0) -> 0.74446217 | I33: =IFERROR(I32/I22,0) -> 0.74446217 | J33: =IFERROR(J32/J22,0) -> 0.74446217 | ... O33: =IFERROR(O32/O22,0) -> 0.74446217 | P33: Calculated value (simulated inputs) | Q33: Contribution margin / revenue
A34: Gross profit | B34: $m | C34: =C22-C30 -> 22.435686 | D34: =D22-D30 -> 23.013723 | E34: =E22-E30 -> 24.503155 | F34: =F22-F30 -> 23.806904 | G34: =G22-G30 -> 24.058873 | H34: =H22-H30 -> 24.786064 | I34: =I22-I30 -> 24.547853 | J34: =J22-J30 -> 24.789558 | ... N34: =N22-N30 -> 23.105428 | O34: =SUM(C34:N34) -> 288.45481 | P34: Calculated value (simulated inputs) | Q34: Revenue - cost of revenue
A35: Gross margin % | B35: % | C35: =IFERROR(C34/C22,0) -> 0.58976914 | D35: =IFERROR(D34/D22,0) -> 0.59236065 | E35: =IFERROR(E34/E22,0) -> 0.59359792 | F35: =IFERROR(F34/F22,0) -> 0.59420769 | G35: =IFERROR(G34/G22,0) -> 0.59449174 | H35: =IFERROR(H34/H22,0) -> 0.59462189 | I35: =IFERROR(I34/I22,0) -> 0.59468076 | J35: =IFERROR(J34/J22,0) -> 0.5947057 | ... O35: =IFERROR(O34/O22,0) -> 0.59397351 | P35: Calculated value (simulated inputs) | Q35: Gross profit / revenue
A37: Signal-chain chips - Simulated data created for portfolio demonstration. It does not represent nonpublic Texas Instruments information.
A38: Seasonality factor | B38: x | C38: =Assumptions!C$73 -> 0.94 | D38: =Assumptions!D$73 -> 0.96 | E38: =Assumptions!E$73 -> 1.02 | F38: =Assumptions!F$73 -> 0.99 | G38: =Assumptions!G$73 -> 1 | H38: =Assumptions!H$73 -> 1.03 | I38: =Assumptions!I$73 -> 1.02 | J38: =Assumptions!J$73 -> 1.03 | ... N38: =Assumptions!N$73 -> 0.96 | O38: =SUM(C38:N38) -> 12 | P38: Calculated value (simulated inputs) | Q38: Link: Assumptions section E
A39: Customer demand | B39: m units | C39: =Assumptions!$D$63*C38/12 -> 40.448136 | D39: =Assumptions!$D$63*D38/12 -> 41.308734 | E39: =Assumptions!$D$63*E38/12 -> 43.89053 | F39: =Assumptions!$D$63*F38/12 -> 42.599632 | G39: =Assumptions!$D$63*G38/12 -> 43.029932 | H39: =Assumptions!$D$63*H38/12 -> 44.32083 | I39: =Assumptions!$D$63*I38/12 -> 43.89053 | J39: =Assumptions!$D$63*J38/12 -> 44.32083 | ... N39: =Assumptions!$D$63*N38/12 -> 41.308734 | O39: =SUM(C39:N39) -> 516.35918 | P39: Calculated value (simulated inputs) | Q39: FY2026 demand x seasonality / 12
A40: Internal final-test capacity | B40: m units | C40: =Assumptions!$D$47 -> 60 | D40: =Assumptions!$D$47 -> 60 | E40: =Assumptions!$D$47 -> 60 | F40: =Assumptions!$D$47 -> 60 | G40: =Assumptions!$D$47 -> 60 | H40: =Assumptions!$D$47 -> 60 | I40: =Assumptions!$D$47 -> 60 | J40: =Assumptions!$D$47 -> 60 | ... N40: =Assumptions!$D$47 -> 60 | O40: =SUM(C40:N40) -> 720 | P40: Calculated value (simulated inputs) | Q40: Monthly capacity (Assumptions D)
A41: Capacity utilization | B41: % | C41: =Assumptions!$D$66 -> 0.78 | D41: =Assumptions!$D$66 -> 0.78 | E41: =Assumptions!$D$66 -> 0.78 | F41: =Assumptions!$D$66 -> 0.78 | G41: =Assumptions!$D$66 -> 0.78 | H41: =Assumptions!$D$66 -> 0.78 | I41: =Assumptions!$D$66 -> 0.78 | J41: =Assumptions!$D$66 -> 0.78 | ... N41: =Assumptions!$D$66 -> 0.78 | O41: =IFERROR(O42/O40,0) -> 0.78 | P41: Calculated value (simulated inputs) | Q41: Scenario utilization. FY = units produced / capacity
A42: Units produced (tested) | B42: m units | C42: =C40*C41 -> 46.8 | D42: =D40*D41 -> 46.8 | E42: =E40*E41 -> 46.8 | F42: =F40*F41 -> 46.8 | G42: =G40*G41 -> 46.8 | H42: =H40*H41 -> 46.8 | I42: =I40*I41 -> 46.8 | J42: =J40*J41 -> 46.8 | ... N42: =N40*N41 -> 46.8 | O42: =SUM(C42:N42) -> 561.6 | P42: Calculated value (simulated inputs) | Q42: Capacity x utilization
A43: Manufacturing yield (final test) | B43: % | C43: =Assumptions!$D$65 -> 0.93 | D43: =Assumptions!$D$65 -> 0.93 | E43: =Assumptions!$D$65 -> 0.93 | F43: =Assumptions!$D$65 -> 0.93 | G43: =Assumptions!$D$65 -> 0.93 | H43: =Assumptions!$D$65 -> 0.93 | I43: =Assumptions!$D$65 -> 0.93 | J43: =Assumptions!$D$65 -> 0.93 | ... N43: =Assumptions!$D$65 -> 0.93 | O43: =IFERROR(O44/O42,0) -> 0.93 | P43: Calculated value (simulated inputs) | Q43: Scenario yield. FY = good units / units produced
A44: Good units produced | B44: m units | C44: =C42*C43 -> 43.524 | D44: =D42*D43 -> 43.524 | E44: =E42*E43 -> 43.524 | F44: =F42*F43 -> 43.524 | G44: =G42*G43 -> 43.524 | H44: =H42*H43 -> 43.524 | I44: =I42*I43 -> 43.524 | J44: =J42*J43 -> 43.524 | ... N44: =N42*N43 -> 43.524 | O44: =SUM(C44:N44) -> 522.288 | P44: Calculated value (simulated inputs) | Q44: Units produced x yield
A45: Opening finished-goods inventory | B45: m units | C45: =Assumptions!$D$68 -> 36.777719 | D45: =C48 -> 39.853584 | E45: =D48 -> 42.068849 | F45: =E48 -> 41.702319 | G45: =F48 -> 42.626687 | H45: =G48 -> 43.120755 | I45: =H48 -> 42.323926 | J45: =I48 -> 41.957395 | K45: =J48 -> 41.160566 | ... N45: =M48 -> 40.491275 | O45: =C45 -> 36.777719 | P45: Calculated value (simulated inputs) | Q45: First month: Assumptions opening balance; then prior month's closing
A46: Available good units | B46: m units | C46: =C45+C44 -> 80.301719 | D46: =D45+D44 -> 83.377584 | E46: =E45+E44 -> 85.592849 | F46: =F45+F44 -> 85.226319 | G46: =G45+G44 -> 86.150687 | H46: =H45+H44 -> 86.644755 | I46: =I45+I44 -> 85.847926 | J46: =J45+J44 -> 85.481395 | ... N46: =N45+N44 -> 84.015275 | P46: Calculated value (simulated inputs) | Q46: Opening inventory + good units produced
A47: Units sold | B47: m units | C47: =MIN(C39,C46) -> 40.448136 | D47: =MIN(D39,D46) -> 41.308734 | E47: =MIN(E39,E46) -> 43.89053 | F47: =MIN(F39,F46) -> 42.599632 | G47: =MIN(G39,G46) -> 43.029932 | H47: =MIN(H39,H46) -> 44.32083 | I47: =MIN(I39,I46) -> 43.89053 | J47: =MIN(J39,J46) -> 44.32083 | ... N47: =MIN(N39,N46) -> 41.308734 | O47: =SUM(C47:N47) -> 516.35918 | P47: Calculated value (simulated inputs) | Q47: MIN(customer demand, available good units)
A48: Closing finished-goods inventory | B48: m units | C48: =C46-C47 -> 39.853584 | D48: =D46-D47 -> 42.068849 | E48: =E46-E47 -> 41.702319 | F48: =F46-F47 -> 42.626687 | G48: =G46-G47 -> 43.120755 | H48: =H46-H47 -> 42.323926 | I48: =I46-I47 -> 41.957395 | J48: =J46-J47 -> 41.160566 | ... N48: =N46-N47 -> 42.70654 | O48: =N48 -> 42.70654 | P48: Calculated value (simulated inputs) | Q48: Available - units sold
A49: Unmet demand (supply shortfall) | B49: m units | C49: =C39-C47 -> 0 | D49: =D39-D47 -> 0 | E49: =E39-E47 -> 0 | F49: =F39-F47 -> 0 | G49: =G39-G47 -> 0 | H49: =H39-H47 -> 0 | I49: =I39-I47 -> 0 | J49: =J39-J47 -> 0 | ... N49: =N39-N47 -> 0 | O49: =SUM(C49:N49) -> 0 | P49: Calculated value (simulated inputs) | Q49: Demand - units sold. >0 means lost or delayed sales
A50: Demand / good-unit capacity (risk ratio) | B50: x | C50: =IFERROR(C39/(C40*C43),0) -> 0.72487698 | D50: =IFERROR(D39/(D40*D43),0) -> 0.7402999 | E50: =IFERROR(E39/(E40*E43),0) -> 0.78656864 | F50: =IFERROR(F39/(F40*F43),0) -> 0.76343427 | G50: =IFERROR(G39/(G40*G43),0) -> 0.77114573 | H50: =IFERROR(H39/(H40*H43),0) -> 0.7942801 | I50: =IFERROR(I39/(I40*I43),0) -> 0.78656864 | J50: =IFERROR(J39/(J40*J43),0) -> 0.7942801 | ... O50: =IFERROR(O39/(O40*O43),0) -> 0.77114573 | P50: Calculated value (simulated inputs) | Q50: Demand / (capacity x yield) = share of full-load good output needed. Feeds the risk heat map
A51: Average selling price | B51: $/unit | C51: =Assumptions!$D$64 -> 0.9405 | D51: =Assumptions!$D$64 -> 0.9405 | E51: =Assumptions!$D$64 -> 0.9405 | F51: =Assumptions!$D$64 -> 0.9405 | G51: =Assumptions!$D$64 -> 0.9405 | H51: =Assumptions!$D$64 -> 0.9405 | I51: =Assumptions!$D$64 -> 0.9405 | J51: =Assumptions!$D$64 -> 0.9405 | ... N51: =Assumptions!$D$64 -> 0.9405 | O51: =IFERROR(O52/O47,0) -> 0.9405 | P51: Calculated value (simulated inputs) | Q51: Scenario ASP. FY = revenue / units sold
A52: Revenue | B52: $m | C52: =C47*C51 -> 38.041472 | D52: =D47*D51 -> 38.850865 | E52: =E47*E51 -> 41.279044 | F52: =F47*F51 -> 40.064954 | G52: =G47*G51 -> 40.469651 | H52: =H47*H51 -> 41.68374 | I52: =I47*I51 -> 41.279044 | J52: =J47*J51 -> 41.68374 | ... N52: =N47*N51 -> 38.850865 | O52: =SUM(C52:N52) -> 485.63581 | P52: Calculated value (simulated inputs) | Q52: Units sold x ASP
A53: Variable cost per unit produced | B53: $/unit | C53: =Assumptions!$D$67 -> 0.2163 | D53: =Assumptions!$D$67 -> 0.2163 | E53: =Assumptions!$D$67 -> 0.2163 | F53: =Assumptions!$D$67 -> 0.2163 | G53: =Assumptions!$D$67 -> 0.2163 | H53: =Assumptions!$D$67 -> 0.2163 | I53: =Assumptions!$D$67 -> 0.2163 | J53: =Assumptions!$D$67 -> 0.2163 | ... N53: =Assumptions!$D$67 -> 0.2163 | O53: =IFERROR(O54/O42,0) -> 0.2163 | P53: Calculated value (simulated inputs) | Q53: Scenario variable cost per unit
A54: Variable manufacturing cost | B54: $m | C54: =C42*C53 -> 10.12284 | D54: =D42*D53 -> 10.12284 | E54: =E42*E53 -> 10.12284 | F54: =F42*F53 -> 10.12284 | G54: =G42*G53 -> 10.12284 | H54: =H42*H53 -> 10.12284 | I54: =I42*I53 -> 10.12284 | J54: =J42*J53 -> 10.12284 | ... N54: =N42*N53 -> 10.12284 | O54: =SUM(C54:N54) -> 121.47408 | P54: Calculated value (simulated inputs) | Q54: Units produced x variable cost per unit
A55: Fixed manufacturing cost | B55: $m | C55: =Assumptions!$D$46 -> 6.2 | D55: =Assumptions!$D$46 -> 6.2 | E55: =Assumptions!$D$46 -> 6.2 | F55: =Assumptions!$D$46 -> 6.2 | G55: =Assumptions!$D$46 -> 6.2 | H55: =Assumptions!$D$46 -> 6.2 | I55: =Assumptions!$D$46 -> 6.2 | J55: =Assumptions!$D$46 -> 6.2 | ... N55: =Assumptions!$D$46 -> 6.2 | O55: =SUM(C55:N55) -> 74.4 | P55: Calculated value (simulated inputs) | Q55: Monthly fixed cost (Assumptions D)
A56: Total manufacturing cost | B56: $m | C56: =C54+C55 -> 16.32284 | D56: =D54+D55 -> 16.32284 | E56: =E54+E55 -> 16.32284 | F56: =F54+F55 -> 16.32284 | G56: =G54+G55 -> 16.32284 | H56: =H54+H55 -> 16.32284 | I56: =I54+I55 -> 16.32284 | J56: =J54+J55 -> 16.32284 | ... N56: =N54+N55 -> 16.32284 | O56: =SUM(C56:N56) -> 195.87408 | P56: Calculated value (simulated inputs) | Q56: Variable + fixed manufacturing cost
A57: Cost per good unit | B57: $/unit | C57: =IFERROR(C56/C44,0) -> 0.37503079 | D57: =IFERROR(D56/D44,0) -> 0.37503079 | E57: =IFERROR(E56/E44,0) -> 0.37503079 | F57: =IFERROR(F56/F44,0) -> 0.37503079 | G57: =IFERROR(G56/G44,0) -> 0.37503079 | H57: =IFERROR(H56/H44,0) -> 0.37503079 | I57: =IFERROR(I56/I44,0) -> 0.37503079 | J57: =IFERROR(J56/J44,0) -> 0.37503079 | ... O57: =IFERROR(O56/O44,0) -> 0.37503079 | P57: Calculated value (simulated inputs) | Q57: Total manufacturing cost / good units. Rises when yield or utilization falls
A58: Opening inventory value | B58: $m | C58: =Assumptions!$D$69 -> 14.504646 | D58: =C61 -> 15.29962 | E58: =D61 -> 15.955374 | F58: =E61 -> 15.726505 | G58: =F61 -> 16.029759 | H58: =G61 -> 16.193353 | I58: =H61 -> 15.883396 | J58: =I61 -> 15.740506 | K58: =J61 -> 15.438979 | ... N58: =M61 -> 15.185744 | O58: =C58 -> 14.504646 | P58: Calculated value (simulated inputs) | Q58: Prior month's closing value
A59: Average cost per available unit | B59: $/unit | C59: =IFERROR((C58+C56)/C46,0) -> 0.38389572 | D59: =IFERROR((D58+D56)/D46,0) -> 0.37926813 | E59: =IFERROR((E58+E56)/E46,0) -> 0.37711344 | F59: =IFERROR((F58+F56)/F46,0) -> 0.37604986 | G59: =IFERROR((G58+G56)/G46,0) -> 0.37553501 | H59: =IFERROR((H58+H56)/H46,0) -> 0.37528173 | I59: =IFERROR((I58+I56)/I46,0) -> 0.3751545 | J59: =IFERROR((J58+J56)/J46,0) -> 0.37509151 | ... N59: =IFERROR((N58+N56)/N46,0) -> 0.37503399 | P59: Calculated value (simulated inputs) | Q59: (Opening value + manufacturing cost) / available units - weighted-average costing
A60: Cost of revenue | B60: $m | C60: =C47*C59 -> 15.527866 | D60: =D47*D59 -> 15.667086 | E60: =E47*E59 -> 16.551709 | F60: =F47*F59 -> 16.019586 | G60: =G47*G59 -> 16.159246 | H60: =H47*H59 -> 16.632797 | I60: =I47*I59 -> 16.46573 | J60: =J47*J59 -> 16.624367 | ... N60: =N47*N59 -> 15.49218 | O60: =SUM(C60:N60) -> 194.36232 | P60: Calculated value (simulated inputs) | Q60: Units sold x average cost
A61: Closing inventory value | B61: $m | C61: =C58+C56-C60 -> 15.29962 | D61: =D58+D56-D60 -> 15.955374 | E61: =E58+E56-E60 -> 15.726505 | F61: =F58+F56-F60 -> 16.029759 | G61: =G58+G56-G60 -> 16.193353 | H61: =H58+H56-H60 -> 15.883396 | I61: =I58+I56-I60 -> 15.740506 | J61: =J58+J56-J60 -> 15.438979 | ... N61: =N58+N56-N60 -> 16.016404 | O61: =N61 -> 16.016404 | P61: Calculated value (simulated inputs) | Q61: Opening value + manufacturing cost - cost of revenue
A62: Contribution margin | B62: $m | C62: =C52-C47*IFERROR(C53/C43,0) -> 28.634018 | D62: =D52-D47*IFERROR(D53/D43,0) -> 29.243253 | E62: =E52-E47*IFERROR(E53/E43,0) -> 31.070956 | F62: =F52-F47*IFERROR(F53/F43,0) -> 30.157104 | G62: =G52-G47*IFERROR(G53/G43,0) -> 30.461721 | H62: =H52-H47*IFERROR(H53/H43,0) -> 31.375573 | I62: =I52-I47*IFERROR(I53/I43,0) -> 31.070956 | J62: =J52-J47*IFERROR(J53/J43,0) -> 31.375573 | ... N62: =N52-N47*IFERROR(N53/N43,0) -> 29.243253 | O62: =SUM(C62:N62) -> 365.54066 | P62: Calculated value (simulated inputs) | Q62: Revenue - units sold x variable cost per good unit (variable cost / yield)
A63: Contribution margin % | B63: % | C63: =IFERROR(C62/C52,0) -> 0.75270532 | D63: =IFERROR(D62/D52,0) -> 0.75270532 | E63: =IFERROR(E62/E52,0) -> 0.75270532 | F63: =IFERROR(F62/F52,0) -> 0.75270532 | G63: =IFERROR(G62/G52,0) -> 0.75270532 | H63: =IFERROR(H62/H52,0) -> 0.75270532 | I63: =IFERROR(I62/I52,0) -> 0.75270532 | J63: =IFERROR(J62/J52,0) -> 0.75270532 | ... O63: =IFERROR(O62/O52,0) -> 0.75270532 | P63: Calculated value (simulated inputs) | Q63: Contribution margin / revenue
A64: Gross profit | B64: $m | C64: =C52-C60 -> 22.513605 | D64: =D52-D60 -> 23.183778 | E64: =E52-E60 -> 24.727335 | F64: =F52-F60 -> 24.045369 | G64: =G52-G60 -> 24.310405 | H64: =H52-H60 -> 25.050943 | I64: =I52-I60 -> 24.813314 | J64: =J52-J60 -> 25.059373 | ... N64: =N52-N60 -> 23.358685 | O64: =SUM(C64:N64) -> 291.27349 | P64: Calculated value (simulated inputs) | Q64: Revenue - cost of revenue
A65: Gross margin % | B65: % | C65: =IFERROR(C64/C52,0) -> 0.59181742 | D65: =IFERROR(D64/D52,0) -> 0.59673777 | E65: =IFERROR(E64/E52,0) -> 0.59902877 | F65: =IFERROR(F64/F52,0) -> 0.60015964 | G65: =IFERROR(G64/G52,0) -> 0.60070706 | H65: =IFERROR(H64/H52,0) -> 0.60097637 | I65: =IFERROR(I64/I52,0) -> 0.60111164 | J65: =IFERROR(J64/J52,0) -> 0.60117862 | ... O65: =IFERROR(O64/O52,0) -> 0.59977761 | P65: Calculated value (simulated inputs) | Q65: Gross profit / revenue
A67: Embedded processors - Simulated data created for portfolio demonstration. It does not represent nonpublic Texas Instruments information.
A68: Seasonality factor | B68: x | C68: =Assumptions!C$73 -> 0.94 | D68: =Assumptions!D$73 -> 0.96 | E68: =Assumptions!E$73 -> 1.02 | F68: =Assumptions!F$73 -> 0.99 | G68: =Assumptions!G$73 -> 1 | H68: =Assumptions!H$73 -> 1.03 | I68: =Assumptions!I$73 -> 1.02 | J68: =Assumptions!J$73 -> 1.03 | ... N68: =Assumptions!N$73 -> 0.96 | O68: =SUM(C68:N68) -> 12 | P68: Calculated value (simulated inputs) | Q68: Link: Assumptions section E
A69: Customer demand | B69: m units | C69: =Assumptions!$E$63*C68/12 -> 4.0549047 | D69: =Assumptions!$E$63*D68/12 -> 4.1411793 | E69: =Assumptions!$E$63*E68/12 -> 4.400003 | F69: =Assumptions!$E$63*F68/12 -> 4.2705911 | G69: =Assumptions!$E$63*G68/12 -> 4.3137284 | H69: =Assumptions!$E$63*H68/12 -> 4.4431403 | I69: =Assumptions!$E$63*I68/12 -> 4.400003 | J69: =Assumptions!$E$63*J68/12 -> 4.4431403 | ... N69: =Assumptions!$E$63*N68/12 -> 4.1411793 | O69: =SUM(C69:N69) -> 51.764741 | P69: Calculated value (simulated inputs) | Q69: FY2026 demand x seasonality / 12
A70: Internal final-test capacity | B70: m units | C70: =Assumptions!$E$47 -> 7 | D70: =Assumptions!$E$47 -> 7 | E70: =Assumptions!$E$47 -> 7 | F70: =Assumptions!$E$47 -> 7 | G70: =Assumptions!$E$47 -> 7 | H70: =Assumptions!$E$47 -> 7 | I70: =Assumptions!$E$47 -> 7 | J70: =Assumptions!$E$47 -> 7 | ... N70: =Assumptions!$E$47 -> 7 | O70: =SUM(C70:N70) -> 84 | P70: Calculated value (simulated inputs) | Q70: Monthly capacity (Assumptions D)
A71: Capacity utilization | B71: % | C71: =Assumptions!$E$66 -> 0.78 | D71: =Assumptions!$E$66 -> 0.78 | E71: =Assumptions!$E$66 -> 0.78 | F71: =Assumptions!$E$66 -> 0.78 | G71: =Assumptions!$E$66 -> 0.78 | H71: =Assumptions!$E$66 -> 0.78 | I71: =Assumptions!$E$66 -> 0.78 | J71: =Assumptions!$E$66 -> 0.78 | ... N71: =Assumptions!$E$66 -> 0.78 | O71: =IFERROR(O72/O70,0) -> 0.78 | P71: Calculated value (simulated inputs) | Q71: Scenario utilization. FY = units produced / capacity
A72: Units produced (tested) | B72: m units | C72: =C70*C71 -> 5.46 | D72: =D70*D71 -> 5.46 | E72: =E70*E71 -> 5.46 | F72: =F70*F71 -> 5.46 | G72: =G70*G71 -> 5.46 | H72: =H70*H71 -> 5.46 | I72: =I70*I71 -> 5.46 | J72: =J70*J71 -> 5.46 | ... N72: =N70*N71 -> 5.46 | O72: =SUM(C72:N72) -> 65.52 | P72: Calculated value (simulated inputs) | Q72: Capacity x utilization
A73: Manufacturing yield (final test) | B73: % | C73: =Assumptions!$E$65 -> 0.88 | D73: =Assumptions!$E$65 -> 0.88 | E73: =Assumptions!$E$65 -> 0.88 | F73: =Assumptions!$E$65 -> 0.88 | G73: =Assumptions!$E$65 -> 0.88 | H73: =Assumptions!$E$65 -> 0.88 | I73: =Assumptions!$E$65 -> 0.88 | J73: =Assumptions!$E$65 -> 0.88 | ... N73: =Assumptions!$E$65 -> 0.88 | O73: =IFERROR(O74/O72,0) -> 0.88 | P73: Calculated value (simulated inputs) | Q73: Scenario yield. FY = good units / units produced
A74: Good units produced | B74: m units | C74: =C72*C73 -> 4.8048 | D74: =D72*D73 -> 4.8048 | E74: =E72*E73 -> 4.8048 | F74: =F72*F73 -> 4.8048 | G74: =G72*G73 -> 4.8048 | H74: =H72*H73 -> 4.8048 | I74: =I72*I73 -> 4.8048 | J74: =J72*J73 -> 4.8048 | ... N74: =N72*N73 -> 4.8048 | O74: =SUM(C74:N74) -> 57.6576 | P74: Calculated value (simulated inputs) | Q74: Units produced x yield
A75: Opening finished-goods inventory | B75: m units | C75: =Assumptions!$E$68 -> 3.957549 | D75: =C78 -> 4.7074443 | E75: =D78 -> 5.371065 | F75: =E78 -> 5.775862 | G75: =F78 -> 6.3100709 | H75: =G78 -> 6.8011424 | I75: =H78 -> 7.1628022 | J75: =I78 -> 7.5675992 | K75: =J78 -> 7.9292589 | ... N75: =M78 -> 9.1867872 | O75: =C75 -> 3.957549 | P75: Calculated value (simulated inputs) | Q75: First month: Assumptions opening balance; then prior month's closing
A76: Available good units | B76: m units | C76: =C75+C74 -> 8.762349 | D76: =D75+D74 -> 9.5122443 | E76: =E75+E74 -> 10.175865 | F76: =F75+F74 -> 10.580662 | G76: =G75+G74 -> 11.114871 | H76: =H75+H74 -> 11.605942 | I76: =I75+I74 -> 11.967602 | J76: =J75+J74 -> 12.372399 | ... N76: =N75+N74 -> 13.991587 | P76: Calculated value (simulated inputs) | Q76: Opening inventory + good units produced
A77: Units sold | B77: m units | C77: =MIN(C69,C76) -> 4.0549047 | D77: =MIN(D69,D76) -> 4.1411793 | E77: =MIN(E69,E76) -> 4.400003 | F77: =MIN(F69,F76) -> 4.2705911 | G77: =MIN(G69,G76) -> 4.3137284 | H77: =MIN(H69,H76) -> 4.4431403 | I77: =MIN(I69,I76) -> 4.400003 | J77: =MIN(J69,J76) -> 4.4431403 | ... N77: =MIN(N69,N76) -> 4.1411793 | O77: =SUM(C77:N77) -> 51.764741 | P77: Calculated value (simulated inputs) | Q77: MIN(customer demand, available good units)
A78: Closing finished-goods inventory | B78: m units | C78: =C76-C77 -> 4.7074443 | D78: =D76-D77 -> 5.371065 | E78: =E76-E77 -> 5.775862 | F78: =F76-F77 -> 6.3100709 | G78: =G76-G77 -> 6.8011424 | H78: =H76-H77 -> 7.1628022 | I78: =I76-I77 -> 7.5675992 | J78: =J76-J77 -> 7.9292589 | ... N78: =N76-N77 -> 9.8504079 | O78: =N78 -> 9.8504079 | P78: Calculated value (simulated inputs) | Q78: Available - units sold
A79: Unmet demand (supply shortfall) | B79: m units | C79: =C69-C77 -> 0 | D79: =D69-D77 -> 0 | E79: =E69-E77 -> 0 | F79: =F69-F77 -> 0 | G79: =G69-G77 -> 0 | H79: =H69-H77 -> 0 | I79: =I69-I77 -> 0 | J79: =J69-J77 -> 0 | ... N79: =N69-N77 -> 0 | O79: =SUM(C79:N79) -> 0 | P79: Calculated value (simulated inputs) | Q79: Demand - units sold. >0 means lost or delayed sales
A80: Demand / good-unit capacity (risk ratio) | B80: x | C80: =IFERROR(C69/(C70*C73),0) -> 0.65826375 | D80: =IFERROR(D69/(D70*D73),0) -> 0.67226936 | E80: =IFERROR(E69/(E70*E73),0) -> 0.7142862 | F80: =IFERROR(F69/(F70*F73),0) -> 0.69327778 | G80: =IFERROR(G69/(G70*G73),0) -> 0.70028059 | H80: =IFERROR(H69/(H70*H73),0) -> 0.72128901 | I80: =IFERROR(I69/(I70*I73),0) -> 0.7142862 | J80: =IFERROR(J69/(J70*J73),0) -> 0.72128901 | ... O80: =IFERROR(O69/(O70*O73),0) -> 0.70028059 | P80: Calculated value (simulated inputs) | Q80: Demand / (capacity x yield) = share of full-load good output needed. Feeds the risk heat map
A81: Average selling price | B81: $/unit | C81: =Assumptions!$E$64 -> 3.366 | D81: =Assumptions!$E$64 -> 3.366 | E81: =Assumptions!$E$64 -> 3.366 | F81: =Assumptions!$E$64 -> 3.366 | G81: =Assumptions!$E$64 -> 3.366 | H81: =Assumptions!$E$64 -> 3.366 | I81: =Assumptions!$E$64 -> 3.366 | J81: =Assumptions!$E$64 -> 3.366 | ... N81: =Assumptions!$E$64 -> 3.366 | O81: =IFERROR(O82/O77,0) -> 3.366 | P81: Calculated value (simulated inputs) | Q81: Scenario ASP. FY = revenue / units sold
A82: Revenue | B82: $m | C82: =C77*C81 -> 13.648809 | D82: =D77*D81 -> 13.939209 | E82: =E77*E81 -> 14.81041 | F82: =F77*F81 -> 14.37481 | G82: =G77*G81 -> 14.52001 | H82: =H77*H81 -> 14.95561 | I82: =I77*I81 -> 14.81041 | J82: =J77*J81 -> 14.95561 | ... N82: =N77*N81 -> 13.939209 | O82: =SUM(C82:N82) -> 174.24012 | P82: Calculated value (simulated inputs) | Q82: Units sold x ASP
A83: Variable cost per unit produced | B83: $/unit | C83: =Assumptions!$E$67 -> 0.9785 | D83: =Assumptions!$E$67 -> 0.9785 | E83: =Assumptions!$E$67 -> 0.9785 | F83: =Assumptions!$E$67 -> 0.9785 | G83: =Assumptions!$E$67 -> 0.9785 | H83: =Assumptions!$E$67 -> 0.9785 | I83: =Assumptions!$E$67 -> 0.9785 | J83: =Assumptions!$E$67 -> 0.9785 | ... N83: =Assumptions!$E$67 -> 0.9785 | O83: =IFERROR(O84/O72,0) -> 0.9785 | P83: Calculated value (simulated inputs) | Q83: Scenario variable cost per unit
A84: Variable manufacturing cost | B84: $m | C84: =C72*C83 -> 5.34261 | D84: =D72*D83 -> 5.34261 | E84: =E72*E83 -> 5.34261 | F84: =F72*F83 -> 5.34261 | G84: =G72*G83 -> 5.34261 | H84: =H72*H83 -> 5.34261 | I84: =I72*I83 -> 5.34261 | J84: =J72*J83 -> 5.34261 | ... N84: =N72*N83 -> 5.34261 | O84: =SUM(C84:N84) -> 64.11132 | P84: Calculated value (simulated inputs) | Q84: Units produced x variable cost per unit
A85: Fixed manufacturing cost | B85: $m | C85: =Assumptions!$E$46 -> 2.5 | D85: =Assumptions!$E$46 -> 2.5 | E85: =Assumptions!$E$46 -> 2.5 | F85: =Assumptions!$E$46 -> 2.5 | G85: =Assumptions!$E$46 -> 2.5 | H85: =Assumptions!$E$46 -> 2.5 | I85: =Assumptions!$E$46 -> 2.5 | J85: =Assumptions!$E$46 -> 2.5 | ... N85: =Assumptions!$E$46 -> 2.5 | O85: =SUM(C85:N85) -> 30 | P85: Calculated value (simulated inputs) | Q85: Monthly fixed cost (Assumptions D)
A86: Total manufacturing cost | B86: $m | C86: =C84+C85 -> 7.84261 | D86: =D84+D85 -> 7.84261 | E86: =E84+E85 -> 7.84261 | F86: =F84+F85 -> 7.84261 | G86: =G84+G85 -> 7.84261 | H86: =H84+H85 -> 7.84261 | I86: =I84+I85 -> 7.84261 | J86: =J84+J85 -> 7.84261 | ... N86: =N84+N85 -> 7.84261 | O86: =SUM(C86:N86) -> 94.11132 | P86: Calculated value (simulated inputs) | Q86: Variable + fixed manufacturing cost
A87: Cost per good unit | B87: $/unit | C87: =IFERROR(C86/C74,0) -> 1.6322448 | D87: =IFERROR(D86/D74,0) -> 1.6322448 | E87: =IFERROR(E86/E74,0) -> 1.6322448 | F87: =IFERROR(F86/F74,0) -> 1.6322448 | G87: =IFERROR(G86/G74,0) -> 1.6322448 | H87: =IFERROR(H86/H74,0) -> 1.6322448 | I87: =IFERROR(I86/I74,0) -> 1.6322448 | J87: =IFERROR(J86/J74,0) -> 1.6322448 | ... O87: =IFERROR(O86/O74,0) -> 1.6322448 | P87: Calculated value (simulated inputs) | Q87: Total manufacturing cost / good units. Rises when yield or utilization falls
A88: Opening inventory value | B88: $m | C88: =Assumptions!$E$69 -> 6.772354 | D88: =C91 -> 7.8516764 | E88: =D91 -> 8.8617397 | F88: =E91 -> 9.4814562 | G88: =F91 -> 10.331687 | H88: =G91 -> 11.120775 | I88: =H91 -> 11.703571 | J88: =I91 -> 12.359842 | K88: =J91 -> 12.947405 | ... N88: =M91 -> 14.996521 | O88: =C88 -> 6.772354 | P88: Calculated value (simulated inputs) | Q88: Prior month's closing value
A89: Average cost per available unit | B89: $/unit | C89: =IFERROR((C88+C86)/C76,0) -> 1.6679276 | D89: =IFERROR((D88+D86)/D76,0) -> 1.6499036 | E89: =IFERROR((E88+E86)/E76,0) -> 1.6415656 | F89: =IFERROR((F88+F86)/F76,0) -> 1.6373329 | G89: =IFERROR((G88+G86)/G76,0) -> 1.6351334 | H89: =IFERROR((H88+H86)/H76,0) -> 1.6339376 | I89: =IFERROR((I88+I86)/I76,0) -> 1.633258 | J89: =IFERROR((J88+J86)/J76,0) -> 1.6328645 | ... N89: =IFERROR((N88+N86)/N76,0) -> 1.6323474 | P89: Calculated value (simulated inputs) | Q89: (Opening value + manufacturing cost) / available units - weighted-average costing
A90: Cost of revenue | B90: $m | C90: =C77*C89 -> 6.7632876 | D90: =D77*D89 -> 6.8325468 | E90: =E77*E89 -> 7.2228934 | F90: =F77*F89 -> 6.9923795 | G90: =G77*G89 -> 7.0535215 | H90: =H77*H89 -> 7.2598138 | I90: =I77*I89 -> 7.1863399 | J90: =J77*J89 -> 7.2550461 | ... N90: =N77*N89 -> 6.7598432 | O90: =SUM(C90:N90) -> 84.804386 | P90: Calculated value (simulated inputs) | Q90: Units sold x average cost
A91: Closing inventory value | B91: $m | C91: =C88+C86-C90 -> 7.8516764 | D91: =D88+D86-D90 -> 8.8617397 | E91: =E88+E86-E90 -> 9.4814562 | F91: =F88+F86-F90 -> 10.331687 | G91: =G88+G86-G90 -> 11.120775 | H91: =H88+H86-H90 -> 11.703571 | I91: =I88+I86-I90 -> 12.359842 | J91: =J88+J86-J90 -> 12.947405 | ... N91: =N88+N86-N90 -> 16.079288 | O91: =N91 -> 16.079288 | P91: Calculated value (simulated inputs) | Q91: Opening value + manufacturing cost - cost of revenue
A92: Contribution margin | B92: $m | C92: =C82-C77*IFERROR(C83/C73,0) -> 9.1400317 | D92: =D82-D77*IFERROR(D83/D73,0) -> 9.3345005 | E92: =E82-E77*IFERROR(E83/E73,0) -> 9.9179067 | F92: =F82-F77*IFERROR(F83/F73,0) -> 9.6262036 | G92: =G82-G77*IFERROR(G83/G73,0) -> 9.723438 | H92: =H82-H77*IFERROR(H83/H73,0) -> 10.015141 | I92: =I82-I77*IFERROR(I83/I73,0) -> 9.9179067 | J92: =J82-J77*IFERROR(J83/J73,0) -> 10.015141 | ... N92: =N82-N77*IFERROR(N83/N73,0) -> 9.3345005 | O92: =SUM(C92:N92) -> 116.68126 | P92: Calculated value (simulated inputs) | Q92: Revenue - units sold x variable cost per good unit (variable cost / yield)
A93: Contribution margin % | B93: % | C93: =IFERROR(C92/C82,0) -> 0.66965781 | D93: =IFERROR(D92/D82,0) -> 0.66965781 | E93: =IFERROR(E92/E82,0) -> 0.66965781 | F93: =IFERROR(F92/F82,0) -> 0.66965781 | G93: =IFERROR(G92/G82,0) -> 0.66965781 | H93: =IFERROR(H92/H82,0) -> 0.66965781 | I93: =IFERROR(I92/I82,0) -> 0.66965781 | J93: =IFERROR(J92/J82,0) -> 0.66965781 | ... O93: =IFERROR(O92/O82,0) -> 0.66965781 | P93: Calculated value (simulated inputs) | Q93: Contribution margin / revenue
A94: Gross profit | B94: $m | C94: =C82-C90 -> 6.8855217 | D94: =D82-D90 -> 7.1066627 | E94: =E82-E90 -> 7.5875166 | F94: =F82-F90 -> 7.3824303 | G94: =G82-G90 -> 7.4664884 | H94: =H82-H90 -> 7.6957964 | I94: =I82-I90 -> 7.6240702 | J94: =J82-J90 -> 7.7005641 | ... N94: =N82-N90 -> 7.1793663 | O94: =SUM(C94:N94) -> 89.435732 | P94: Calculated value (simulated inputs) | Q94: Revenue - cost of revenue
A95: Gross margin % | B95: % | C95: =IFERROR(C94/C82,0) -> 0.50447783 | D95: =IFERROR(D94/D82,0) -> 0.50983255 | E95: =IFERROR(E94/E82,0) -> 0.51230969 | F95: =IFERROR(F94/F82,0) -> 0.51356717 | G95: =IFERROR(G94/G82,0) -> 0.51422061 | H95: =IFERROR(H94/H82,0) -> 0.51457589 | I95: =IFERROR(I94/I82,0) -> 0.51477779 | J95: =IFERROR(J94/J82,0) -> 0.51489468 | ... O95: =IFERROR(O94/O82,0) -> 0.51329012 | P95: Calculated value (simulated inputs) | Q95: Gross profit / revenue
A97: Division total - Simulated data created for portfolio demonstration. It does not represent nonpublic Texas Instruments information.
A98: Revenue | B98: $m | C98: =C22+C52+C82 -> 89.731753 | D98: =D22+D52+D82 -> 91.640939 | E98: =E22+E52+E82 -> 97.368497 | F98: =F22+F52+F82 -> 94.504718 | G98: =G22+G52+G82 -> 95.459311 | H98: =H22+H52+H82 -> 98.323091 | I98: =I22+I52+I82 -> 97.368497 | J98: =J22+J52+J82 -> 98.323091 | ... N98: =N22+N52+N82 -> 91.640939 | O98: =SUM(C98:N98) -> 1145.5117 | P98: Calculated value (simulated inputs) | Q98: Sum of the three product lines
A99: Variable manufacturing cost | B99: $m | C99: =C24+C54+C84 -> 25.363338 | D99: =D24+D54+D84 -> 25.363338 | E99: =E24+E54+E84 -> 25.363338 | F99: =F24+F54+F84 -> 25.363338 | G99: =G24+G54+G84 -> 25.363338 | H99: =H24+H54+H84 -> 25.363338 | I99: =I24+I54+I84 -> 25.363338 | J99: =J24+J54+J84 -> 25.363338 | ... N99: =N24+N54+N84 -> 25.363338 | O99: =SUM(C99:N99) -> 304.36006 | P99: Calculated value (simulated inputs) | Q99: Sum of the three product lines
A100: Fixed manufacturing cost | B100: $m | C100: =C25+C55+C85 -> 14.5 | D100: =D25+D55+D85 -> 14.5 | E100: =E25+E55+E85 -> 14.5 | F100: =F25+F55+F85 -> 14.5 | G100: =G25+G55+G85 -> 14.5 | H100: =H25+H55+H85 -> 14.5 | I100: =I25+I55+I85 -> 14.5 | J100: =J25+J55+J85 -> 14.5 | ... N100: =N25+N55+N85 -> 14.5 | O100: =SUM(C100:N100) -> 174 | P100: Calculated value (simulated inputs) | Q100: Sum of the three product lines
A101: Total manufacturing cost | B101: $m | C101: =C26+C56+C86 -> 39.863338 | D101: =D26+D56+D86 -> 39.863338 | E101: =E26+E56+E86 -> 39.863338 | F101: =F26+F56+F86 -> 39.863338 | G101: =G26+G56+G86 -> 39.863338 | H101: =H26+H56+H86 -> 39.863338 | I101: =I26+I56+I86 -> 39.863338 | J101: =J26+J56+J86 -> 39.863338 | ... N101: =N26+N56+N86 -> 39.863338 | O101: =SUM(C101:N101) -> 478.36006 | P101: Calculated value (simulated inputs) | Q101: Sum of the three product lines
A102: Cost of revenue | B102: $m | C102: =C30+C60+C90 -> 37.896939 | D102: =D30+D60+D90 -> 38.336775 | E102: =E30+E60+E90 -> 40.550491 | F102: =F30+F60+F90 -> 39.270015 | G102: =G30+G60+G90 -> 39.623545 | H102: =H30+H60+H90 -> 40.790287 | I102: =I30+I60+I90 -> 40.383261 | J102: =J30+J60+J90 -> 40.773595 | ... N102: =N30+N60+N90 -> 37.99746 | O102: =SUM(C102:N102) -> 476.34771 | P102: Calculated value (simulated inputs) | Q102: Sum of the three product lines
A103: Contribution margin | B103: $m | C103: =C32+C62+C92 -> 66.094486 | D103: =D32+D62+D92 -> 67.500752 | E103: =E32+E62+E92 -> 71.719549 | F103: =F32+F62+F92 -> 69.61015 | G103: =G32+G62+G92 -> 70.313283 | H103: =H32+H62+H92 -> 72.422682 | I103: =I32+I62+I92 -> 71.719549 | J103: =J32+J62+J92 -> 72.422682 | ... N103: =N32+N62+N92 -> 67.500752 | O103: =SUM(C103:N103) -> 843.7594 | P103: Calculated value (simulated inputs) | Q103: Sum of the three product lines
A104: Contribution margin % | B104: % | C104: =IFERROR(C103/C98,0) -> 0.73657857 | D104: =IFERROR(D103/D98,0) -> 0.73657857 | E104: =IFERROR(E103/E98,0) -> 0.73657857 | F104: =IFERROR(F103/F98,0) -> 0.73657857 | G104: =IFERROR(G103/G98,0) -> 0.73657857 | H104: =IFERROR(H103/H98,0) -> 0.73657857 | I104: =IFERROR(I103/I98,0) -> 0.73657857 | J104: =IFERROR(J103/J98,0) -> 0.73657857 | ... O104: =IFERROR(O103/O98,0) -> 0.73657857 | P104: Calculated value (simulated inputs) | Q104: Contribution margin / revenue
...

Sheet Revenue
A1: Monthly Revenue Forecast - FY2026 (active scenario)
A2: Revenue by product line, units in millions, $m. Simulated data created for portfolio demonstration. It does not represent nonpublic Texas Instruments information.
A3: Simulated data created for portfolio demonstration. It does not represent nonpublic Texas Instruments information.
A4: Scenario shown: | B4: =Assumptions!$C$6 -> Base
A6: Line item | B6: Units | C6: =Ops_Model!C$6 -> 46023 | D6: =Ops_Model!D$6 -> 46054 | E6: =Ops_Model!E$6 -> 46082 | F6: =Ops_Model!F$6 -> 46113 | G6: =Ops_Model!G$6 -> 46143 | H6: =Ops_Model!H$6 -> 46174 | I6: =Ops_Model!I$6 -> 46204 | J6: =Ops_Model!J$6 -> 46235 | ... N6: =Ops_Model!N$6 -> 46357 | O6: FY2026 | P6: Q1 FY26 | Q6: Q2 FY26 | R6: Q3 FY26 | S6: Q4 FY26 | T6: FY2025 base | U6: FY26 vs FY25 | V6: Classification | W6: Formula
A7: Power-management chips
A8: Units sold | B8: m units | C8: =Ops_Model!C$17 -> 64.042882 | D8: =Ops_Model!D$17 -> 65.405496 | E8: =Ops_Model!E$17 -> 69.49334 | F8: =Ops_Model!F$17 -> 67.449418 | G8: =Ops_Model!G$17 -> 68.130725 | H8: =Ops_Model!H$17 -> 70.174647 | I8: =Ops_Model!I$17 -> 69.49334 | J8: =Ops_Model!J$17 -> 70.174647 | ... N8: =Ops_Model!N$17 -> 65.405496 | O8: =SUM(C8:N8) -> 817.5687 | P8: =SUM(C8:E8) -> 198.94172 | Q8: =SUM(F8:H8) -> 205.75479 | R8: =SUM(I8:K8) -> 211.20525 | S8: =SUM(L8:N8) -> 201.66695 | T8: =Assumptions!C$52 -> 698.77667 | U8: =IFERROR(O8/T8-1,"") -> 0.17 | V8: Calculated value (simulated inputs) | W8: Link: Ops_Model units sold
A9: Revenue | B9: $m | C9: =Ops_Model!C$22 -> 38.041472 | D9: =Ops_Model!D$22 -> 38.850865 | E9: =Ops_Model!E$22 -> 41.279044 | F9: =Ops_Model!F$22 -> 40.064954 | G9: =Ops_Model!G$22 -> 40.469651 | H9: =Ops_Model!H$22 -> 41.68374 | I9: =Ops_Model!I$22 -> 41.279044 | J9: =Ops_Model!J$22 -> 41.68374 | ... N9: =Ops_Model!N$22 -> 38.850865 | O9: =SUM(C9:N9) -> 485.63581 | P9: =SUM(C9:E9) -> 118.17138 | Q9: =SUM(F9:H9) -> 122.21834 | R9: =SUM(I9:K9) -> 125.45592 | S9: =SUM(L9:N9) -> 119.79017 | T9: =Assumptions!C$42 -> 419.266 | U9: =IFERROR(O9/T9-1,"") -> 0.1583 | V9: Calculated value (simulated inputs) | W9: Link: Ops_Model revenue
A10: Average selling price | B10: $/unit | C10: =IFERROR(C9/C8,0) -> 0.594 | D10: =IFERROR(D9/D8,0) -> 0.594 | E10: =IFERROR(E9/E8,0) -> 0.594 | F10: =IFERROR(F9/F8,0) -> 0.594 | G10: =IFERROR(G9/G8,0) -> 0.594 | H10: =IFERROR(H9/H8,0) -> 0.594 | I10: =IFERROR(I9/I8,0) -> 0.594 | J10: =IFERROR(J9/J8,0) -> 0.594 | ... T10: =IFERROR(T9/T8,0) -> 0.6 | V10: Calculated value (simulated inputs) | W10: Revenue / units sold
A12: Signal-chain chips
A13: Units sold | B13: m units | C13: =Ops_Model!C$47 -> 40.448136 | D13: =Ops_Model!D$47 -> 41.308734 | E13: =Ops_Model!E$47 -> 43.89053 | F13: =Ops_Model!F$47 -> 42.599632 | G13: =Ops_Model!G$47 -> 43.029932 | H13: =Ops_Model!H$47 -> 44.32083 | I13: =Ops_Model!I$47 -> 43.89053 | J13: =Ops_Model!J$47 -> 44.32083 | ... N13: =Ops_Model!N$47 -> 41.308734 | O13: =SUM(C13:N13) -> 516.35918 | P13: =SUM(C13:E13) -> 125.6474 | Q13: =SUM(F13:H13) -> 129.95039 | R13: =SUM(I13:K13) -> 133.39279 | S13: =SUM(L13:N13) -> 127.3686 | T13: =Assumptions!D$52 -> 441.33263 | U13: =IFERROR(O13/T13-1,"") -> 0.17 | V13: Calculated value (simulated inputs) | W13: Link: Ops_Model units sold
A14: Revenue | B14: $m | C14: =Ops_Model!C$52 -> 38.041472 | D14: =Ops_Model!D$52 -> 38.850865 | E14: =Ops_Model!E$52 -> 41.279044 | F14: =Ops_Model!F$52 -> 40.064954 | G14: =Ops_Model!G$52 -> 40.469651 | H14: =Ops_Model!H$52 -> 41.68374 | I14: =Ops_Model!I$52 -> 41.279044 | J14: =Ops_Model!J$52 -> 41.68374 | ... N14: =Ops_Model!N$52 -> 38.850865 | O14: =SUM(C14:N14) -> 485.63581 | P14: =SUM(C14:E14) -> 118.17138 | Q14: =SUM(F14:H14) -> 122.21834 | R14: =SUM(I14:K14) -> 125.45592 | S14: =SUM(L14:N14) -> 119.79017 | T14: =Assumptions!D$42 -> 419.266 | U14: =IFERROR(O14/T14-1,"") -> 0.1583 | V14: Calculated value (simulated inputs) | W14: Link: Ops_Model revenue
A15: Average selling price | B15: $/unit | C15: =IFERROR(C14/C13,0) -> 0.9405 | D15: =IFERROR(D14/D13,0) -> 0.9405 | E15: =IFERROR(E14/E13,0) -> 0.9405 | F15: =IFERROR(F14/F13,0) -> 0.9405 | G15: =IFERROR(G14/G13,0) -> 0.9405 | H15: =IFERROR(H14/H13,0) -> 0.9405 | I15: =IFERROR(I14/I13,0) -> 0.9405 | J15: =IFERROR(J14/J13,0) -> 0.9405 | ... T15: =IFERROR(T14/T13,0) -> 0.95 | V15: Calculated value (simulated inputs) | W15: Revenue / units sold
A17: Embedded processors
A18: Units sold | B18: m units | C18: =Ops_Model!C$77 -> 4.0549047 | D18: =Ops_Model!D$77 -> 4.1411793 | E18: =Ops_Model!E$77 -> 4.400003 | F18: =Ops_Model!F$77 -> 4.2705911 | G18: =Ops_Model!G$77 -> 4.3137284 | H18: =Ops_Model!H$77 -> 4.4431403 | I18: =Ops_Model!I$77 -> 4.400003 | J18: =Ops_Model!J$77 -> 4.4431403 | ... N18: =Ops_Model!N$77 -> 4.1411793 | O18: =SUM(C18:N18) -> 51.764741 | P18: =SUM(C18:E18) -> 12.596087 | Q18: =SUM(F18:H18) -> 13.02746 | R18: =SUM(I18:K18) -> 13.372558 | S18: =SUM(L18:N18) -> 12.768636 | T18: =Assumptions!E$52 -> 47.490588 | U18: =IFERROR(O18/T18-1,"") -> 0.09 | V18: Calculated value (simulated inputs) | W18: Link: Ops_Model units sold
A19: Revenue | B19: $m | C19: =Ops_Model!C$82 -> 13.648809 | D19: =Ops_Model!D$82 -> 13.939209 | E19: =Ops_Model!E$82 -> 14.81041 | F19: =Ops_Model!F$82 -> 14.37481 | G19: =Ops_Model!G$82 -> 14.52001 | H19: =Ops_Model!H$82 -> 14.95561 | I19: =Ops_Model!I$82 -> 14.81041 | J19: =Ops_Model!J$82 -> 14.95561 | ... N19: =Ops_Model!N$82 -> 13.939209 | O19: =SUM(C19:N19) -> 174.24012 | P19: =SUM(C19:E19) -> 42.398429 | Q19: =SUM(F19:H19) -> 43.85043 | R19: =SUM(I19:K19) -> 45.012031 | S19: =SUM(L19:N19) -> 42.979229 | T19: =Assumptions!E$42 -> 161.468 | U19: =IFERROR(O19/T19-1,"") -> 0.0791 | V19: Calculated value (simulated inputs) | W19: Link: Ops_Model revenue
A20: Average selling price | B20: $/unit | C20: =IFERROR(C19/C18,0) -> 3.366 | D20: =IFERROR(D19/D18,0) -> 3.366 | E20: =IFERROR(E19/E18,0) -> 3.366 | F20: =IFERROR(F19/F18,0) -> 3.366 | G20: =IFERROR(G19/G18,0) -> 3.366 | H20: =IFERROR(H19/H18,0) -> 3.366 | I20: =IFERROR(I19/I18,0) -> 3.366 | J20: =IFERROR(J19/J18,0) -> 3.366 | ... T20: =IFERROR(T19/T18,0) -> 3.4 | V20: Calculated value (simulated inputs) | W20: Revenue / units sold
A22: Division
A23: Division revenue | B23: $m | C23: =C9+C14+C19 -> 89.731753 | D23: =D9+D14+D19 -> 91.640939 | E23: =E9+E14+E19 -> 97.368497 | F23: =F9+F14+F19 -> 94.504718 | G23: =G9+G14+G19 -> 95.459311 | H23: =H9+H14+H19 -> 98.323091 | I23: =I9+I14+I19 -> 97.368497 | J23: =J9+J14+J19 -> 98.323091 | ... N23: =N9+N14+N19 -> 91.640939 | O23: =SUM(C23:N23) -> 1145.5117 | P23: =SUM(C23:E23) -> 278.74119 | Q23: =SUM(F23:H23) -> 288.28712 | R23: =SUM(I23:K23) -> 295.92386 | S23: =SUM(L23:N23) -> 282.55956 | T23: =T9+T14+T19 -> 1000 | U23: =IFERROR(O23/T23-1,"") -> 0.14551173 | V23: Calculated value (simulated inputs) | W23: Sum of product lines
A24: Mix - Power-management chips | B24: % | C24: =IFERROR(C9/C23,0) -> 0.4239466 | D24: =IFERROR(D9/D23,0) -> 0.4239466 | E24: =IFERROR(E9/E23,0) -> 0.4239466 | F24: =IFERROR(F9/F23,0) -> 0.4239466 | G24: =IFERROR(G9/G23,0) -> 0.4239466 | H24: =IFERROR(H9/H23,0) -> 0.4239466 | I24: =IFERROR(I9/I23,0) -> 0.4239466 | J24: =IFERROR(J9/J23,0) -> 0.4239466 | ... T24: =IFERROR(T9/T23,0) -> 0.419266 | V24: Calculated value (simulated inputs) | W24: Product revenue / division revenue
A25: Mix - Signal-chain chips | B25: % | C25: =IFERROR(C14/C23,0) -> 0.4239466 | D25: =IFERROR(D14/D23,0) -> 0.4239466 | E25: =IFERROR(E14/E23,0) -> 0.4239466 | F25: =IFERROR(F14/F23,0) -> 0.4239466 | G25: =IFERROR(G14/G23,0) -> 0.4239466 | H25: =IFERROR(H14/H23,0) -> 0.4239466 | I25: =IFERROR(I14/I23,0) -> 0.4239466 | J25: =IFERROR(J14/J23,0) -> 0.4239466 | ... T25: =IFERROR(T14/T23,0) -> 0.419266 | V25: Calculated value (simulated inputs) | W25: Product revenue / division revenue
A26: Mix - Embedded processors | B26: % | C26: =IFERROR(C19/C23,0) -> 0.15210679 | D26: =IFERROR(D19/D23,0) -> 0.15210679 | E26: =IFERROR(E19/E23,0) -> 0.15210679 | F26: =IFERROR(F19/F23,0) -> 0.15210679 | G26: =IFERROR(G19/G23,0) -> 0.15210679 | H26: =IFERROR(H19/H23,0) -> 0.15210679 | I26: =IFERROR(I19/I23,0) -> 0.15210679 | J26: =IFERROR(J19/J23,0) -> 0.15210679 | ... T26: =IFERROR(T19/T23,0) -> 0.161468 | V26: Calculated value (simulated inputs) | W26: Product revenue / division revenue
A27: Mix total | B27: % | C27: =C24+C25+C26 -> 1 | D27: =D24+D25+D26 -> 1 | E27: =E24+E25+E26 -> 1 | F27: =F24+F25+F26 -> 1 | G27: =G24+G25+G26 -> 1 | H27: =H24+H25+H26 -> 1 | I27: =I24+I25+I26 -> 1 | J27: =J24+J25+J26 -> 1 | ... T27: =T24+T25+T26 -> 1 | V27: Calculated value (simulated inputs) | W27: Must be 100%

Sheet PnL
A1: Monthly P&L Forecast - FY2026 (active scenario)
A2: Division P&L to net income, $m. No division-level interest (financing sits at corporate). Simulated data created for portfolio demonstration. It does not represent nonpublic Texas Instruments information.
A3: Simulated data created for portfolio demonstration. It does not represent nonpublic Texas Instruments information.
A4: Scenario shown: | B4: =Assumptions!$C$6 -> Base
A6: Line item | B6: Units | C6: =Ops_Model!C$6 -> 46023 | D6: =Ops_Model!D$6 -> 46054 | E6: =Ops_Model!E$6 -> 46082 | F6: =Ops_Model!F$6 -> 46113 | G6: =Ops_Model!G$6 -> 46143 | H6: =Ops_Model!H$6 -> 46174 | I6: =Ops_Model!I$6 -> 46204 | J6: =Ops_Model!J$6 -> 46235 | ... N6: =Ops_Model!N$6 -> 46357 | O6: FY2026 | P6: Q1 FY26 | Q6: Q2 FY26 | R6: Q3 FY26 | S6: Q4 FY26 | T6: FY2025 base | U6: FY26 vs FY25 | V6: Classification | W6: Formula
A7: Income statement
A8: Revenue | B8: $m | C8: =Revenue!C$23 -> 89.731753 | D8: =Revenue!D$23 -> 91.640939 | E8: =Revenue!E$23 -> 97.368497 | F8: =Revenue!F$23 -> 94.504718 | G8: =Revenue!G$23 -> 95.459311 | H8: =Revenue!H$23 -> 98.323091 | I8: =Revenue!I$23 -> 97.368497 | J8: =Revenue!J$23 -> 98.323091 | ... N8: =Revenue!N$23 -> 91.640939 | O8: =SUM(C8:N8) -> 1145.5117 | P8: =SUM(C8:E8) -> 278.74119 | Q8: =SUM(F8:H8) -> 288.28712 | R8: =SUM(I8:K8) -> 295.92386 | S8: =SUM(L8:N8) -> 282.55956 | T8: =Assumptions!$F$32 -> 1000 | U8: =IFERROR(O8/T8-1,"") -> 0.14551173 | V8: Calculated value (simulated inputs) | W8: Link: Revenue tab
A9: Cost of revenue - manufacturing | B9: $m | C9: =Ops_Model!C$102 -> 37.896939 | D9: =Ops_Model!D$102 -> 38.336775 | E9: =Ops_Model!E$102 -> 40.550491 | F9: =Ops_Model!F$102 -> 39.270015 | G9: =Ops_Model!G$102 -> 39.623545 | H9: =Ops_Model!H$102 -> 40.790287 | I9: =Ops_Model!I$102 -> 40.383261 | J9: =Ops_Model!J$102 -> 40.773595 | ... N9: =Ops_Model!N$102 -> 37.99746 | O9: =SUM(C9:N9) -> 476.34771 | P9: =SUM(C9:E9) -> 116.78421 | Q9: =SUM(F9:H9) -> 119.68385 | R9: =SUM(I9:K9) -> 122.71928 | S9: =SUM(L9:N9) -> 117.16038 | T9: =Assumptions!$F$57 -> 427.90162 | U9: =IFERROR(O9/T9-1,"") -> 0.11321783 | V9: Calculated value (simulated inputs) | W9: Link: Ops_Model (weighted-average inventory cost)
A10: Cost of revenue - depreciation on FY2026 capex | B10: $m | C10: =FCF!C$9 -> 0 | D10: =FCF!D$9 -> 0.07477646 | E10: =FCF!E$9 -> 0.15114391 | F10: =FCF!F$9 -> 0.23228432 | G10: =FCF!G$9 -> 0.31103826 | H10: =FCF!H$9 -> 0.39058768 | I10: =FCF!I$9 -> 0.47252359 | J10: =FCF!J$9 -> 0.553664 | ... N10: =FCF!N$9 -> 0.87822566 | O10: =SUM(C10:N10) -> 5.2192378 | P10: =SUM(C10:E10) -> 0.22592037 | Q10: =SUM(F10:H10) -> 0.93391026 | R10: =SUM(I10:K10) -> 1.6617875 | S10: =SUM(L10:N10) -> 2.3976197 | T10: =0 -> 0 | V10: Calculated value (simulated inputs) | W10: Link: FCF tab section A
A11: Total cost of revenue | B11: $m | C11: =C9+C10 -> 37.896939 | D11: =D9+D10 -> 38.411551 | E11: =E9+E10 -> 40.701635 | F11: =F9+F10 -> 39.5023 | G11: =G9+G10 -> 39.934583 | H11: =H9+H10 -> 41.180875 | I11: =I9+I10 -> 40.855784 | J11: =J9+J10 -> 41.327259 | ... N11: =N9+N10 -> 38.875686 | O11: =SUM(C11:N11) -> 481.56695 | P11: =SUM(C11:E11) -> 117.01013 | Q11: =SUM(F11:H11) -> 120.61776 | R11: =SUM(I11:K11) -> 124.38106 | S11: =SUM(L11:N11) -> 119.558 | T11: =T9+T10 -> 427.90162 | U11: =IFERROR(O11/T11-1,"") -> 0.12541511 | V11: Calculated value (simulated inputs) | W11: Manufacturing + new-capex depreciation
A12: Gross profit | B12: $m | C12: =C8-C11 -> 51.834813 | D12: =D8-D11 -> 53.229388 | E12: =E8-E11 -> 56.666862 | F12: =F8-F11 -> 55.002418 | G12: =G8-G11 -> 55.524728 | H12: =H8-H11 -> 57.142216 | I12: =I8-I11 -> 56.512713 | J12: =J8-J11 -> 56.995831 | ... N12: =N8-N11 -> 52.765253 | O12: =SUM(C12:N12) -> 663.94479 | P12: =SUM(C12:E12) -> 161.73106 | Q12: =SUM(F12:H12) -> 167.66936 | R12: =SUM(I12:K12) -> 171.5428 | S12: =SUM(L12:N12) -> 163.00156 | T12: =T8-T11 -> 572.09838 | U12: =IFERROR(O12/T12-1,"") -> 0.16054303 | V12: Calculated value (simulated inputs) | W12: Revenue - cost of revenue
A13: Gross margin | B13: % | C13: =IFERROR(C12/C8,0) -> 0.57766411 | D13: =IFERROR(D12/D8,0) -> 0.58084726 | E13: =IFERROR(E12/E8,0) -> 0.58198353 | F13: =IFERROR(F12/F8,0) -> 0.58200711 | G13: =IFERROR(G12/G8,0) -> 0.58165858 | H13: =IFERROR(H12/H8,0) -> 0.58116782 | I13: =IFERROR(I12/I8,0) -> 0.58040038 | J13: =IFERROR(J12/J8,0) -> 0.579679 | ... T13: =IFERROR(T12/T8,0) -> 0.57209838 | V13: Calculated value (simulated inputs) | W13: Gross profit / revenue
A14: Research and development | B14: $m | C14: =Assumptions!$F$33*(1+Assumptions!$F$15)/12 -> 10.5 | D14: =Assumptions!$F$33*(1+Assumptions!$F$15)/12 -> 10.5 | E14: =Assumptions!$F$33*(1+Assumptions!$F$15)/12 -> 10.5 | F14: =Assumptions!$F$33*(1+Assumptions!$F$15)/12 -> 10.5 | G14: =Assumptions!$F$33*(1+Assumptions!$F$15)/12 -> 10.5 | H14: =Assumptions!$F$33*(1+Assumptions!$F$15)/12 -> 10.5 | I14: =Assumptions!$F$33*(1+Assumptions!$F$15)/12 -> 10.5 | J14: =Assumptions!$F$33*(1+Assumptions!$F$15)/12 -> 10.5 | ... N14: =Assumptions!$F$33*(1+Assumptions!$F$15)/12 -> 10.5 | O14: =SUM(C14:N14) -> 126 | P14: =SUM(C14:E14) -> 31.5 | Q14: =SUM(F14:H14) -> 31.5 | R14: =SUM(I14:K14) -> 31.5 | S14: =SUM(L14:N14) -> 31.5 | T14: =Assumptions!$F$33 -> 120 | U14: =IFERROR(O14/T14-1,"") -> 0.05 | V14: Calculated value (simulated inputs) | W14: Base-year R&D x (1 + R&D growth) / 12
A15: Selling, general and administrative | B15: $m | C15: =Assumptions!$F$34*(1+Assumptions!$F$16)/12 -> 8.5833333 | D15: =Assumptions!$F$34*(1+Assumptions!$F$16)/12 -> 8.5833333 | E15: =Assumptions!$F$34*(1+Assumptions!$F$16)/12 -> 8.5833333 | F15: =Assumptions!$F$34*(1+Assumptions!$F$16)/12 -> 8.5833333 | G15: =Assumptions!$F$34*(1+Assumptions!$F$16)/12 -> 8.5833333 | H15: =Assumptions!$F$34*(1+Assumptions!$F$16)/12 -> 8.5833333 | I15: =Assumptions!$F$34*(1+Assumptions!$F$16)/12 -> 8.5833333 | J15: =Assumptions!$F$34*(1+Assumptions!$F$16)/12 -> 8.5833333 | ... N15: =Assumptions!$F$34*(1+Assumptions!$F$16)/12 -> 8.5833333 | O15: =SUM(C15:N15) -> 103 | P15: =SUM(C15:E15) -> 25.75 | Q15: =SUM(F15:H15) -> 25.75 | R15: =SUM(I15:K15) -> 25.75 | S15: =SUM(L15:N15) -> 25.75 | T15: =Assumptions!$F$34 -> 100 | U15: =IFERROR(O15/T15-1,"") -> 0.03 | V15: Calculated value (simulated inputs) | W15: Base-year SG&A x (1 + SG&A growth) / 12
A16: Total operating expenses | B16: $m | C16: =C14+C15 -> 19.083333 | D16: =D14+D15 -> 19.083333 | E16: =E14+E15 -> 19.083333 | F16: =F14+F15 -> 19.083333 | G16: =G14+G15 -> 19.083333 | H16: =H14+H15 -> 19.083333 | I16: =I14+I15 -> 19.083333 | J16: =J14+J15 -> 19.083333 | ... N16: =N14+N15 -> 19.083333 | O16: =SUM(C16:N16) -> 229 | P16: =SUM(C16:E16) -> 57.25 | Q16: =SUM(F16:H16) -> 57.25 | R16: =SUM(I16:K16) -> 57.25 | S16: =SUM(L16:N16) -> 57.25 | T16: =T14+T15 -> 220 | U16: =IFERROR(O16/T16-1,"") -> 0.040909091 | V16: Calculated value (simulated inputs) | W16: R&D + SG&A
A17: Operating profit | B17: $m | C17: =C12-C16 -> 32.75148 | D17: =D12-D16 -> 34.146054 | E17: =E12-E16 -> 37.583529 | F17: =F12-F16 -> 35.919085 | G17: =G12-G16 -> 36.441395 | H17: =H12-H16 -> 38.058882 | I17: =I12-I16 -> 37.42938 | J17: =J12-J16 -> 37.912498 | ... N17: =N12-N16 -> 33.68192 | O17: =SUM(C17:N17) -> 434.94479 | P17: =SUM(C17:E17) -> 104.48106 | Q17: =SUM(F17:H17) -> 110.41936 | R17: =SUM(I17:K17) -> 114.2928 | S17: =SUM(L17:N17) -> 105.75156 | T17: =T12-T16 -> 352.09838 | U17: =IFERROR(O17/T17-1,"") -> 0.23529334 | V17: Calculated value (simulated inputs) | W17: Gross profit - operating expenses
A18: Operating margin | B18: % | C18: =IFERROR(C17/C8,0) -> 0.3649932 | D18: =IFERROR(D17/D8,0) -> 0.37260699 | E18: =IFERROR(E17/E8,0) -> 0.3859927 | F18: =IFERROR(F17/F8,0) -> 0.38007716 | G18: =IFERROR(G17/G8,0) -> 0.38174793 | H18: =IFERROR(H17/H8,0) -> 0.3870798 | I18: =IFERROR(I17/I8,0) -> 0.38440955 | J18: =IFERROR(J17/J8,0) -> 0.38559099 | ... T18: =IFERROR(T17/T8,0) -> 0.35209838 | V18: Calculated value (simulated inputs) | W18: Operating profit / revenue
A19: Pre-tax income | B19: $m | C19: =C17 -> 32.75148 | D19: =D17 -> 34.146054 | E19: =E17 -> 37.583529 | F19: =F17 -> 35.919085 | G19: =G17 -> 36.441395 | H19: =H17 -> 38.058882 | I19: =I17 -> 37.42938 | J19: =J17 -> 37.912498 | ... N19: =N17 -> 33.68192 | O19: =SUM(C19:N19) -> 434.94479 | P19: =SUM(C19:E19) -> 104.48106 | Q19: =SUM(F19:H19) -> 110.41936 | R19: =SUM(I19:K19) -> 114.2928 | S19: =SUM(L19:N19) -> 105.75156 | V19: Calculated value (simulated inputs) | W19: Equals operating profit (no division-level interest or other income)
A20: Income tax | B20: $m | C20: =C19*Assumptions!$F$18 -> 4.2576924 | D20: =D19*Assumptions!$F$18 -> 4.4389871 | E20: =E19*Assumptions!$F$18 -> 4.8858588 | F20: =F19*Assumptions!$F$18 -> 4.669481 | G20: =G19*Assumptions!$F$18 -> 4.7373813 | H20: =H19*Assumptions!$F$18 -> 4.9476547 | I20: =I19*Assumptions!$F$18 -> 4.8658194 | J20: =J19*Assumptions!$F$18 -> 4.9286247 | ... N20: =N19*Assumptions!$F$18 -> 4.3786496 | O20: =SUM(C20:N20) -> 56.542822 | P20: =SUM(C20:E20) -> 13.582538 | Q20: =SUM(F20:H20) -> 14.354517 | R20: =SUM(I20:K20) -> 14.858064 | S20: =SUM(L20:N20) -> 13.747703 | V20: Calculated value (simulated inputs) | W20: Pre-tax income x scenario tax rate (a loss month gives a tax credit)
A21: Net income | B21: $m | C21: =C19-C20 -> 28.493788 | D21: =D19-D20 -> 29.707067 | E21: =E19-E20 -> 32.69767 | F21: =F19-F20 -> 31.249604 | G21: =G19-G20 -> 31.704013 | H21: =H19-H20 -> 33.111228 | I21: =I19-I20 -> 32.56356 | J21: =J19-J20 -> 32.983873 | ... N21: =N19-N20 -> 29.30327 | O21: =SUM(C21:N21) -> 378.40196 | P21: =SUM(C21:E21) -> 90.898525 | Q21: =SUM(F21:H21) -> 96.064845 | R21: =SUM(I21:K21) -> 99.434736 | S21: =SUM(L21:N21) -> 92.003858 | V21: Calculated value (simulated inputs) | W21: Pre-tax income - tax
A22: Net margin | B22: % | C22: =IFERROR(C21/C8,0) -> 0.31754409 | D22: =IFERROR(D21/D8,0) -> 0.32416808 | E22: =IFERROR(E21/E8,0) -> 0.33581365 | F22: =IFERROR(F21/F8,0) -> 0.33066713 | G22: =IFERROR(G21/G8,0) -> 0.3321207 | H22: =IFERROR(H21/H8,0) -> 0.33675943 | I22: =IFERROR(I21/I8,0) -> 0.3344363 | J22: =IFERROR(J21/J8,0) -> 0.33546416 | ... S22: =IFERROR(S21/S8,0) -> 0.32560872 | V22: Calculated value (simulated inputs) | W22: Net income / revenue
A24: Memo
A25: Depreciation (from FCF tab) | B25: $m | C25: =FCF!C$11 -> 5.075 | D25: =FCF!D$11 -> 5.1497765 | E25: =FCF!E$11 -> 5.2261439 | F25: =FCF!F$11 -> 5.3072843 | G25: =FCF!G$11 -> 5.3860383 | H25: =FCF!H$11 -> 5.4655877 | I25: =FCF!I$11 -> 5.5475236 | J25: =FCF!J$11 -> 5.628664 | ... N25: =FCF!N$11 -> 5.9532257 | O25: =SUM(C25:N25) -> 66.119238 | P25: =SUM(C25:E25) -> 15.45092 | Q25: =SUM(F25:H25) -> 16.15891 | R25: =SUM(I25:K25) -> 16.886788 | S25: =SUM(L25:N25) -> 17.62262 | V25: Calculated value (simulated inputs) | W25: Link: FCF tab total depreciation
A26: EBITDA | B26: $m | C26: =C17+C25 -> 37.82648 | D26: =D17+D25 -> 39.295831 | E26: =E17+E25 -> 42.809673 | F26: =F17+F25 -> 41.226369 | G26: =G17+G25 -> 41.827433 | H26: =H17+H25 -> 43.52447 | I26: =I17+I25 -> 42.976903 | J26: =J17+J25 -> 43.541162 | ... N26: =N17+N25 -> 39.635146 | O26: =SUM(C26:N26) -> 501.06402 | P26: =SUM(C26:E26) -> 119.93198 | Q26: =SUM(F26:H26) -> 126.57827 | R26: =SUM(I26:K26) -> 131.17959 | S26: =SUM(L26:N26) -> 123.37418 | V26: Calculated value (simulated inputs) | W26: Operating profit + depreciation
A27: EBITDA margin | B27: % | C27: =IFERROR(C26/C8,0) -> 0.42155066 | D27: =IFERROR(D26/D8,0) -> 0.42880214 | E27: =IFERROR(E26/E8,0) -> 0.43966657 | F27: =IFERROR(F26/F8,0) -> 0.4362361 | G27: =IFERROR(G26/G8,0) -> 0.43817028 | H27: =IFERROR(H26/H8,0) -> 0.44266784 | I27: =IFERROR(I26/I8,0) -> 0.44138407 | J27: =IFERROR(J26/J8,0) -> 0.4428376 | ... S27: =IFERROR(S26/S8,0) -> 0.43663071 | V27: Calculated value (simulated inputs) | W27: EBITDA / revenue
A28: Contribution margin (from Ops_Model) | B28: $m | C28: =Ops_Model!C$103 -> 66.094486 | D28: =Ops_Model!D$103 -> 67.500752 | E28: =Ops_Model!E$103 -> 71.719549 | F28: =Ops_Model!F$103 -> 69.61015 | G28: =Ops_Model!G$103 -> 70.313283 | H28: =Ops_Model!H$103 -> 72.422682 | I28: =Ops_Model!I$103 -> 71.719549 | J28: =Ops_Model!J$103 -> 72.422682 | ... N28: =Ops_Model!N$103 -> 67.500752 | O28: =SUM(C28:N28) -> 843.7594 | P28: =SUM(C28:E28) -> 205.31479 | Q28: =SUM(F28:H28) -> 212.34612 | R28: =SUM(I28:K28) -> 217.97118 | S28: =SUM(L28:N28) -> 208.12732 | V28: Calculated value (simulated inputs) | W28: Revenue - variable cost of units sold

Sheet FCF
A1: Free Cash Flow Forecast - FY2026 (active scenario)
A2: FCF = net income + depreciation - capital expenditures - increase in working capital. Simulated data created for portfolio demonstration. It does not represent nonpublic Texas Instruments information.
A3: Simulated data created for portfolio demonstration. It does not represent nonpublic Texas Instruments information.
A4: Scenario shown: | B4: =Assumptions!$C$6 -> Base
A6: Line item | B6: Units | C6: =Ops_Model!C$6 -> 46023 | D6: =Ops_Model!D$6 -> 46054 | E6: =Ops_Model!E$6 -> 46082 | F6: =Ops_Model!F$6 -> 46113 | G6: =Ops_Model!G$6 -> 46143 | H6: =Ops_Model!H$6 -> 46174 | I6: =Ops_Model!I$6 -> 46204 | J6: =Ops_Model!J$6 -> 46235 | ... N6: =Ops_Model!N$6 -> 46357 | O6: FY2026 | P6: Q1 FY26 | Q6: Q2 FY26 | R6: Q3 FY26 | S6: Q4 FY26 | T6: FY2025 base | U6: FY26 vs FY25 | V6: Classification | W6: Formula
A7: A. Capital expenditures and depreciation
A8: Capital expenditures | B8: $m | C8: =Revenue!C$23*Assumptions!$F$17 -> 4.4865876 | D8: =Revenue!D$23*Assumptions!$F$17 -> 4.5820469 | E8: =Revenue!E$23*Assumptions!$F$17 -> 4.8684249 | F8: =Revenue!F$23*Assumptions!$F$17 -> 4.7252359 | G8: =Revenue!G$23*Assumptions!$F$17 -> 4.7729656 | H8: =Revenue!H$23*Assumptions!$F$17 -> 4.9161545 | I8: =Revenue!I$23*Assumptions!$F$17 -> 4.8684249 | J8: =Revenue!J$23*Assumptions!$F$17 -> 4.9161545 | ... N8: =Revenue!N$23*Assumptions!$F$17 -> 4.5820469 | O8: =SUM(C8:N8) -> 57.275587 | P8: =SUM(C8:E8) -> 13.937059 | Q8: =SUM(F8:H8) -> 14.414356 | R8: =SUM(I8:K8) -> 14.796193 | S8: =SUM(L8:N8) -> 14.127978 | V8: Calculated value (simulated inputs) | W8: Revenue x capex % (scenario). Excludes the Phase 5 test-equipment proposal
A9: Depreciation on FY2026 capex | B9: $m | C9: =0 -> 0 | D9: =SUM($C$8:C8)/Assumptions!$F$86 -> 0.07477646 | E9: =SUM($C$8:D8)/Assumptions!$F$86 -> 0.15114391 | F9: =SUM($C$8:E8)/Assumptions!$F$86 -> 0.23228432 | G9: =SUM($C$8:F8)/Assumptions!$F$86 -> 0.31103826 | H9: =SUM($C$8:G8)/Assumptions!$F$86 -> 0.39058768 | I9: =SUM($C$8:H8)/Assumptions!$F$86 -> 0.47252359 | J9: =SUM($C$8:I8)/Assumptions!$F$86 -> 0.553664 | K9: =SUM($C$8:J8)/Assumptions!$F$86 -> 0.63559991 | ... N9: =SUM($C$8:M8)/Assumptions!$F$86 -> 0.87822566 | O9: =SUM(C9:N9) -> 5.2192378 | P9: =SUM(C9:E9) -> 0.22592037 | Q9: =SUM(F9:H9) -> 0.93391026 | R9: =SUM(I9:K9) -> 1.6617875 | S9: =SUM(L9:N9) -> 2.3976197 | V9: Calculated value (simulated inputs) | W9: Straight-line over useful life; starts the month after spend
A10: Depreciation inside fixed manufacturing cost | B10: $m | C10: =Ops_Model!C$100*Assumptions!$F$85 -> 5.075 | D10: =Ops_Model!D$100*Assumptions!$F$85 -> 5.075 | E10: =Ops_Model!E$100*Assumptions!$F$85 -> 5.075 | F10: =Ops_Model!F$100*Assumptions!$F$85 -> 5.075 | G10: =Ops_Model!G$100*Assumptions!$F$85 -> 5.075 | H10: =Ops_Model!H$100*Assumptions!$F$85 -> 5.075 | I10: =Ops_Model!I$100*Assumptions!$F$85 -> 5.075 | J10: =Ops_Model!J$100*Assumptions!$F$85 -> 5.075 | ... N10: =Ops_Model!N$100*Assumptions!$F$85 -> 5.075 | O10: =SUM(C10:N10) -> 60.9 | P10: =SUM(C10:E10) -> 15.225 | Q10: =SUM(F10:H10) -> 15.225 | R10: =SUM(I10:K10) -> 15.225 | S10: =SUM(L10:N10) -> 15.225 | V10: Calculated value (simulated inputs) | W10: Fixed manufacturing cost x depreciation share
A11: Total depreciation | B11: $m | C11: =C9+C10 -> 5.075 | D11: =D9+D10 -> 5.1497765 | E11: =E9+E10 -> 5.2261439 | F11: =F9+F10 -> 5.3072843 | G11: =G9+G10 -> 5.3860383 | H11: =H9+H10 -> 5.4655877 | I11: =I9+I10 -> 5.5475236 | J11: =J9+J10 -> 5.628664 | ... N11: =N9+N10 -> 5.9532257 | O11: =SUM(C11:N11) -> 66.119238 | P11: =SUM(C11:E11) -> 15.45092 | Q11: =SUM(F11:H11) -> 16.15891 | R11: =SUM(I11:K11) -> 16.886788 | S11: =SUM(L11:N11) -> 17.62262 | V11: Calculated value (simulated inputs) | W11: Sum of the two lines above
A13: B. Operating working capital (period-end balances)
A14: Accounts receivable | B14: $m | C14: =Revenue!C$23*12*Assumptions!$F$83/365 -> 118.0034 | D14: =Revenue!D$23*12*Assumptions!$F$83/365 -> 120.51411 | E14: =Revenue!E$23*12*Assumptions!$F$83/365 -> 128.04624 | F14: =Revenue!F$23*12*Assumptions!$F$83/365 -> 124.28018 | G14: =Revenue!G$23*12*Assumptions!$F$83/365 -> 125.53553 | H14: =Revenue!H$23*12*Assumptions!$F$83/365 -> 129.3016 | I14: =Revenue!I$23*12*Assumptions!$F$83/365 -> 128.04624 | J14: =Revenue!J$23*12*Assumptions!$F$83/365 -> 129.3016 | ... N14: =Revenue!N$23*12*Assumptions!$F$83/365 -> 120.51411 | O14: =N14 -> 120.51411 | P14: =E14 -> 128.04624 | Q14: =H14 -> 129.3016 | R14: =K14 -> 131.81231 | S14: =N14 -> 120.51411 | V14: Calculated value (simulated inputs) | W14: Monthly revenue x 12 x DSO / 365
A15: Inventory (finished goods) | B15: $m | C15: =Ops_Model!C$107 -> 37.624867 | D15: =Ops_Model!D$107 -> 39.15143 | E15: =Ops_Model!E$107 -> 38.464277 | F15: =Ops_Model!F$107 -> 39.0576 | G15: =Ops_Model!G$107 -> 39.297393 | H15: =Ops_Model!H$107 -> 38.370444 | I15: =Ops_Model!I$107 -> 37.850521 | J15: =Ops_Model!J$107 -> 36.940263 | ... N15: =Ops_Model!N$107 -> 37.670815 | O15: =N15 -> 37.670815 | P15: =E15 -> 38.464277 | Q15: =H15 -> 38.370444 | R15: =K15 -> 35.241181 | S15: =N15 -> 37.670815 | V15: Calculated value (simulated inputs) | W15: Link: Ops_Model closing inventory value
A16: Accounts payable | B16: $m | C16: =Ops_Model!C$99*12*Assumptions!$F$84/365 -> 30.019074 | D16: =Ops_Model!D$99*12*Assumptions!$F$84/365 -> 30.019074 | E16: =Ops_Model!E$99*12*Assumptions!$F$84/365 -> 30.019074 | F16: =Ops_Model!F$99*12*Assumptions!$F$84/365 -> 30.019074 | G16: =Ops_Model!G$99*12*Assumptions!$F$84/365 -> 30.019074 | H16: =Ops_Model!H$99*12*Assumptions!$F$84/365 -> 30.019074 | I16: =Ops_Model!I$99*12*Assumptions!$F$84/365 -> 30.019074 | J16: =Ops_Model!J$99*12*Assumptions!$F$84/365 -> 30.019074 | ... N16: =Ops_Model!N$99*12*Assumptions!$F$84/365 -> 30.019074 | O16: =N16 -> 30.019074 | P16: =E16 -> 30.019074 | Q16: =H16 -> 30.019074 | R16: =K16 -> 30.019074 | S16: =N16 -> 30.019074 | V16: Calculated value (simulated inputs) | W16: Monthly variable manufacturing cost x 12 x DPO / 365
A17: Operating working capital | B17: $m | C17: =C14+C15-C16 -> 125.60919 | D17: =D14+D15-D16 -> 129.64647 | E17: =E14+E15-E16 -> 136.49145 | F17: =F14+F15-F16 -> 133.3187 | G17: =G14+G15-G16 -> 134.81385 | H17: =H14+H15-H16 -> 137.65297 | I17: =I14+I15-I16 -> 135.87769 | J17: =J14+J15-J16 -> 136.22279 | ... N17: =N14+N15-N16 -> 128.16585 | O17: =N17 -> 128.16585 | P17: =E17 -> 136.49145 | Q17: =H17 -> 137.65297 | R17: =K17 -> 137.03442 | S17: =N17 -> 128.16585 | V17: Calculated value (simulated inputs) | W17: AR + inventory - AP
A18: Increase in working capital | B18: $m | C18: =C17-Assumptions!$F$93 -> 5.4040356 | D18: =D17-C17 -> 4.0372741 | E18: =E17-D17 -> 6.8449787 | F18: =F17-E17 -> -3.1727434 | G18: =G17-F17 -> 1.4951482 | H18: =H17-G17 -> 2.8391169 | I18: =I17-H17 -> -1.775278 | J18: =J17-I17 -> 0.34509787 | K18: =K17-J17 -> 0.81162806 | ... N18: =N17-M17 -> -0.6448325 | O18: =SUM(C18:N18) -> 7.9606941 | P18: =SUM(C18:E18) -> 16.286288 | Q18: =SUM(F18:H18) -> 1.1615217 | R18: =SUM(I18:K18) -> -0.61855209 | S18: =SUM(L18:N18) -> -8.868564 | V18: Calculated value (simulated inputs) | W18: This month's working capital - prior month's (first month vs 31-Dec-2025 opening balance)
A20: C. Free cash flow
A21: Net income | B21: $m | C21: =PnL!C$21 -> 28.493788 | D21: =PnL!D$21 -> 29.707067 | E21: =PnL!E$21 -> 32.69767 | F21: =PnL!F$21 -> 31.249604 | G21: =PnL!G$21 -> 31.704013 | H21: =PnL!H$21 -> 33.111228 | I21: =PnL!I$21 -> 32.56356 | J21: =PnL!J$21 -> 32.983873 | ... N21: =PnL!N$21 -> 29.30327 | O21: =SUM(C21:N21) -> 378.40196 | P21: =SUM(C21:E21) -> 90.898525 | Q21: =SUM(F21:H21) -> 96.064845 | R21: =SUM(I21:K21) -> 99.434736 | S21: =SUM(L21:N21) -> 92.003858 | V21: Calculated value (simulated inputs) | W21: Link: PnL
A22: + Depreciation | B22: $m | C22: =C11 -> 5.075 | D22: =D11 -> 5.1497765 | E22: =E11 -> 5.2261439 | F22: =F11 -> 5.3072843 | G22: =G11 -> 5.3860383 | H22: =H11 -> 5.4655877 | I22: =I11 -> 5.5475236 | J22: =J11 -> 5.628664 | ... N22: =N11 -> 5.9532257 | O22: =SUM(C22:N22) -> 66.119238 | P22: =SUM(C22:E22) -> 15.45092 | Q22: =SUM(F22:H22) -> 16.15891 | R22: =SUM(I22:K22) -> 16.886788 | S22: =SUM(L22:N22) -> 17.62262 | V22: Calculated value (simulated inputs) | W22: Section A
A23: - Capital expenditures | B23: $m | C23: =-C8 -> -4.4865876 | D23: =-D8 -> -4.5820469 | E23: =-E8 -> -4.8684249 | F23: =-F8 -> -4.7252359 | G23: =-G8 -> -4.7729656 | H23: =-H8 -> -4.9161545 | I23: =-I8 -> -4.8684249 | J23: =-J8 -> -4.9161545 | ... N23: =-N8 -> -4.5820469 | O23: =SUM(C23:N23) -> -57.275587 | P23: =SUM(C23:E23) -> -13.937059 | Q23: =SUM(F23:H23) -> -14.414356 | R23: =SUM(I23:K23) -> -14.796193 | S23: =SUM(L23:N23) -> -14.127978 | V23: Calculated value (simulated inputs) | W23: Section A
A24: - Increase in working capital | B24: $m | C24: =-C18 -> -5.4040356 | D24: =-D18 -> -4.0372741 | E24: =-E18 -> -6.8449787 | F24: =-F18 -> 3.1727434 | G24: =-G18 -> -1.4951482 | H24: =-H18 -> -2.8391169 | I24: =-I18 -> 1.775278 | J24: =-J18 -> -0.34509787 | ... N24: =-N18 -> 0.6448325 | O24: =SUM(C24:N24) -> -7.9606941 | P24: =SUM(C24:E24) -> -16.286288 | Q24: =SUM(F24:H24) -> -1.1615217 | R24: =SUM(I24:K24) -> 0.61855209 | S24: =SUM(L24:N24) -> 8.868564 | V24: Calculated value (simulated inputs) | W24: Section B
A25: Free cash flow | B25: $m | C25: =C21+C22+C23+C24 -> 23.678164 | D25: =D21+D22+D23+D24 -> 26.237523 | E25: =E21+E22+E23+E24 -> 26.210411 | F25: =F21+F22+F23+F24 -> 35.004396 | G25: =G21+G22+G23+G24 -> 30.821938 | H25: =H21+H22+H23+H24 -> 30.821544 | I25: =I21+I22+I23+I24 -> 35.017937 | J25: =J21+J22+J23+J24 -> 33.351285 | ... N25: =N21+N22+N23+N24 -> 31.319282 | O25: =SUM(C25:N25) -> 379.28492 | P25: =SUM(C25:E25) -> 76.126098 | Q25: =SUM(F25:H25) -> 96.647877 | R25: =SUM(I25:K25) -> 102.14388 | S25: =SUM(L25:N25) -> 104.36706 | V25: Calculated value (simulated inputs) | W25: Net income + depreciation - capex - increase in working capital
A26: FCF margin | B26: % | C26: =IFERROR(C25/Revenue!C$23,0) -> 0.26387721 | D26: =IFERROR(D25/Revenue!D$23,0) -> 0.28630788 | E26: =IFERROR(E25/Revenue!E$23,0) -> 0.26918779 | F26: =IFERROR(F25/Revenue!F$23,0) -> 0.37039839 | G26: =IFERROR(G25/Revenue!G$23,0) -> 0.32288037 | H26: =IFERROR(H25/Revenue!H$23,0) -> 0.31347208 | I26: =IFERROR(I25/Revenue!I$23,0) -> 0.3596434 | J26: =IFERROR(J25/Revenue!J$23,0) -> 0.33920094 | ... S26: =IFERROR(S25/Revenue!S$23,0) -> 0.36936306 | V26: Calculated value (simulated inputs) | W26: FCF / revenue
A27: FCF conversion (FCF / net income) | B27: x | C27: =IFERROR(C25/C21,0) -> 0.83099392 | D27: =IFERROR(D25/D21,0) -> 0.88320811 | E27: =IFERROR(E25/E21,0) -> 0.80159872 | F27: =IFERROR(F25/F21,0) -> 1.1201549 | G27: =IFERROR(G25/G21,0) -> 0.9721778 | H27: =IFERROR(H25/H21,0) -> 0.93084872 | I27: =IFERROR(I25/I21,0) -> 1.0753719 | J27: =IFERROR(J25/J21,0) -> 1.0111391 | ... S27: =IFERROR(S25/S21,0) -> 1.134377 | V27: Calculated value (simulated inputs) | W27: FCF / net income
A28: Cumulative free cash flow | B28: $m | C28: =C25 -> 23.678164 | D28: =C28+D25 -> 49.915687 | E28: =D28+E25 -> 76.126098 | F28: =E28+F25 -> 111.13049 | G28: =F28+G25 -> 141.95243 | H28: =G28+H25 -> 172.77398 | I28: =H28+I25 -> 207.79191 | J28: =I28+J25 -> 241.1432 | K28: =J28+K25 -> 274.91786 | ... N28: =M28+N25 -> 379.28492 | O28: =N28 -> 379.28492 | P28: =E28 -> 76.126098 | Q28: =H28 -> 172.77398 | R28: =K28 -> 274.91786 | S28: =N28 -> 379.28492 | V28: Calculated value (simulated inputs) | W28: Running total from January 2026

Sheet Budget
A1: FY2026 Budget - Base scenario, LOCKED
A2: Reads the Base column (Assumptions column D) directly, so it does NOT change with the scenario selector.
A3: Simulated data created for portfolio demonstration. It does not represent nonpublic Texas Instruments information.
A6: Line item | B6: Units | C6: =Ops_Model!C$6 -> 46023 | D6: =Ops_Model!D$6 -> 46054 | E6: =Ops_Model!E$6 -> 46082 | F6: =Ops_Model!F$6 -> 46113 | G6: =Ops_Model!G$6 -> 46143 | H6: =Ops_Model!H$6 -> 46174 | I6: =Ops_Model!I$6 -> 46204 | J6: =Ops_Model!J$6 -> 46235 | ... N6: =Ops_Model!N$6 -> 46357 | O6: FY2026 | P6: YTD Jan-May | Q6: Classification | R6: Formula
A8: Budget drivers (links to the Base column of Assumptions section A)
A9: Customer demand growth | C9: =Assumptions!$D$10 -> 0.15 | Q9: User-provided assumption (Base)
A10: Average selling price change | C10: =Assumptions!$D$11 -> -0.01 | Q10: User-provided assumption (Base)
A11: Manufacturing yield change (percentage points vs base-year yield) | C11: =Assumptions!$D$12 -> 0 | Q11: User-provided assumption (Base)
A12: Capacity utilization (internal final test) | C12: =Assumptions!$D$13 -> 0.78 | Q12: User-provided assumption (Base)
A13: Material-cost inflation (variable cost per unit) | C13: =Assumptions!$D$14 -> 0.03 | Q13: User-provided assumption (Base)
A14: R&D expense growth | C14: =Assumptions!$D$15 -> 0.05 | Q14: User-provided assumption (Base)
A15: SG&A expense growth | C15: =Assumptions!$D$16 -> 0.03 | Q15: User-provided assumption (Base)
A16: Capital expenditures (% of revenue, excl. proposed test-equipment project) | C16: =Assumptions!$D$17 -> 0.05 | Q16: User-provided assumption (Base)
A18: Power-management chips - budget (Simulated data created for portfolio demonstration. It does not represent nonpublic Texas Instruments information.)
A19: Customer demand | B19: m units | C19: =Assumptions!$C$52*(1+$C$9+Assumptions!$C$48)*Assumptions!C$73/12 -> 64.042882 | D19: =Assumptions!$C$52*(1+$C$9+Assumptions!$C$48)*Assumptions!D$73/12 -> 65.405496 | E19: =Assumptions!$C$52*(1+$C$9+Assumptions!$C$48)*Assumptions!E$73/12 -> 69.49334 | F19: =Assumptions!$C$52*(1+$C$9+Assumptions!$C$48)*Assumptions!F$73/12 -> 67.449418 | G19: =Assumptions!$C$52*(1+$C$9+Assumptions!$C$48)*Assumptions!G$73/12 -> 68.130725 | H19: =Assumptions!$C$52*(1+$C$9+Assumptions!$C$48)*Assumptions!H$73/12 -> 70.174647 | I19: =Assumptions!$C$52*(1+$C$9+Assumptions!$C$48)*Assumptions!I$73/12 -> 69.49334 | J19: =Assumptions!$C$52*(1+$C$9+Assumptions!$C$48)*Assumptions!J$73/12 -> 70.174647 | ... N19: =Assumptions!$C$52*(1+$C$9+Assumptions!$C$48)*Assumptions!N$73/12 -> 65.405496 | O19: =SUM(C19:N19) -> 817.5687 | P19: =SUM(C19:G19) -> 334.52186 | Q19: Calculated value (budget)
A20: Internal final-test capacity | B20: m units | C20: =Assumptions!$C$47 -> 88 | D20: =Assumptions!$C$47 -> 88 | E20: =Assumptions!$C$47 -> 88 | F20: =Assumptions!$C$47 -> 88 | G20: =Assumptions!$C$47 -> 88 | H20: =Assumptions!$C$47 -> 88 | I20: =Assumptions!$C$47 -> 88 | J20: =Assumptions!$C$47 -> 88 | ... N20: =Assumptions!$C$47 -> 88 | O20: =SUM(C20:N20) -> 1056 | P20: =SUM(C20:G20) -> 440 | Q20: Calculated value (budget)
A21: Capacity utilization | B21: % | C21: =$C$12 -> 0.78 | D21: =$C$12 -> 0.78 | E21: =$C$12 -> 0.78 | F21: =$C$12 -> 0.78 | G21: =$C$12 -> 0.78 | H21: =$C$12 -> 0.78 | I21: =$C$12 -> 0.78 | J21: =$C$12 -> 0.78 | ... N21: =$C$12 -> 0.78 | O21: =IFERROR(O22/O20,0) -> 0.78 | P21: =IFERROR(P22/P20,0) -> 0.78 | Q21: Calculated value (budget)
A22: Units produced (tested) | B22: m units | C22: =C20*C21 -> 68.64 | D22: =D20*D21 -> 68.64 | E22: =E20*E21 -> 68.64 | F22: =F20*F21 -> 68.64 | G22: =G20*G21 -> 68.64 | H22: =H20*H21 -> 68.64 | I22: =I20*I21 -> 68.64 | J22: =J20*J21 -> 68.64 | ... N22: =N20*N21 -> 68.64 | O22: =SUM(C22:N22) -> 823.68 | P22: =SUM(C22:G22) -> 343.2 | Q22: Calculated value (budget) | R22: Capacity x utilization
A23: Manufacturing yield (final test) | B23: % | C23: =MIN(1,MAX(0,Assumptions!$C$44+$C$11)) -> 0.95 | D23: =MIN(1,MAX(0,Assumptions!$C$44+$C$11)) -> 0.95 | E23: =MIN(1,MAX(0,Assumptions!$C$44+$C$11)) -> 0.95 | F23: =MIN(1,MAX(0,Assumptions!$C$44+$C$11)) -> 0.95 | G23: =MIN(1,MAX(0,Assumptions!$C$44+$C$11)) -> 0.95 | H23: =MIN(1,MAX(0,Assumptions!$C$44+$C$11)) -> 0.95 | I23: =MIN(1,MAX(0,Assumptions!$C$44+$C$11)) -> 0.95 | J23: =MIN(1,MAX(0,Assumptions!$C$44+$C$11)) -> 0.95 | ... N23: =MIN(1,MAX(0,Assumptions!$C$44+$C$11)) -> 0.95 | O23: =IFERROR(O24/O22,0) -> 0.95 | P23: =IFERROR(P24/P22,0) -> 0.95 | Q23: Calculated value (budget)
A24: Good units produced | B24: m units | C24: =C22*C23 -> 65.208 | D24: =D22*D23 -> 65.208 | E24: =E22*E23 -> 65.208 | F24: =F22*F23 -> 65.208 | G24: =G22*G23 -> 65.208 | H24: =H22*H23 -> 65.208 | I24: =I22*I23 -> 65.208 | J24: =J22*J23 -> 65.208 | ... N24: =N22*N23 -> 65.208 | O24: =SUM(C24:N24) -> 782.496 | P24: =SUM(C24:G24) -> 326.04 | Q24: Calculated value (budget) | R24: Units produced x yield
A25: Opening finished-goods inventory | B25: m units | C25: =Assumptions!$C$68 -> 58.231389 | D25: =C28 -> 59.396507 | E25: =D28 -> 59.199011 | F25: =E28 -> 54.913672 | G25: =F28 -> 52.672254 | H25: =G28 -> 49.749529 | I25: =H28 -> 44.782882 | J25: =I28 -> 40.497543 | K25: =J28 -> 35.530896 | ... N25: =M28 -> 23.356185 | O25: =C25 -> 58.231389 | P25: =C25 -> 58.231389 | Q25: Calculated value (budget)
A26: Available good units | B26: m units | C26: =C25+C24 -> 123.43939 | D26: =D25+D24 -> 124.60451 | E26: =E25+E24 -> 124.40701 | F26: =F25+F24 -> 120.12167 | G26: =G25+G24 -> 117.88025 | H26: =H25+H24 -> 114.95753 | I26: =I25+I24 -> 109.99088 | J26: =J25+J24 -> 105.70554 | ... N26: =N25+N24 -> 88.564185 | Q26: Calculated value (budget)
A27: Units sold | B27: m units | C27: =MIN(C19,C26) -> 64.042882 | D27: =MIN(D19,D26) -> 65.405496 | E27: =MIN(E19,E26) -> 69.49334 | F27: =MIN(F19,F26) -> 67.449418 | G27: =MIN(G19,G26) -> 68.130725 | H27: =MIN(H19,H26) -> 70.174647 | I27: =MIN(I19,I26) -> 69.49334 | J27: =MIN(J19,J26) -> 70.174647 | ... N27: =MIN(N19,N26) -> 65.405496 | O27: =SUM(C27:N27) -> 817.5687 | P27: =SUM(C27:G27) -> 334.52186 | Q27: Calculated value (budget) | R27: MIN(demand, available)
A28: Closing finished-goods inventory | B28: m units | C28: =C26-C27 -> 59.396507 | D28: =D26-D27 -> 59.199011 | E28: =E26-E27 -> 54.913672 | F28: =F26-F27 -> 52.672254 | G28: =G26-G27 -> 49.749529 | H28: =H26-H27 -> 44.782882 | I28: =I26-I27 -> 40.497543 | J28: =J26-J27 -> 35.530896 | ... N28: =N26-N27 -> 23.158689 | O28: =N28 -> 23.158689 | P28: =G28 -> 49.749529 | Q28: Calculated value (budget) | R28: Available - sold
A29: Unmet demand | B29: m units | C29: =C19-C27 -> 0 | D29: =D19-D27 -> 0 | E29: =E19-E27 -> 0 | F29: =F19-F27 -> 0 | G29: =G19-G27 -> 0 | H29: =H19-H27 -> 0 | I29: =I19-I27 -> 0 | J29: =J19-J27 -> 0 | ... N29: =N19-N27 -> 0 | O29: =SUM(C29:N29) -> 0 | P29: =SUM(C29:G29) -> 0 | Q29: Calculated value (budget)
A30: Average selling price | B30: $/unit | C30: =Assumptions!$C$43*(1+$C$10) -> 0.594 | D30: =Assumptions!$C$43*(1+$C$10) -> 0.594 | E30: =Assumptions!$C$43*(1+$C$10) -> 0.594 | F30: =Assumptions!$C$43*(1+$C$10) -> 0.594 | G30: =Assumptions!$C$43*(1+$C$10) -> 0.594 | H30: =Assumptions!$C$43*(1+$C$10) -> 0.594 | I30: =Assumptions!$C$43*(1+$C$10) -> 0.594 | J30: =Assumptions!$C$43*(1+$C$10) -> 0.594 | ... N30: =Assumptions!$C$43*(1+$C$10) -> 0.594 | O30: =IFERROR(O31/O27,0) -> 0.594 | P30: =IFERROR(P31/P27,0) -> 0.594 | Q30: Calculated value (budget)
A31: Revenue | B31: $m | C31: =C27*C30 -> 38.041472 | D31: =D27*D30 -> 38.850865 | E31: =E27*E30 -> 41.279044 | F31: =F27*F30 -> 40.064954 | G31: =G27*G30 -> 40.469651 | H31: =H27*H30 -> 41.68374 | I31: =I27*I30 -> 41.279044 | J31: =J27*J30 -> 41.68374 | ... N31: =N27*N30 -> 38.850865 | O31: =SUM(C31:N31) -> 485.63581 | P31: =SUM(C31:G31) -> 198.70598 | Q31: Calculated value (budget) | R31: Units sold x ASP
A32: Variable cost per unit produced | B32: $/unit | C32: =Assumptions!$C$45*(1+$C$13) -> 0.1442 | D32: =Assumptions!$C$45*(1+$C$13) -> 0.1442 | E32: =Assumptions!$C$45*(1+$C$13) -> 0.1442 | F32: =Assumptions!$C$45*(1+$C$13) -> 0.1442 | G32: =Assumptions!$C$45*(1+$C$13) -> 0.1442 | H32: =Assumptions!$C$45*(1+$C$13) -> 0.1442 | I32: =Assumptions!$C$45*(1+$C$13) -> 0.1442 | J32: =Assumptions!$C$45*(1+$C$13) -> 0.1442 | ... N32: =Assumptions!$C$45*(1+$C$13) -> 0.1442 | O32: =IFERROR(O33/O22,0) -> 0.1442 | P32: =IFERROR(P33/P22,0) -> 0.1442 | Q32: Calculated value (budget)
A33: Variable manufacturing cost | B33: $m | C33: =C22*C32 -> 9.897888 | D33: =D22*D32 -> 9.897888 | E33: =E22*E32 -> 9.897888 | F33: =F22*F32 -> 9.897888 | G33: =G22*G32 -> 9.897888 | H33: =H22*H32 -> 9.897888 | I33: =I22*I32 -> 9.897888 | J33: =J22*J32 -> 9.897888 | ... N33: =N22*N32 -> 9.897888 | O33: =SUM(C33:N33) -> 118.77466 | P33: =SUM(C33:G33) -> 49.48944 | Q33: Calculated value (budget) | R33: Units produced x variable cost
A34: Fixed manufacturing cost | B34: $m | C34: =Assumptions!$C$46 -> 5.8 | D34: =Assumptions!$C$46 -> 5.8 | E34: =Assumptions!$C$46 -> 5.8 | F34: =Assumptions!$C$46 -> 5.8 | G34: =Assumptions!$C$46 -> 5.8 | H34: =Assumptions!$C$46 -> 5.8 | I34: =Assumptions!$C$46 -> 5.8 | J34: =Assumptions!$C$46 -> 5.8 | ... N34: =Assumptions!$C$46 -> 5.8 | O34: =SUM(C34:N34) -> 69.6 | P34: =SUM(C34:G34) -> 29 | Q34: Calculated value (budget)
A35: Total manufacturing cost | B35: $m | C35: =C33+C34 -> 15.697888 | D35: =D33+D34 -> 15.697888 | E35: =E33+E34 -> 15.697888 | F35: =F33+F34 -> 15.697888 | G35: =G33+G34 -> 15.697888 | H35: =H33+H34 -> 15.697888 | I35: =I33+I34 -> 15.697888 | J35: =J33+J34 -> 15.697888 | ... N35: =N33+N34 -> 15.697888 | O35: =SUM(C35:N35) -> 188.37466 | P35: =SUM(C35:G35) -> 78.48944 | Q35: Calculated value (budget) | R35: Variable + fixed
A36: Cost per good unit | B36: $/unit | C36: =IFERROR(C35/C24,0) -> 0.24073562 | D36: =IFERROR(D35/D24,0) -> 0.24073562 | E36: =IFERROR(E35/E24,0) -> 0.24073562 | F36: =IFERROR(F35/F24,0) -> 0.24073562 | G36: =IFERROR(G35/G24,0) -> 0.24073562 | H36: =IFERROR(H35/H24,0) -> 0.24073562 | I36: =IFERROR(I35/I24,0) -> 0.24073562 | J36: =IFERROR(J35/J24,0) -> 0.24073562 | ... P36: =IFERROR(P35/P24,0) -> 0.24073562 | Q36: Calculated value (budget)
A37: Opening inventory value | B37: $m | C37: =Assumptions!$C$69 -> 14.381468 | D37: =C40 -> 14.47357 | E37: =D40 -> 14.334317 | F37: =E40 -> 13.256316 | G37: =F40 -> 12.696154 | H37: =G40 -> 11.983264 | I37: =H40 -> 10.783476 | J37: =I40 -> 9.7501734 | K37: =J40 -> 8.553879 | ... N37: =M40 -> 5.622672 | O37: =C37 -> 14.381468 | P37: =C37 -> 14.381468 | Q37: Calculated value (budget)
A38: Average cost per available unit | B38: $/unit | C38: =IFERROR((C37+C35)/C26,0) -> 0.24367713 | D38: =IFERROR((D37+D35)/D26,0) -> 0.24213778 | E38: =IFERROR((E37+E35)/E26,0) -> 0.24140283 | F38: =IFERROR((F37+F35)/F26,0) -> 0.24104063 | G38: =IFERROR((G37+G35)/G26,0) -> 0.24087191 | H38: =IFERROR((H37+H35)/H26,0) -> 0.2407946 | I38: =IFERROR((I37+I35)/I26,0) -> 0.24075963 | J38: =IFERROR((J37+J35)/J26,0) -> 0.24074482 | ... N38: =IFERROR((N37+N35)/N26,0) -> 0.24073569 | Q38: Calculated value (budget) | R38: Weighted-average cost
A39: Cost of revenue (manufacturing) | B39: $m | C39: =C27*C38 -> 15.605785 | D39: =D27*D38 -> 15.837141 | E39: =E27*E38 -> 16.775889 | F39: =F27*F38 -> 16.25805 | G39: =G27*G38 -> 16.410778 | H39: =H27*H38 -> 16.897676 | I39: =I27*I38 -> 16.731191 | J39: =J27*J38 -> 16.894182 | ... N39: =N27*N38 -> 15.745437 | O39: =SUM(C39:N39) -> 197.181 | P39: =SUM(C39:G39) -> 80.887644 | Q39: Calculated value (budget) | R39: Units sold x average cost
A40: Closing inventory value | B40: $m | C40: =C37+C35-C39 -> 14.47357 | D40: =D37+D35-D39 -> 14.334317 | E40: =E37+E35-E39 -> 13.256316 | F40: =F37+F35-F39 -> 12.696154 | G40: =G37+G35-G39 -> 11.983264 | H40: =H37+H35-H39 -> 10.783476 | I40: =I37+I35-I39 -> 9.7501734 | J40: =J37+J35-J39 -> 8.553879 | ... N40: =N37+N35-N39 -> 5.5751229 | O40: =N40 -> 5.5751229 | P40: =G40 -> 11.983264 | Q40: Calculated value (budget) | R40: Opening + manufacturing cost - cost of revenue
A41: Gross profit (before new-capex depreciation) | B41: $m | C41: =C31-C39 -> 22.435686 | D41: =D31-D39 -> 23.013723 | E41: =E31-E39 -> 24.503155 | F41: =F31-F39 -> 23.806904 | G41: =G31-G39 -> 24.058873 | H41: =H31-H39 -> 24.786064 | I41: =I31-I39 -> 24.547853 | J41: =J31-J39 -> 24.789558 | ... N41: =N31-N39 -> 23.105428 | O41: =SUM(C41:N41) -> 288.45481 | P41: =SUM(C41:G41) -> 117.81834 | Q41: Calculated value (budget) | R41: Revenue - cost of revenue
A42: Gross margin | B42: % | C42: =IFERROR(C41/C31,0) -> 0.58976914 | D42: =IFERROR(D41/D31,0) -> 0.59236065 | E42: =IFERROR(E41/E31,0) -> 0.59359792 | F42: =IFERROR(F41/F31,0) -> 0.59420769 | G42: =IFERROR(G41/G31,0) -> 0.59449174 | H42: =IFERROR(H41/H31,0) -> 0.59462189 | I42: =IFERROR(I41/I31,0) -> 0.59468076 | J42: =IFERROR(J41/J31,0) -> 0.5947057 | ... P42: =IFERROR(P41/P31,0) -> 0.59292799 | Q42: Calculated value (budget)
A44: Signal-chain chips - budget (Simulated data created for portfolio demonstration. It does not represent nonpublic Texas Instruments information.)
A45: Customer demand | B45: m units | C45: =Assumptions!$D$52*(1+$C$9+Assumptions!$D$48)*Assumptions!C$73/12 -> 40.448136 | D45: =Assumptions!$D$52*(1+$C$9+Assumptions!$D$48)*Assumptions!D$73/12 -> 41.308734 | E45: =Assumptions!$D$52*(1+$C$9+Assumptions!$D$48)*Assumptions!E$73/12 -> 43.89053 | F45: =Assumptions!$D$52*(1+$C$9+Assumptions!$D$48)*Assumptions!F$73/12 -> 42.599632 | G45: =Assumptions!$D$52*(1+$C$9+Assumptions!$D$48)*Assumptions!G$73/12 -> 43.029932 | H45: =Assumptions!$D$52*(1+$C$9+Assumptions!$D$48)*Assumptions!H$73/12 -> 44.32083 | I45: =Assumptions!$D$52*(1+$C$9+Assumptions!$D$48)*Assumptions!I$73/12 -> 43.89053 | J45: =Assumptions!$D$52*(1+$C$9+Assumptions!$D$48)*Assumptions!J$73/12 -> 44.32083 | ... N45: =Assumptions!$D$52*(1+$C$9+Assumptions!$D$48)*Assumptions!N$73/12 -> 41.308734 | O45: =SUM(C45:N45) -> 516.35918 | P45: =SUM(C45:G45) -> 211.27696 | Q45: Calculated value (budget)
A46: Internal final-test capacity | B46: m units | C46: =Assumptions!$D$47 -> 60 | D46: =Assumptions!$D$47 -> 60 | E46: =Assumptions!$D$47 -> 60 | F46: =Assumptions!$D$47 -> 60 | G46: =Assumptions!$D$47 -> 60 | H46: =Assumptions!$D$47 -> 60 | I46: =Assumptions!$D$47 -> 60 | J46: =Assumptions!$D$47 -> 60 | ... N46: =Assumptions!$D$47 -> 60 | O46: =SUM(C46:N46) -> 720 | P46: =SUM(C46:G46) -> 300 | Q46: Calculated value (budget)
A47: Capacity utilization | B47: % | C47: =$C$12 -> 0.78 | D47: =$C$12 -> 0.78 | E47: =$C$12 -> 0.78 | F47: =$C$12 -> 0.78 | G47: =$C$12 -> 0.78 | H47: =$C$12 -> 0.78 | I47: =$C$12 -> 0.78 | J47: =$C$12 -> 0.78 | ... N47: =$C$12 -> 0.78 | O47: =IFERROR(O48/O46,0) -> 0.78 | P47: =IFERROR(P48/P46,0) -> 0.78 | Q47: Calculated value (budget)
A48: Units produced (tested) | B48: m units | C48: =C46*C47 -> 46.8 | D48: =D46*D47 -> 46.8 | E48: =E46*E47 -> 46.8 | F48: =F46*F47 -> 46.8 | G48: =G46*G47 -> 46.8 | H48: =H46*H47 -> 46.8 | I48: =I46*I47 -> 46.8 | J48: =J46*J47 -> 46.8 | ... N48: =N46*N47 -> 46.8 | O48: =SUM(C48:N48) -> 561.6 | P48: =SUM(C48:G48) -> 234 | Q48: Calculated value (budget) | R48: Capacity x utilization
A49: Manufacturing yield (final test) | B49: % | C49: =MIN(1,MAX(0,Assumptions!$D$44+$C$11)) -> 0.93 | D49: =MIN(1,MAX(0,Assumptions!$D$44+$C$11)) -> 0.93 | E49: =MIN(1,MAX(0,Assumptions!$D$44+$C$11)) -> 0.93 | F49: =MIN(1,MAX(0,Assumptions!$D$44+$C$11)) -> 0.93 | G49: =MIN(1,MAX(0,Assumptions!$D$44+$C$11)) -> 0.93 | H49: =MIN(1,MAX(0,Assumptions!$D$44+$C$11)) -> 0.93 | I49: =MIN(1,MAX(0,Assumptions!$D$44+$C$11)) -> 0.93 | J49: =MIN(1,MAX(0,Assumptions!$D$44+$C$11)) -> 0.93 | ... N49: =MIN(1,MAX(0,Assumptions!$D$44+$C$11)) -> 0.93 | O49: =IFERROR(O50/O48,0) -> 0.93 | P49: =IFERROR(P50/P48,0) -> 0.93 | Q49: Calculated value (budget)
A50: Good units produced | B50: m units | C50: =C48*C49 -> 43.524 | D50: =D48*D49 -> 43.524 | E50: =E48*E49 -> 43.524 | F50: =F48*F49 -> 43.524 | G50: =G48*G49 -> 43.524 | H50: =H48*H49 -> 43.524 | I50: =I48*I49 -> 43.524 | J50: =J48*J49 -> 43.524 | ... N50: =N48*N49 -> 43.524 | O50: =SUM(C50:N50) -> 522.288 | P50: =SUM(C50:G50) -> 217.62 | Q50: Calculated value (budget) | R50: Units produced x yield
A51: Opening finished-goods inventory | B51: m units | C51: =Assumptions!$D$68 -> 36.777719 | D51: =C54 -> 39.853584 | E51: =D54 -> 42.068849 | F51: =E54 -> 41.702319 | G51: =F54 -> 42.626687 | H51: =G54 -> 43.120755 | I51: =H54 -> 42.323926 | J51: =I54 -> 41.957395 | K51: =J54 -> 41.160566 | ... N51: =M54 -> 40.491275 | O51: =C51 -> 36.777719 | P51: =C51 -> 36.777719 | Q51: Calculated value (budget)
A52: Available good units | B52: m units | C52: =C51+C50 -> 80.301719 | D52: =D51+D50 -> 83.377584 | E52: =E51+E50 -> 85.592849 | F52: =F51+F50 -> 85.226319 | G52: =G51+G50 -> 86.150687 | H52: =H51+H50 -> 86.644755 | I52: =I51+I50 -> 85.847926 | J52: =J51+J50 -> 85.481395 | ... N52: =N51+N50 -> 84.015275 | Q52: Calculated value (budget)
A53: Units sold | B53: m units | C53: =MIN(C45,C52) -> 40.448136 | D53: =MIN(D45,D52) -> 41.308734 | E53: =MIN(E45,E52) -> 43.89053 | F53: =MIN(F45,F52) -> 42.599632 | G53: =MIN(G45,G52) -> 43.029932 | H53: =MIN(H45,H52) -> 44.32083 | I53: =MIN(I45,I52) -> 43.89053 | J53: =MIN(J45,J52) -> 44.32083 | ... N53: =MIN(N45,N52) -> 41.308734 | O53: =SUM(C53:N53) -> 516.35918 | P53: =SUM(C53:G53) -> 211.27696 | Q53: Calculated value (budget) | R53: MIN(demand, available)
A54: Closing finished-goods inventory | B54: m units | C54: =C52-C53 -> 39.853584 | D54: =D52-D53 -> 42.068849 | E54: =E52-E53 -> 41.702319 | F54: =F52-F53 -> 42.626687 | G54: =G52-G53 -> 43.120755 | H54: =H52-H53 -> 42.323926 | I54: =I52-I53 -> 41.957395 | J54: =J52-J53 -> 41.160566 | ... N54: =N52-N53 -> 42.70654 | O54: =N54 -> 42.70654 | P54: =G54 -> 43.120755 | Q54: Calculated value (budget) | R54: Available - sold
A55: Unmet demand | B55: m units | C55: =C45-C53 -> 0 | D55: =D45-D53 -> 0 | E55: =E45-E53 -> 0 | F55: =F45-F53 -> 0 | G55: =G45-G53 -> 0 | H55: =H45-H53 -> 0 | I55: =I45-I53 -> 0 | J55: =J45-J53 -> 0 | ... N55: =N45-N53 -> 0 | O55: =SUM(C55:N55) -> 0 | P55: =SUM(C55:G55) -> 0 | Q55: Calculated value (budget)
A56: Average selling price | B56: $/unit | C56: =Assumptions!$D$43*(1+$C$10) -> 0.9405 | D56: =Assumptions!$D$43*(1+$C$10) -> 0.9405 | E56: =Assumptions!$D$43*(1+$C$10) -> 0.9405 | F56: =Assumptions!$D$43*(1+$C$10) -> 0.9405 | G56: =Assumptions!$D$43*(1+$C$10) -> 0.9405 | H56: =Assumptions!$D$43*(1+$C$10) -> 0.9405 | I56: =Assumptions!$D$43*(1+$C$10) -> 0.9405 | J56: =Assumptions!$D$43*(1+$C$10) -> 0.9405 | ... N56: =Assumptions!$D$43*(1+$C$10) -> 0.9405 | O56: =IFERROR(O57/O53,0) -> 0.9405 | P56: =IFERROR(P57/P53,0) -> 0.9405 | Q56: Calculated value (budget)
A57: Revenue | B57: $m | C57: =C53*C56 -> 38.041472 | D57: =D53*D56 -> 38.850865 | E57: =E53*E56 -> 41.279044 | F57: =F53*F56 -> 40.064954 | G57: =G53*G56 -> 40.469651 | H57: =H53*H56 -> 41.68374 | I57: =I53*I56 -> 41.279044 | J57: =J53*J56 -> 41.68374 | ... N57: =N53*N56 -> 38.850865 | O57: =SUM(C57:N57) -> 485.63581 | P57: =SUM(C57:G57) -> 198.70598 | Q57: Calculated value (budget) | R57: Units sold x ASP
A58: Variable cost per unit produced | B58: $/unit | C58: =Assumptions!$D$45*(1+$C$13) -> 0.2163 | D58: =Assumptions!$D$45*(1+$C$13) -> 0.2163 | E58: =Assumptions!$D$45*(1+$C$13) -> 0.2163 | F58: =Assumptions!$D$45*(1+$C$13) -> 0.2163 | G58: =Assumptions!$D$45*(1+$C$13) -> 0.2163 | H58: =Assumptions!$D$45*(1+$C$13) -> 0.2163 | I58: =Assumptions!$D$45*(1+$C$13) -> 0.2163 | J58: =Assumptions!$D$45*(1+$C$13) -> 0.2163 | ... N58: =Assumptions!$D$45*(1+$C$13) -> 0.2163 | O58: =IFERROR(O59/O48,0) -> 0.2163 | P58: =IFERROR(P59/P48,0) -> 0.2163 | Q58: Calculated value (budget)
A59: Variable manufacturing cost | B59: $m | C59: =C48*C58 -> 10.12284 | D59: =D48*D58 -> 10.12284 | E59: =E48*E58 -> 10.12284 | F59: =F48*F58 -> 10.12284 | G59: =G48*G58 -> 10.12284 | H59: =H48*H58 -> 10.12284 | I59: =I48*I58 -> 10.12284 | J59: =J48*J58 -> 10.12284 | ... N59: =N48*N58 -> 10.12284 | O59: =SUM(C59:N59) -> 121.47408 | P59: =SUM(C59:G59) -> 50.6142 | Q59: Calculated value (budget) | R59: Units produced x variable cost
A60: Fixed manufacturing cost | B60: $m | C60: =Assumptions!$D$46 -> 6.2 | D60: =Assumptions!$D$46 -> 6.2 | E60: =Assumptions!$D$46 -> 6.2 | F60: =Assumptions!$D$46 -> 6.2 | G60: =Assumptions!$D$46 -> 6.2 | H60: =Assumptions!$D$46 -> 6.2 | I60: =Assumptions!$D$46 -> 6.2 | J60: =Assumptions!$D$46 -> 6.2 | ... N60: =Assumptions!$D$46 -> 6.2 | O60: =SUM(C60:N60) -> 74.4 | P60: =SUM(C60:G60) -> 31 | Q60: Calculated value (budget)
A61: Total manufacturing cost | B61: $m | C61: =C59+C60 -> 16.32284 | D61: =D59+D60 -> 16.32284 | E61: =E59+E60 -> 16.32284 | F61: =F59+F60 -> 16.32284 | G61: =G59+G60 -> 16.32284 | H61: =H59+H60 -> 16.32284 | I61: =I59+I60 -> 16.32284 | J61: =J59+J60 -> 16.32284 | ... N61: =N59+N60 -> 16.32284 | O61: =SUM(C61:N61) -> 195.87408 | P61: =SUM(C61:G61) -> 81.6142 | Q61: Calculated value (budget) | R61: Variable + fixed
A62: Cost per good unit | B62: $/unit | C62: =IFERROR(C61/C50,0) -> 0.37503079 | D62: =IFERROR(D61/D50,0) -> 0.37503079 | E62: =IFERROR(E61/E50,0) -> 0.37503079 | F62: =IFERROR(F61/F50,0) -> 0.37503079 | G62: =IFERROR(G61/G50,0) -> 0.37503079 | H62: =IFERROR(H61/H50,0) -> 0.37503079 | I62: =IFERROR(I61/I50,0) -> 0.37503079 | J62: =IFERROR(J61/J50,0) -> 0.37503079 | ... P62: =IFERROR(P61/P50,0) -> 0.37503079 | Q62: Calculated value (budget)
A63: Opening inventory value | B63: $m | C63: =Assumptions!$D$69 -> 14.504646 | D63: =C66 -> 15.29962 | E63: =D66 -> 15.955374 | F63: =E66 -> 15.726505 | G63: =F66 -> 16.029759 | H63: =G66 -> 16.193353 | I63: =H66 -> 15.883396 | J63: =I66 -> 15.740506 | K63: =J66 -> 15.438979 | ... N63: =M66 -> 15.185744 | O63: =C63 -> 14.504646 | P63: =C63 -> 14.504646 | Q63: Calculated value (budget)
A64: Average cost per available unit | B64: $/unit | C64: =IFERROR((C63+C61)/C52,0) -> 0.38389572 | D64: =IFERROR((D63+D61)/D52,0) -> 0.37926813 | E64: =IFERROR((E63+E61)/E52,0) -> 0.37711344 | F64: =IFERROR((F63+F61)/F52,0) -> 0.37604986 | G64: =IFERROR((G63+G61)/G52,0) -> 0.37553501 | H64: =IFERROR((H63+H61)/H52,0) -> 0.37528173 | I64: =IFERROR((I63+I61)/I52,0) -> 0.3751545 | J64: =IFERROR((J63+J61)/J52,0) -> 0.37509151 | ... N64: =IFERROR((N63+N61)/N52,0) -> 0.37503399 | Q64: Calculated value (budget) | R64: Weighted-average cost
A65: Cost of revenue (manufacturing) | B65: $m | C65: =C53*C64 -> 15.527866 | D65: =D53*D64 -> 15.667086 | E65: =E53*E64 -> 16.551709 | F65: =F53*F64 -> 16.019586 | G65: =G53*G64 -> 16.159246 | H65: =H53*H64 -> 16.632797 | I65: =I53*I64 -> 16.46573 | J65: =J53*J64 -> 16.624367 | ... N65: =N53*N64 -> 15.49218 | O65: =SUM(C65:N65) -> 194.36232 | P65: =SUM(C65:G65) -> 79.925493 | Q65: Calculated value (budget) | R65: Units sold x average cost
A66: Closing inventory value | B66: $m | C66: =C63+C61-C65 -> 15.29962 | D66: =D63+D61-D65 -> 15.955374 | E66: =E63+E61-E65 -> 15.726505 | F66: =F63+F61-F65 -> 16.029759 | G66: =G63+G61-G65 -> 16.193353 | H66: =H63+H61-H65 -> 15.883396 | I66: =I63+I61-I65 -> 15.740506 | J66: =J63+J61-J65 -> 15.438979 | ... N66: =N63+N61-N65 -> 16.016404 | O66: =N66 -> 16.016404 | P66: =G66 -> 16.193353 | Q66: Calculated value (budget) | R66: Opening + manufacturing cost - cost of revenue
A67: Gross profit (before new-capex depreciation) | B67: $m | C67: =C57-C65 -> 22.513605 | D67: =D57-D65 -> 23.183778 | E67: =E57-E65 -> 24.727335 | F67: =F57-F65 -> 24.045369 | G67: =G57-G65 -> 24.310405 | H67: =H57-H65 -> 25.050943 | I67: =I57-I65 -> 24.813314 | J67: =J57-J65 -> 25.059373 | ... N67: =N57-N65 -> 23.358685 | O67: =SUM(C67:N67) -> 291.27349 | P67: =SUM(C67:G67) -> 118.78049 | Q67: Calculated value (budget) | R67: Revenue - cost of revenue
A68: Gross margin | B68: % | C68: =IFERROR(C67/C57,0) -> 0.59181742 | D68: =IFERROR(D67/D57,0) -> 0.59673777 | E68: =IFERROR(E67/E57,0) -> 0.59902877 | F68: =IFERROR(F67/F57,0) -> 0.60015964 | G68: =IFERROR(G67/G57,0) -> 0.60070706 | H68: =IFERROR(H67/H57,0) -> 0.60097637 | I68: =IFERROR(I67/I57,0) -> 0.60111164 | J68: =IFERROR(J67/J57,0) -> 0.60117862 | ... P68: =IFERROR(P67/P57,0) -> 0.59777008 | Q68: Calculated value (budget)
A70: Embedded processors - budget (Simulated data created for portfolio demonstration. It does not represent nonpublic Texas Instruments information.)
A71: Customer demand | B71: m units | C71: =Assumptions!$E$52*(1+$C$9+Assumptions!$E$48)*Assumptions!C$73/12 -> 4.0549047 | D71: =Assumptions!$E$52*(1+$C$9+Assumptions!$E$48)*Assumptions!D$73/12 -> 4.1411793 | E71: =Assumptions!$E$52*(1+$C$9+Assumptions!$E$48)*Assumptions!E$73/12 -> 4.400003 | F71: =Assumptions!$E$52*(1+$C$9+Assumptions!$E$48)*Assumptions!F$73/12 -> 4.2705911 | G71: =Assumptions!$E$52*(1+$C$9+Assumptions!$E$48)*Assumptions!G$73/12 -> 4.3137284 | H71: =Assumptions!$E$52*(1+$C$9+Assumptions!$E$48)*Assumptions!H$73/12 -> 4.4431403 | I71: =Assumptions!$E$52*(1+$C$9+Assumptions!$E$48)*Assumptions!I$73/12 -> 4.400003 | J71: =Assumptions!$E$52*(1+$C$9+Assumptions!$E$48)*Assumptions!J$73/12 -> 4.4431403 | ... N71: =Assumptions!$E$52*(1+$C$9+Assumptions!$E$48)*Assumptions!N$73/12 -> 4.1411793 | O71: =SUM(C71:N71) -> 51.764741 | P71: =SUM(C71:G71) -> 21.180407 | Q71: Calculated value (budget)
A72: Internal final-test capacity | B72: m units | C72: =Assumptions!$E$47 -> 7 | D72: =Assumptions!$E$47 -> 7 | E72: =Assumptions!$E$47 -> 7 | F72: =Assumptions!$E$47 -> 7 | G72: =Assumptions!$E$47 -> 7 | H72: =Assumptions!$E$47 -> 7 | I72: =Assumptions!$E$47 -> 7 | J72: =Assumptions!$E$47 -> 7 | ... N72: =Assumptions!$E$47 -> 7 | O72: =SUM(C72:N72) -> 84 | P72: =SUM(C72:G72) -> 35 | Q72: Calculated value (budget)
A73: Capacity utilization | B73: % | C73: =$C$12 -> 0.78 | D73: =$C$12 -> 0.78 | E73: =$C$12 -> 0.78 | F73: =$C$12 -> 0.78 | G73: =$C$12 -> 0.78 | H73: =$C$12 -> 0.78 | I73: =$C$12 -> 0.78 | J73: =$C$12 -> 0.78 | ... N73: =$C$12 -> 0.78 | O73: =IFERROR(O74/O72,0) -> 0.78 | P73: =IFERROR(P74/P72,0) -> 0.78 | Q73: Calculated value (budget)
A74: Units produced (tested) | B74: m units | C74: =C72*C73 -> 5.46 | D74: =D72*D73 -> 5.46 | E74: =E72*E73 -> 5.46 | F74: =F72*F73 -> 5.46 | G74: =G72*G73 -> 5.46 | H74: =H72*H73 -> 5.46 | I74: =I72*I73 -> 5.46 | J74: =J72*J73 -> 5.46 | ... N74: =N72*N73 -> 5.46 | O74: =SUM(C74:N74) -> 65.52 | P74: =SUM(C74:G74) -> 27.3 | Q74: Calculated value (budget) | R74: Capacity x utilization
A75: Manufacturing yield (final test) | B75: % | C75: =MIN(1,MAX(0,Assumptions!$E$44+$C$11)) -> 0.88 | D75: =MIN(1,MAX(0,Assumptions!$E$44+$C$11)) -> 0.88 | E75: =MIN(1,MAX(0,Assumptions!$E$44+$C$11)) -> 0.88 | F75: =MIN(1,MAX(0,Assumptions!$E$44+$C$11)) -> 0.88 | G75: =MIN(1,MAX(0,Assumptions!$E$44+$C$11)) -> 0.88 | H75: =MIN(1,MAX(0,Assumptions!$E$44+$C$11)) -> 0.88 | I75: =MIN(1,MAX(0,Assumptions!$E$44+$C$11)) -> 0.88 | J75: =MIN(1,MAX(0,Assumptions!$E$44+$C$11)) -> 0.88 | ... N75: =MIN(1,MAX(0,Assumptions!$E$44+$C$11)) -> 0.88 | O75: =IFERROR(O76/O74,0) -> 0.88 | P75: =IFERROR(P76/P74,0) -> 0.88 | Q75: Calculated value (budget)
A76: Good units produced | B76: m units | C76: =C74*C75 -> 4.8048 | D76: =D74*D75 -> 4.8048 | E76: =E74*E75 -> 4.8048 | F76: =F74*F75 -> 4.8048 | G76: =G74*G75 -> 4.8048 | H76: =H74*H75 -> 4.8048 | I76: =I74*I75 -> 4.8048 | J76: =J74*J75 -> 4.8048 | ... N76: =N74*N75 -> 4.8048 | O76: =SUM(C76:N76) -> 57.6576 | P76: =SUM(C76:G76) -> 24.024 | Q76: Calculated value (budget) | R76: Units produced x yield
A77: Opening finished-goods inventory | B77: m units | C77: =Assumptions!$E$68 -> 3.957549 | D77: =C80 -> 4.7074443 | E77: =D80 -> 5.371065 | F77: =E80 -> 5.775862 | G77: =F80 -> 6.3100709 | H77: =G80 -> 6.8011424 | I77: =H80 -> 7.1628022 | J77: =I80 -> 7.5675992 | K77: =J80 -> 7.9292589 | ... N77: =M80 -> 9.1867872 | O77: =C77 -> 3.957549 | P77: =C77 -> 3.957549 | Q77: Calculated value (budget)
A78: Available good units | B78: m units | C78: =C77+C76 -> 8.762349 | D78: =D77+D76 -> 9.5122443 | E78: =E77+E76 -> 10.175865 | F78: =F77+F76 -> 10.580662 | G78: =G77+G76 -> 11.114871 | H78: =H77+H76 -> 11.605942 | I78: =I77+I76 -> 11.967602 | J78: =J77+J76 -> 12.372399 | ... N78: =N77+N76 -> 13.991587 | Q78: Calculated value (budget)
A79: Units sold | B79: m units | C79: =MIN(C71,C78) -> 4.0549047 | D79: =MIN(D71,D78) -> 4.1411793 | E79: =MIN(E71,E78) -> 4.400003 | F79: =MIN(F71,F78) -> 4.2705911 | G79: =MIN(G71,G78) -> 4.3137284 | H79: =MIN(H71,H78) -> 4.4431403 | I79: =MIN(I71,I78) -> 4.400003 | J79: =MIN(J71,J78) -> 4.4431403 | ... N79: =MIN(N71,N78) -> 4.1411793 | O79: =SUM(C79:N79) -> 51.764741 | P79: =SUM(C79:G79) -> 21.180407 | Q79: Calculated value (budget) | R79: MIN(demand, available)
A80: Closing finished-goods inventory | B80: m units | C80: =C78-C79 -> 4.7074443 | D80: =D78-D79 -> 5.371065 | E80: =E78-E79 -> 5.775862 | F80: =F78-F79 -> 6.3100709 | G80: =G78-G79 -> 6.8011424 | H80: =H78-H79 -> 7.1628022 | I80: =I78-I79 -> 7.5675992 | J80: =J78-J79 -> 7.9292589 | ... N80: =N78-N79 -> 9.8504079 | O80: =N80 -> 9.8504079 | P80: =G80 -> 6.8011424 | Q80: Calculated value (budget) | R80: Available - sold
A81: Unmet demand | B81: m units | C81: =C71-C79 -> 0 | D81: =D71-D79 -> 0 | E81: =E71-E79 -> 0 | F81: =F71-F79 -> 0 | G81: =G71-G79 -> 0 | H81: =H71-H79 -> 0 | I81: =I71-I79 -> 0 | J81: =J71-J79 -> 0 | ... N81: =N71-N79 -> 0 | O81: =SUM(C81:N81) -> 0 | P81: =SUM(C81:G81) -> 0 | Q81: Calculated value (budget)
A82: Average selling price | B82: $/unit | C82: =Assumptions!$E$43*(1+$C$10) -> 3.366 | D82: =Assumptions!$E$43*(1+$C$10) -> 3.366 | E82: =Assumptions!$E$43*(1+$C$10) -> 3.366 | F82: =Assumptions!$E$43*(1+$C$10) -> 3.366 | G82: =Assumptions!$E$43*(1+$C$10) -> 3.366 | H82: =Assumptions!$E$43*(1+$C$10) -> 3.366 | I82: =Assumptions!$E$43*(1+$C$10) -> 3.366 | J82: =Assumptions!$E$43*(1+$C$10) -> 3.366 | ... N82: =Assumptions!$E$43*(1+$C$10) -> 3.366 | O82: =IFERROR(O83/O79,0) -> 3.366 | P82: =IFERROR(P83/P79,0) -> 3.366 | Q82: Calculated value (budget)
A83: Revenue | B83: $m | C83: =C79*C82 -> 13.648809 | D83: =D79*D82 -> 13.939209 | E83: =E79*E82 -> 14.81041 | F83: =F79*F82 -> 14.37481 | G83: =G79*G82 -> 14.52001 | H83: =H79*H82 -> 14.95561 | I83: =I79*I82 -> 14.81041 | J83: =J79*J82 -> 14.95561 | ... N83: =N79*N82 -> 13.939209 | O83: =SUM(C83:N83) -> 174.24012 | P83: =SUM(C83:G83) -> 71.293249 | Q83: Calculated value (budget) | R83: Units sold x ASP
A84: Variable cost per unit produced | B84: $/unit | C84: =Assumptions!$E$45*(1+$C$13) -> 0.9785 | D84: =Assumptions!$E$45*(1+$C$13) -> 0.9785 | E84: =Assumptions!$E$45*(1+$C$13) -> 0.9785 | F84: =Assumptions!$E$45*(1+$C$13) -> 0.9785 | G84: =Assumptions!$E$45*(1+$C$13) -> 0.9785 | H84: =Assumptions!$E$45*(1+$C$13) -> 0.9785 | I84: =Assumptions!$E$45*(1+$C$13) -> 0.9785 | J84: =Assumptions!$E$45*(1+$C$13) -> 0.9785 | ... N84: =Assumptions!$E$45*(1+$C$13) -> 0.9785 | O84: =IFERROR(O85/O74,0) -> 0.9785 | P84: =IFERROR(P85/P74,0) -> 0.9785 | Q84: Calculated value (budget)
A85: Variable manufacturing cost | B85: $m | C85: =C74*C84 -> 5.34261 | D85: =D74*D84 -> 5.34261 | E85: =E74*E84 -> 5.34261 | F85: =F74*F84 -> 5.34261 | G85: =G74*G84 -> 5.34261 | H85: =H74*H84 -> 5.34261 | I85: =I74*I84 -> 5.34261 | J85: =J74*J84 -> 5.34261 | ... N85: =N74*N84 -> 5.34261 | O85: =SUM(C85:N85) -> 64.11132 | P85: =SUM(C85:G85) -> 26.71305 | Q85: Calculated value (budget) | R85: Units produced x variable cost
A86: Fixed manufacturing cost | B86: $m | C86: =Assumptions!$E$46 -> 2.5 | D86: =Assumptions!$E$46 -> 2.5 | E86: =Assumptions!$E$46 -> 2.5 | F86: =Assumptions!$E$46 -> 2.5 | G86: =Assumptions!$E$46 -> 2.5 | H86: =Assumptions!$E$46 -> 2.5 | I86: =Assumptions!$E$46 -> 2.5 | J86: =Assumptions!$E$46 -> 2.5 | ... N86: =Assumptions!$E$46 -> 2.5 | O86: =SUM(C86:N86) -> 30 | P86: =SUM(C86:G86) -> 12.5 | Q86: Calculated value (budget)
A87: Total manufacturing cost | B87: $m | C87: =C85+C86 -> 7.84261 | D87: =D85+D86 -> 7.84261 | E87: =E85+E86 -> 7.84261 | F87: =F85+F86 -> 7.84261 | G87: =G85+G86 -> 7.84261 | H87: =H85+H86 -> 7.84261 | I87: =I85+I86 -> 7.84261 | J87: =J85+J86 -> 7.84261 | ... N87: =N85+N86 -> 7.84261 | O87: =SUM(C87:N87) -> 94.11132 | P87: =SUM(C87:G87) -> 39.21305 | Q87: Calculated value (budget) | R87: Variable + fixed
A88: Cost per good unit | B88: $/unit | C88: =IFERROR(C87/C76,0) -> 1.6322448 | D88: =IFERROR(D87/D76,0) -> 1.6322448 | E88: =IFERROR(E87/E76,0) -> 1.6322448 | F88: =IFERROR(F87/F76,0) -> 1.6322448 | G88: =IFERROR(G87/G76,0) -> 1.6322448 | H88: =IFERROR(H87/H76,0) -> 1.6322448 | I88: =IFERROR(I87/I76,0) -> 1.6322448 | J88: =IFERROR(J87/J76,0) -> 1.6322448 | ... P88: =IFERROR(P87/P76,0) -> 1.6322448 | Q88: Calculated value (budget)
A89: Opening inventory value | B89: $m | C89: =Assumptions!$E$69 -> 6.772354 | D89: =C92 -> 7.8516764 | E89: =D92 -> 8.8617397 | F89: =E92 -> 9.4814562 | G89: =F92 -> 10.331687 | H89: =G92 -> 11.120775 | I89: =H92 -> 11.703571 | J89: =I92 -> 12.359842 | K89: =J92 -> 12.947405 | ... N89: =M92 -> 14.996521 | O89: =C89 -> 6.772354 | P89: =C89 -> 6.772354 | Q89: Calculated value (budget)
A90: Average cost per available unit | B90: $/unit | C90: =IFERROR((C89+C87)/C78,0) -> 1.6679276 | D90: =IFERROR((D89+D87)/D78,0) -> 1.6499036 | E90: =IFERROR((E89+E87)/E78,0) -> 1.6415656 | F90: =IFERROR((F89+F87)/F78,0) -> 1.6373329 | G90: =IFERROR((G89+G87)/G78,0) -> 1.6351334 | H90: =IFERROR((H89+H87)/H78,0) -> 1.6339376 | I90: =IFERROR((I89+I87)/I78,0) -> 1.633258 | J90: =IFERROR((J89+J87)/J78,0) -> 1.6328645 | ... N90: =IFERROR((N89+N87)/N78,0) -> 1.6323474 | Q90: Calculated value (budget) | R90: Weighted-average cost
A91: Cost of revenue (manufacturing) | B91: $m | C91: =C79*C90 -> 6.7632876 | D91: =D79*D90 -> 6.8325468 | E91: =E79*E90 -> 7.2228934 | F91: =F79*F90 -> 6.9923795 | G91: =G79*G90 -> 7.0535215 | H91: =H79*H90 -> 7.2598138 | I91: =I79*I90 -> 7.1863399 | J91: =J79*J90 -> 7.2550461 | ... N91: =N79*N90 -> 6.7598432 | O91: =SUM(C91:N91) -> 84.804386 | P91: =SUM(C91:G91) -> 34.864629 | Q91: Calculated value (budget) | R91: Units sold x average cost
A92: Closing inventory value | B92: $m | C92: =C89+C87-C91 -> 7.8516764 | D92: =D89+D87-D91 -> 8.8617397 | E92: =E89+E87-E91 -> 9.4814562 | F92: =F89+F87-F91 -> 10.331687 | G92: =G89+G87-G91 -> 11.120775 | H92: =H89+H87-H91 -> 11.703571 | I92: =I89+I87-I91 -> 12.359842 | J92: =J89+J87-J91 -> 12.947405 | ... N92: =N89+N87-N91 -> 16.079288 | O92: =N92 -> 16.079288 | P92: =G92 -> 11.120775 | Q92: Calculated value (budget) | R92: Opening + manufacturing cost - cost of revenue
A93: Gross profit (before new-capex depreciation) | B93: $m | C93: =C83-C91 -> 6.8855217 | D93: =D83-D91 -> 7.1066627 | E93: =E83-E91 -> 7.5875166 | F93: =F83-F91 -> 7.3824303 | G93: =G83-G91 -> 7.4664884 | H93: =H83-H91 -> 7.6957964 | I93: =I83-I91 -> 7.6240702 | J93: =J83-J91 -> 7.7005641 | ... N93: =N83-N91 -> 7.1793663 | O93: =SUM(C93:N93) -> 89.435732 | P93: =SUM(C93:G93) -> 36.42862 | Q93: Calculated value (budget) | R93: Revenue - cost of revenue
A94: Gross margin | B94: % | C94: =IFERROR(C93/C83,0) -> 0.50447783 | D94: =IFERROR(D93/D83,0) -> 0.50983255 | E94: =IFERROR(E93/E83,0) -> 0.51230969 | F94: =IFERROR(F93/F83,0) -> 0.51356717 | G94: =IFERROR(G93/G83,0) -> 0.51422061 | H94: =IFERROR(H93/H83,0) -> 0.51457589 | I94: =IFERROR(I93/I83,0) -> 0.51477779 | J94: =IFERROR(J93/J83,0) -> 0.51489468 | ... P94: =IFERROR(P93/P83,0) -> 0.51096872 | Q94: Calculated value (budget)
A96: Division budget P&L to operating profit (Simulated data created for portfolio demonstration. It does not represent nonpublic Texas Instruments information.)
A97: Revenue | B97: $m | C97: =C31+C57+C83 -> 89.731753 | D97: =D31+D57+D83 -> 91.640939 | E97: =E31+E57+E83 -> 97.368497 | F97: =F31+F57+F83 -> 94.504718 | G97: =G31+G57+G83 -> 95.459311 | H97: =H31+H57+H83 -> 98.323091 | I97: =I31+I57+I83 -> 97.368497 | J97: =J31+J57+J83 -> 98.323091 | ... N97: =N31+N57+N83 -> 91.640939 | O97: =SUM(C97:N97) -> 1145.5117 | P97: =SUM(C97:G97) -> 468.70522 | Q97: Calculated value (budget)
A98: Variable manufacturing cost | B98: $m | C98: =C33+C59+C85 -> 25.363338 | D98: =D33+D59+D85 -> 25.363338 | E98: =E33+E59+E85 -> 25.363338 | F98: =F33+F59+F85 -> 25.363338 | G98: =G33+G59+G85 -> 25.363338 | H98: =H33+H59+H85 -> 25.363338 | I98: =I33+I59+I85 -> 25.363338 | J98: =J33+J59+J85 -> 25.363338 | ... N98: =N33+N59+N85 -> 25.363338 | O98: =SUM(C98:N98) -> 304.36006 | P98: =SUM(C98:G98) -> 126.81669 | Q98: Calculated value (budget)
A99: Fixed manufacturing cost | B99: $m | C99: =C34+C60+C86 -> 14.5 | D99: =D34+D60+D86 -> 14.5 | E99: =E34+E60+E86 -> 14.5 | F99: =F34+F60+F86 -> 14.5 | G99: =G34+G60+G86 -> 14.5 | H99: =H34+H60+H86 -> 14.5 | I99: =I34+I60+I86 -> 14.5 | J99: =J34+J60+J86 -> 14.5 | ... N99: =N34+N60+N86 -> 14.5 | O99: =SUM(C99:N99) -> 174 | P99: =SUM(C99:G99) -> 72.5 | Q99: Calculated value (budget)
A100: Cost of revenue - manufacturing | B100: $m | C100: =C39+C65+C91 -> 37.896939 | D100: =D39+D65+D91 -> 38.336775 | E100: =E39+E65+E91 -> 40.550491 | F100: =F39+F65+F91 -> 39.270015 | G100: =G39+G65+G91 -> 39.623545 | H100: =H39+H65+H91 -> 40.790287 | I100: =I39+I65+I91 -> 40.383261 | J100: =J39+J65+J91 -> 40.773595 | ... N100: =N39+N65+N91 -> 37.99746 | O100: =SUM(C100:N100) -> 476.34771 | P100: =SUM(C100:G100) -> 195.67777 | Q100: Calculated value (budget)
A101: Capital expenditures | B101: $m | C101: =C97*$C$16 -> 4.4865876 | D101: =D97*$C$16 -> 4.5820469 | E101: =E97*$C$16 -> 4.8684249 | F101: =F97*$C$16 -> 4.7252359 | G101: =G97*$C$16 -> 4.7729656 | H101: =H97*$C$16 -> 4.9161545 | I101: =I97*$C$16 -> 4.8684249 | J101: =J97*$C$16 -> 4.9161545 | ... N101: =N97*$C$16 -> 4.5820469 | O101: =SUM(C101:N101) -> 57.275587 | P101: =SUM(C101:G101) -> 23.435261 | Q101: Calculated value (budget)
A102: Depreciation on FY2026 capex | B102: $m | C102: =0 -> 0 | D102: =SUM($C$101:C101)/Assumptions!$F$86 -> 0.07477646 | E102: =SUM($C$101:D101)/Assumptions!$F$86 -> 0.15114391 | F102: =SUM($C$101:E101)/Assumptions!$F$86 -> 0.23228432 | G102: =SUM($C$101:F101)/Assumptions!$F$86 -> 0.31103826 | H102: =SUM($C$101:G101)/Assumptions!$F$86 -> 0.39058768 | I102: =SUM($C$101:H101)/Assumptions!$F$86 -> 0.47252359 | J102: =SUM($C$101:I101)/Assumptions!$F$86 -> 0.553664 | K102: =SUM($C$101:J101)/Assumptions!$F$86 -> 0.63559991 | ... N102: =SUM($C$101:M101)/Assumptions!$F$86 -> 0.87822566 | O102: =SUM(C102:N102) -> 5.2192378 | P102: =SUM(C102:G102) -> 0.76924295 | Q102: Calculated value (budget)
A103: Total cost of revenue | B103: $m | C103: =C100+C102 -> 37.896939 | D103: =D100+D102 -> 38.411551 | E103: =E100+E102 -> 40.701635 | F103: =F100+F102 -> 39.5023 | G103: =G100+G102 -> 39.934583 | H103: =H100+H102 -> 41.180875 | I103: =I100+I102 -> 40.855784 | J103: =J100+J102 -> 41.327259 | ... N103: =N100+N102 -> 38.875686 | O103: =SUM(C103:N103) -> 481.56695 | P103: =SUM(C103:G103) -> 196.44701 | Q103: Calculated value (budget)
A104: Gross profit | B104: $m | C104: =C97-C103 -> 51.834813 | D104: =D97-D103 -> 53.229388 | E104: =E97-E103 -> 56.666862 | F104: =F97-F103 -> 55.002418 | G104: =G97-G103 -> 55.524728 | H104: =H97-H103 -> 57.142216 | I104: =I97-I103 -> 56.512713 | J104: =J97-J103 -> 56.995831 | ... N104: =N97-N103 -> 52.765253 | O104: =SUM(C104:N104) -> 663.94479 | P104: =SUM(C104:G104) -> 272.25821 | Q104: Calculated value (budget)
A105: Gross margin | B105: % | C105: =IFERROR(C104/C97,0) -> 0.57766411 | D105: =IFERROR(D104/D97,0) -> 0.58084726 | E105: =IFERROR(E104/E97,0) -> 0.58198353 | F105: =IFERROR(F104/F97,0) -> 0.58200711 | G105: =IFERROR(G104/G97,0) -> 0.58165858 | H105: =IFERROR(H104/H97,0) -> 0.58116782 | I105: =IFERROR(I104/I97,0) -> 0.58040038 | J105: =IFERROR(J104/J97,0) -> 0.579679 | ... P105: =IFERROR(P104/P97,0) -> 0.58087301 | Q105: Calculated value (budget)
A106: Research and development | B106: $m | C106: =Assumptions!$F$33*(1+$C$14)/12 -> 10.5 | D106: =Assumptions!$F$33*(1+$C$14)/12 -> 10.5 | E106: =Assumptions!$F$33*(1+$C$14)/12 -> 10.5 | F106: =Assumptions!$F$33*(1+$C$14)/12 -> 10.5 | G106: =Assumptions!$F$33*(1+$C$14)/12 -> 10.5 | H106: =Assumptions!$F$33*(1+$C$14)/12 -> 10.5 | I106: =Assumptions!$F$33*(1+$C$14)/12 -> 10.5 | J106: =Assumptions!$F$33*(1+$C$14)/12 -> 10.5 | ... N106: =Assumptions!$F$33*(1+$C$14)/12 -> 10.5 | O106: =SUM(C106:N106) -> 126 | P106: =SUM(C106:G106) -> 52.5 | Q106: Calculated value (budget)
A107: Selling, general and administrative | B107: $m | C107: =Assumptions!$F$34*(1+$C$15)/12 -> 8.5833333 | D107: =Assumptions!$F$34*(1+$C$15)/12 -> 8.5833333 | E107: =Assumptions!$F$34*(1+$C$15)/12 -> 8.5833333 | F107: =Assumptions!$F$34*(1+$C$15)/12 -> 8.5833333 | G107: =Assumptions!$F$34*(1+$C$15)/12 -> 8.5833333 | H107: =Assumptions!$F$34*(1+$C$15)/12 -> 8.5833333 | I107: =Assumptions!$F$34*(1+$C$15)/12 -> 8.5833333 | J107: =Assumptions!$F$34*(1+$C$15)/12 -> 8.5833333 | ... N107: =Assumptions!$F$34*(1+$C$15)/12 -> 8.5833333 | O107: =SUM(C107:N107) -> 103 | P107: =SUM(C107:G107) -> 42.916667 | Q107: Calculated value (budget)
...

Sheet Actuals
A1: Actual Results - Jan-May 2026 (SIMULATED)
A2: Simulated actuals for the budget-vs-actual exercise. Same operating logic as the budget, different inputs.
A3: Simulated data created for portfolio demonstration. It does not represent nonpublic Texas Instruments information. ALL VALUES ON THIS TAB ARE SIMULATED.
A6: Line item | B6: Units | C6: =Ops_Model!C$6 -> 46023 | D6: =Ops_Model!D$6 -> 46054 | E6: =Ops_Model!E$6 -> 46082 | F6: =Ops_Model!F$6 -> 46113 | G6: =Ops_Model!G$6 -> 46143 | H6: YTD Jan-May | I6: Classification | J6: Formula
A8: Simulated actual inputs
A9: Input | B9: Units | C9: Power | D9: Signal chain | E9: Embedded | I9: Classification | J9: Note
A10: Demand vs budget | B10: % | C10: 0.05 | D10: 0.01 | E10: -0.05 | I10: Simulated operational data | J10: Power demand ahead on industrial and automotive restocking; embedded behind plan
A11: ASP change vs FY2025 base-year ASP | B11: % | C11: -0.015 | D11: -0.005 | E11: 0.01 | I11: Simulated operational data | J11: Budget assumed -1.0% for every product
A12: Actual final-test yield | B12: % | C12: 0.945 | D12: 0.93 | E12: 0.86 | I12: Simulated operational data | J12: Embedded yield below plan on the older test handlers (budget 88%)
A13: Actual capacity utilization | B13: % | C13: 0.84 | D13: 0.76 | E13: 0.72 | I13: Simulated operational data | J13: Power test floor run hard to meet demand; embedded loading cut (budget 78%)
A14: Variable cost change vs FY2025 base-year cost | B14: % | C14: 0.045 | D14: 0.035 | E14: 0.04 | I14: Simulated operational data | J14: Wafer and substrate price increases (budget +3.0%)
A15: Actual fixed manufacturing cost per month | B15: $m | C15: 5.9 | D15: 6.2 | E15: 2.6 | I15: Simulated operational data | J15: Power overtime on the test floor
A16: Actual R&D expense per month | B16: $m | C16: 10.8 | I16: Simulated operational data | J16: Budget $10.5m: added design engineers
A17: Actual SG&A expense per month | B17: $m | C17: 8.4 | I17: Simulated operational data | J17: Budget $8.58m: travel and marketing held back
A18: Actual capex % of revenue | B18: % | C18: 0.045 | I18: Simulated operational data | J18: Budget 5.0%: some projects deferred
A19: Monthly demand noise (applies to all products) | B19: x | C19: 1.01 | D19: 0.98 | E19: 1.02 | F19: 0.99 | G19: 1 | I19: Simulated operational data | J19: Row is by month (Jan-May), not by product
A21: Power-management chips - actual (Simulated data created for portfolio demonstration. It does not represent nonpublic Texas Instruments information.)
A22: Customer demand | B22: m units | C22: =Budget!C19*(1+$C$10)*C$19 -> 67.917476 | D22: =Budget!D19*(1+$C$10)*D$19 -> 67.302255 | E22: =Budget!E19*(1+$C$10)*E$19 -> 74.427367 | F22: =Budget!F19*(1+$C$10)*F$19 -> 70.11367 | G22: =Budget!G19*(1+$C$10)*G$19 -> 71.537261 | H22: =SUM(C22:G22) -> 351.29803 | I22: Simulated operational data
A23: Internal final-test capacity | B23: m units | C23: =Assumptions!$C$47 -> 88 | D23: =Assumptions!$C$47 -> 88 | E23: =Assumptions!$C$47 -> 88 | F23: =Assumptions!$C$47 -> 88 | G23: =Assumptions!$C$47 -> 88 | H23: =SUM(C23:G23) -> 440 | I23: Simulated operational data
A24: Capacity utilization | B24: % | C24: =$C$13 -> 0.84 | D24: =$C$13 -> 0.84 | E24: =$C$13 -> 0.84 | F24: =$C$13 -> 0.84 | G24: =$C$13 -> 0.84 | H24: =IFERROR(H25/H23,0) -> 0.84 | I24: Simulated operational data
A25: Units produced (tested) | B25: m units | C25: =C23*C24 -> 73.92 | D25: =D23*D24 -> 73.92 | E25: =E23*E24 -> 73.92 | F25: =F23*F24 -> 73.92 | G25: =G23*G24 -> 73.92 | H25: =SUM(C25:G25) -> 369.6 | I25: Simulated operational data | J25: Capacity x utilization
A26: Manufacturing yield (final test) | B26: % | C26: =$C$12 -> 0.945 | D26: =$C$12 -> 0.945 | E26: =$C$12 -> 0.945 | F26: =$C$12 -> 0.945 | G26: =$C$12 -> 0.945 | H26: =IFERROR(H27/H25,0) -> 0.945 | I26: Simulated operational data
A27: Good units produced | B27: m units | C27: =C25*C26 -> 69.8544 | D27: =D25*D26 -> 69.8544 | E27: =E25*E26 -> 69.8544 | F27: =F25*F26 -> 69.8544 | G27: =G25*G26 -> 69.8544 | H27: =SUM(C27:G27) -> 349.272 | I27: Simulated operational data | J27: Units produced x yield
A28: Opening finished-goods inventory | B28: m units | C28: =Assumptions!$C$68 -> 58.231389 | D28: =C31 -> 60.168313 | E28: =D31 -> 62.720458 | F28: =E31 -> 58.147491 | G28: =F31 -> 57.888221 | H28: =C28 -> 58.231389 | I28: Simulated operational data
A29: Available good units | B29: m units | C29: =C28+C27 -> 128.08579 | D29: =D28+D27 -> 130.02271 | E29: =E28+E27 -> 132.57486 | F29: =F28+F27 -> 128.00189 | G29: =G28+G27 -> 127.74262 | I29: Simulated operational data
A30: Units sold | B30: m units | C30: =MIN(C22,C29) -> 67.917476 | D30: =MIN(D22,D29) -> 67.302255 | E30: =MIN(E22,E29) -> 74.427367 | F30: =MIN(F22,F29) -> 70.11367 | G30: =MIN(G22,G29) -> 71.537261 | H30: =SUM(C30:G30) -> 351.29803 | I30: Simulated operational data | J30: MIN(demand, available)
A31: Closing finished-goods inventory | B31: m units | C31: =C29-C30 -> 60.168313 | D31: =D29-D30 -> 62.720458 | E31: =E29-E30 -> 58.147491 | F31: =F29-F30 -> 57.888221 | G31: =G29-G30 -> 56.20536 | H31: =G31 -> 56.20536 | I31: Simulated operational data | J31: Available - sold
A32: Unmet demand | B32: m units | C32: =C22-C30 -> 0 | D32: =D22-D30 -> 0 | E32: =E22-E30 -> 0 | F32: =F22-F30 -> 0 | G32: =G22-G30 -> 0 | H32: =SUM(C32:G32) -> 0 | I32: Simulated operational data
A33: Average selling price | B33: $/unit | C33: =Assumptions!$C$43*(1+$C$11) -> 0.591 | D33: =Assumptions!$C$43*(1+$C$11) -> 0.591 | E33: =Assumptions!$C$43*(1+$C$11) -> 0.591 | F33: =Assumptions!$C$43*(1+$C$11) -> 0.591 | G33: =Assumptions!$C$43*(1+$C$11) -> 0.591 | H33: =IFERROR(H34/H30,0) -> 0.591 | I33: Simulated operational data
A34: Revenue | B34: $m | C34: =C30*C33 -> 40.139228 | D34: =D30*D33 -> 39.775633 | E34: =E30*E33 -> 43.986574 | F34: =F30*F33 -> 41.437179 | G34: =G30*G33 -> 42.278521 | H34: =SUM(C34:G34) -> 207.61714 | I34: Simulated operational data | J34: Units sold x ASP
A35: Variable cost per unit produced | B35: $/unit | C35: =Assumptions!$C$45*(1+$C$14) -> 0.1463 | D35: =Assumptions!$C$45*(1+$C$14) -> 0.1463 | E35: =Assumptions!$C$45*(1+$C$14) -> 0.1463 | F35: =Assumptions!$C$45*(1+$C$14) -> 0.1463 | G35: =Assumptions!$C$45*(1+$C$14) -> 0.1463 | H35: =IFERROR(H36/H25,0) -> 0.1463 | I35: Simulated operational data
A36: Variable manufacturing cost | B36: $m | C36: =C25*C35 -> 10.814496 | D36: =D25*D35 -> 10.814496 | E36: =E25*E35 -> 10.814496 | F36: =F25*F35 -> 10.814496 | G36: =G25*G35 -> 10.814496 | H36: =SUM(C36:G36) -> 54.07248 | I36: Simulated operational data | J36: Units produced x variable cost
A37: Fixed manufacturing cost | B37: $m | C37: =$C$15 -> 5.9 | D37: =$C$15 -> 5.9 | E37: =$C$15 -> 5.9 | F37: =$C$15 -> 5.9 | G37: =$C$15 -> 5.9 | H37: =SUM(C37:G37) -> 29.5 | I37: Simulated operational data
A38: Total manufacturing cost | B38: $m | C38: =C36+C37 -> 16.714496 | D38: =D36+D37 -> 16.714496 | E38: =E36+E37 -> 16.714496 | F38: =F36+F37 -> 16.714496 | G38: =G36+G37 -> 16.714496 | H38: =SUM(C38:G38) -> 83.57248 | I38: Simulated operational data | J38: Variable + fixed
A39: Cost per good unit | B39: $/unit | C39: =IFERROR(C38/C27,0) -> 0.23927621 | D39: =IFERROR(D38/D27,0) -> 0.23927621 | E39: =IFERROR(E38/E27,0) -> 0.23927621 | F39: =IFERROR(F38/F27,0) -> 0.23927621 | G39: =IFERROR(G38/G27,0) -> 0.23927621 | H39: =IFERROR(H38/H27,0) -> 0.23927621 | I39: Simulated operational data
A40: Opening inventory value | B40: $m | C40: =Assumptions!$C$69 -> 14.381468 | D40: =C43 -> 14.607332 | E40: =D43 -> 15.109048 | F40: =E43 -> 13.957844 | G40: =F43 -> 13.871414 | H40: =C40 -> 14.381468 | I40: Simulated operational data
A41: Average cost per available unit | B41: $/unit | C41: =IFERROR((C40+C38)/C29,0) -> 0.2427745 | D41: =IFERROR((D40+D38)/D29,0) -> 0.24089505 | E41: =IFERROR((E40+E38)/E29,0) -> 0.24004208 | F41: =IFERROR((F40+F38)/F29,0) -> 0.23962412 | G41: =IFERROR((G40+G38)/G29,0) -> 0.23943387 | I41: Simulated operational data | J41: Weighted-average cost
A42: Cost of revenue (manufacturing) | B42: $m | C42: =C30*C41 -> 16.488631 | D42: =D30*D41 -> 16.21278 | E42: =E30*E41 -> 17.8657 | F42: =F30*F41 -> 16.800926 | G42: =G30*G41 -> 17.128443 | H42: =SUM(C42:G42) -> 84.496481 | I42: Simulated operational data | J42: Units sold x average cost
A43: Closing inventory value | B43: $m | C43: =C40+C38-C42 -> 14.607332 | D43: =D40+D38-D42 -> 15.109048 | E43: =E40+E38-E42 -> 13.957844 | F43: =F40+F38-F42 -> 13.871414 | G43: =G40+G38-G42 -> 13.457467 | H43: =G43 -> 13.457467 | I43: Simulated operational data | J43: Opening + manufacturing cost - cost of revenue
A44: Gross profit (before new-capex depreciation) | B44: $m | C44: =C34-C42 -> 23.650597 | D44: =D34-D42 -> 23.562853 | E44: =E34-E42 -> 26.120874 | F44: =F34-F42 -> 24.636252 | G44: =G34-G42 -> 25.150078 | H44: =SUM(C44:G44) -> 123.12065 | I44: Simulated operational data | J44: Revenue - cost of revenue
A45: Gross margin | B45: % | C45: =IFERROR(C44/C34,0) -> 0.58921404 | D45: =IFERROR(D44/D34,0) -> 0.59239416 | E45: =IFERROR(E44/E34,0) -> 0.59383744 | F45: =IFERROR(F44/F34,0) -> 0.59454464 | G45: =IFERROR(G44/G34,0) -> 0.59486655 | H45: =IFERROR(H44/H34,0) -> 0.59301779 | I45: Simulated operational data
A47: Signal-chain chips - actual (Simulated data created for portfolio demonstration. It does not represent nonpublic Texas Instruments information.)
A48: Customer demand | B48: m units | C48: =Budget!C45*(1+$D$10)*C$19 -> 41.261143 | D48: =Budget!D45*(1+$D$10)*D$19 -> 40.887385 | E48: =Budget!E45*(1+$D$10)*E$19 -> 45.216024 | F48: =Budget!F45*(1+$D$10)*F$19 -> 42.595372 | G48: =Budget!G45*(1+$D$10)*G$19 -> 43.460231 | H48: =SUM(C48:G48) -> 213.42016 | I48: Simulated operational data
A49: Internal final-test capacity | B49: m units | C49: =Assumptions!$D$47 -> 60 | D49: =Assumptions!$D$47 -> 60 | E49: =Assumptions!$D$47 -> 60 | F49: =Assumptions!$D$47 -> 60 | G49: =Assumptions!$D$47 -> 60 | H49: =SUM(C49:G49) -> 300 | I49: Simulated operational data
A50: Capacity utilization | B50: % | C50: =$D$13 -> 0.76 | D50: =$D$13 -> 0.76 | E50: =$D$13 -> 0.76 | F50: =$D$13 -> 0.76 | G50: =$D$13 -> 0.76 | H50: =IFERROR(H51/H49,0) -> 0.76 | I50: Simulated operational data
A51: Units produced (tested) | B51: m units | C51: =C49*C50 -> 45.6 | D51: =D49*D50 -> 45.6 | E51: =E49*E50 -> 45.6 | F51: =F49*F50 -> 45.6 | G51: =G49*G50 -> 45.6 | H51: =SUM(C51:G51) -> 228 | I51: Simulated operational data | J51: Capacity x utilization
A52: Manufacturing yield (final test) | B52: % | C52: =$D$12 -> 0.93 | D52: =$D$12 -> 0.93 | E52: =$D$12 -> 0.93 | F52: =$D$12 -> 0.93 | G52: =$D$12 -> 0.93 | H52: =IFERROR(H53/H51,0) -> 0.93 | I52: Simulated operational data
A53: Good units produced | B53: m units | C53: =C51*C52 -> 42.408 | D53: =D51*D52 -> 42.408 | E53: =E51*E52 -> 42.408 | F53: =F51*F52 -> 42.408 | G53: =G51*G52 -> 42.408 | H53: =SUM(C53:G53) -> 212.04 | I53: Simulated operational data | J53: Units produced x yield
A54: Opening finished-goods inventory | B54: m units | C54: =Assumptions!$D$68 -> 36.777719 | D54: =C57 -> 37.924576 | E54: =D57 -> 39.445191 | F54: =E57 -> 36.637167 | G54: =F57 -> 36.449794 | H54: =C54 -> 36.777719 | I54: Simulated operational data
A55: Available good units | B55: m units | C55: =C54+C53 -> 79.185719 | D55: =D54+D53 -> 80.332576 | E55: =E54+E53 -> 81.853191 | F55: =F54+F53 -> 79.045167 | G55: =G54+G53 -> 78.857794 | I55: Simulated operational data
A56: Units sold | B56: m units | C56: =MIN(C48,C55) -> 41.261143 | D56: =MIN(D48,D55) -> 40.887385 | E56: =MIN(E48,E55) -> 45.216024 | F56: =MIN(F48,F55) -> 42.595372 | G56: =MIN(G48,G55) -> 43.460231 | H56: =SUM(C56:G56) -> 213.42016 | I56: Simulated operational data | J56: MIN(demand, available)
A57: Closing finished-goods inventory | B57: m units | C57: =C55-C56 -> 37.924576 | D57: =D55-D56 -> 39.445191 | E57: =E55-E56 -> 36.637167 | F57: =F55-F56 -> 36.449794 | G57: =G55-G56 -> 35.397563 | H57: =G57 -> 35.397563 | I57: Simulated operational data | J57: Available - sold
A58: Unmet demand | B58: m units | C58: =C48-C56 -> 0 | D58: =D48-D56 -> 0 | E58: =E48-E56 -> 0 | F58: =F48-F56 -> 0 | G58: =G48-G56 -> 0 | H58: =SUM(C58:G58) -> 0 | I58: Simulated operational data
A59: Average selling price | B59: $/unit | C59: =Assumptions!$D$43*(1+$D$11) -> 0.94525 | D59: =Assumptions!$D$43*(1+$D$11) -> 0.94525 | E59: =Assumptions!$D$43*(1+$D$11) -> 0.94525 | F59: =Assumptions!$D$43*(1+$D$11) -> 0.94525 | G59: =Assumptions!$D$43*(1+$D$11) -> 0.94525 | H59: =IFERROR(H60/H56,0) -> 0.94525 | I59: Simulated operational data
A60: Revenue | B60: $m | C60: =C56*C59 -> 39.002096 | D60: =D56*D59 -> 38.648801 | E60: =E56*E59 -> 42.740447 | F60: =F56*F59 -> 40.263276 | G60: =G56*G59 -> 41.080783 | H60: =SUM(C60:G60) -> 201.7354 | I60: Simulated operational data | J60: Units sold x ASP
A61: Variable cost per unit produced | B61: $/unit | C61: =Assumptions!$D$45*(1+$D$14) -> 0.21735 | D61: =Assumptions!$D$45*(1+$D$14) -> 0.21735 | E61: =Assumptions!$D$45*(1+$D$14) -> 0.21735 | F61: =Assumptions!$D$45*(1+$D$14) -> 0.21735 | G61: =Assumptions!$D$45*(1+$D$14) -> 0.21735 | H61: =IFERROR(H62/H51,0) -> 0.21735 | I61: Simulated operational data
A62: Variable manufacturing cost | B62: $m | C62: =C51*C61 -> 9.91116 | D62: =D51*D61 -> 9.91116 | E62: =E51*E61 -> 9.91116 | F62: =F51*F61 -> 9.91116 | G62: =G51*G61 -> 9.91116 | H62: =SUM(C62:G62) -> 49.5558 | I62: Simulated operational data | J62: Units produced x variable cost
A63: Fixed manufacturing cost | B63: $m | C63: =$D$15 -> 6.2 | D63: =$D$15 -> 6.2 | E63: =$D$15 -> 6.2 | F63: =$D$15 -> 6.2 | G63: =$D$15 -> 6.2 | H63: =SUM(C63:G63) -> 31 | I63: Simulated operational data
A64: Total manufacturing cost | B64: $m | C64: =C62+C63 -> 16.11116 | D64: =D62+D63 -> 16.11116 | E64: =E62+E63 -> 16.11116 | F64: =F62+F63 -> 16.11116 | G64: =G62+G63 -> 16.11116 | H64: =SUM(C64:G64) -> 80.5558 | I64: Simulated operational data | J64: Variable + fixed
A65: Cost per good unit | B65: $/unit | C65: =IFERROR(C64/C53,0) -> 0.37990851 | D65: =IFERROR(D64/D53,0) -> 0.37990851 | E65: =IFERROR(E64/E53,0) -> 0.37990851 | F65: =IFERROR(F64/F53,0) -> 0.37990851 | G65: =IFERROR(G64/G53,0) -> 0.37990851 | H65: =IFERROR(H64/H53,0) -> 0.37990851 | I65: Simulated operational data
A66: Opening inventory value | B66: $m | C66: =Assumptions!$D$69 -> 14.504646 | D66: =C69 -> 14.66289 | E66: =D69 -> 15.110785 | F66: =E69 -> 13.97482 | G66: =F69 -> 13.873432 | H66: =C66 -> 14.504646 | I66: Simulated operational data
A67: Average cost per available unit | B67: $/unit | C67: =IFERROR((C66+C64)/C55,0) -> 0.38663293 | D67: =IFERROR((D66+D64)/D55,0) -> 0.38308307 | E67: =IFERROR((E66+E64)/E55,0) -> 0.38143833 | F67: =IFERROR((F66+F64)/F55,0) -> 0.38061758 | G67: =IFERROR((G66+G64)/G55,0) -> 0.38023626 | I67: Simulated operational data | J67: Weighted-average cost
A68: Cost of revenue (manufacturing) | B68: $m | C68: =C56*C67 -> 15.952917 | D68: =D56*D67 -> 15.663265 | E68: =E56*E67 -> 17.247125 | F68: =F56*F67 -> 16.212547 | G68: =G56*G67 -> 16.525155 | H68: =SUM(C68:G68) -> 81.601009 | I68: Simulated operational data | J68: Units sold x average cost
A69: Closing inventory value | B69: $m | C69: =C66+C64-C68 -> 14.66289 | D69: =D66+D64-D68 -> 15.110785 | E69: =E66+E64-E68 -> 13.97482 | F69: =F66+F64-F68 -> 13.873432 | G69: =G66+G64-G68 -> 13.459437 | H69: =G69 -> 13.459437 | I69: Simulated operational data | J69: Opening + manufacturing cost - cost of revenue
A70: Gross profit (before new-capex depreciation) | B70: $m | C70: =C60-C68 -> 23.049179 | D70: =D60-D68 -> 22.985536 | E70: =E60-E68 -> 25.493322 | F70: =F60-F68 -> 24.050728 | G70: =G60-G68 -> 24.555628 | H70: =SUM(C70:G70) -> 120.13439 | I70: Simulated operational data | J70: Revenue - cost of revenue
A71: Gross margin | B71: % | C71: =IFERROR(C70/C60,0) -> 0.59097284 | D71: =IFERROR(D70/D60,0) -> 0.59472831 | E71: =IFERROR(E70/E60,0) -> 0.59646831 | F71: =IFERROR(F70/F60,0) -> 0.5973366 | G71: =IFERROR(G70/G60,0) -> 0.59774001 | H71: =IFERROR(H70/H60,0) -> 0.59550476 | I71: Simulated operational data
A73: Embedded processors - actual (Simulated data created for portfolio demonstration. It does not represent nonpublic Texas Instruments information.)
A74: Customer demand | B74: m units | C74: =Budget!C71*(1+$E$10)*C$19 -> 3.8906811 | D74: =Budget!D71*(1+$E$10)*D$19 -> 3.8554379 | E74: =Budget!E71*(1+$E$10)*E$19 -> 4.2636029 | F74: =Budget!F71*(1+$E$10)*F$19 -> 4.016491 | G74: =Budget!G71*(1+$E$10)*G$19 -> 4.098042 | H74: =SUM(C74:G74) -> 20.124255 | I74: Simulated operational data
A75: Internal final-test capacity | B75: m units | C75: =Assumptions!$E$47 -> 7 | D75: =Assumptions!$E$47 -> 7 | E75: =Assumptions!$E$47 -> 7 | F75: =Assumptions!$E$47 -> 7 | G75: =Assumptions!$E$47 -> 7 | H75: =SUM(C75:G75) -> 35 | I75: Simulated operational data
A76: Capacity utilization | B76: % | C76: =$E$13 -> 0.72 | D76: =$E$13 -> 0.72 | E76: =$E$13 -> 0.72 | F76: =$E$13 -> 0.72 | G76: =$E$13 -> 0.72 | H76: =IFERROR(H77/H75,0) -> 0.72 | I76: Simulated operational data
A77: Units produced (tested) | B77: m units | C77: =C75*C76 -> 5.04 | D77: =D75*D76 -> 5.04 | E77: =E75*E76 -> 5.04 | F77: =F75*F76 -> 5.04 | G77: =G75*G76 -> 5.04 | H77: =SUM(C77:G77) -> 25.2 | I77: Simulated operational data | J77: Capacity x utilization
A78: Manufacturing yield (final test) | B78: % | C78: =$E$12 -> 0.86 | D78: =$E$12 -> 0.86 | E78: =$E$12 -> 0.86 | F78: =$E$12 -> 0.86 | G78: =$E$12 -> 0.86 | H78: =IFERROR(H79/H77,0) -> 0.86 | I78: Simulated operational data
A79: Good units produced | B79: m units | C79: =C77*C78 -> 4.3344 | D79: =D77*D78 -> 4.3344 | E79: =E77*E78 -> 4.3344 | F79: =F77*F78 -> 4.3344 | G79: =G77*G78 -> 4.3344 | H79: =SUM(C79:G79) -> 21.672 | I79: Simulated operational data | J79: Units produced x yield
A80: Opening finished-goods inventory | B80: m units | C80: =Assumptions!$E$68 -> 3.957549 | D80: =C83 -> 4.4012679 | E80: =D83 -> 4.88023 | F80: =E83 -> 4.9510271 | G80: =F83 -> 5.2689361 | H80: =C80 -> 3.957549 | I80: Simulated operational data
A81: Available good units | B81: m units | C81: =C80+C79 -> 8.291949 | D81: =D80+D79 -> 8.7356679 | E81: =E80+E79 -> 9.21463 | F81: =F80+F79 -> 9.2854271 | G81: =G80+G79 -> 9.6033361 | I81: Simulated operational data
A82: Units sold | B82: m units | C82: =MIN(C74,C81) -> 3.8906811 | D82: =MIN(D74,D81) -> 3.8554379 | E82: =MIN(E74,E81) -> 4.2636029 | F82: =MIN(F74,F81) -> 4.016491 | G82: =MIN(G74,G81) -> 4.098042 | H82: =SUM(C82:G82) -> 20.124255 | I82: Simulated operational data | J82: MIN(demand, available)
A83: Closing finished-goods inventory | B83: m units | C83: =C81-C82 -> 4.4012679 | D83: =D81-D82 -> 4.88023 | E83: =E81-E82 -> 4.9510271 | F83: =F81-F82 -> 5.2689361 | G83: =G81-G82 -> 5.5052941 | H83: =G83 -> 5.5052941 | I83: Simulated operational data | J83: Available - sold
A84: Unmet demand | B84: m units | C84: =C74-C82 -> 0 | D84: =D74-D82 -> 0 | E84: =E74-E82 -> 0 | F84: =F74-F82 -> 0 | G84: =G74-G82 -> 0 | H84: =SUM(C84:G84) -> 0 | I84: Simulated operational data
A85: Average selling price | B85: $/unit | C85: =Assumptions!$E$43*(1+$E$11) -> 3.434 | D85: =Assumptions!$E$43*(1+$E$11) -> 3.434 | E85: =Assumptions!$E$43*(1+$E$11) -> 3.434 | F85: =Assumptions!$E$43*(1+$E$11) -> 3.434 | G85: =Assumptions!$E$43*(1+$E$11) -> 3.434 | H85: =IFERROR(H86/H82,0) -> 3.434 | I85: Simulated operational data
A86: Revenue | B86: $m | C86: =C82*C85 -> 13.360599 | D86: =D82*D85 -> 13.239574 | E86: =E82*E85 -> 14.641212 | F86: =F82*F85 -> 13.79263 | G86: =G82*G85 -> 14.072676 | H86: =SUM(C86:G86) -> 69.106691 | I86: Simulated operational data | J86: Units sold x ASP
A87: Variable cost per unit produced | B87: $/unit | C87: =Assumptions!$E$45*(1+$E$14) -> 0.988 | D87: =Assumptions!$E$45*(1+$E$14) -> 0.988 | E87: =Assumptions!$E$45*(1+$E$14) -> 0.988 | F87: =Assumptions!$E$45*(1+$E$14) -> 0.988 | G87: =Assumptions!$E$45*(1+$E$14) -> 0.988 | H87: =IFERROR(H88/H77,0) -> 0.988 | I87: Simulated operational data
A88: Variable manufacturing cost | B88: $m | C88: =C77*C87 -> 4.97952 | D88: =D77*D87 -> 4.97952 | E88: =E77*E87 -> 4.97952 | F88: =F77*F87 -> 4.97952 | G88: =G77*G87 -> 4.97952 | H88: =SUM(C88:G88) -> 24.8976 | I88: Simulated operational data | J88: Units produced x variable cost
A89: Fixed manufacturing cost | B89: $m | C89: =$E$15 -> 2.6 | D89: =$E$15 -> 2.6 | E89: =$E$15 -> 2.6 | F89: =$E$15 -> 2.6 | G89: =$E$15 -> 2.6 | H89: =SUM(C89:G89) -> 13 | I89: Simulated operational data
A90: Total manufacturing cost | B90: $m | C90: =C88+C89 -> 7.57952 | D90: =D88+D89 -> 7.57952 | E90: =E88+E89 -> 7.57952 | F90: =F88+F89 -> 7.57952 | G90: =G88+G89 -> 7.57952 | H90: =SUM(C90:G90) -> 37.8976 | I90: Simulated operational data | J90: Variable + fixed
A91: Cost per good unit | B91: $/unit | C91: =IFERROR(C90/C79,0) -> 1.7486896 | D91: =IFERROR(D90/D79,0) -> 1.7486896 | E91: =IFERROR(E90/E79,0) -> 1.7486896 | F91: =IFERROR(F90/F79,0) -> 1.7486896 | G91: =IFERROR(G90/G79,0) -> 1.7486896 | H91: =IFERROR(H90/H79,0) -> 1.7486896 | I91: Simulated operational data
A92: Opening inventory value | B92: $m | C92: =Assumptions!$E$69 -> 6.772354 | D92: =C95 -> 7.6178041 | E92: =D95 -> 8.4900706 | F92: =E95 -> 8.6342022 | G92: =F95 -> 9.2003379 | H92: =C92 -> 6.772354 | I92: Simulated operational data
A93: Average cost per available unit | B93: $/unit | C93: =IFERROR((C92+C90)/C81,0) -> 1.7308203 | D93: =IFERROR((D92+D90)/D81,0) -> 1.7396866 | E93: =IFERROR((E92+E90)/E81,0) -> 1.7439214 | F93: =IFERROR((F92+F90)/F81,0) -> 1.7461472 | G93: =IFERROR((G92+G90)/G81,0) -> 1.7472947 | I93: Simulated operational data | J93: Weighted-average cost
A94: Cost of revenue (manufacturing) | B94: $m | C94: =C82*C93 -> 6.73407 | D94: =D82*D93 -> 6.7072535 | E94: =E82*E93 -> 7.4353884 | F94: =F82*F93 -> 7.0133843 | G94: =G82*G93 -> 7.1604869 | H94: =SUM(C94:G94) -> 35.050583 | I94: Simulated operational data | J94: Units sold x average cost
A95: Closing inventory value | B95: $m | C95: =C92+C90-C94 -> 7.6178041 | D95: =D92+D90-D94 -> 8.4900706 | E95: =E92+E90-E94 -> 8.6342022 | F95: =F92+F90-F94 -> 9.2003379 | G95: =G92+G90-G94 -> 9.619371 | H95: =G95 -> 9.619371 | I95: Simulated operational data | J95: Opening + manufacturing cost - cost of revenue
A96: Gross profit (before new-capex depreciation) | B96: $m | C96: =C86-C94 -> 6.6265289 | D96: =D86-D94 -> 6.5323203 | E96: =E86-E94 -> 7.205824 | F96: =F86-F94 -> 6.7792457 | G96: =G86-G94 -> 6.9121894 | H96: =SUM(C96:G96) -> 34.056108 | I96: Simulated operational data | J96: Revenue - cost of revenue
A97: Gross margin | B97: % | C97: =IFERROR(C96/C86,0) -> 0.49597544 | D97: =IFERROR(D96/D86,0) -> 0.49339355 | E97: =IFERROR(E96/E86,0) -> 0.49216034 | F97: =IFERROR(F96/F86,0) -> 0.49151218 | G97: =IFERROR(G96/G86,0) -> 0.49117803 | H97: =IFERROR(H96/H86,0) -> 0.49280479 | I97: Simulated operational data
A99: Division actual P&L to operating profit (Simulated data created for portfolio demonstration. It does not represent nonpublic Texas Instruments information.)
A100: Revenue | B100: $m | C100: =C34+C60+C86 -> 92.501923 | D100: =D34+D60+D86 -> 91.664008 | E100: =E34+E60+E86 -> 101.36823 | F100: =F34+F60+F86 -> 95.493084 | G100: =G34+G60+G86 -> 97.431981 | H100: =SUM(C100:G100) -> 478.45923 | I100: Simulated operational data
A101: Variable manufacturing cost | B101: $m | C101: =C36+C62+C88 -> 25.705176 | D101: =D36+D62+D88 -> 25.705176 | E101: =E36+E62+E88 -> 25.705176 | F101: =F36+F62+F88 -> 25.705176 | G101: =G36+G62+G88 -> 25.705176 | H101: =SUM(C101:G101) -> 128.52588 | I101: Simulated operational data
A102: Fixed manufacturing cost | B102: $m | C102: =C37+C63+C89 -> 14.7 | D102: =D37+D63+D89 -> 14.7 | E102: =E37+E63+E89 -> 14.7 | F102: =F37+F63+F89 -> 14.7 | G102: =G37+G63+G89 -> 14.7 | H102: =SUM(C102:G102) -> 73.5 | I102: Simulated operational data
A103: Cost of revenue - manufacturing | B103: $m | C103: =C42+C68+C94 -> 39.175618 | D103: =D42+D68+D94 -> 38.583299 | E103: =E42+E68+E94 -> 42.548213 | F103: =F42+F68+F94 -> 40.026858 | G103: =G42+G68+G94 -> 40.814086 | H103: =SUM(C103:G103) -> 201.14807 | I103: Simulated operational data
A104: Capital expenditures | B104: $m | C104: =C100*$C$18 -> 4.1625865 | D104: =D100*$C$18 -> 4.1248803 | E104: =E100*$C$18 -> 4.5615705 | F104: =F100*$C$18 -> 4.2971888 | G104: =G100*$C$18 -> 4.3844391 | H104: =SUM(C104:G104) -> 21.530665 | I104: Simulated operational data
A105: Depreciation on FY2026 capex | B105: $m | C105: =0 -> 0 | D105: =SUM($C$104:C104)/Assumptions!$F$86 -> 0.069376442 | E105: =SUM($C$104:D104)/Assumptions!$F$86 -> 0.13812445 | F105: =SUM($C$104:E104)/Assumptions!$F$86 -> 0.21415062 | G105: =SUM($C$104:F104)/Assumptions!$F$86 -> 0.28577044 | H105: =SUM(C105:G105) -> 0.70742195 | I105: Simulated operational data
A106: Total cost of revenue | B106: $m | C106: =C103+C105 -> 39.175618 | D106: =D103+D105 -> 38.652675 | E106: =E103+E105 -> 42.686337 | F106: =F103+F105 -> 40.241009 | G106: =G103+G105 -> 41.099856 | H106: =SUM(C106:G106) -> 201.8555 | I106: Simulated operational data
A107: Gross profit | B107: $m | C107: =C100-C106 -> 53.326305 | D107: =D100-D106 -> 53.011332 | E107: =E100-E106 -> 58.681896 | F107: =F100-F106 -> 55.252076 | G107: =G100-G106 -> 56.332125 | H107: =SUM(C107:G107) -> 276.60373 | I107: Simulated operational data
...

Sheet Variance
A1: Budget vs Actual - YTD Jan-May 2026
A2: Favorable = positive (adds to profit). Components are computed separately and must reconcile to the totals.
A3: Simulated data created for portfolio demonstration. It does not represent nonpublic Texas Instruments information. (Actuals are simulated.)
A5: A. YTD P&L summary
A6: Line | B6: Units | C6: Budget | D6: Actual | E6: Variance | F6: Variance % | G6: Fav / Unfav | H6: Definition
A7: Revenue - Power-management chips | B7: $m | C7: =Budget!$P$31 -> 198.70598 | D7: =Actuals!$H$34 -> 207.61714 | E7: =D7-C7 -> 8.9111503 | F7: =IFERROR(E7/ABS(C7),0) -> 0.044845908 | G7: =IF(ABS(E7)<0.0005,"On budget",IF(E7>0,"Favorable","Unfavorable")) -> Favorable | H7: Actual - budget
A8: Revenue - Signal-chain chips | B8: $m | C8: =Budget!$P$57 -> 198.70598 | D8: =Actuals!$H$60 -> 201.7354 | E8: =D8-C8 -> 3.0294176 | F8: =IFERROR(E8/ABS(C8),0) -> 0.015245729 | G8: =IF(ABS(E8)<0.0005,"On budget",IF(E8>0,"Favorable","Unfavorable")) -> Favorable | H8: Actual - budget
